Workbook

Sheet Executive Scorecard
A1: EXECUTIVE SCORECARD · ServiceBridge Franchisor GTM Engagement · April – June 2026
A2: Prepared by Velocity GTM Co LLC · Michael Montgomery Flynt Jr · Metrics auto-update as activity is logged across all tabs
B3: METRIC | D3: TARGET | E3: ACTUAL | F3: % TO GOAL | G3: STATUS
B5: PHASE 1 · 30-DAY · DEVELOP
B6: Target: End of April 2026 · Build the foundation for both tracks
B8: TRACK 1 — FRANCHISOR
B9: Franchisors Profiled (deep research complete) | D9: 9 | E9: =COUNTIF('Track 1 · Franchisors'!D4:D12,"TIER 1")+COUNTIF('Track 1 · Franchisors'!D4:D12,"TIER 2")+COUNTIF('Track 1 · Franchisors'!D4:D12,"TIER 3") -> 0 | F9: =IFERROR(E9/9,0) -> 0 | G9: =IF(E9>=9,"✅ On Track",IF(E9>=9*0.7,"⚠️ At Risk","🔴 Behind")) -> 🔴 Behind
B10: Contacts Mapped (3+ per franchisor = 27 total) | D10: 27 | E10: =0 -> 0 | F10: =IFERROR(E10/27,0) -> 0 | G10: =IF(E10>=27,"✅ On Track",IF(E10>=27*0.7,"⚠️ At Risk","🔴 Behind")) -> 🔴 Behind
B11: Outreach Sequences Live (both tracks active) | D11: 9 | E11: =COUNTIFS('Track 1 · Franchisors'!L4:L12,"Contacted")+COUNTIFS('Track 1 · Franchisors'!L4:L12,"Replied")+COUNTIFS('Track 1 · Franchisors'!L4:L12,"Call Scheduled")+COUNTIFS('Track 1 · Franchisors'!L4:L12,"Discovery Done")+COUNTIFS('Track 1 · Franchisors'!L4:L12,"Proposal Sent")+COUNTIFS('Track 1 · Franchisors'!L4:L12,"Negotiating")+COUNTIFS('Track 1 · Franchisors'!L4:L12,"Pilot Closed") -> 0 | F11: =IFERROR(E11/9,0) -> 0 | G11: =IF(E11>=9,"✅ On Track",IF(E11>=9*0.7,"⚠️ At Risk","🔴 Behind")) -> 🔴 Behind
B12: TRACK 2 — FRANCHISEE
B13: Franchisee Brands Scored (all 85 in database) | D13: 85 | E13: =COUNTA('Track 2 · Franchisees'!B4:B88)-COUNTBLANK('Track 2 · Franchisees'!B4:B88) -> 71 | F13: =IFERROR(E13/85,0) -> 0.83529412 | G13: =IF(E13>=85,"✅ On Track",IF(E13>=85*0.7,"⚠️ At Risk","🔴 Behind")) -> ⚠️ At Risk
B14: Contacts Validated (one per brand) | D14: 85 | E14: =COUNTA('Track 2 · Franchisees'!J4:J88)-COUNTIF('Track 2 · Franchisees'!J4:J88,"(Franchisee Owner)")-COUNTIF('Track 2 · Franchisees'!J4:J88,"(TBD — Research)")-COUNTIF('Track 2 · Franchisees'!J4:J88,"") -> 71 | F14: =IFERROR(E14/85,0) -> 0.83529412 | G14: =IF(E14>=85,"✅ On Track",IF(E14>=85*0.7,"⚠️ At Risk","🔴 Behind")) -> ⚠️ At Risk
B15: Outreach Sequences Live (brands contacted) | D15: 85 | E15: =COUNTIFS('Track 2 · Franchisees'!L4:L88,"Contacted")+COUNTIFS('Track 2 · Franchisees'!L4:L88,"Replied")+COUNTIFS('Track 2 · Franchisees'!L4:L88,"Call Scheduled")+COUNTIFS('Track 2 · Franchisees'!L4:L88,"Discovery Done")+COUNTIFS('Track 2 · Franchisees'!L4:L88,"Proposal Sent")+COUNTIFS('Track 2 · Franchisees'!L4:L88,"Negotiating")+COUNTIFS('Track 2 · Franchisees'!L4:L88,"Pilot Closed") -> 0 | F15: =IFERROR(E15/85,0) -> 0 | G15: =IF(E15>=85,"✅ On Track",IF(E15>=85*0.7,"⚠️ At Risk","🔴 Behind")) -> 🔴 Behind
B16: ENGAGEMENT ACTIVITY — CRM LOG
B17: Total Touchpoints Logged (all channels) | D17: 30 | E17: =COUNTA('Engagement Log'!B5:B80)-COUNTBLANK('Engagement Log'!B5:B80) -> -34 | F17: =IFERROR(E17/30,0) -> -1.1333333 | G17: =IF(E17>=30,"✅ On Track",IF(E17>=30*0.7,"⚠️ At Risk","🔴 Behind")) -> 🔴 Behind
B18: Positive Outcomes (replied, calls, meetings) | D18: 5 | E18: =COUNTIF('Engagement Log'!I5:I80,"Replied – Positive")+COUNTIF('Engagement Log'!I5:I80,"Call Scheduled")+COUNTIF('Engagement Log'!I5:I80,"Call Complete")+COUNTIF('Engagement Log'!I5:I80,"Meeting Complete")+COUNTIF('Engagement Log'!I5:I80,"Pilot Agreed") -> 2 | F18: =IFERROR(E18/5,0) -> 0.4 | G18: =IF(E18>=5,"✅ On Track",IF(E18>=5*0.7,"⚠️ At Risk","🔴 Behind")) -> 🔴 Behind
B20: PHASE 2 · 60-DAY · ENGAGE
B21: Target: End of May 2026 · Drive active conversations on both tracks
B23: TRACK 1 — FRANCHISOR
B24: Franchisors in Active Conversation | D24: 3 | E24: =COUNTIFS('Track 1 · Franchisors'!L4:L12,"Discovery Done")+COUNTIFS('Track 1 · Franchisors'!L4:L12,"Proposal Sent")+COUNTIFS('Track 1 · Franchisors'!L4:L12,"Negotiating")+COUNTIFS('Track 1 · Franchisors'!L4:L12,"Pilot Closed") -> 0 | F24: =IFERROR(E24/3,0) -> 0 | G24: =IF(E24>=3,"✅ On Track",IF(E24>=3*0.7,"⚠️ At Risk","🔴 Behind")) -> 🔴 Behind
B25: Mandate Validated (confirmed at franchisor level) | D25: 3 req. | E25: =0 -> 0 | F25: — | G25: Manual
B26: Franchisor Discovery Calls Completed | D26: 3 | E26: =COUNTIF('Engagement Log'!H5:H80,"Discovery Call") -> 2 | F26: =IFERROR(E26/3,0) -> 0.66666667 | G26: =IF(E26>=3,"✅ On Track",IF(E26>=3*0.7,"⚠️ At Risk","🔴 Behind")) -> 🔴 Behind
B27: Proposals / ROI Models Submitted | D27: 1 | E27: =COUNTIFS('Track 1 · Franchisors'!L4:L12,"Proposal Sent")+COUNTIFS('Track 1 · Franchisors'!L4:L12,"Negotiating") -> 0 | F27: =IFERROR(E27/1,0) -> 0 | G27: =IF(E27>=1,"✅ On Track",IF(E27>=1*0.7,"⚠️ At Risk","🔴 Behind")) -> 🔴 Behind
B28: TRACK 2 — FRANCHISEE
B29: Franchisees Engaged (in active conversation) | D29: 25 | E29: =COUNTIFS('Track 2 · Franchisees'!L4:L88,"Replied")+COUNTIFS('Track 2 · Franchisees'!L4:L88,"Call Scheduled")+COUNTIFS('Track 2 · Franchisees'!L4:L88,"Discovery Done")+COUNTIFS('Track 2 · Franchisees'!L4:L88,"Proposal Sent")+COUNTIFS('Track 2 · Franchisees'!L4:L88,"Negotiating")+COUNTIFS('Track 2 · Franchisees'!L4:L88,"Pilot Closed") -> 0 | F29: =IFERROR(E29/25,0) -> 0 | G29: =IF(E29>=25,"✅ On Track",IF(E29>=25*0.7,"⚠️ At Risk","🔴 Behind")) -> 🔴 Behind
B30: Confirmed Next Steps (committed to follow-up) | D30: 10 | E30: =COUNTIFS('Track 2 · Franchisees'!L4:L88,"Call Scheduled")+COUNTIFS('Track 2 · Franchisees'!L4:L88,"Discovery Done")+COUNTIFS('Track 2 · Franchisees'!L4:L88,"Proposal Sent")+COUNTIFS('Track 2 · Franchisees'!L4:L88,"Negotiating")+COUNTIFS('Track 2 · Franchisees'!L4:L88,"Pilot Closed") -> 0 | F30: =IFERROR(E30/10,0) -> 0 | G30: =IF(E30>=10,"✅ On Track",IF(E30>=10*0.7,"⚠️ At Risk","🔴 Behind")) -> 🔴 Behind
B31: Pilots Seeded (pilot conversation started) | D31: 3–5 | E31: =COUNTIFS('Track 2 · Franchisees'!L4:L88,"Proposal Sent")+COUNTIFS('Track 2 · Franchisees'!L4:L88,"Negotiating")+COUNTIFS('Track 2 · Franchisees'!L4:L88,"Pilot Closed") -> 0 | F31: — | G31: Manual
B32: HIGH Pilot Potential Accounts Contacted | D32: 15 | E32: =COUNTIFS('Track 2 · Franchisees'!I4:I88,"HIGH",'Track 2 · Franchisees'!L4:L88,"Contacted")+COUNTIFS('Track 2 · Franchisees'!I4:I88,"HIGH",'Track 2 · Franchisees'!L4:L88,"Replied")+COUNTIFS('Track 2 · Franchisees'!I4:I88,"HIGH",'Track 2 · Franchisees'!L4:L88,"Call Scheduled")+COUNTIFS('Track 2 · Franchisees'!I4:I88,"HIGH",'Track 2 · Franchisees'!L4:L88,"Discovery Done")+COUNTIFS('Track 2 · Franchisees'!I4:I88,"HIGH",'Track 2 · Franchisees'!L4:L88,"Proposal Sent")+COUNTIFS('Track 2 · Franchisees'!I4:I88,"HIGH",'Track 2 · Franchisees'!L4:L88,"Pilot Closed") -> 0 | F32: =IFERROR(E32/15,0) -> 0 | G32: =IF(E32>=15,"✅ On Track",IF(E32>=15*0.7,"⚠️ At Risk","🔴 Behind")) -> 🔴 Behind
B34: PHASE 3 · 90-DAY · CLOSE
B35: Target: End of June 2026 · Close pilots, advance franchisors, deliver playbook
B37: TRACK 1 — FRANCHISOR
B38: Franchisor in Qualified Interest Discussion | D38: 1+ req. | E38: =COUNTIFS('Track 1 · Franchisors'!L4:L12,"Negotiating")+COUNTIFS('Track 1 · Franchisors'!L4:L12,"Pilot Closed") -> 0 | F38: — | G38: Manual
B39: Franchisor Deal in Progress / Closed | D39: 1 | E39: =COUNTIFS('Track 1 · Franchisors'!L4:L12,"Pilot Closed") -> 0 | F39: =IFERROR(E39/1,0) -> 0 | G39: =IF(E39>=1,"✅ On Track",IF(E39>=1*0.7,"⚠️ At Risk","🔴 Behind")) -> 🔴 Behind
B40: PE Warm Intros Activated (Charles path) | D40: Manual | E40: =0 -> 0 | F40: — | G40: Manual
B41: GTM Playbook Delivered | D41: Yes/No | E41: No | F41: — | G41: Manual
B42: TRACK 2 — FRANCHISEE
B43: Pilots Closed (signed agreements) | D43: 2 | E43: =COUNTIFS('Track 2 · Franchisees'!L4:L88,"Pilot Closed") -> 0 | F43: =IFERROR(E43/2,0) -> 0 | G43: =IF(E43>=2,"✅ On Track",IF(E43>=2*0.7,"⚠️ At Risk","🔴 Behind")) -> 🔴 Behind
B44: Pilots in Active Negotiation | D44: 3 | E44: =COUNTIFS('Track 2 · Franchisees'!L4:L88,"Negotiating") -> 0 | F44: =IFERROR(E44/3,0) -> 0 | G44: =IF(E44>=3,"✅ On Track",IF(E44>=3*0.7,"⚠️ At Risk","🔴 Behind")) -> 🔴 Behind
B45: Total Pipeline Value Created (Closed + Negotiating) | D45: $50K+ | E45: =0 -> 0 | F45: — | G45: Manual
B46: Extension Plan Presented to Core Team | D46: Yes/No | E46: No | F46: — | G46: Manual
B48: FRANCHISOR ACCOUNT SCORECARD · Status by Account
B49: Live from Top 9 Franchisors tab · Update status there and this auto-refreshes
B51: ACCOUNT | D51: TIER | E51: STATUS | F51: TEMP | G51: NOTES
B52: BELFOR | D52: TIER 1 | E52: ='Track 1 · Franchisors'!L4 -> 0 | F52: =IFERROR(VLOOKUP("BELFOR",'Account Feedback'!A4:I28,9,0),"❄ Cold") -> 🌡 Warming | G52: ='Track 1 · Franchisors'!Q4 -> Gagan Sinha = CIO (joined Sep 2025). ST renewal window 2025–2027. PE play only.
B53: THRESHOLD | D53: TIER 1 | E53: ='Track 1 · Franchisors'!L5 -> 0 | F53: =IFERROR(VLOOKUP("THRESHOLD BRANDS",'Account Feedback'!A4:I28,9,0),"❄ Cold") -> ❄ Cold | G53: ='Track 1 · Franchisors'!Q5 -> 9 of 12 brands have no ServiceTitan. No displacement. Ryan Bowes = Chief Dev Officer.
B54: EMPOWER | D54: TIER 1 | E54: ='Track 1 · Franchisors'!L6 -> 0 | F54: =IFERROR(VLOOKUP("EMPOWER BRANDS",'Account Feedback'!A4:I28,9,0),"❄ Cold") -> ❄ Cold | G54: ='Track 1 · Franchisors'!Q6 -> Gary Bauer (JAN-PRO Brand President) is brand-level wedge. EBITDA before exit window.
B55: PREMIUM SVC | D55: TIER 2 | E55: ='Track 1 · Franchisors'!L7 -> 0 | F55: =IFERROR(VLOOKUP("PREMIUM SERVICE BRANDS",'Account Feedback'!A4:I28,9,0),"❄ Cold") -> ❄ Cold | G55: ='Track 1 · Franchisors'!Q7 -> Founder-backed. No PE committee. One conversation closes this. $1.67/tech/day message.
B56: RESIBRANDS | D56: TIER 2 | E56: ='Track 1 · Franchisors'!L8 -> 0 | F56: =IFERROR(VLOOKUP("RESIBRANDS",'Account Feedback'!A4:I28,9,0),"❄ Cold") -> 🔥 Hot | G56: ='Track 1 · Franchisors'!Q8 -> Princeton Equity Year 5. EBITDA story lands immediately. Greenfield — no incumbent.
B57: FIVE STAR | D57: TIER 2 | E57: ='Track 1 · Franchisors'!L9 -> 0 | F57: =IFERROR(VLOOKUP("FIVE STAR FRANCHISING",'Account Feedback'!A4:I28,9,0),"❄ Cold") -> ❄ Cold | G57: ='Track 1 · Franchisors'!Q9 -> RooterMan brand president (name TBD) is 300-loc plumbing wedge into PSB portfolio.
B58: HOMEFRONT | D58: TIER 2 | E58: ='Track 1 · Franchisors'!L10 -> 0 | F58: =IFERROR(VLOOKUP("HOMEFRONT BRANDS",'Account Feedback'!A4:I28,9,0),"❄ Cold") -> ❄ Cold | G58: ='Track 1 · Franchisors'!Q10 -> Jeff Dudan is a podcaster + Forbes contributor — accessible. Tyler Kirk (Window Hero) is wedge.
B59: AUTHORITY | D59: TIER 3 | E59: ='Track 1 · Franchisors'!L11 -> 0 | F59: =IFERROR(VLOOKUP("AUTHORITY BRANDS",'Account Feedback'!A4:I28,9,0),"❄ Cold") -> ❄ Cold | G59: ='Track 1 · Franchisors'!Q11 -> 0
B60: NEIGHBORLY | D60: TIER 3 | E60: ='Track 1 · Franchisors'!L12 -> 0 | F60: =IFERROR(VLOOKUP("NEIGHBORLY",'Account Feedback'!A4:I28,9,0),"❄ Cold") -> 🌡 Warming | G60: ='Track 1 · Franchisors'!Q12 -> ═ P2 · DE-FACTO ANCHOR ═ Year 6 hold — American Securities exit window 2026-2027. HOODZ + DUCTZ at 94% SB de facto. Convert de facto into mandate before exit. | Zero FSM mandate. 30 new territories Dec 2024. Start here.
B62: FRANCHISEE PIPELINE SUMMARY · By Stage
B63: Live from 85 Franchisees tab · Status dropdowns drive these counts automatically
B65: PIPELINE STAGE | D65: TARGET | E65: ACTUAL COUNT | F65: % OF TOTAL | G65: STATUS
B66: Total Brands in Database | D66: 85 | E66: =COUNTA('Track 2 · Franchisees'!B4:B88)-COUNTBLANK('Track 2 · Franchisees'!B4:B88) -> 71 | F66: =IFERROR(E66/85,0) -> 0.83529412 | G66: Reference
B67: HIGH Pilot Potential Brands | D67: 30 | E67: =COUNTIF('Track 2 · Franchisees'!I4:I88,"HIGH") -> 0 | F67: =IFERROR(E67/85,0) -> 0 | G67: Reference
B68: MED Pilot Potential Brands | D68: 40 | E68: =COUNTIF('Track 2 · Franchisees'!I4:I88,"MED") -> 36 | F68: =IFERROR(E68/85,0) -> 0.42352941 | G68: Reference
B69: GPS Warm Accounts (YES) | D69: 10 | E69: =COUNTIF('Track 2 · Franchisees'!H4:H88,"YES") -> 7 | F69: =IFERROR(E69/85,0) -> 0.082352941 | G69: Reference
B70: Researching | D70: 10 | E70: =COUNTIF('Track 2 · Franchisees'!L4:L88,"Researching") -> 0 | F70: =IFERROR(E70/85,0) -> 0 | G70: =IF(E70>=10,"✅ On Track",IF(E70>=10*0.6,"⚠️ At Risk","🔴 Behind")) -> 🔴 Behind
B71: Contacted (outreach sent) | D71: 40 | E71: =COUNTIF('Track 2 · Franchisees'!L4:L88,"Contacted") -> 0 | F71: =IFERROR(E71/85,0) -> 0 | G71: =IF(E71>=40,"✅ On Track",IF(E71>=40*0.6,"⚠️ At Risk","🔴 Behind")) -> 🔴 Behind
B72: Replied (any response) | D72: 10 | E72: =COUNTIF('Track 2 · Franchisees'!L4:L88,"Replied") -> 0 | F72: =IFERROR(E72/85,0) -> 0 | G72: =IF(E72>=10,"✅ On Track",IF(E72>=10*0.6,"⚠️ At Risk","🔴 Behind")) -> 🔴 Behind
B73: Call Scheduled | D73: 5 | E73: =COUNTIF('Track 2 · Franchisees'!L4:L88,"Call Scheduled") -> 0 | F73: =IFERROR(E73/85,0) -> 0 | G73: =IF(E73>=5,"✅ On Track",IF(E73>=5*0.6,"⚠️ At Risk","🔴 Behind")) -> 🔴 Behind
B74: Discovery Done | D74: 3 | E74: =COUNTIF('Track 2 · Franchisees'!L4:L88,"Discovery Done") -> 0 | F74: =IFERROR(E74/85,0) -> 0 | G74: =IF(E74>=3,"✅ On Track",IF(E74>=3*0.6,"⚠️ At Risk","🔴 Behind")) -> 🔴 Behind
B75: Proposal Sent / Negotiating | D75: 3 | E75: =COUNTIF('Track 2 · Franchisees'!L4:L88,"Proposal Sent")+COUNTIF('Track 2 · Franchisees'!L4:L88,"Negotiating") -> 0 | F75: =IFERROR(E75/85,0) -> 0 | G75: =IF(E75>=3,"✅ On Track",IF(E75>=3*0.6,"⚠️ At Risk","🔴 Behind")) -> 🔴 Behind
B76: Pilot Closed 🎯 | D76: 2 | E76: =COUNTIF('Track 2 · Franchisees'!L4:L88,"Pilot Closed") -> 0 | F76: =IFERROR(E76/85,0) -> 0 | G76: =IF(E76>=2,"✅ On Track",IF(E76>=2*0.6,"⚠️ At Risk","🔴 Behind")) -> 🔴 Behind
B77: Stalled | D77: 5 | E77: =COUNTIF('Track 2 · Franchisees'!L4:L88,"Stalled") -> 0 | F77: =IFERROR(E77/85,0) -> 0 | G77: =IF(E77>=5,"✅ On Track",IF(E77>=5*0.6,"⚠️ At Risk","🔴 Behind")) -> 🔴 Behind
B80: PE RELATIONSHIP TRACKER · GPS Insight Actions Required
B81: Live from the 🔑 PE Relationship Map tab · Update status there — this section reflects the current state of all GPS Insight intro requests
B83: PE RELATIONSHIP / GPS ASK
B84: Accel-KKR Deal Team Brief (All PE intros flow from this)
B85: KKR → Felix Gernburd (Neighborly Board — ST renewal window 2025–27)
B86: Insight Engine ROI Model Sign-Off (Required before external use)
B87: American Securities → BELFOR (Board-level intro needed)
B88: Riverside Company → Threshold Brands (Approaching exit — EBITDA story) | D88: 🟡 HIGH | E88: GPS Insight (Charles Layne, CEO) | F88: =IFERROR('PE Relationship Map'!I15,"Not Started") -> 0 | G88: 📞 On me — once the AKKR brief is confirmed, asking Charles to assign the Riverside intro to GPS Insight.
B90: GPS Insight Telematics List (Conflict check — required before outreach) | D90: 🔴 CRITICAL | E90: GPS Insight (Andrea Rowan, GM) | F90: Manual — update when received | G90: 📋 GPS Insight to provide the telematics client list. On me to run the conflict check once received.
B91: Micro-Franchise List from Angie (Expands Track 2 beyond 85 brands) | D91: 🟡 HIGH | E91: GPS Insight (Angie, Data Strategist) | F91: Manual — update when received | G91: 📋 GPS Insight (Angie) to pull the micro-franchise list. On me to score and integrate into Track 2 once received.
B92: Apax Partners → Authority Brands (CTO Tij Bedi — tech agenda active) | D92: 🟡 HIGH | E92: GPS Insight (Charles Layne, CEO) | F92: =IFERROR('PE Relationship Map'!I27,"Not Started") -> Not Started | G92: 🔍 On me — researching and asking Charles if AKKR has any Apax overlap. GPS Insight to surface the intro if the connection exists.
B93: Princeton Equity → Five Star Franchising (Year 5 — exit building) | D93: 🔵 MEDIUM | E93: GPS Insight (Charles Layne, CEO) | F93: =IFERROR('PE Relationship Map'!I23,"Not Started") -> 0 | G93: 📞 On me — asking Charles to surface the Princeton Equity connection. GPS Insight to facilitate if the path exists.
B97: LAST UPDATED · Update this cell manually each Friday before sending to Andrea
B98: April 14, 2026 · Week 1 · Engagement not yet started
B100: HOW THIS SCORECARD WORKS
B101: 1. All ACTUAL numbers pull live from the other tabs via COUNTIF formulas — no manual entry needed for counts.
B102: 2. STATUS auto-calculates: ✅ On Track = at or above target · ⚠️ At Risk = 70%+ of target · 🔴 Behind = below 70%
B103: 3. Items marked 'Manual' in the ACTUAL column need to be updated by you — they cannot be counted automatically.
B104: 4. Franchisor Account Scorecard pulls status from the Top 9 Franchisors tab and temperature from Account Feedback Cards.
B105: 5. To update: change status dropdowns in Tab 2 (Top 9) or Tab 3 (85 Franchisees) — this scorecard refreshes automatically.
A107: Prepared by Velocity GTM Co LLC on behalf of GPS Insight / ServiceBridge · Michael Montgomery Flynt Jr · 919.434.6720 · mflyntjr@gmail.com · Confidential · April 2026
A109: 📊 INSIGHT ENGINE · Use Insight_Engine_Excel_v3.xlsx for all ROI conversations · FDD unit economics loaded into Track 1 col V · 3-Way Scenario = PE/CFO boardroom document

Sheet Changelog v15.6
A1: CRM v15.6 — Validation Changelog
A2: Validated April 29, 2026 by Velocity GTM Co LLC. 9 changes applied to Track 2 · Franchisees sheet.
A4: Date | B4: Row | C4: Brand | D4: Field Changed | E4: Old Value | F4: New Value | G4: Reason for Change
A5: 2026-04-29 20:24 | B5: 40 | C5: USA Insulation | D5: FSM Status | E5: Greenfield | F5: At-Risk SB | G5: Per Andrea Apr 2026: 75% SB penetration but transitioning OFF over next year. Not greenfield — retention/monitor play.
A6: 2026-04-29 20:24 | B6: 40 | C6: USA Insulation | D6: Current FSM Platform | E6: Greenfield / Paper | F6: ServiceBridge (75%, AT-RISK — transitioning off per Andrea Apr 2026) | G6: Andrea confirmed Apr 2026: USA Insulation transitioning off ServiceBridge over the next year. Not greenfield.
A7: 2026-04-29 20:24 | B7: 40 | C7: USA Insulation | D7: Notes | E7: Seasonal scheduling — strong dispatch fit | F7: ⚠️ AT-RISK / RETENTION PLAY — Andrea confirmed Apr 2026: USA Insulation transitioning off ServiceBridge over next year. Posture: dual-track — defend if reversible, reset relationship at brand-corp lev | G7: Added retention-play context per Threshold P2 readiness package.
A8: 2026-04-29 20:24 | B8: 40 | C8: USA Insulation | D8: Combined Score | E8: 84 🟡 QUEUE | F8: 84* ⚠️ RECALIBRATE — at-risk, not greenfield | G8: Score derived from greenfield assumption that does not apply. Flagged for recalibration.
A9: 2026-04-29 20:24 | B9: 37 | C9: BELFOR Property Restoration | D9: FSM Status | E9: Greenfield | F9: Not FSM Scope | G9: BELFOR Property Restoration is the parent restoration business — runs on restoration management software (Xactimate/Symbility), not FSM. Out of ServiceBridge category.
A10: 2026-04-29 20:24 | B10: 37 | C10: BELFOR Property Restoration | D10: Current FSM Platform | E10: Greenfield / Paper | F10: Restoration management software (Xactimate/Symbility ecosystem) — not FSM category | G10: Restoration management is a different software category. Not displaceable by FSM.
A11: 2026-04-29 20:24 | B11: 37 | C11: BELFOR Property Restoration | D11: Combined Score | E11: 116 🔴 LEAD PILOT | F11: EXCLUDE ⛔ NOT FSM SCOPE | G11: Excluded from FSM engagement. Score was based on incorrect greenfield framework.
A12: 2026-04-29 20:24 | B12: 37 | C12: BELFOR Property Restoration | D12: Notes | E12: Large restoration crews — documentation + compliance | F12: ⛔ EXCLUDED — different software ecosystem (restoration management). Engage at parent franchisor level (BELFOR FG) only, not as Stage 2 brand-corp target. | Large restoration crews — documentation + co | G12: Added exclusion rationale.
A13: 2026-04-29 20:24 | B13: 2 | C13: (Header) | D13: Subheader version stamp | E13: Velocity GTM Co LLC · Sorted by parent franchisor · GPS Insight warm accounts highlighted · Pilot potential scored HIGH / MED / LOW | F13: Velocity GTM Co LLC · Sorted by parent franchisor · GPS Insight warm accounts prioritized · v15.6 — validated April 29, 2026 | G13: Version bump and validation date.
A16: Validation Summary
A17: ✓ Total brands in Track 2 reviewed: 78
A18: ✓ Portfolio assignments verified — CRM is correct (no misassignments found)
A19: ✓ Score-FSM consistency check passed — no logic errors
A20: ✓ No duplicate brand entries
A21: ✓ All 78 brands have parent franchisor, trade, location, FSM status fields populated
A22: ⚠️ 64 of 78 brands marked "Validate with Andrea" for GPSI customer overlap — REQUIRES GPSI team query
A23: ⚠️ ~68 of 78 brands have "TBD" for Owner/Decision Maker — REQUIRES Andrea/Marketing team intel
A24: ⚠️ 2 substantive corrections applied: USA Insulation (At-Risk, not Greenfield) + BELFOR Property Restoration (Not FSM scope)
A26: NEXT STEPS for full data closure:
A27: 1. GPSI customer database query for all 78 brands → fills GPSI Customer column + Telematics column
A28: 2. Brand-corp leadership intel from Andrea/Marketing team → fills Owner/DM column for ~68 brands
... A32: Track 1 · Franchisors V2 Realignment (April 29, 2026)
A33: 2026-04-29 | B33: 4-14 | C33: NEIGHBORLY | D33: V2 Track 1 position | E33: 9 | F33: 1 | G33: V2 ranking
A34: 2026-04-29 | B34: 4-14 | C34: NEIGHBORLY | D34: TIER label | E34: TIER 3 | F34: P1 #1 · PE-GATED | G34: V2 character label
A35: 2026-04-29 | B35: 4-14 | C35: NEIGHBORLY | D35: FRANCHISOR SCORE | E35: 39 ⚪ BUILD | F35: 76.5 🔴 PE-GATED — DO NOT APPROACH DIRECT | G35: V2 score (greenfield-weighted)
A36: 2026-04-29 | B36: 4-14 | C36: AUTHORITY BRANDS | D36: V2 Track 1 position | E36: 8 | F36: 2 | G36: V2 ranking
A37: 2026-04-29 | B37: 4-14 | C37: AUTHORITY BRANDS | D37: TIER label | E37: TIER 3 | F37: P1 #2 · DISPLACEMENT-READY | G37: V2 character label
A38: 2026-04-29 | B38: 4-14 | C38: AUTHORITY BRANDS | D38: FRANCHISOR SCORE | E38: 61 🟡 ACTIVE | F38: 68.5 🟡 ACTIVE | G38: V2 score (greenfield-weighted)
A39: 2026-04-29 | B39: 4-14 | C39: EMPOWER BRANDS | D39: V2 Track 1 position | E39: 3 | F39: 3 | G39: V2 ranking
A40: 2026-04-29 | B40: 4-14 | C40: EMPOWER BRANDS | D40: TIER label | E40: TIER 1 | F40: P1 #3 · GREENFIELD-LED | G40: V2 character label
A41: 2026-04-29 | B41: 4-14 | C41: EMPOWER BRANDS | D41: FRANCHISOR SCORE | E41: 60 🟡 ACTIVE | F41: 66.2 🟡 ACTIVE | G41: V2 score (greenfield-weighted)
A42: 2026-04-29 | B42: 4-14 | C42: RESIBRANDS | D42: V2 Track 1 position | E42: 5 | F42: 4 | G42: V2 ranking
A43: 2026-04-29 | B43: 4-14 | C43: RESIBRANDS | D43: TIER label | E43: TIER 2 | F43: P1 #4 · FAST-CYCLE | G43: V2 character label
A44: 2026-04-29 | B44: 4-14 | C44: RESIBRANDS | D44: FRANCHISOR SCORE | E44: 58 🟡 ACTIVE | F44: 60.2 🟢 ACTIVE | G44: V2 score (greenfield-weighted)
... A60: 2026-04-29 | B60: 4-14 | C60: THRESHOLD | D60: FRANCHISOR SCORE | E60: 73 🔴 MOVE NOW | F60: P2 SET | G60: P2 set qualitatively classified
A62: Other CRM Tabs V2 Realignment (April 29, 2026)
A63: 2026-04-29 | B63: 💡 Engagement Ideas | C63: BELFOR | D63: Priority cell | E63: 🔴 #1 | F63: 🟡 P2 DE-FACTO ANCHOR — HOODZ + DUCTZ at 94% SB; convert to mandate | G63: V2 ranking realignment — was old framework priority, now V2 character label.
A64: 2026-04-29 | B64: 💡 Engagement Ideas | C64: THRESHOLD BRANDS | D64: Priority cell | E64: 🟡 #2 | F64: 🔴 P2 AT-RISK ANCHOR — USA Insulation transitioning off SB; defensive | G64: V2 ranking realignment — was old framework priority, now V2 character label.
A65: 2026-04-29 | B65: 💡 Engagement Ideas | C65: EMPOWER BRANDS | D65: Priority cell | E65: 🟡 #3 | F65: 🟡 P1 #3 GREENFIELD-LED — strongest greenfield, Commercial mix | G65: V2 ranking realignment — was old framework priority, now V2 character label.
A66: 2026-04-29 | B66: 💡 Engagement Ideas | C66: RESIBRANDS | D66: Priority cell | E66: 🔴 #1 | F66: 🟢 P1 #4 FAST-CYCLE — founder-direct, fastest decision | G66: V2 ranking realignment — was old framework priority, now V2 character label.
A67: 2026-04-29 | B67: 💡 Engagement Ideas | C67: FIVE STAR FRANCHISING | D67: Priority cell | E67: 🟡 #4 | F67: 🟡 P1 #5 WEDGE-BRAND — Mosquito Shield wedge entry | G67: V2 ranking realignment — was old framework priority, now V2 character label.
A68: 2026-04-29 | B68: 💡 Engagement Ideas | C68: HOMEFRONT BRANDS | D68: Priority cell | E68: 🟡 #5 | F68: ⚪ P1 #7 MONITOR-MODE — Q3/Q4 2026 reassessment posture | G68: V2 ranking realignment — was old framework priority, now V2 character label.
A69: 2026-04-29 | B69: 💡 Engagement Ideas | C69: AUTHORITY BRANDS | D69: Priority cell | E69: 🟡 #6 | F69: 🟡 P1 #2 DISPLACEMENT-READY — leadership transition window | G69: V2 ranking realignment — was old framework priority, now V2 character label.
A70: 2026-04-29 | B70: 💡 Engagement Ideas | C70: NEIGHBORLY | D70: Priority cell | E70: ⚪ PE Only | F70: 🔴 P1 #1 PE-GATED — DO NOT APPROACH DIRECT (KKR warm path required) | G70: V2 ranking realignment — was old framework priority, now V2 character label.
A71: 2026-04-29 | B71: 💡 Engagement Ideas | C71: PREMIUM SERVICE BRANDS | D71: Priority cell | E71: 🟡 #7 | F71: 🟡 P1 #6 GREENFIELD-OPEN — RooterMan dominant brand wedge | G71: V2 ranking realignment — was old framework priority, now V2 character label.
A72: 2026-04-29 | B72: 📊 Scoring Model | C72: (Header) | D72: Subtitle | E72: Velocity GTM Co LLC · Two-level scoring: Franchisor score (Track 1) feeds a bonus into Franchisee score (Track 2). Combined score (max 125) determines pilot priority and outreach sequencing. | F72: Velocity GTM Co LLC · V2 Greenfield-Weighted Methodology · Track 1 + Track 2 use same 7 dimensions, reweighted per stage · Updated April 28, 2026 | G72: V2 methodology — same 7 dimensions across Stage 1/Stage 2 with stage-specific weights.
A73: 2026-04-29 | B73: 📊 Scoring Model | C73: Level 1 | D73: Range/Max | E73: 7 dimensions · Max 100 points | F73: 7 V2 dimensions · Max 100 points | G73: Updated to V2 framework
A74: 2026-04-29 | B74: 📊 Scoring Model | C74: Level 1 | D74: Description | E74: Scores each of the 9 PE-backed franchisor targets. Determines where we focus GTM effort at the network level. Also feeds directly into the franchisee bonus calculation. | F74: Scores each of the 7 P1 franchisor targets using V2 dimensions: Greenfield (20%), Network (15%), PE (15%), DM Access (15%), Urgency (15%), Displacement (10%), C/B Mix (10%). Determines where to focus | G74: V2 description
... A112: 2026-04-29 | B112: 📅 Event Intelligence | C112: NEIGHBORLY | D112: Franchisor label (col 1) | E112: NEIGHBORLY | F112: NEIGHBORLY · P1 #1 PE-GATED | G112: Added V2 priority/character label for visibility

Sheet PE Relationship Map
A1: PE RELATIONSHIP MAP · GPS Insight Warm Introduction Paths · ServiceBridge GTM Engagement
A2: Velocity GTM Co LLC · These introductions require GPS Insight coordination · Every row is a GPS Insight ask tracked to completion
A3: 🔑 Each row on this tab represents an introduction path that runs through GPS Insight's PE network · Status updated as introductions progress
B5: WHY THIS TAB EXISTS
B6: A warm PE-level introduction compresses a 6-month enterprise sales cycle to 6 weeks. Accel-KKR (GPS Insight's backer) has portfolio relationships, co-investment networks, and operating partner connections that give you an immediate credibility bridge to the PE firms backing your 9 priority franchisor accounts. None of these introductions happen without Charles Layne. This tab tracks every PE relationship, who at GPS Insight owns it, what the ask is, and where the introduction stands.
B8: PE FIRM | C8: FUND TYPE & AUM | D8: PORTFOLIO COMPANY | E8: GPS INSIGHT OWNER | F8: PE TARGET CONTACT (Named Individuals) | G8: INTRO PATH | H8: PRIORITY | I8: INTRO STATUS | J8: LAST GPS ACTION | K8: NEXT GPS ACTION NEEDED | L8: NEXT DATE | M8: NOTES / INTELLIGENCE | N8: PE DEAL TEAM FOCAL POINTS ← Researched contacts
B10: SECTION 1 · ACCEL-KKR NETWORK · GPS Insight's Own PE Backer · Highest Leverage
B11: Accel-KKR backed GPS Insight. This is your warmest possible intro path. Charles Layne has direct relationships with the AKKR deal team.
B13: Accel-KKR | C13: Tech-Focused PE ~$10B+ AUM | D13: GPS Insight / ServiceBridge (Portfolio Company) | E13: GPS Insight (Charles Layne, CEO) | F13: Accel-KKR Internal (GPS Insight board-level) | G13: Charles Layne → AKKR deal team → PE portfolio introductions | H13: 🔴 Critical | I13: Not Started | K13: 📞 On me — calling Charles. Asking GPS Insight to brief AKKR and open intro paths to the four PE firms. | L13: Week 1 | M13: GPS Insight backer. Charles Layne has direct AKKR deal team relationships. This single conversation unlocks all downstream PE intros. | N13: TBD — Accel-KKR deal team partner for GPS Insight ← Charles Layne is the direct relationship Accel-KKR = GPS Insight's own PE backer — highest leverage intro chain
B14: KKR | C14: Large-Cap PE $349B+ AUM | D14: Neighborly (16 brands, 13,259 techs) | E14: GPS Insight (Charles Layne, CEO) | F14: Felix Gernburd Managing Director, KKR Led Neighborly acquisition 2021 North American PE fund | G14: Charles → Accel-KKR deal team → KKR deal team → Felix Gernburd | H14: 🔴 Critical | I14: Not Started | K14: Flag to Charles that the Accel-KKR → KKR path is the play for Neighborly. Ask him to request a warm intro to Felix Gernburd — KKR Partner, Neighborly board seat. | L14: Week 1 | M14: KKR acquired Neighborly (Jul 2021) from Harvest Partners. Felix Gernburd is on Neighborly board. ST renewal window 2025–2027. One KKR-level conversation positions us for that window. | N14: Felix Gernburd — Managing Director, KKR Named in KKR/Neighborly acquisition press release as deal lead Intro path: Charles Layne → Accel-KKR → KKR → Felix Gernburd ⚠️ DO NOT cold outreach — PE intro only
B16: SECTION 2 · TIER 1 FRANCHISOR PE BACKERS · Active Introduction Requests
B17: These PE firms back your Tier 1 accounts. A single intro at the PE level is worth months of direct franchisor outreach.
B19: American Securities | C19: Mid-Market PE ~$10B AUM | D19: BELFOR Franchise Group (14 brands, 9,250 techs) | E19: GPS Insight (Charles Layne, CEO) | F19: David Horing Co-Chair Investment Committee Director, BELFOR (since 1995) Managing Member, active funds Ryan Nolan Director, BELFOR Joined 2017, ex-JPMorgan David Musicant Director, BELFOR Joined 2011, deal sourcing Ex-BofA/Merrill Lynch MD Loren Easton Chairman, BELFOR board | G19: Charles → AKKR deal team → American Securities operating partners | H19: 🔴 Critical | I19: Not Started | K19: Week 1 — Charles Layne call. Ask him to surface any AKKR → American Securities relationship. American Securities has board representation at BELFOR — an operating partner intro skips directly to the mandate decision. | L19: Week 1 | M19: American Securities board is active on ops improvement at BELFOR. Tech standardization directly supports their portfolio thesis. BELFOR sold 30 new franchise territories Dec 2024 — mandate now = every new franchisee is a guaranteed adoption. | N19: PRIMARY: David Horing (Co-Chair IC, Director BELFOR since 1995) OPERATIONAL: Ryan Nolan (Director BELFOR, joined 2017, ex-JPMorgan) RELATIONSHIPS: David Musicant (Director BELFOR, deal sourcing/capital markets) CHAIRMAN: Loren Easton (BELFOR board chairman) INTRO PATH: Charles Layne → Accel-KKR → American Securities Source: american-securities.com team pages (confirmed)
B20: The Riverside Company | C20: Global Mid-Market PE $13B+ AUM | D20: Threshold Brands (10 brands, 6,250 techs) | E20: GPS Insight (Charles Layne, CEO) | F20: Loren Schlachet Managing Partner, Riverside Leads Threshold platform Brian Sauer Senior Partner, Riverside Named on Threshold press releases Steve Rice Principal Caroline Quoyeser Assistant Vice President Deniz Oran Associate Tom Silk Operating Partner Chrissie Yim Finance Director | G20: Charles → AKKR deal team → Riverside Company LP or operating partner relationship | H20: 🟡 High | I20: Not Started | K20: Once the AKKR brief is confirmed, ask Charles to surface any Riverside connection through the PE network. Riverside is approaching exit window — technology standardization improves the EBITDA multiple. | L20: Week 2 | M20: Threshold is Riverside's home services platform (formed 2021). Glassdoor shows high turnover and EBITDA pressure from Riverside. LP-reportable tech standardization is the pitch to the PE firm, not to Hagan Kappler. | N20: PRIMARY: Loren Schlachet (Managing Partner — leads Threshold platform) DEAL LEAD: Brian Sauer (Senior Partner — named on all Threshold add-on releases) OPERATIONAL: Steve Rice (Principal) + Caroline Quoyeser (AVP) + Deniz Oran (Associate) FINANCE: Chrissie Yim (Finance Director) SOURCING: Jeremy Holland (Partner) + Connor McLaughlin (VP Origination) Source: Riverside press release — Miracle Method add-on (Dec 2023)
B21: MidOcean Partners | C21: Mid-Market PE $6B+ AUM | D21: Empower Brands (10 brands, 5,150 techs) | E21: GPS Insight (Charles Layne, CEO) | F21: Eric Roth Principal/Partner, MidOcean Covers Empower Brands Christopher M. Grandpre Operating Partner, MidOcean Chairman, Empower Brands 30+ yrs franchise M&A Founded Outdoor Living Brands 2008 | G21: Charles → AKKR deal team → MidOcean operating partner | H21: 🟡 High | I21: Not Started | K21: Ask Charles about MidOcean connection through Charles / AKKR. MidOcean invested in Empower Dec 2020 — approaching exit window. EBITDA improvement before exit is the story. | L21: Week 2 | M21: MidOcean invested in Empower Brands Dec 2020. Typical hold 5–7 years puts exit window at 2025–2027. First-mover FSM standardization documented before exit = multiple expansion story for MidOcean LPs. | N21: PRIMARY: Eric Roth (covers Empower Brands at MidOcean — confirmed on MidOcean website) OPERATING: Christopher M. Grandpre (Operating Partner + Chairman of Empower Brands) → Founded Outdoor Living Brands 2008 (precursor to Empower) → 30+ years franchise M&A / investment banking INTRO PATH: Charles Layne → MidOcean → Eric Roth or Grandpre Source: midoceanpartners.com + The Joint Corp. press release (May 2025)
B23: SECTION 3 · TIER 2 FRANCHISOR PE BACKERS · Build Relationships in Parallel
B24: Smaller or founder-backed platforms. PE path may be lighter — but still surface any connections through Charles before going cold.
B26: Susquehanna Private Capital | C26: Growth Equity (Susquehanna Int'l Group) | D26: Premium Service Brands (8 brands, 4,950 techs) | E26: GPS Insight (Charles Layne, CEO) | F26: Kyle Squillario Co-Head, Susquehanna Private Capital Named in PSB deal announcement SPC Team: 7 people total 2 Partners, 5 Principals Bala Cynwyd PA | G26: Charles → AKKR → Susquehanna Private Capital connection (if any) | H26: 🔵 Medium | I26: Not Started | K26: Check with Charles if AKKR has any Susquehanna / SGE connection. If not, direct approach to Paul Flick (CEO) is the primary path — SGE is growth equity, not traditional PE, so the founder is the decision-maker. | L26: Week 2 | M26: Susquehanna Private Capital is the investment arm of Susquehanna International Group. PSB is founder-led with PE backing — Paul Flick still runs the business. Direct CEO outreach is the backup if PE path yields nothing. | N26: PRIMARY: Kyle Squillario (Co-Head, SPC — quoted in PSB press release 2021) FIRM: Susquehanna Private Capital — funded by founders of Susquehanna Int'l Group SPC SIZE: ~7 person team, 2 partners — small firm, direct access INTRO: Charles Layne → SPC → Kyle Squillario Source: BusinessWire PSB/SPC announcement (March 2021)
B27: Princeton Equity Group | C27: Franchise-Focused PE Franchise-only investor | D27: Five Star Franchising (5 brands, 2,350 techs) | E27: GPS Insight (Charles Layne, CEO) | F27: Derek DeBenedetto Princeton Equity Group Email: derek@princetonequity.com IFA/conference meeting contact Paul Kuppich Partner (joined 2025) Capital formation focus | G27: Charles → AKKR → Princeton Equity (franchise-focused PE — likely known in network) | H27: 🔵 Medium | I27: Not Started | K27: Week 2 — Princeton Equity exclusively invests in franchise companies — very tight network. Ask Charles if AKKR has any Princeton connection. Year 5 of investment means exit pressure building. | L27: Week 2 | M27: Princeton Equity Group exclusively invests in franchisors and multi-unit companies. Five Star is in Year 5 (invested Jun 2021). EBITDA improvement documented now = higher exit multiple for Princeton. Scott Abbott (CEO) is founder — direct outreach is solid backup. | N27: MEETING CONTACT: Derek DeBenedetto (derek@princetonequity.com) → Listed as IFA 2026 meeting contact in Princeton Year in Review PARTNER: Paul Kuppich (joined 2025 — capital formation + investor relations) FIRM CONTEXT: Princeton invested 2021, Five Star in Year 5 — exit window approaching → ~$350M deployed 2025 across 3 new platforms INTRO PATH: Charles Layne → Princeton Equity → Derek DeBenedetto Source: Princeton 2025 Year in Review + LinkedIn announcement
B28: Dudan Group | C28: Family Office (Founder Capital) | D28: HomeFront Brands (5 brands, 2,550 techs) | E28: GPS Insight (Charles Layne, CEO) | F28: Jeff Dudan Chairman & CEO, HomeFront Founder, Dudan Group Forbes contributor, podcaster Zack Dudan CGO, HomeFront Brands Family office — no external PE team | G28: Direct — Jeff Dudan is both the PE backer AND the CEO. No intermediary needed. | H28: ⚪ Low | I28: Not Started | K28: NO GPS INTRO NEEDED: Jeff Dudan controls both the capital and the operating company. Approach directly. This is the one account where PE intro is not the accelerant — the CEO relationship is. | L28: Week 2 | M28: Dudan Group is Jeff Dudan's family office. He is Chairman + CEO. Direct LinkedIn / podcast outreach to Jeff is faster than any PE path. Note for Charles: no intro needed here. | N28: FAMILY OFFICE: Dudan Group = Jeff Dudan's personal capital — no external PE team DIRECT APPROACH: Jeff Dudan is both PE backer AND operating CEO → Forbes contributor, podcaster — content/thought leadership angle OPERATIONAL: Zack Dudan (CGO) = franchise operations + Homecoming vendor path NO PE INTRO NEEDED — direct approach is the right path Source: HomeFront public filings + Forbes contributor profile
B30: SECTION 4 · TIER 3 FRANCHISOR PE BACKERS · Long Cycle · Relationship Play
B31: Authority Brands and Neighborly have large PE backers. The cycle is long — but the deal size is enormous. Build the relationship now.
B33: Apax Partners + BCI | C33: Large-Cap PE Apax $60B+ · BCI C$211B | D33: Authority Brands (12 brands, 12,098 techs) | E33: GPS Insight (Charles Layne, CEO) | F33: Ashish Karandikar Partner, Apax Partners Led Authority Brands acquisition 2018 Quoted in deal press release BCI (minority stake 2022) British Columbia Investment Mgmt Corp | G33: Charles → AKKR deal team → Apax Partners relationship (LP or co-invest level) | H33: 🟡 High | I33: Not Started | K33: WEEK 1 (research): Ask Charles if AKKR has any LP overlap with Apax fund. Apax explicitly cited 'digitalization' as the AB investment thesis — that is ServiceBridge's positioning. BCI co-invested Sep 2022. | L33: Week 1 (research) | M33: Apax acquired Authority Brands Sep 2017. BCI co-invested Sep 2022 for 'technology transformation.' Apax partner Ashish Karandikar led the deal. Tij Bedi (CTO) was hired Aug 2024 — the tech agenda is active. A PE-level intro to Apax gets us to Tij Bedi much faster. | N33: APAX LEAD: Ashish Karandikar (Partner, Apax — quoted as deal lead in 2018 acquisition) → 'We have been attracted to the home services market for some time' BCI: British Columbia Investment Management Corp (significant minority stake, Sep 2022) → Largest institutional investor in Canada INTRO PATH: Charles Layne → Apax → Ashish Karandikar NOTE: Apax-focused on digitisation/tech for Authority — CTO Tij Bedi (Aug 2024) is the signal Source: Apax.com + PRNewswire acquisition announcement (Sep 2018)
B34: KKR (Neighborly) | C34: Already covered in Section 1 $349B+ AUM | D34: Neighborly (16 brands, 13,259 techs) | E34: GPS Insight (Charles Layne, CEO) | F34: Felix Gernburd Managing Director, KKR Led Neighborly acquisition 2021 ⚠️ DO NOT approach direct | G34: See Section 1 — same KKR path. Do not duplicate effort. | H34: 🔴 Critical | I34: Not Started | K34: ↑ Same KKR path as Section 1 — no separate ask needed. Tracking there. | L34: Week 1 | M34: Neighborly is tracked in Section 1 under the KKR relationship. This row is a reminder that Neighborly PE path and Authority Brands PE path are separate KKR / Apax conversations. | N34: Same as Section 1 — Felix Gernburd is the KKR Neighborly contact ⚠️ DO NOT approach direct under any circumstances INTRO PATH ONLY: Charles Layne → Accel-KKR → KKR → Felix Gernburd Source: KKR/Neighborly acquisition press release BusinessWire (July 2021)
B36: GPS INSIGHT ACTION SUMMARY · The Specific Asks for Charles Layne by Week
B38: WEEK | C38: GPS CONTACT | E38: THE ASK | I38: FOR ACCOUNT | K38: URGENCY | L38: STATUS
B39: Week 1 | C39: GPS Insight (Charles Layne, CEO) | E39: Brief the Accel-KKR deal team on the ServiceBridge GTM initiative. Need AKKR to facilitate PE-level introductions to American Securities (BELFOR), Riverside (Threshold), MidOcean (Empower), and KKR (Neighborly). | I39: ALL 9 FRANCHISORS | K39: 🔴 Critical | L39: Not Started
B40: Week 1 | C40: GPS Insight (Charles Layne, CEO) | E40: Specific KKR ask: Ask for Accel-KKR → KKR deal team intro to Felix Gernburd (KKR Partner / Neighborly Board). One call at the KKR level positions ServiceBridge for the Neighborly ST contract renewal window 2025–2027. | I40: NEIGHBORLY | K40: 🔴 Critical | L40: Not Started
B41: Week 1 | C41: GPS Insight (Garrett Else, CFO) | E41: Schedule 30-minute session to walk through the Insight Engine ROI model assumptions. Garrett's sign-off validates the financial narrative before we take it external to any PE operating partner or franchisor CFO. | I41: ALL ACCOUNTS (ROI Model) | K41: 🔴 Critical | L41: Not Started
B42: Week 1 | C42: GPS Insight (Andrea Rowan, GM) | E42: Connect Mike Flynt with Angie (GPS Insight data strategist) to obtain the micro-franchise company list. This expands Track 2 pipeline beyond the current 85-brand database. | I42: TRACK 2 FRANCHISEE | K42: 🟡 High | L42: Not Started
B43: Week 1 | C43: GPS Insight (Andrea Rowan, GM) | E43: Get the GPS Insight existing telematics client list for cross-referencing against all 9 franchisor accounts. Required conflict check before any outreach begins. | I43: ALL 9 FRANCHISORS | K43: 🔴 Critical | L43: Not Started
B44: Week 2 | C44: GPS Insight (Charles Layne, CEO) | E44: Follow-up on AKKR intro request. Confirm which PE firms have responded and whether any calls are scheduled. If American Securities intro is confirmed, brief Mike before the call. | I44: BELFOR American Securities | K44: 🟡 High | L44: Not Started
B45: Week 2 | C45: GPS Insight (Charles Layne, CEO) | E45: 🔍 On me to check whether there's any Apax Partners (Authority Brands backer) connection through AKKR LP network or co-investment relationships. Apax cited 'digitalization' as their Authority Brands investment thesis — perfect alignment. | I45: AUTHORITY BRANDS Apax Partners | K45: 🟡 High | L45: Not Started
B46: Week 3 | C46: GPS Insight (Garrett Else, CFO) | E46: ROI model sign-off — confirm which assumptions are cleared for external use. Garrett's endorsement as GPS Insight CFO is the credibility layer when the model goes in front of a PE operating partner or franchisor CFO. | I46: ALL ACCOUNTS (ROI Model) | K46: 🔴 Critical | L46: Not Started
B47: Week 4 | C47: GPS Insight (Charles Layne, CEO) | E47: 30-Day check-in: Where do the PE intro paths stand? Which firms have responded? Is a KKR / Felix Gernburd call on the calendar? Any additional PE relationships to activate in Month 2? | I47: ALL PE PATHS | K47: 🟡 High | L47: Not Started
B48: Month 2 | C48: GPS Insight (Charles Layne, CEO) | E48: If Accel-KKR intro has not yet produced a franchisor meeting: ask Charles to make a direct personal call to the PE operating partner. His personal relationship is the accelerant — not a formal intro request. | I48: STALLED ACCOUNTS | K48: 🔵 Medium | L48: Not Started
A50: Prepared by Velocity GTM Co LLC on behalf of GPS Insight / ServiceBridge · Michael Montgomery Flynt Jr · 919.434.6720 · mflyntjr@gmail.com · Confidential · April 2026

Sheet Track 1 · Franchisors
A1: TOP FRANCHISOR ACCOUNTS · Track 1 (P1 ×7) + P2 Set (×3) · V2 Greenfield-Weighted Ranking
A2: Velocity GTM Co LLC · GPS Insight / ServiceBridge Engagement · V2 Ranking April 28, 2026 · CRM v15.6 — validated April 29, 2026
A3: # | B3: FRANCHISOR | C3: PE BACKER | D3: TIER | E3: BRANDS | F3: TECHS | G3: ARR EST. | H3: CEO | I3: CFO | J3: COO / PRESIDENT | K3: BD / FRANCHISE DEV | L3: ENGAGEMENT STATUS | M3: LAST CONTACT | N3: NEXT STEP | O3: NEXT DATE | P3: GPS INSIGHT SUPPORT | Q3: NOTES | R3: ANNUAL CONVENTION | S3: VENDORS / PARTNERS INVITED? | T3: INSURANCE PROGRAM / CARRIER | U3: INSURANCE GTM ANGLE | V3: FDD INTEL (Items 8·11·19) | W3: INSIGHT ENGINE INPUTS ← Pre-populate ROI Calc | X3: FRANCHISOR SCORE / 100 | Y3: GPS INSIGHT EXEC CONTACT ← Internal intro path | Z3: GREENFIELD SCORE (V2 · 20%) | AA3: NETWORK SCORE (V2 · 15%) | AB3: PE SCORE (V2 · 15%) | AC3: DM ACCESS SCORE (V2 · 15%) | AD3: URGENCY SCORE (V2 · 15%) | AE3: DISPLACEMENT SCORE (V2 · 10%) | AF3: C/B MIX SCORE (V2 · 10%)
A4: 1 | B4: NEIGHBORLY | C4: KKR ($349B+ AUM) | D4: P1 #1 · PE-GATED | E4: 16 | F4: 13259 | G4: $198K | H4: Mike Davis CEO (joined Jul 2024) | I4: Benjamin Lamb CFO (joined May 2025) | J4: Jason Himber Group President, Repair Brands | K4: Felix Gernburd KKR Partner / Board ← PE TARGET | N4: Flag to Charles — KKR intro is Week 1 GPS ask | O4: Week 1 (GPS only) | P4: GPS: THIS IS THE #1 GPS ACTION — Charles → Accel-KKR → KKR → Felix Gernburd. DO NOT approach Neighborly direct. | Q4: Gagan Sinha = CIO (joined Sep 2025). ST renewal window 2025–2027. PE play only. | R4: Neighborly Reunion · Oct 2025 held Nashville — next ~Oct 2026 Nashville. DO NOT attend without PE intro. | S4: ✅ Yes — vendor partners attend | T4: ProTradeNet preferred insurance broker (confirmed — ~170 vendors incl. insurance brokers). Validate specific broker via FDD. | U4: 🟡 Medium — ProTradeNet broker is warm intro path to COO/CFO. PE intro only. | V4: SOURCE: Mr. Rooter FDD (franchiseba.com 2025) / Aire Serv FDD 2025 / ProTradeNet confirmed via neighborlybrands.com ITEM 11 — Technology: ServiceTitan explicitly named as required software system across all core brands. On ST since 2012 (Mr. Handyman, Aire Serv, Mr. Rooter, Mr. Electric per ServiceTitan press release). ITEM 8 — Vendors: ProTradeNet ~170 preferred vendors including insurance brokers. Specific broker named in brand-level FDDs. Broker = warm intro path to COO/CFO. ITEM 19 — Aire Serv 2025: 158 reporting businesses, 1/1/24-12/31/24 per FDD. Full financials behind paywall. ⚠️ DO NOT APPROACH DIRECT. PE intro only via Charles → KKR → Felix Gernburd. ST RENEWAL WINDOW: 2025-2027. Only leverage is PE relationship. | W4: 📊 USE INSIGHT ENGINE → ROI Calculator tab ⚠️ DO NOT RUN INSIGHT ENGINE until PE intro confirmed. IF/WHEN PE intro secured, pre-populate: • Technicians: 13,259 • Avg Jobs/Tech/Day: 5 (mature ST-optimized system) • Avg Revenue/Job: $400 • Focus: ST renewal window — Telematics angle via GPS Insight Conversation is about GPS Insight telematics (Smart Fleet USA contract renewal), not ServiceBridge FSM displacement. 3-Way Scenario: KKR exit at 10-12x multiple. | X4: 76.5 🔴 PE-GATED — DO NOT APPROACH DIRECT | Y4: Charles Layne → Accel-KKR → KKR → Felix Gernburd ⚠️ DO NOT approach direct under any circumstances GPS Insight #1 priority action — Charles follow-up TODAY | Z4: 4/20 20 (limited; ST mandate caps) | AA4: 14/15 90 (13,259 techs — largest in P1) | AB4: 13/15 85 (KKR — active investor, exit-driven) | AC4: 13/15 85 (Charles Layne → Accel-KKR → KKR warm path) | AD4: 15/15 95 (highest — ST renewals 2025-2027 + KKR window) | AE4: 5/10 50 (ST partial mandate, displaceable on non-ST brands) | AF4: 8/10 80 (consumer-led mix)
A5: 2 | B5: AUTHORITY BRANDS | C5: Apax Partners + BCI | D5: P1 #2 · DISPLACEMENT-READY | E5: 12 | F5: 12098 | G5: $181K | H5: Jay Caiafa CEO (joined Aug 2025) Prev: COO Americas, IHG Hotels 4,600 hotels, 26 countries Data/AI focus — new leadership Rob Weddle — OUT (was CEO) | I5: Josh (last name TBD) CFO (joined Sep 2025) Prev: CFO Primrose Schools Prev: VP Strategy, Cracker Barrel Prev: Home Depot finance | J5: Steve Clemente President & COO, Trades | K5: Tij Bedi CTO (joined Aug 2024) ← PRIMARY entry point Tech/FSM mandate angle 9 non-ST brands greenfield Note: Jay Caiafa (CEO) has data + AI background — lead with operational efficiency | N5: Map 9 non-ST brands + Tij Bedi research | O5: Week 1 (research) | P5: GPS: Apax Partners → Charles Layne for PE intro. Tij Bedi is primary tech champion. | Q5: 9 of 12 brands have no ServiceTitan. No displacement. Ryan Bowes = Chief Dev Officer. | R5: Annual Convention — research needed | S5: Unknown | T5: National program likely via Apax Partners — validate FDD Item 8/11 | U5: 🟡 Medium — $2B+ revenue, institutional program almost certain. Tij Bedi (CTO) not the right contact here. | V5: SOURCE: ServiceTitan press release Sep 2024 / public FDD summaries ITEM 11 — Technology: ServiceTitan named as required platform for 3 brands (Benjamin Franklin, Mister Sparky, One Hour) — announced Sep 2024, transition in 2025. 9 remaining brands have NO FSM mandate. PRIOR PLATFORM: Successware (acquired by Authority Brands 2019) — being replaced by ServiceTitan. ✅ GREENFIELD: ASP, Cleaning Authority, DRYmedic, Junkluggers, Lawn Squad, Monster Tree, Mosquito Squad, Screenmobile, STOP Restoration — 9 brands, no mandate. PRIMARY CONTACT: Tij Bedi (CTO, joined Aug 2024) building tech infrastructure. | W5: 📊 USE INSIGHT ENGINE → ROI Calculator tab PRE-POPULATE WITH (9 non-ST greenfield brands only): • Technicians: ~5,000 (9 non-ST brands est.) • Avg Jobs/Tech/Day: 4 • Avg Revenue/Job: $350 • Working Days: 260 PRIMARY AUDIENCE: Tij Bedi (CTO) — use Competitive Matrix tab to show ServiceBridge vs ServiceTitan side by side. Key message: ServiceBridge for the 9 brands ST doesn't serve. No displacement of existing ST mandate. | X5: 68.5 🟡 ACTIVE | Y5: Charles Layne → Apax Partners PE intro path Tij Bedi (CTO Authority Brands) — new hire Aug 2024, direct LinkedIn Andrea Rowan for brand-level account data | Z5: 12/20 60 (mixed — 3 brands ST mandated, 12 brands open) | AA5: 13/15 85 (12,098 techs) | AB5: 12/15 80 (Apax — active investor + co-investor BCI) | AC5: 11/15 70 (Tij Bedi CTO direct, plus parent path) | AD5: 13/15 85 (Jay Caiafa CEO Aug 2025, Josh Greear CFO Sept 2025 — fresh tech direction) | AE5: 7/10 70 (ServiceTitan partial — 12 non-ST brands displaceable) | AF5: 7/10 70 (mix B2B + consumer)
A6: 3 | B6: EMPOWER BRANDS | C6: MidOcean Partners | D6: P1 #3 · GREENFIELD-LED | E6: 10 | F6: 5150 | G6: $77K | H6: Scott Zide CEO | I6: Michael Borreca SVP & CFO | J6: Tom (last name TBD) COO ⚠️ Verify | K6: R. Scott Sutton Chief Dev Officer | N6: JAN-PRO brand wedge + CEO outreach | O6: Week 1 | P6: GPS: MidOcean → Charles Layne for PE intro before approaching Scott Zide | Q6: Gary Bauer (JAN-PRO Brand President) is brand-level wedge. EBITDA before exit window. | R6: Ignite · Feb 10–12 (just held — next ~Feb 2027, Orlando) | S6: ✅ Yes — 85 vendors attended | T6: Preferred broker via MidOcean PE (likely) — validate FDD Item 8/11 | U6: 🟡 Medium — CFO Michael Borreca owns this. MidOcean institutional. | V6: SOURCE: FDD Exchange 2025 / franchiseba.com / assettfranchise.com JAN-PRO ITEM 8 — Technology: Proprietary software mandated. Technology fee: up to $60/month per franchisee. JAN-PRO ITEM 19: 11,265 unit franchises. Regional developer investment $130K-$421.5K. ⚠️ CONFLICT FLAG: JAN-PRO has proprietary FSM with fee already built in. Confirm gap vs ServiceBridge before outreach on JAN-PRO specifically. ✅ GREENFIELD: 9 non-JAN-PRO brands (Archadeck, Bumble, Canopy, Conserva, FRSTeam, Koala, OLP, Superior Fence, Wallaby) — no FSM named in FDD. These are the entry point with Scott Zide. | W6: 📊 USE INSIGHT ENGINE → ROI Calculator tab PRE-POPULATE WITH (9 non-JAN-PRO greenfield brands): • Technicians: ~3,500 (excl. JAN-PRO) • Avg Jobs/Tech/Day: 3.5 • Avg Revenue/Job: $350 • Working Days: 260 ⚠️ EXCLUDE JAN-PRO from model — proprietary FSM conflict. Run separate scenario for the 9 greenfield brands only. MidOcean exit window framing: EBITDA uplift × 8x multiple = enterprise value story for Scott Zide + Michael Borreca. | X6: 66.2 🟡 ACTIVE | Y6: Charles Layne (CEO) — MidOcean Partners PE intro path Andrea Rowan (GM) — account detail ⚠️ JAN-PRO conflict — approach via 9 greenfield brands only | Z6: 18/20 90 (highest — ServiceMinder partial, most brands open) | AA6: 8/15 55 (5,150 techs — mid-tier) | AB6: 12/15 80 (MidOcean Year 3-4, building toward exit) | AC6: 12/15 80 (Scott Zide CEO + Gary Bauer JAN-PRO brand wedge) | AD6: 9/15 60 (mid-term, not immediate) | AE6: 3/10 30 (ServiceMinder 2-4x partial) | AF6: 4/10 40 (Commercial 70%+ — weaker consumer fit)
A7: 4 | B7: RESIBRANDS | C7: Angel / Codie Sanchez | D7: P1 #4 · FAST-CYCLE | E7: 5 | F7: 2550 | G7: $38K | H7: Steven Montgomery Founder & CEO | I7: (None confirmed) Lean team | J7: Allan (last name TBD) Co-Founder ⚠️ Verify | K7: Steven Montgomery (handles directly) | N7: Direct LinkedIn to Steven Montgomery | O7: Week 2 | Q7: Founder-backed. No PE committee. One conversation closes this. $1.67/tech/day message. | R7: No confirmed annual event (emerging brand) | S7: Unknown | T7: Franchisees self-direct — lean founder operation, no group program likely | U7: 🟢 Low | V7: SOURCE: Public company info / IFA 2026 ITEM 11 — Technology: ResiConnect handles inbound scheduling only. No full FSM disclosed in any publicly available FDD summary. ITEM 19 — Unit Economics: FDD not publicly analyzed. Angel/founder-backed — lean disclosure likely. APPROACH: Steven Montgomery directly accessible. No FDD deep-dive needed before first conversation. | W7: 📊 USE INSIGHT ENGINE → ROI Calculator tab PRE-POPULATE WITH: • Technicians: 2,550 • Avg Jobs/Tech/Day: 5 (painting model — volume-based) • Avg Revenue/Job: $200 • Working Days: 260 FOUNDER PITCH: $1.67/tech/day message. Run Insight Engine conservative scenario only — Steven Montgomery responds to simplicity, not PE math. Total: 2,550 techs × $1.67/day × 260 days = ~$1.1M annual value | X7: 60.2 🟢 ACTIVE | Y7: No current GPS Insight relationship Steven Montgomery accessible directly — call scheduled Apr 15 Direct founder path — no GPS intro needed | Z7: 17/20 85 (ResiConnect = scheduling only, paper for ops) | AA7: 7/15 45 (2,550 techs — smallest) | AB7: 6/15 40 (Angel/founder, no PE pressure) | AC7: 14/15 90 (Kevin Luu direct, fast decision velocity) | AD7: 11/15 75 (entrepreneurial — moves fast) | AE7: 7/10 70 (mostly greenfield) | AF7: 8/10 75 (consumer-led)
A8: 5 | B8: FIVE STAR FRANCHISING | C8: Princeton Equity Group | D8: P1 #5 · WEDGE-BRAND | E8: 5 | F8: 2350 | G8: $35K | H8: Scott Abbott CEO & Co-Founder | I8: Steve White CFO | J8: Chad Jones COO & Co-Founder | K8: Michael Moorhouse Brand President, Mosquito Shield | N8: Mosquito Shield brand wedge + CEO outreach | O8: Week 2 | Q8: Princeton Equity Year 5. EBITDA story lands immediately. Greenfield — no incumbent. | R8: Home Services Summit (HSS) · Jan 14–17 (just held — next ~Jan 2027, Las Vegas) | S8: ✅ Yes — vendor partners attend | T8: Preferred broker likely via Princeton Equity — validate FDD | U8: 🟡 Medium — Year 5 PE. CFO Steve White owns. | V8: SOURCE: Public FDD summaries — full FDD not yet pulled ITEM 11 — Technology: ProNexis named as 24/7 sales support system. No FSM platform mandated in publicly available analysis. ACTION: Pull California or Wisconsin FDD for Items 8 and 11 before scripting. KNOWN: Princeton Equity Year 5. CFO Steve White owns the numbers conversation. | W8: 📊 USE INSIGHT ENGINE → ROI Calculator tab PRE-POPULATE WITH: • Technicians: 2,350 • Avg Jobs/Tech/Day: 4 • Avg Revenue/Job: $300 • Working Days: 260 Princeton Equity Year 5 → exit window framing. Run 3-Way Scenario with 8x multiple for Steve White (CFO). Mosquito Shield wedge: seasonal route model, strong FSM fit. FieldRoutes conflict risk — verify Mosquito Shield before model. | X8: 59.2 🟡 ACTIVE | Y8: No current GPS Insight relationship Princeton Equity → Charles Layne path for PE intro Scott Abbott direct on LinkedIn — Five Star CEO accessible | Z8: 14/20 70 (mixed — FieldRoutes possible at Mosquito Shield) | AA8: 7/15 45 (2,350 techs) | AB8: 9/15 60 (Princeton Equity) | AC8: 11/15 75 (Mosquito Shield wedge to Five Star CEO Scott Abbott) | AD8: 9/15 60 (mid-term) | AE8: 5/10 50 (FieldRoutes possible) | AF8: 7/10 70 (consumer-led)
A9: 6 | B9: PREMIUM SERVICE BRANDS | C9: Susquehanna Private Capital | D9: P1 #6 · GREENFIELD-OPEN | E9: 8 | F9: 4950 | G9: $74K | H9: Paul Flick Founder & CEO | I9: (TBD) VP Finance ⚠️ Research | J9: Roxanne Conrad COO | K9: Gabe Colon EVP Performance | N9: RooterMan brand president outreach | O9: Week 2 | Q9: RooterMan brand president (name TBD) is 300-loc plumbing wedge into PSB portfolio. | R9: Annual Convention — research needed | S9: Unknown | T9: Validate via FDD Item 8/11 — Susquehanna PE backed | U9: 🟡 Medium — validate before outreach | V9: SOURCE: State registries — FDD not yet pulled ACTION: Pull Wisconsin or California FDD for Items 8, 11, 19 before outreach. KNOWN: RooterMan = 300 plumbing locations. PSB backed by Susquehanna Private Capital. | W9: 📊 USE INSIGHT ENGINE → ROI Calculator tab PRE-POPULATE WITH: • Technicians: 4,950 • Avg Jobs/Tech/Day: 4 • Avg Revenue/Job: $300 (painting/cleaning/plumbing mix) • Working Days: 260 RooterMan wedge: 300 locations, plumbing dispatch. Run Insight Engine at brand level first (RooterMan) → then scale to full PSB network for CFO conversation. | X9: 59.0 🟡 ACTIVE | Y9: Andrea Rowan (GM, ServiceBridge) — day-to-day contact Verify GPS Insight telematics customers in PSB network via Andrea Paul Flick direct path — no PE intro needed | Z9: 17/20 85 (RooterMan dominates — paper-based) | AA9: 8/15 50 (4,950 techs) | AB9: 6/15 40 (Susquehanna — less active) | AC9: 9/15 60 (Paul Flick CEO — verify warm path) | AD9: 8/15 50 (mid-term) | AE9: 7/10 70 (mostly greenfield) | AF9: 7/10 70 (consumer-led)
A10: 7 | B10: HOMEFRONT BRANDS | C10: Dudan Group (Family Office) | D10: P1 #7 · MONITOR-MODE | E10: 5 | F10: 2550 | G10: $38K | H10: Jeff Dudan Chairman & CEO | I10: Mike Dudan CFO | J10: Michael O'Driscoll COO & President of Franchising | K10: Zack Dudan Chief Growth Officer | N10: CEO direct outreach + Window Hero brand wedge | O10: Week 2 | Q10: Jeff Dudan is a podcaster + Forbes contributor — accessible. Tyler Kirk (Window Hero) is wedge. | R10: Homecoming (4th annual) · ~Nov 2026, Orlando — STILL TIME TO GET IN | S10: ✅ Yes — vendor partners attend | T10: Likely individual franchisee insurance — young company, no group program confirmed | U10: 🟢 Low — Jeff Dudan family office, not institutional PE | V10: SOURCE: Public company info / franchisewire.com ITEM 11 — Technology: No FSM platform disclosed in any public FDD analysis. Homecoming 3 (Nov 2025) featured digital marketing speaker — no FSM announced. NOTE: Franchisee satisfaction issues flagged Dec 2025 (Unhappy Franchisee post). Verify system health before vendor commitment. APPROACH: Jeff Dudan directly via podcast/Forbes channel first. | W10: 📊 USE INSIGHT ENGINE → ROI Calculator tab PRE-POPULATE WITH: • Technicians: 2,550 • Avg Jobs/Tech/Day: 3 • Avg Revenue/Job: $400 (fence/exterior) • Working Days: 260 Jeff Dudan is founder-operated — run conservative scenario only. Focus on per-franchisee story, not PE exit math. ⚠️ Note franchisee satisfaction issues — position ServiceBridge as proof point for system health, not just efficiency. | X10: 44.0 ⚪ MONITOR | Y10: No current GPS Insight relationship Jeff Dudan — founder, podcaster, Forbes contributor — direct approach Homecoming 4 vendor path = Zack Dudan (CGO) | Z10: 16/20 80 (newer brands — paper-based) | AA10: 5/15 35 (2,550 techs — smaller) | AB10: 3/15 20 (Family office, no exit pressure) | AC10: 8/15 50 (Tyler Kirk Window Hero, Jeff/Zack Dudan corp) | AD10: 5/15 30 (Q3/Q4 2026 reassessment) | AE10: 6/10 60 (mostly greenfield) | AF10: 7/10 70 (consumer)
B11: ═══ P2 FRANCHISORS · EXISTING FOOTPRINT ═══
A12: P2-1 | B12: BELFOR | C12: American Securities | D12: P2 · DE-FACTO ANCHOR | E12: 14 | F12: 9250 | G12: $260K+ | H12: Rusty Amarante, CR President, BFG | I12: Sheldon Yellen CEO, Holdings | J12: Dan Tarantin COO, BFG | K12: Doug Smith SVP Franchise Dev Beth Toenies VP Franchise Dev | N12: Deep profile + contact map | O12: Week 1 | P12: GPS: American Securities → Charles Layne → PE warm intro before outreach to Sheldon Yellen | Q12: ═ P2 · DE-FACTO ANCHOR ═ Year 6 hold — American Securities exit window 2026-2027. HOODZ + DUCTZ at 94% SB de facto. Convert de facto into mandate before exit. | Zero FSM mandate. 30 new territories Dec 2024. Start here. | R12: BELFOR Annual Conference · March (just held — next ~Mar 2027) | S12: Unknown | T12: Insurance carriers ARE the revenue channel for restoration brands. Claims Partnership Program launched Oct 2024. Carriers: Travelers, Allstate, State Farm, USAA. | U12: 🔴 HIGH — Carriers dispatch restoration brands. ServiceBridge job documentation = defensible claims record. Reframe pitch to Rusty as carrier relationship tool, not FSM. | V12: SOURCE: Publicly available FDD analysis (2024 FDD) + franchiseba.com ITEM 11 — Technology: 'Proprietary business management and job tracking tools' named. No third-party FSM disclosed. GREENFIELD confirmed. ITEM 19 — Unit Economics (2023 data, 94 franchisees, 157 locations): • Avg gross sales per location: ~$480K • Top 25% avg: $1,654,321 • Est. EBITDA at 15% margin: ~$72K/location • Avg invoice per job: ~$4,500 • Insurance carriers refer ~40% of jobs ROYALTY: 10% on first $499K → 7% above $2M + 2% Marketing Fund SERVICEBRIDGE EBITDA CASE: 5-pt margin improvement = $24K addl EBITDA/location. Across 178 locations = $4.3M system-wide EBITDA creation. | W12: 📊 USE INSIGHT ENGINE → ROI Calculator tab PRE-POPULATE WITH: • Technicians: 9,250 (network) | Per brand: see below • Avg Jobs/Tech/Day: 3 (restoration = emergency dispatch, lower frequency) • Avg Revenue/Job: $4,500 (FDD-sourced: avg 1-800 WD invoice 2024) • Working Days: 260 • Avg Tech Wage: $28/hr FSM UPLIFT (conservative for greenfield): • Additional Jobs: 0.3/tech/day • Admin Saved: 1.0 hr/tech/day • Invoice Cycle Reduction: 5 days (critical for insurance payment lag) TELEMATICS (GPS Insight warm flag): • Fuel Savings: $1,800/vehicle/yr • Insurance Reduction: 8% 3-WAY SCENARIO OUTPUTS (base case, 1-800 WD 178 locations): • FDD Item 19: $480K avg/location • 5-pt margin improvement = $24K EBITDA/location • 178 locations × $24K = $4.3M system EBITDA creation • At 8x exit multiple = $34.4M enterprise value uplift ⚠️ USE THE TOP-25% NUMBER ($1.65M) for STRETCH scenario with Rusty | X12: P2 SET 🟡 EXISTING FOOTPRINT | Y12: Charles Layne (CEO, GPS Insight) — Personal friend + primary exec relationship American Securities → Accel-KKR → KKR intro chain Charles owns the PE intro. Mike owns the direct franchisee path. | Z12: 25/25 Greenfield — no FSM mandate found | AA12: 15/20 9,250 techs — large network | AB12: 15/20 American Securities — active PE, EBITDA expansion thesis | AC12: 15/15 Full FDD analysis loaded — unit economics confirmed | AD12: 10/10 Charles Layne direct — highest access level | AE12: 5/5 GPS Insight relationship confirmed | AF12: 5/5 14 brands — multiple pilot targets within network
A13: P2-2 | B13: EVIVE BRANDS | C13: The Riverside Company ($13B+ AUM) | D13: P2 · GROWING ANCHOR | E13: 7 | F13: 1100 | G13: $30K-50K (estimated) | H13: Ryan Parsons CEO, Evive Brands Known-friendly to Mike — warm path | I13: TBD — research | J13: TBD — research | K13: TBD — research | L13: P2 — RESEARCH | N13: Profile + Brothers Gutters anchor leverage | P13: GPS: Riverside PE → Charles Layne. Andrea direct on Brothers Gutters. | Q13: ═ P2 · GROWING ANCHOR ═ Year 3 hold — Riverside-owned (formed 2023). Brothers Gutters at 43% SB under new contract. Maid Brigade (2024 acquisition) greenfield within Evive. Ryan Parsons = warmest P2 relationship. Same parent as Threshold (Riverside) — coordinate engagement. | X13: P2 SET 🟢 EXISTING FOOTPRINT — GROWING
A14: P2-3 | B14: THRESHOLD BRANDS | C14: Riverside Company | D14: P2 · AT-RISK ANCHOR | E14: 10 | F14: 6250 | G14: $94K | H14: Hagan Kappler CEO ⚠️ VERIFY | I14: Scott Fink / Brandon Brown CFO ⚠️ VERIFY | J14: Andrea Hohermuth COO | K14: Scott Sutton Chief Growth Officer | N14: Profile + contacts map | O14: Week 1 | P14: GPS: Riverside PE → Charles Layne. ⚠️ Verify Hagan Kappler still CEO (Daisy link 2025) | Q14: ═ P2 · AT-RISK ANCHOR ═ Year 6+ hold — Riverside-owned. USA Insulation transitioning OFF SB (75% → 0% over next year). Ted DeMarino CEO + Billy Newby CFO new. Defensive posture: defend if reversible, reset relationship at brand-corp level. Same parent as Evive. | Promised franchisees proprietary software — undelivered. ServiceBridge closes that gap. | R14: Annual Convention · Date/location TBD — research needed | S14: Unknown | T14: Preferred broker via Riverside PE (likely) — validate FDD Item 8/11 | U14: 🟡 Medium — PE-backed with structured program. CFO contact. | V14: SOURCE: Public FDD summaries / state registries ITEM 11 — Technology: Promised 'proprietary technology' to franchisees — undelivered per franchisee feedback (Glassdoor, FDD analysis). ITEM 19 — Unit Economics: Not publicly detailed in FDD analysis. Validate via Wisconsin/California FDD registry. KEY ANGLE: Unfulfilled tech promise = ServiceBridge delivers what Threshold told franchisees they'd get. | W14: 📊 USE INSIGHT ENGINE → ROI Calculator tab PRE-POPULATE WITH: • Technicians: 6,250 (network total) • Avg Jobs/Tech/Day: 4 • Avg Revenue/Job: $250 (cleaning/pest model) • Working Days: 260 KEY ANGLE FOR THRESHOLD: Unfulfilled tech promise = franchisees already expect this. Position ServiceBridge as delivering what Threshold promised. Run 3-Way Scenario showing EBITDA uplift before Riverside PE exit. | X14: P2 SET 🔴 EXISTING FOOTPRINT — AT-RISK | Y14: Charles Layne (CEO) — Riverside Company PE intro path Andrea Rowan (GM) — account detail + telematics customer list Verify Hagan Kappler CEO status before outreach | Z14: 10/25 FSM status unconfirmed — action needed | AA14: 15/20 6,250 techs — large network | AB14: 18/20 Riverside Company — Year 4, approaching exit window | AC14: 15/15 Full FDD analysis loaded — unit economics confirmed | AD14: 10/10 Charles Layne direct — highest access level | AE14: 5/5 GPS Insight relationship confirmed | AF14: 5/5 10 brands — multiple pilot targets within network

Sheet Track 2 · Franchisees
A1: 85 PRIORITY FRANCHISEE BRANDS · Track 2 · Greenfield Volume Pipeline
A2: Velocity GTM Co LLC · Sorted by parent franchisor · GPS Insight warm accounts prioritized · v15.6 — validated April 29, 2026
A3: # | B3: BRAND / FRANCHISEE | C3: PARENT FRANCHISOR | D3: TRADE | E3: LOCATIONS | F3: TECHS (EST.) | G3: FSM STATUS | H3: GPS WARM? | I3: PILOT POTENTIAL | J3: CURRENT FSM PLATFORM | K3: CONFLICT RISK | L3: TELEMATICS PROVIDER | M3: GPS INSIGHT CUSTOMER? ← Andrea to Verify | N3: INSURANCE PROGRAM / CARRIER | O3: INSURANCE GTM ANGLE | P3: PRIMARY CONTACT | Q3: CONTACT TITLE | R3: OWNER / DECISION MAKER | S3: OPS MGR / OFFICE MANAGER | T3: GPS INSIGHT ACCOUNT REP ← Warm intro path | U3: OUTREACH STATUS | V3: LAST CONTACT | W3: NEXT STEP | X3: NEXT DATE | Y3: NOTES | Z3: FDD INTEL (Source + Key Facts) | AA3: INSIGHT ENGINE NOTES ← ROI angle for outreach | AE3: FRANCHISEE SCORE / 100 | AF3: FRANCHISOR BONUS + 0/5/15/25 | AG3: COMBINED SCORE / 125
A4: 1 | B4: Aire Serv | C4: Neighborly | D4: HVAC | E4: 500 | F4: 5 | G4: Partial/ST | H4: TBD | I4: MED | J4: ServiceTitan | K4: 🔴 High | L4: Smart Fleet USA | M4: No — Smart Fleet USA | N4: ProTradeNet preferred broker — validate FDD | O4: 🟡 Medium | P4: (Franchisee Owner) | Q4: Owner/Operator | R4: TBD — franchisee owner ⚠️ DO NOT approach — Neighborly PE intro required first KKR → Charles Layne → Felix Gernburd — PE intro only | S4: TBD — office manager Smart Fleet USA telematics (NOT GPS Insight) | T4: Smart Fleet USA (NOT GPS Insight) ⚠️ No warm GPS Insight intro path Do not approach without PE intro confirmed | W4: Profile + conflict check | Y4: ServiceTitan incumbent — check mandate status before outreach | Z4: SOURCE: Aire Serv FDD 2025 / franchise.neighborly.com ITEM 11: ServiceTitan REQUIRED — 'our Software System' referenced in Item 19. ITEM 19 (2024 data): 158 reporting businesses, 1/1/24-12/31/24 full year. Avg gross sales: not disclosed in public summary — pull FDD. Telematics: Smart Fleet USA confirmed. CONFLICT: High on FSM. | AA4: ⚠️ ST mandated — no FSM pitch. Telematics only if GPS Insight customer confirmed. Do not run Insight Engine until PE intro secured. | AE4: 36 | AF4: +5 | AG4: 41 ⚪ HOLD
A5: 2 | B5: Glass Doctor | C5: Neighborly | D5: Auto/Home Glass | E5: 500 | F5: 3 | G5: Partial/ST | H5: TBD | I5: LOW | J5: ServiceTitan | K5: 🔴 High | L5: Smart Fleet USA | M5: No — Smart Fleet USA | N5: ProTradeNet preferred broker — validate FDD | O5: 🟡 Medium | P5: (Franchisee Owner) | Q5: Owner/Operator | R5: TBD — franchisee owner ⚠️ DO NOT approach — Neighborly PE intro required first KKR → Charles Layne → Felix Gernburd — PE intro only | S5: TBD — office manager Smart Fleet USA telematics (NOT GPS Insight) | T5: Smart Fleet USA (NOT GPS Insight) ⚠️ No warm GPS Insight intro path Do not approach without PE intro confirmed | W5: Profile + conflict check | Y5: ST mandate — check renewal window | Z5: Pull from Wisconsin/California FDD registry. Neighborly brand — verify ST mandate status first. | AA5: ⚠️ ST mandated — no FSM pitch. Telematics only if GPS Insight customer confirmed. Do not run Insight Engine until PE intro secured. | AE5: 19 | AF5: +5 | AG5: 24 ⚪ HOLD
A6: 3 | B6: Lawn Pride | C6: Neighborly | D6: Lawn Care | E6: 150 | F6: 3 | G6: Partial/ST | H6: TBD | I6: MED | J6: FieldRoutes (ST) | K6: 🔴 High | L6: Smart Fleet USA | M6: No — Smart Fleet USA | N6: Validate via FDD | O6: ❓ Unknown | P6: (Franchisee Owner) | Q6: Owner/Operator | R6: TBD — franchisee owner ⚠️ DO NOT approach — Neighborly PE intro required first KKR → Charles Layne → Felix Gernburd — PE intro only | S6: TBD — office manager Smart Fleet USA telematics (NOT GPS Insight) | T6: Smart Fleet USA (NOT GPS Insight) ⚠️ No warm GPS Insight intro path Do not approach without PE intro confirmed | W6: Profile + conflict check | Y6: Route model — check ST mandate status | Z6: Pull from Wisconsin/California FDD registry. Neighborly brand — verify ST mandate status first. | AA6: ⚠️ ST mandated — no FSM pitch. Telematics only if GPS Insight customer confirmed. Do not run Insight Engine until PE intro secured. | AE6: 24 | AF6: +5 | AG6: 29 ⚪ HOLD
A7: 4 | B7: Molly Maid | C7: Neighborly | D7: Cleaning | E7: 448 | F7: 3 | G7: Partial/ST | H7: TBD | I7: MED | J7: ServiceTitan | K7: 🔴 High | L7: Smart Fleet USA | M7: No — Smart Fleet USA | N7: Validate via FDD | O7: ❓ Unknown | P7: (Franchisee Owner) | Q7: Owner/Operator | R7: TBD — franchisee owner ⚠️ DO NOT approach — Neighborly PE intro required first KKR → Charles Layne → Felix Gernburd — PE intro only | S7: TBD — office manager Smart Fleet USA telematics (NOT GPS Insight) | T7: Smart Fleet USA (NOT GPS Insight) ⚠️ No warm GPS Insight intro path Do not approach without PE intro confirmed | W7: Profile + conflict check | Y7: Recurring cleaning crews | Z7: Pull from Wisconsin/California FDD registry. Neighborly brand — verify ST mandate status first. | AA7: ⚠️ ST mandated — no FSM pitch. Telematics only if GPS Insight customer confirmed. Do not run Insight Engine until PE intro secured. | AE7: 21 | AF7: +5 | AG7: 26 ⚪ HOLD
A8: 5 | B8: Mosquito Joe | C8: Neighborly | D8: Pest Control | E8: 400 | F8: 3 | G8: Partial/ST | H8: TBD | I8: HIGH — ServiceTitan mandated via Neighborly group contract — do not pitch FSM | J8: FieldRoutes (ST) | K8: 🔴 High | L8: Smart Fleet USA | M8: No — Smart Fleet USA | N8: Validate via FDD | O8: ❓ Unknown | P8: (Franchisee Owner) | Q8: Owner/Operator | R8: TBD — franchisee owner ⚠️ DO NOT approach — Neighborly PE intro required first KKR → Charles Layne → Felix Gernburd — PE intro only | S8: TBD — office manager Smart Fleet USA telematics (NOT GPS Insight) | T8: Smart Fleet USA (NOT GPS Insight) ⚠️ No warm GPS Insight intro path Do not approach without PE intro confirmed | W8: Profile + conflict check | Y8: Route recurring — strong FSM fit if not ST | Z8: Pull from Wisconsin/California FDD registry. Neighborly brand — verify ST mandate status first. | AA8: ⚠️ ST mandated — no FSM pitch. Telematics only if GPS Insight customer confirmed. Do not run Insight Engine until PE intro secured. | AE8: 24 | AF8: +5 | AG8: 29 ⚪ HOLD
A9: 6 | B9: Mr. Appliance | C9: Neighborly | D9: Appliance Repair | E9: 150 | F9: 3 | G9: Partial/ST | H9: TBD | I9: MED | J9: ServiceTitan | K9: 🔴 High | L9: Smart Fleet USA | M9: No — Smart Fleet USA | N9: Validate via FDD | O9: ❓ Unknown | P9: (Franchisee Owner) | Q9: Owner/Operator | R9: TBD — franchisee owner ⚠️ DO NOT approach — Neighborly PE intro required first KKR → Charles Layne → Felix Gernburd — PE intro only | S9: TBD — office manager Smart Fleet USA telematics (NOT GPS Insight) | T9: Smart Fleet USA (NOT GPS Insight) ⚠️ No warm GPS Insight intro path Do not approach without PE intro confirmed | W9: Profile + conflict check | Y9: Solo tech model | Z9: Pull from Wisconsin/California FDD registry. Neighborly brand — verify ST mandate status first. | AA9: ⚠️ ST mandated — no FSM pitch. Telematics only if GPS Insight customer confirmed. Do not run Insight Engine until PE intro secured. | AE9: 26 | AF9: +5 | AG9: 31 ⚪ HOLD
A10: 7 | B10: Mr. Electric | C10: Neighborly | D10: Electrical | E10: 219 | F10: 5 | G10: Partial/ST | H10: TBD | I10: HIGH — ServiceTitan MANDATED — on ST since 2012, confirmed in FDD Item 11 | J10: ServiceTitan | K10: 🔴 High | L10: Smart Fleet USA | M10: No — Smart Fleet USA | N10: ProTradeNet preferred broker — validate FDD | O10: 🟡 Medium | P10: (Franchisee Owner) | Q10: Owner/Operator | R10: TBD — franchisee owner ⚠️ DO NOT approach — Neighborly PE intro required first KKR → Charles Layne → Felix Gernburd — PE intro only | S10: TBD — office manager Smart Fleet USA telematics (NOT GPS Insight) | T10: Smart Fleet USA (NOT GPS Insight) ⚠️ No warm GPS Insight intro path Do not approach without PE intro confirmed | W10: Profile + conflict check | Y10: Licensed electricians — dispatch + compliance fit | Z10: SOURCE: ServiceTitan acquisition of Servant Systems 2020 ITEM 11: ServiceTitan REQUIRED — on ST since 2012 per ST press release. Telematics: Smart Fleet USA confirmed. CONFLICT: High on FSM. | AA10: ⚠️ ST mandated — no FSM pitch. Telematics only if GPS Insight customer confirmed. Do not run Insight Engine until PE intro secured. | AE10: 36 | AF10: +5 | AG10: 41 ⚪ HOLD
A11: 8 | B11: Mr. Handyman | C11: Neighborly | D11: Handyman | E11: 150 | F11: 3 | G11: Partial/ST | H11: TBD | I11: MED | J11: ServiceTitan | K11: 🔴 High | L11: Smart Fleet USA | M11: No — Smart Fleet USA | N11: Validate via FDD | O11: ❓ Unknown | P11: (Franchisee Owner) | Q11: Owner/Operator | R11: TBD — franchisee owner ⚠️ DO NOT approach — Neighborly PE intro required first KKR → Charles Layne → Felix Gernburd — PE intro only | S11: TBD — office manager Smart Fleet USA telematics (NOT GPS Insight) | T11: Smart Fleet USA (NOT GPS Insight) ⚠️ No warm GPS Insight intro path Do not approach without PE intro confirmed | W11: Profile + conflict check | Y11: Multi-trade skilled service | Z11: SOURCE: ServiceTitan acquisition of Servant Systems 2020 ITEM 11: ServiceTitan REQUIRED — on ST since 2012. Telematics: Smart Fleet USA confirmed. CONFLICT: High on FSM. | AA11: ⚠️ ST mandated — no FSM pitch. Telematics only if GPS Insight customer confirmed. Do not run Insight Engine until PE intro secured. | AE11: 19 | AF11: +5 | AG11: 24 ⚪ HOLD
A12: 9 | B12: Mr. Rooter | C12: Neighborly | D12: Plumbing | E12: 237 | F12: 6 | G12: Partial/ST | H12: TBD | I12: HIGH — ServiceTitan MANDATED — on ST since 2012, confirmed in FDD Item 11 | J12: ServiceTitan | K12: 🔴 High | L12: Smart Fleet USA | M12: No — Smart Fleet USA | N12: ProTradeNet preferred broker — validate FDD | O12: 🟡 Medium | P12: (Franchisee Owner) | Q12: Owner/Operator | R12: TBD — franchisee owner ⚠️ DO NOT approach — Neighborly PE intro required first KKR → Charles Layne → Felix Gernburd — PE intro only | S12: TBD — office manager Smart Fleet USA telematics (NOT GPS Insight) | T12: Smart Fleet USA (NOT GPS Insight) ⚠️ No warm GPS Insight intro path Do not approach without PE intro confirmed | W12: Profile + conflict check | Y12: 237 locations FDD 2025. Emergency + scheduled dispatch | Z12: SOURCE: Mr. Rooter FDD 2025 / franchiseba.com 2026 ITEM 11: ServiceTitan REQUIRED — named explicitly. On ST since 2012. Also required: Qvinci, QuickBooks Online. ITEM 19: 188 franchised businesses reporting. Avg not disclosed in public summaries. Telematics: Smart Fleet USA (Neighborly preferred provider, confirmed). CONFLICT: High on FSM. No GPS Insight path. | AA12: ⚠️ ST mandated — no FSM pitch. Telematics only if GPS Insight customer confirmed. Do not run Insight Engine until PE intro secured. | AE12: 36 | AF12: +5 | AG12: 41 ⚪ HOLD
A13: 10 | B13: Precision Door Service | C13: Neighborly | D13: Garage Doors | E13: 150 | F13: 3 | G13: Partial/ST | H13: TBD | I13: HIGH — ServiceTitan mandated via Neighborly group contract — do not pitch FSM | J13: ServiceTitan | K13: 🔴 High | L13: Smart Fleet USA | M13: No — Smart Fleet USA | N13: Validate via FDD | O13: ❓ Unknown | P13: (Franchisee Owner) | Q13: Owner/Operator | R13: TBD — franchisee owner ⚠️ DO NOT approach — Neighborly PE intro required first KKR → Charles Layne → Felix Gernburd — PE intro only | S13: TBD — office manager Smart Fleet USA telematics (NOT GPS Insight) | T13: Smart Fleet USA (NOT GPS Insight) ⚠️ No warm GPS Insight intro path Do not approach without PE intro confirmed | W13: Profile + conflict check | Y13: High dispatch fit | Z13: Pull from Wisconsin/California FDD registry. Neighborly brand — verify ST mandate status first. | AA13: ⚠️ ST mandated — no FSM pitch. Telematics only if GPS Insight customer confirmed. Do not run Insight Engine until PE intro secured. | AE13: 19 | AF13: +5 | AG13: 24 ⚪ HOLD
A14: 11 | B14: Rainbow Restoration | C14: Neighborly | D14: Restoration | E14: 330 | F14: 5 | G14: Partial/ST | H14: TBD | I14: MED | J14: ServiceTitan | K14: 🔴 High | L14: Smart Fleet USA | M14: No — Smart Fleet USA | N14: Insurance dispatch + ProTradeNet broker | O14: 🔴 High | P14: (Franchisee Owner) | Q14: Owner/Operator | R14: TBD — franchisee owner ⚠️ DO NOT approach — Neighborly PE intro required first KKR → Charles Layne → Felix Gernburd — PE intro only | S14: TBD — office manager Smart Fleet USA telematics (NOT GPS Insight) | T14: Smart Fleet USA (NOT GPS Insight) ⚠️ No warm GPS Insight intro path Do not approach without PE intro confirmed | W14: Profile + conflict check | Y14: Event-driven restoration crews | Z14: Pull from Wisconsin/California FDD registry. Neighborly brand — verify ST mandate status first. | AA14: ⚠️ ST mandated — no FSM pitch. Telematics only if GPS Insight customer confirmed. Do not run Insight Engine until PE intro secured. | AE14: 39 | AF14: +5 | AG14: 44 ⚪ HOLD
A15: 12 | B15: Window Genie | C15: Neighborly | D15: Window/Exterior | E15: 200 | F15: 3 | G15: Partial/ST | H15: TBD | I15: MED | J15: ServiceTitan | K15: 🔴 High | L15: Smart Fleet USA | M15: No — Smart Fleet USA | N15: Validate via FDD | O15: ❓ Unknown | P15: (Franchisee Owner) | Q15: Owner/Operator | R15: TBD — franchisee owner ⚠️ DO NOT approach — Neighborly PE intro required first KKR → Charles Layne → Felix Gernburd — PE intro only | S15: TBD — office manager Smart Fleet USA telematics (NOT GPS Insight) | T15: Smart Fleet USA (NOT GPS Insight) ⚠️ No warm GPS Insight intro path Do not approach without PE intro confirmed | W15: Profile + conflict check | Y15: Seasonal recurring route | Z15: Pull from Wisconsin/California FDD registry. Neighborly brand — verify ST mandate status first. | AA15: ⚠️ ST mandated — no FSM pitch. Telematics only if GPS Insight customer confirmed. Do not run Insight Engine until PE intro secured. | AE15: 21 | AF15: +5 | AG15: 26 ⚪ HOLD
... A47: 44 | B47: Sir Grout | C47: Threshold Brands | D47: Tile/Grout | E47: 150 | F47: 3 | G47: Greenfield | H47: TBD | I47: MED | J47: Greenfield / Paper | K47: 🟢 None | L47: Validate with Andrea | M47: Validate with Andrea | N47: Validate via FDD | O47: ❓ Unknown | P47: (Franchisee Owner) | Q47: Owner/Operator | R47: TBD — franchisee owner/operator | S47: TBD — office manager / dispatcher | T47: TBD — verify GPS Insight customer status via Andrea | W47: Profile + outreach | Y47: Small crew tile/grout restoration | Z47: SOURCE: 2025 FDD — sharpsheets.io + franzimp.com ITEM 19 — Unit Economics: • Avg gross revenue: $482,000/location (sharpsheets) • Est. $366,058 (franchimp analysis) • 61 franchised locations, 20 states (2024 FDD) • Investment range: $120,930–$183,110 • Royalty: 7% + 2% marketing • Hard surface restoration — tile, grout, stone, caulking ITEM 11 — Technology: No specific FSM mandate found — GREENFIELD likely Project-based model (residential + commercial) National call center provided by Threshold Brands NOTE: Part of Threshold Brands (Riverside). Small brand — wait for franchisor mandate conversation before direct outreach | AA47: USE: ROI Calculator — PROJECT MODEL PRE-POPULATE: • Avg revenue/location: $482K • Project-based: avg job $500-$1,500 (hard surface restoration) • Estimate-to-invoice flow KEY ANGLES: • Digital estimates + photo capture • Same-day payment • $482K × 5% lift = $24K/location • Wait for Threshold mandate conversation first | AE47: 49 | AF47: +25 | AG47: 74 🟡 QUEUE
A48: 45 | B48: TruBlue | C48: Threshold Brands | D48: Handyman/Senior | E48: 100 | F48: 3 | G48: Greenfield | H48: TBD | I48: MED | J48: Greenfield / Paper | K48: 🟢 None | L48: Validate with Andrea | M48: Validate with Andrea | N48: Validate via FDD | O48: ❓ Unknown | P48: (Franchisee Owner) | Q48: Owner/Operator | R48: TBD — franchisee owner/operator | S48: TBD — office manager / dispatcher | T48: TBD — verify GPS Insight customer status via Andrea | W48: Profile + outreach | Y48: Home maintenance for seniors — recurring | Z48: SOURCE: 2025 FDD (2024 data) — franchisechatter.com + franchisepayback.com ITEM 19 — Unit Economics: • 104 franchises as of Dec 31, 2024 • 44 initial units reporting full year 2024 (continuous ownership) • Avg gross revenue: ~$319,000/location • Investment range: $70,000–$96,400 • Royalty: 6% gross revenues ($500/mo min yr 1; $1,000/mo thereafter) • National Branding Fee: 2% or $500/mo • Senior home care + handyman = recurring subscription model ITEM 11 — Technology: No specific FSM mandate found — GREENFIELD likely Home-based model — limited tech stack visible in public sources Senior care focus = appointment scheduling, 2-way SMS critical MODEL: Subscription/recurring services for seniors aging in place | AA48: USE: ROI Calculator — SUBSCRIPTION/RECURRING MODEL PRE-POPULATE: • Avg revenue/location: $319K • Recurring subscription model (weekly/monthly care visits) • Senior/handyman = avg job $150-$400 KEY ANGLES: • 2-way SMS job confirmations = critical for senior clients • Recurring scheduling automation • Job completion docs = family peace of mind • $319K × 5% lift = $16K/location • 104 locations × $16K = $1.7M system case • Riverside PE exit math — Threshold Year 4 | AE48: 49 | AF48: +25 | AG48: 74 🟡 QUEUE
A49: 46 | B49: JAN-PRO | C49: Empower Brands | D49: Commercial Cleaning | E49: 1000 | F49: 4 | G49: Greenfield | H49: TBD | I49: HIGH — Proprietary FSM mandated — $60/month tech fee, confirmed in FDD Item 8/11 | J49: Aspire (ST) possible | K49: 🟡 Medium | L49: Validate with Andrea | M49: Validate with Andrea | N49: Validate via FDD | O49: ❓ Unknown | P49: Gary Bauer | Q49: Brand President, JAN-PRO | R49: Gary Bauer Brand President, JAN-PRO Systems International 30+ yr ServiceMaster background. Knows Aspire inside out. ⚠️ Approach via Scott Zide (CEO Empower) — not direct | S49: TBD — regional developer contact | T49: No confirmed GPS Insight relationship ⚠️ JAN-PRO has proprietary FSM with $60/mo fee — conflict risk | W49: Gary Bauer direct outreach | Y49: 30+ yrs ServiceMaster background. PRIMARY brand wedge into Empower | Z49: SOURCE: assettfranchise.com analysis of 2024/2025 FDD ITEM 8/11: Proprietary software MANDATED with $60/month technology fee. Three-level structure: Empower → Regional Developer → Unit Franchisee. Mandate must come from Scott Zide (CEO) level. ⚠️ CONFLICT FLAG: Proprietary FSM already in place and fee built into cost structure. Confirm gap vs ServiceBridge functionality before outreach. | AA49: ⚠️ CONFLICT — proprietary FSM with $60/mo fee in FDD. DO NOT run standard Insight Engine pitch. If ServiceBridge can replace/augment at lower cost: Model the $60/mo saving × 11,265 units = $8.1M/yr cost elimination. | AE49: 48 | AF49: +15 | AG49: 63 🟡 QUEUE
A50: 47 | B50: Archadeck Outdoor Living | C50: Empower Brands | D50: Outdoor Living | E50: 100 | F50: 4 | G50: Greenfield | H50: TBD | I50: MED | J50: Greenfield / Paper | K50: 🟢 None | L50: Validate with Andrea | M50: Validate with Andrea | N50: Validate via FDD | O50: ❓ Unknown | P50: (Franchisee Owner) | Q50: Owner/Operator | R50: TBD — franchisee owner/operator | S50: TBD — office manager / dispatcher | T50: TBD — verify GPS Insight customer status via Andrea | W50: Profile + outreach | Y50: Project-based outdoor construction | Z50: SOURCE: Empower Brands + franchise directories 2025 ITEM 19 — Unit Economics: • Outdoor living + deck construction • Part of Empower Brands (MidOcean Partners) • High avg ticket — $30K-$100K+ per project • Investment range: est. $80K-$180K ITEM 11 — Technology: Empower Brands tech stack — verify FSM mandate Project-based construction model NOTE: 9 non-JAN-PRO Empower brands are GREENFIELD entry point. Scott Zide (CEO) + Michael Borreca (CFO) = top contacts | AA50: USE: ROI Calculator — HIGH TICKET PROJECT MODEL KEY ANGLES: • Digital estimates for large projects • GreenSky financing for $30K-$100K projects • Job photo documentation • Empower mandate = top-down play via Scott Zide | AE50: 46 | AF50: +15 | AG50: 61 🟡 QUEUE
A51: 48 | B51: Bumble Roofing | C51: Empower Brands | D51: Roofing | E51: 100 | F51: 5 | G51: Greenfield | H51: TBD | I51: NONE — Greenfield confirmed — Empower Brands, no FSM mandate found; roofing project model | J51: Greenfield / Paper | K51: 🟢 None | L51: Validate with Andrea | M51: Validate with Andrea | N51: Validate via FDD | O51: ❓ Unknown | P51: (Franchisee Owner) | Q51: Owner/Operator | R51: TBD — Bumble Roofing brand president ← Approach via Scott Zide (CEO Empower Brands) Fastest growing Empower brand in 2025 | S51: TBD | T51: No confirmed GPS Insight relationship | W51: Profile + outreach | Y51: Project-based roofing — estimate to invoice flow | Z51: SOURCE: Empower Brands + franchise directories 2025 ITEM 19 — Unit Economics: • Residential roofing franchise • Part of Empower Brands • High ticket: avg roof job $8K-$25K • Insurance + cash pay model ITEM 11 — Technology: Empower Brands tech stack — verify FSM mandate Insurance roofing = job documentation critical NOTE: Empower Brands. GREENFIELD entry point. | AA51: KEY ANGLES: • GreenSky financing for $8K-$25K jobs • Insurance job documentation • Empower mandate = top-down play | AE51: 56 | AF51: +15 | AG51: 71 🟡 QUEUE
A52: 49 | B52: Canopy Lawn Care | C52: Empower Brands | D52: Lawn Care | E52: 100 | F52: 4 | G52: Greenfield | H52: TBD | I52: NONE — Greenfield likely — Empower Brands, no mandate found; lawn care route model | J52: FieldRoutes possible | K52: 🟡 Medium | L52: Validate with Andrea | M52: Validate with Andrea | N52: Validate via FDD | O52: ❓ Unknown | P52: (Franchisee Owner) | Q52: Owner/Operator | R52: TBD — Canopy Lawn Care brand president ← Approach via Scott Zide (CEO Empower Brands) ⚠️ FieldRoutes conflict possible — verify first | S52: TBD | T52: No confirmed GPS Insight relationship | W52: Profile + outreach | Y52: Route-intensive lawn care — recurring | Z52: SOURCE: Empower Brands + franchise directories 2025 ITEM 19 — Unit Economics: • Lawn care + landscaping • Part of Empower Brands • Recurring route model ITEM 11 — Technology: Empower Brands tech stack — verify FSM mandate Route-based recurring model NOTE: Empower Brands. GREENFIELD entry point. | AA52: KEY ANGLES: • Route optimization • Empower mandate = top-down play | AE52: 51 | AF52: +15 | AG52: 66 🟡 QUEUE
A53: 50 | B53: Conserva Irrigation | C53: Empower Brands | D53: Irrigation | E53: 100 | F53: 3 | G53: Greenfield | H53: TBD | I53: MED | J53: Greenfield / Paper | K53: 🟢 None | L53: Validate with Andrea | M53: Validate with Andrea | N53: Validate via FDD | O53: ❓ Unknown | P53: (Franchisee Owner) | Q53: Owner/Operator | R53: TBD — franchisee owner/operator | S53: TBD — office manager / dispatcher | T53: TBD — verify GPS Insight customer status via Andrea | W53: Profile + outreach | Y53: Seasonal irrigation service | Z53: SOURCE: Empower Brands + franchise directories 2025 ITEM 19 — Unit Economics: • Irrigation system service + repair • Part of Empower Brands • Recurring maintenance + seasonal model ITEM 11 — Technology: Empower Brands tech stack Seasonal recurring model NOTE: Empower Brands. GREENFIELD entry point. | AA53: KEY ANGLES: • Seasonal scheduling + recurring • Empower mandate = top-down play | AE53: 46 | AF53: +15 | AG53: 61 🟡 QUEUE
A54: 51 | B54: FRSTeam | C54: Empower Brands | D54: Contents/Restoration | E54: 100 | F54: 5 | G54: Greenfield | H54: TBD | I54: MED | J54: Greenfield / Paper | K54: 🟢 None | L54: Validate with Andrea | M54: Validate with Andrea | N54: Validate via FDD | O54: ❓ Unknown | P54: (Franchisee Owner) | Q54: Owner/Operator | R54: TBD — franchisee owner/operator | S54: TBD — office manager / dispatcher | T54: TBD — verify GPS Insight customer status via Andrea | W54: Profile + outreach | Y54: Contents restoration crews | Z54: SOURCE: Empower Brands + franchise directories 2025 ITEM 19 — Unit Economics: • Fabric + textile restoration — insurance model • Part of Empower Brands • Insurance-paid contents restoration ITEM 11 — Technology: Empower Brands tech stack Insurance restoration = job documentation critical NOTE: Empower Brands. GREENFIELD entry point. | AA54: KEY ANGLES: • Insurance job documentation • Empower mandate = top-down play | AE54: 66 | AF54: +15 | AG54: 81 🟡 QUEUE
A55: 52 | B55: Koala Insulation | C55: Empower Brands | D55: Insulation | E55: 100 | F55: 4 | G55: Greenfield | H55: TBD | I55: MED | J55: Greenfield / Paper | K55: 🟢 None | L55: Validate with Andrea | M55: Validate with Andrea | N55: Validate via FDD | O55: ❓ Unknown | P55: (Franchisee Owner) | Q55: Owner/Operator | R55: TBD — franchisee owner/operator | S55: TBD — office manager / dispatcher | T55: TBD — verify GPS Insight customer status via Andrea | W55: Profile + outreach | Y55: Growing brand — newer in Empower portfolio | Z55: SOURCE: Empower Brands + franchise directories 2025 ITEM 19 — Unit Economics: • Insulation installation • Part of Empower Brands • High avg ticket: $2K-$10K per job • Fast-growing brand — energy efficiency market ITEM 11 — Technology: Empower Brands tech stack Project-based model NOTE: Empower Brands. GREENFIELD entry point. | AA55: KEY ANGLES: • GreenSky financing for insulation jobs • Energy efficiency angle (GreenSky green financing) • Empower mandate = top-down play | AE55: 46 | AF55: +15 | AG55: 61 🟡 QUEUE
A56: 53 | B56: Outdoor Lighting Perspectives | C56: Empower Brands | D56: Lighting | E56: 150 | F56: 3 | G56: Greenfield | H56: TBD | I56: MED | J56: Greenfield / Paper | K56: 🟢 None | L56: Validate with Andrea | M56: Validate with Andrea | N56: Validate via FDD | O56: ❓ Unknown | P56: (Franchisee Owner) | Q56: Owner/Operator | R56: TBD — franchisee owner/operator | S56: TBD — office manager / dispatcher | T56: TBD — verify GPS Insight customer status via Andrea | W56: Profile + outreach | Y56: Seasonal lighting — route + project mix | Z56: SOURCE: Empower Brands + franchise directories 2025 ITEM 19 — Unit Economics: • Outdoor lighting design + installation • Part of Empower Brands • High avg ticket: $3K-$15K per installation ITEM 11 — Technology: Empower Brands tech stack Project + seasonal model NOTE: Empower Brands. GREENFIELD entry point. | AA56: KEY ANGLES: • GreenSky for $3K-$15K installations • Empower mandate = top-down play | AE56: 46 | AF56: +15 | AG56: 61 🟡 QUEUE
A57: 54 | B57: Superior Fence & Rail | C57: Empower Brands | D57: Fence | E57: 100 | F57: 5 | G57: Greenfield | H57: TBD | I57: MED | J57: Greenfield / Paper | K57: 🟢 None | L57: Validate with Andrea | M57: Validate with Andrea | N57: Validate via FDD | O57: ❓ Unknown | P57: (Franchisee Owner) | Q57: Owner/Operator | R57: TBD — franchisee owner/operator | S57: TBD — office manager / dispatcher | T57: TBD — verify GPS Insight customer status via Andrea | W57: Profile + outreach | Y57: Project-based fencing | Z57: SOURCE: Empower Brands + franchise directories 2025 ITEM 19 — Unit Economics: • Fence installation franchise • Part of Empower Brands • High avg ticket: $3K-$10K+ per project • Fast-growing national brand ITEM 11 — Technology: Empower Brands tech stack Project-based install model NOTE: Empower Brands. GREENFIELD entry point. | AA57: KEY ANGLES: • Digital estimates + photo documentation • GreenSky for fence projects • Empower mandate = top-down play | AE57: 56 | AF57: +15 | AG57: 71 🟡 QUEUE
A58: 55 | B58: Wallaby Windows | C58: Empower Brands | D58: Window Cleaning | E58: 100 | F58: 3 | G58: Greenfield | H58: TBD | I58: MED | J58: Greenfield / Paper | K58: 🟢 None | L58: Validate with Andrea | M58: Validate with Andrea | N58: Validate via FDD | O58: ❓ Unknown | P58: (Franchisee Owner) | Q58: Owner/Operator | R58: TBD — franchisee owner/operator | S58: TBD — office manager / dispatcher | T58: TBD — verify GPS Insight customer status via Andrea | W58: Profile + outreach | Y58: Exterior window cleaning — route model | Z58: SOURCE: Empower Brands + franchise directories 2025 ITEM 19 — Unit Economics: • Window installation + replacement • Part of Empower Brands • High avg ticket: $5K-$20K per job ITEM 11 — Technology: Empower Brands tech stack Project-based install model NOTE: Empower Brands. GREENFIELD entry point. | AA58: KEY ANGLES: • GreenSky for $5K-$20K window projects • Empower mandate = top-down play | AE58: 48 | AF58: +15 | AG58: 63 🟡 QUEUE
A59: 56 | B59: RooterMan | C59: Premium Service Brands | D59: Plumbing | E59: 300 | F59: 5 | G59: Greenfield | H59: TBD | I59: NONE — Greenfield likely — PSB brand, no specific FSM mandate found; plumbing dispatch | J59: Greenfield / Paper | K59: 🟢 None | L59: Validate with Andrea | M59: Validate with Andrea | N59: Validate via FDD | O59: ❓ Unknown | P59: (TBD — Research) | Q59: Brand President | R59: TBD — RooterMan brand president ← Approach via Paul Flick (Founder & CEO, PSB) or Roxanne Conrad (COO, PSB) PSB acquired RooterMan. 776+ locations. Franchise 500 #298 in 2025. | S59: TBD — RooterMan ops contact at PSB level Gabe Colon — EVP of Performance, PSB (franchisee training) | T59: No confirmed GPS Insight relationship Verify via Andrea before outreach | W59: Research brand president then outreach | Y59: 300 locations — BRAND WEDGE into PSB. Find brand president first | Z59: SOURCE: PSB + franchise directories 2025 ITEM 19 — Unit Economics: • Plumbing + drain services franchise • Part of PSB portfolio • Emergency dispatch + recurring maintenance • Investment range: est. $70K-$130K ITEM 11 — Technology: PSB CRM-based — verify FSM overlap Emergency dispatch model NOTE: PSB portfolio. One PSB win = access to all 8 brands | AA59: KEY ANGLES: • Emergency dispatch optimization • Same-day service + payment • PSB portfolio play | AE59: 61 | AF59: +15 | AG59: 76 🟡 QUEUE
A60: 57 | B60: 360 Painting | C60: Premium Service Brands | D60: Painting | E60: 300 | F60: 4 | G60: Greenfield | H60: TBD | I60: VERIFY — PSB uses proprietary CRM for job tracking — confirm overlap with ServiceBridge FSM before outreach | J60: Greenfield / Paper | K60: 🟢 None | L60: Validate with Andrea | M60: Validate with Andrea | N60: Validate via FDD | O60: ❓ Unknown | P60: (Franchisee Owner) | Q60: Owner/Operator | R60: TBD — 360 Painting brand president ← Approach via Paul Flick (CEO PSB) Roxanne Conrad was a 360 Painting franchisee before joining as COO PSB | S60: Roxanne Conrad COO, Premium Service Brands (former 360 Painting franchisee — knows the brand inside out) | T60: No confirmed GPS Insight relationship | W60: Profile + outreach | Y60: Large painting network | Z60: SOURCE: 2025 FDD (2024 data) — franchisechatter.com + franchimp.com ITEM 19 — Unit Economics: • 86 franchisees / 102 franchised businesses reporting full year 2024 • 2024 gross sales total: $48,598,055 (86 franchisees) • Avg gross sales/franchised business: ~$476,451 • Avg est per unit: $433,123-$516,000 depending on source • 102 total units, 191 total (including non-reporting) • Investment range: $101,350-$145,000 • Royalty: 6% gross sales + national marketing fee • Residential + light commercial painting ITEM 11 — Technology: 360 Painting uses PROPRIETARY CRM — franchisees required to submit jobs FDD notes 25.63% of jobs NOT submitted through CRM CONFLICT RISK: Medium — CRM may overlap with ServiceBridge FSM functions PSB parent manages technology centrally across all brands | AA60: VERIFY: PSB CRM overlap with ServiceBridge — confirm with Roxanne Conrad PRE-POPULATE: • Avg revenue/unit: $476K • Project-based: avg paint job $2,000-$8,000 • 102 units KEY ANGLES: • Digital estimates + photo before/after • GreenSky for larger interior/exterior projects • Job completion documentation • $476K x 5% lift = $24K/unit • PSB portfolio play — if one brand signs, others follow • Susquehanna PE exit math | AE60: 46 | AF60: +15 | AG60: 61 🟡 QUEUE
... A81: 78 | B81: Monty's Handyman | C81: ResiBrands | D81: Handyman | E81: 50 | F81: 3 | G81: Greenfield | H81: TBD | I81: MED | J81: Greenfield / Paper | K81: 🟢 None | L81: Validate with Andrea | M81: Validate with Andrea | N81: Validate via FDD | O81: ❓ Unknown | P81: (Franchisee Owner) | Q81: Owner/Operator | R81: TBD — franchisee owner/operator | S81: TBD — office manager / dispatcher | T81: TBD — verify GPS Insight customer status via Andrea | W81: Profile + outreach | Y81: Newest ResiBrands launch 2025 | Z81: SOURCE: Franchise directories 2025 ITEM 19 — Unit Economics: • Handyman services • Independent brand • Multi-service dispatch model ITEM 11 — Technology: Unknown — verify FSM status NOTE: Independent brand. Lower priority. | AA81: KEY ANGLES: • Multi-service scheduling • 2-way SMS | AE81: 49 | AF81: +15 | AG81: 64 🟡 QUEUE

Sheet Engagement Log
A1: CRM · ENGAGEMENT LOG · Every Touchpoint · Every Response · ServiceBridge GTM
A2: Velocity GTM Co LLC · One row per interaction · Log calls, emails, LinkedIn, meetings · Verbatim feedback captured per contact
A3: Track 1 = Franchisor accounts (green rows) Track 2 = Franchisee accounts (blue rows) | I3: GPS Insight ▸ items (blue) require Charles, Garrett, Andrea, or Angie involvement · New event types added: Conference/Industry Event · Franchisor Annual Convention · Trade Show · Event Follow-Up · Referral from Event
A4: LOG # | B4: DATE | C4: TRACK | D4: ACCOUNT / BRAND | E4: CONTACT NAME | F4: CONTACT TITLE | G4: CHANNEL | H4: TYPE | I4: OUTCOME | J4: THEIR FEEDBACK (Verbatim) | K4: OBJECTIONS RAISED | L4: GPS INSIGHT ACTION NEEDED | M4: YOUR NEXT STEP | N4: NEXT DATE | O4: STATUS | P4: INTERNAL NOTES
A5: 1 | B5: 2026-04-07 | C5: Track 1 | D5: BELFOR | E5: Rusty Amarante, CR | F5: President, BELFOR FG | G5: LinkedIn | H5: First Touch | I5: No Response | L5: 📞 On me — asking Charles. GPS Insight to surface the American Securities connection through AKKR. | M5: Follow up LinkedIn Day 5 — send connection + note referencing HOODZ Triangle award winner (local NC connection) | N5: 2026-04-14 | O5: Contacted | P5: Connection request sent. Personalized msg referencing 14-brand network + Dec 2024 territory growth.
A6: 2 | B6: 2026-04-07 | C6: Track 1 | D6: NEIGHBORLY | E6: Charles Layne | F6: CEO, GPS Insight | G6: Phone Call | H6: Discovery Call | I6: Call Complete | J6: Charles confirmed he'll reach out to Accel-KKR deal team re: KKR/Neighborly intro this week. | L6: GPS: Charles initiating Accel-KKR → KKR → Felix Gernburd intro | M6: Follow up Charles today (Apr 14) on KKR intro status | N6: 2026-04-14 | O6: Pending GPS Action | P6: Critical call. Charles confirmed. KKR intro is the #1 GPS action Week 1.
A7: 3 | B7: 2026-04-08 | C7: Track 1 | D7: EMPOWER BRANDS | E7: Scott Zide | F7: CEO, Empower Brands | G7: LinkedIn | H7: First Touch | I7: No Response | M7: Follow-up email with Empower ROI model attached | N7: 2026-04-13 | O7: Contacted | P7: Connection request sent. EBITDA before exit window — MidOcean narrative.
A8: 4 | B8: 2026-04-09 | C8: Track 2 | D8: RooterMan | E8: (TBD) | F8: Brand President, RooterMan | G8: LinkedIn | H8: First Touch | I8: No Response | M8: Research brand president name first | N8: 2026-04-11 | O8: Researching | P8: find RooterMan brand president name before outreach. Check PSB website.
A9: 5 | B9: 2026-04-09 | C9: Track 1 | D9: RESIBRANDS | E9: Steven Montgomery | F9: Founder & CEO, ResiBrands | G9: LinkedIn | H9: First Touch | I9: Replied – Positive | J9: Steven replied within 2 hours. Said he is interested in seeing the ops stack comparison. Asked to set up a call. | M9: Prep ResiBrands Insight Engine ROI model. Load: 2,550 techs, $200/job, 5 jobs/day. Run conservative + base scenarios only. | N9: 2026-04-15 | O9: Call Scheduled — 🔥 HOT | P9: 🔥 HOT LEAD. Fastest response. Founder-backed — decision comes fast. Prep ResiBrands ROI model before call.
A10: 6 | B10: 2026-04-14 | C10: Track 1 | D10: BELFOR | E10: Rusty Amarante, CR | F10: President, BELFOR FG | G10: LinkedIn | H10: Follow-Up Touch | I10: Pending | L10: 📞 On me — Charles to surface American Securities / Accel-KKR path | M10: Send follow-up note referencing HOODZ Triangle Franchise of Year + 30 new territories Dec 2024 | N10: 2026-04-14 | O10: Queued | P10: Use local NC angle: HOODZ of the Triangle just won BELFOR FoY. Personal connection point.
A11: 7 | B11: 2026-04-14 | C11: Track 1 | D11: NEIGHBORLY | E11: Charles Layne | F11: CEO, GPS Insight | G11: Text/Call | H11: GPS Action Follow-Up | I11: Pending | L11: GPS: Charles → Accel-KKR → KKR → Felix Gernburd. TODAY is follow-up day. | M11: Confirm KKR intro status from Charles. This is #1 GPS action. | N11: 2026-04-14 | O11: GPS Action Due | P11: Charles confirmed Apr 7. Two-week follow window. Do not let this slip.
A12: 8 | B12: 2026-04-15 | C12: Track 1 | D12: RESIBRANDS | E12: Steven Montgomery | F12: Founder & CEO, ResiBrands | G12: Phone/Video | H12: Discovery Call | I12: Scheduled | J12: Replied positive Apr 9. Wants ops stack comparison. | M12: Prep Insight Engine: 2,550 techs, $200/job. Run conservative + base. Print 3-Way Scenario. | N12: 2026-04-15 | O12: Call Scheduled — 🔥 | P12: First Tier 1 call. Founder-backed — decision comes fast. Lead with $1.67/tech/day message. Have Insight Engine open.
A13: 9 | B13: 2026-04-15 | C13: Track 1 | D13: EMPOWER BRANDS | E13: Scott Zide | F13: CEO, Empower Brands | G13: Email | H13: Follow-Up Email | I13: Pending | M13: Send follow-up email. Attach Insight Engine 3-Way Scenario pre-populated for 9 non-JAN-PRO brands. MidOcean exit window angle. | N13: 2026-04-15 | O13: Queued | P13: Connection sent Apr 8. No response. Follow up via email referencing Ignite conference 'Accelerate Growth' theme.
A14: 10 | B14: 2026-04-16 | C14: Track 1 | D14: HOMEFRONT BRANDS | E14: Jeff Dudan | F14: Chairman & CEO, HomeFront Brands | G14: LinkedIn | H14: First Touch | I14: Pending | M14: Connection request + note referencing Forbes contributor work + Homecoming 4 vendor opportunity | N14: 2026-04-16 | O14: Queued | P14: Podcaster/Forbes angle — lead with content, not pitch. Reference Homecoming 4 vendor path. Window Hero brand wedge.
A15: 11 | B15: 2026-04-17 | C15: Track 1 | D15: FIVE STAR FRANCHISING | E15: Scott Abbott | F15: CEO & Co-Founder | G15: LinkedIn | H15: First Touch | I15: Pending | M15: Connection + note referencing HSS 2026 'Home Services Summit' + Princeton Equity Year 5 framing | N15: 2026-04-17 | O15: Queued | P15: Lead with HSS energy + Mosquito Shield as brand wedge. Princeton Equity Year 5 = exit window. CFO Steve White is the numbers conversation.
A16: 12 | B16: 2026-04-18 | C16: Track 1 | D16: THRESHOLD BRANDS | E16: Andrea Hohermuth | F16: COO, Threshold Brands | G16: LinkedIn | H16: First Touch | I16: Pending | L16: GPS: Riverside PE → Charles Layne intro path | M16: Verify Hagan Kappler CEO status first. If confirmed: approach CEO. If not: COO Andrea Hohermuth is primary. | N16: 2026-04-18 | O16: Queued | P16: ⚠️ Verify Hagan Kappler still CEO before outreach. Use unfulfilled tech promise angle. ServiceBridge = what Threshold promised franchisees.
A17: 13 | B17: 2026-04-19 | C17: Track 2 | D17: 1-800 Water Damage | E17: Local franchisee (TBD) | F17: Owner/Operator | G17: Phone | H17: Warm Outreach | I17: Pending | L17: 📋 Getting GPS Insight telematics customer list from Andrea — cross-reference BELFOR first | M17: Identify 2-3 GPS Insight telematics customers within BELFOR network. These are warmest Track 2 calls. | N17: 2026-04-19 | O17: Waiting on Andrea | P17: GPS warm flag confirmed for BELFOR network. Andrea's telematics list unlocks the warm Track 2 path.
A18: 14 | B18: 2026-04-21 | C18: Track 1 | D18: AUTHORITY BRANDS | E18: Tij Bedi | F18: CTO, Authority Brands | G18: LinkedIn | H18: First Touch | I18: Pending | L18: GPS: Apax Partners → Charles Layne for PE intro before direct outreach | M18: Research Tij Bedi LinkedIn profile. Connect referencing 9 non-ST brands + tech infrastructure build mandate. | N18: 2026-04-21 | O18: Queued | P18: Joined Aug 2024. Building tech infrastructure from scratch for 9 greenfield brands. CTO = tech champion, not gatekeeper. Direct outreach appropriate.
A19: 15 | B19: 2026-04-21 | C19: Track 2 | D19: That 1 Painter | E19: Steven Montgomery | F19: Founder & CEO, ResiBrands | G19: Discovery Call | H19: Brand Discussion | I19: Pending | M19: If ResiBrands call goes well Apr 15 — expand to That 1 Painter specifically. 800+ territories. | N19: 2026-04-21 | O19: Post-Call Action | P19: 800+ territories. ResiConnect handles scheduling. ServiceBridge handles field. Position as complement.
A20: 16 | B20: 2026-04-22 | C20: Track 1 | D20: PREMIUM SERVICE BRANDS | E20: Paul Flick | F20: Founder & CEO, PSB | G20: LinkedIn | H20: First Touch | I20: Pending | M20: Connection + note referencing RooterMan 300-location plumbing network as entry point | N20: 2026-04-22 | O20: Queued | P20: RooterMan = 300 locations = largest PSB brand by location count. PSB is greenfield across all 8 brands.
A21: 17 | B21: 2026-04-25 | C21: Track 1 | D21: BELFOR | E21: Sheldon Yellen | F21: CEO, BELFOR Holdings | G21: PE Path | H21: PE Intro Research | I21: Pending | L21: GPS: American Securities → Charles Layne → PE warm intro. Do NOT approach Sheldon direct. | M21: Charles to map American Securities connection. Sheldon approached only via PE intro, not cold. | N21: 2026-04-25 | O21: Waiting on GPS | P21: Sheldon Yellen is the top-of-house decision maker. American Securities backed. Charles Layne must own this intro path.
A22: 18 | B22: 2026-04-28 | C22: Track 2 | D22: DUCTZ | E22: Local franchisee (TBD) | F22: Owner/Operator | G22: Phone | H22: Track 2 Warm Outreach | I22: Pending | L22: 📋 Cross-reference GPS Insight telematics list — DUCTZ route model = strong dispatch fit | M22: Target GPS Insight telematics customers in DUCTZ network. Route-based duct cleaning = repeatable dispatch pattern. | N22: 2026-04-28 | O22: Waiting on Andrea | P22: DUCTZ is recurring route model — annual duct cleanings. Strong ServiceBridge fit. GPS warm flag may unlock direct intro.
A23: 19 | B23: 2026-04-28 | C23: Track 1 | D23: EMPOWER BRANDS | E23: Gary Bauer | F23: Brand President, JAN-PRO | G23: LinkedIn | H23: Brand Wedge Touch | I23: Pending | M23: Connect referencing Ignite conference + JAN-PRO's 30+ year ServiceMaster background. Discuss Aspire conflict carefully. | N23: 2026-04-28 | O23: Queued | P23: ⚠️ JAN-PRO has proprietary FSM. Gary Bauer comes from ServiceMaster — knows Aspire. Approach as conversation, not pitch. Focus on gap between what JAN-PRO has vs ServiceBridge capability.
A24: 20 | B24: 2026-05-01 | C24: Track 2 | D24: Top Rail Fence | E24: Zack Dudan | F24: CGO, HomeFront Brands | G24: Event | H24: Homecoming 4 Vendor Research | I24: Pending | M24: Research HomeFront Homecoming 4 vendor registration process. Target Nov 2026 Orlando. | N24: 2026-05-01 | O24: Research | P24: Top Rail Fence was Homecoming 3 Franchisee of the Year. Zack Dudan (CGO) runs vendor relationships. Homecoming 4 = still time to get in as vendor.
A25: 21 | B25: 2026-04-14 | C25: Internal | D25: GPS Insight / ServiceBridge | E25: Andrea Rowan | F25: GM, ServiceBridge | G25: Internal | H25: Reference Validation | I25: Action Required | L25: 📋 On me — GPS Insight to review ALL current ServiceBridge testimonials and case studies. SB ADVANTAGE DOC ALREADY CONTAINS: 1. Robertson Pools (Dallas-Fort Worth TX) — Kelli Griffin, Service Manager Results: 64% revenue growth · 2pt net profit increase · Week 1 platform ROI 2. Critter Control (National Franchise Network) — Joe Felegi, President Results: Headcount-neutral growth · Improved lead-to-sale ratio · Eliminated daily office visits 3. Master Mastic (Regional Operator) — Brian Stilwell, Owner Results: 2x sales growth · Reduced admin overhead · Eliminated QB double-entry ACTION: Andrea to confirm: a) Are these three clients still active and referenceable? b) Can their names/results be used in franchise prospect meetings? c) Are there any additional ServiceBridge clients (especially restoration, plumbing, pest control) that could serve as references for BELFOR/PSB/Empower outreach? d) Does GPS Insight have any existing BELFOR network telematics customers who could serve as a warm pilot candidate? | M25: Once references confirmed — populate Trade Reference tab in Insight_Engine_Excel_v3.xlsx with real client data to validate Insight Engine benchmarks before Rusty Amarante meeting. | N25: 2026-04-18 | O25: GPS Action Due | P25: Robertson Pools: 64% revenue growth. Critter Control: headcount-neutral growth. Master Mastic: 2x sales. All three in SB Advantage doc already. These are the pilot reference conversation starters. Validate referenceable status before using in any prospect conversation.
A81: 77 | B81: 2026-04-14 | C81: Internal | D81: GPS Insight / ServiceBridge | E81: Charles Layne | F81: CEO, GPS Insight | G81: LinkedIn / Internal | H81: Product Update | I81: Received | J81: Charles shared Spring Release: 3 new features — Smart Scheduler (AI dispatch), Job Confirmations (2-way SMS), GreenSky® Consumer Financing. | L81: 📋 GPS ACTION — three things: 1. Brief Mike on how Smart Scheduler works in franchise context 2. Confirm GreenSky® eligibility for franchise mandate pricing 3. Confirm third-party telematics API status (Samsara/VC/Geotab) — does ServiceBridge accept third-party telematics data via API? | M81: Incorporate Spring Release features into Insight Engine pitch and Engagement Ideas scripting. Smart Scheduler is the biggest GTM story — AI-driven dispatch is exactly what the 'orchestration' positioning needs. | N81: 2026-04-18 | O81: GPS Action Due | P81: Spring Into Smarter Service 🌸 release. Charles shared via LinkedIn Apr 11. Three features: Smart Scheduler (AI), Job Confirmations (2-way SMS), GreenSky® financing. All relevant to franchise pitch.
A82: 78 | B82: 2026-04-14 | C82: Internal | D82: GPS Insight / ServiceBridge | E82: Andrea Rowan | F82: GM, ServiceBridge | G82: Internal | H82: Product Verification | I82: Action Required | L82: 📋 GPS ACTION — Critical product question before scripting: Does ServiceBridge support third-party telematics providers via API? Confirmed native integrations: GPS Insight + ClearPathGPS ONLY. Specific question: Can ServiceBridge ingest location/vehicle data from: • Samsara (Neighborly Smart Fleet network uses Samsara-adjacent tech) • Verizon Connect • Geotab • Motive Answer materially changes pitch for any account NOT on GPS Insight telematics. Two-pitch framework until answered: PITCH A (GPS Insight customers): Full Ownership + Orchestration story PITCH B (Other telematics): ServiceBridge FSM standalone → GPS Insight at telematics renewal | M82: Confirm with Andrea/product team before scripting any account on Samsara/VC/Geotab. | N82: 2026-04-18 | O82: GPS Action Due | P82: This answer changes the pitch for Authority Brands, Five Star, HomeFront, and any other account with existing non-GPS Insight telematics.

Sheet Account Feedback
A1: ACCOUNT FEEDBACK CARDS · Pipeline Status by Account · Updated Weekly
A2: Velocity GTM Co LLC · One row per account · Status, touch count, verbatim feedback, objections, temperature · Friday report to GPS Insight
A3: ACCOUNT | B3: TRACK | C3: STATUS | D3: # TOUCHES | E3: LAST CONTACT | F3: LAST OUTCOME | G3: KEY FEEDBACK (Their Words) | H3: OBJECTIONS RAISED | I3: TEMPERATURE | J3: NEXT MILESTONE
A4: BELFOR | B4: P2 Set | C4: Researching | D4: 1 | E4: 2026-04-14 | F4: LinkedIn — no response yet | G4: No response to LinkedIn yet | I4: 🌡 Warming | J4: GPS PE intro via American Securities → Charles Layne. Meanwhile: HOODZ Triangle FoY local angle. Insight Engine pre-loaded: $4,500/job, 40% carrier-referred, $4.3M system EBITDA case.
A5: THRESHOLD BRANDS | B5: P2 Set | C5: Researching | D5: 0 | F5: Not contacted yet | G5: ⚠️ Must verify Hagan Kappler CEO status before outreach | I5: ❄ Cold | J5: Unfulfilled tech promise = ServiceBridge delivers what they promised. Andrea Hohermuth (COO) is backup primary if Kappler unconfirmed. Riverside PE intro path via Charles.
A6: EMPOWER BRANDS | B6: Track 1 | C6: Contacted | D6: 1 | E6: 2026-04-08 | F6: LinkedIn — no response | G6: ⚠️ JAN-PRO proprietary FSM conflict. Lead with 9 greenfield brands only. | I6: ❄ Cold | J6: Follow-up email Apr 15 with Insight Engine 3-Way Scenario for 9 non-JAN-PRO brands. MidOcean exit window angle for Scott Zide. Gary Bauer (JAN-PRO) is separate conversation.
A7: PREMIUM SERVICE BRANDS | B7: Track 1 | C7: Not Started | D7: 0 | F7: Not contacted yet | G7: RooterMan brand president name TBD — research needed | I7: ❄ Cold | J7: RooterMan = 300 locations = best entry point. Paul Flick is founder — accessible. Full greenfield across all 8 PSB brands.
A8: RESIBRANDS | B8: Track 1 | C8: Call Scheduled | D8: 2 | E8: 2026-04-09 | F8: LinkedIn — Replied Positive within 2 hours | G8: Steven replied: interested in ops stack comparison. Call Apr 15. | H8: None raised | I8: 🔥 Hot | J8: BEST LEAD IN PIPELINE. Founder-backed = fast decision. Prep Insight Engine conservative scenario: $1.67/tech/day message. Target: close pilot agreement on first or second call.
A9: FIVE STAR FRANCHISING | B9: Track 1 | C9: Not Started | D9: 0 | F9: Not contacted yet | G9: Check FieldRoutes conflict on Mosquito Shield before outreach | I9: ❄ Cold | J9: Princeton Equity Year 5 = exit window opening. Scott Abbott (CEO) + Steve White (CFO) dual-track. Mosquito Shield brand wedge — verify FieldRoutes first.
A10: HOMEFRONT BRANDS | B10: Track 1 | C10: Not Started | D10: 0 | F10: Not contacted yet | G10: ⚠️ Franchisee satisfaction issues flagged Dec 2025. Verify system health first. | I10: ❄ Cold | J10: Jeff Dudan is podcaster + Forbes contributor — use content angle first. Homecoming 4 vendor path = highest leverage. Window Hero (Tyler Kirk) is brand-level wedge.
A11: AUTHORITY BRANDS | B11: Track 1 | C11: Not Started | D11: 0 | F11: Not contacted yet | G11: 9 non-ST brands = greenfield. Tij Bedi (CTO) is primary contact. | I11: ❄ Cold | J11: ST mandated for 3 brands only. 9 brands fully greenfield. Tij Bedi hired Aug 2024 to build tech infrastructure — ServiceBridge is exactly what he needs. GPS Apax Partners intro path via Charles.
A12: NEIGHBORLY | B12: Track 1 | C12: GPS Action Pending | D12: 1 | E12: 2026-04-07 | F12: Charles Layne confirmed KKR intro path | G12: Charles confirmed Accel-KKR → KKR → Felix Gernburd intro | H12: ST mandate locked | I12: 🌡 Warming | J12: DO NOT approach direct. PE intro only. Charles follow-up today (Apr 14) on KKR intro status. ST renewal window 2025-2027 is the leverage point.
A13: BELFOR (franchise network) | B13: Track 2 | C13: Researching | D13: 0 | F13: Waiting on Andrea telematics list | G13: Need GPS Insight telematics customer list from Andrea | I13: 🌡 Warming | J13: Full greenfield across all 14 brands. GPS Insight warm flag confirmed. Andrea's telematics list = warmest Track 2 calls. 1-800 WD Insight Engine pre-loaded with FDD data.
A14: That 1 Painter (ResiBrands) | B14: Track 2 | C14: Pending | D14: 0 | F14: Waiting on ResiBrands call (Apr 15) | G14: Steven Montgomery is the decision-maker for all ResiBrands | I14: 🌡 Warming | J14: 800+ territories. ResiConnect = scheduling only. ServiceBridge = field ops layer. Position as complement not replacement. Follow ResiBrands call Apr 15 with specific That 1 Painter pilot proposal.
A15: JAN-PRO (Empower) | B15: Track 2 | C15: Researching | D15: 0 | F15: Not contacted yet | G15: ⚠️ $60/month proprietary tech fee in FDD. Conflict flag. | H15: Proprietary FSM conflict | I15: ❄ Cold | J15: Approach via Scott Zide (CEO) level only. Gary Bauer (30yr ServiceMaster background) is brand president. Model the $8.1M/yr system cost elimination if ServiceBridge replaces proprietary platform.
A16: RooterMan (PSB) | B16: Track 2 | C16: Researching | D16: 0 | F16: Brand president name TBD | G16: Must find brand president name before outreach | I16: ❄ Cold | J16: 300 locations. Plumbing dispatch. Entry point for full PSB conversation with Paul Flick. Full greenfield — no FSM mandate.
A17: Mosquito Shield (Five Star) | B17: Track 2 | C17: Researching | D17: 0 | F17: Not contacted yet | G17: ⚠️ FieldRoutes (ServiceTitan subsidiary) may be in use — verify first | H17: FieldRoutes possible conflict | I17: ❄ Cold | J17: Michael Moorhouse is Brand President. Route/recurring model — strong dispatch fit IF FieldRoutes not mandated. Verify via Five Star FDD before outreach.
A18: Window Hero (HomeFront) | B18: Track 2 | C18: Not Started | D18: 0 | F18: Not contacted yet | G18: HomeFront Homecoming 4 is the vendor entry path — Nov 2026 | I18: ❄ Cold | J18: Tyler Kirk is founder. Jeff Dudan connection. Homecoming 4 vendor registration = right path. Small exterior cleaning crew — simple FSM pitch.
A19: MaidPro (Threshold) | B19: Track 2 | C19: Not Started | D19: 0 | F19: Not contacted yet | G19: MaidPro had proprietary scheduling software pre-Threshold acquisition | H19: Proprietary system possible | I19: ❄ Cold | J19: Largest Threshold brand by location. Proprietary system status post-acquisition unclear. Threshold unfulfilled tech promise = ServiceBridge opportunity.
A20: USA Insulation (Threshold) | B20: Track 2 | C20: Not Started | D20: 0 | F20: Not contacted yet | G20: ⚠️ AT-RISK: 75% SB penetration transitioning off over next year (Andrea Apr 2026). Retention play — defend if reversible. | I20: ❄ Cold | J20: Insulation install = project-based. Estimate → schedule → install → invoice flow. Strong FSM fit for job documentation.
A21: Mosquito Joe (Neighborly) | B21: Track 2 | C21: Researching | D21: 0 | F21: Not contacted yet | G21: ⚠️ Neighborly brand — ST or FieldRoutes mandate. Check before outreach. | H21: ST/FieldRoutes mandate likely | I21: ❄ Cold | J21: Smart Fleet USA confirmed telematics. Route recurring model. Do not approach until Neighborly PE intro confirmed.
A22: Mr. Rooter (Neighborly) | B22: Track 2 | C22: Researching | D22: 0 | F22: Not contacted yet | G22: ServiceTitan required per FDD. GPS Insight telematics angle only. | H22: ST mandated since 2012 | I22: ❄ Cold | J22: 188 reporting franchisees (2025 FDD). Smart Fleet USA telematics. No FSM displacement angle. GPS Insight only if confirmed customer.
A23: Benjamin Franklin Plumbing (Authority) | B23: Track 2 | C23: Researching | D23: 0 | F23: Not contacted yet | G23: ServiceTitan mandate announced Sep 2024. High conflict risk. | H23: ST mandated Sep 2024 | I23: ❄ Cold | J23: ST mandated — do not pitch ServiceBridge as FSM. GPS Insight telematics only if Andrea confirms as customer.
A24: GarageUp (ResiBrands) | B24: Track 2 | C24: Pending | D24: 0 | F24: Waiting on ResiBrands call (Apr 15) | G24: ResiConnect handles scheduling only — field ops greenfield | I24: 🌡 Warming | J24: Route + project mix. Strong dispatch fit — garage door service = emergency + scheduled. Part of ResiBrands — Steven Montgomery decides.
A25: Bumble Roofing (Empower) | B25: Track 2 | C25: Not Started | D25: 0 | F25: Not contacted yet | G25: Part of Empower — approach via Scott Zide mandate first | I25: ❄ Cold | J25: Project roofing — estimate to invoice workflow. Greenfield. No FSM named in FDD. Fastest growing Empower brand 2025.
A26: 360 Painting (PSB) | B26: Track 2 | C26: Not Started | D26: 0 | F26: Not contacted yet | G26: Part of PSB — approach via Paul Flick mandate first | I26: ❄ Cold | J26: Large painting network. Project-based — quote, schedule, crews, invoice. Greenfield — no FSM mandate.
A27: Canopy Lawn Care (Empower) | B27: Track 2 | C27: Researching | D27: 0 | F27: Not contacted yet | G27: ⚠️ Lawn care = FieldRoutes (ST subsidiary) possible. Verify FDD first. | H27: FieldRoutes possible conflict | I27: ❄ Cold | J27: Route-intensive recurring lawn model. FieldRoutes is dominant in this trade. Verify before any outreach.
A28: Top Rail Fence (HomeFront) | B28: Track 2 | C28: Not Started | D28: 0 | F28: Not contacted yet | G28: Homecoming 3 Franchisee of the Year 2025 — warm brand reputation | I28: ❄ Cold | J28: Project fencing. Homecoming 4 vendor path = right entry. FoY winner builds credibility for vendor conversation.
A29: GPS Insight — Testimonial Review | B29: Internal | C29: Action Required | D29: 0 | E29: 2026-04-14 | F29: Action assigned | G29: SB Advantage already contains 3 references: Robertson Pools (64% rev growth), Critter Control (national franchise — headcount-neutral), Master Mastic (2x sales). Confirm referenceable status. | H29: None — internal action | I29: 🌡 Action Due | J29: Andrea to confirm: (1) all 3 references still active + referenceable, (2) any additional restoration/plumbing/pest clients for franchise outreach, (3) BELFOR telematics customers for pilot candidate identification. Populate Trade Reference tab in Insight Engine once confirmed.

Sheet Field Guide
A1: SERVICEBRIDGE GTM ENGAGEMENT TRACKER · Field Guide & Reference
A2: Prepared by Velocity GTM Co LLC · Michael Montgomery Flynt Jr · In Partnership with GPS Insight / ServiceBridge · April 2026
B4: WHAT THIS FILE IS
B5: This is your complete GTM command center for the ServiceBridge franchise engagement. It replaces a CRM for this engagement. Every franchisor, every franchisee brand, every call, email, and meeting lives here. Keep it open. Update it in real time. On Friday, the Account Feedback Cards tab is your weekly status report to Andrea.
B7: THE 4 TABS · What Each One Does
B9: Tab 1 · Top 9 Franchisors
B10: Your Track 1 enterprise pipeline. One row per franchisor account. Shows CEO, CFO, COO, and BD lead for each account. Use this to track which franchisors are in active conversation, what your next step is, and whether you need GPS Insight involvement. GPS Insight items are highlighted in blue.
B12: Tab 2 · 85 Franchisees
B13: Your Track 2 greenfield volume pipeline. All 85 brands sorted by parent franchisor so you can see each group together. Each brand shows FSM status, GPS warm flag, pilot potential score, contact, and outreach status. Start with HIGH pilot potential and YES GPS warm accounts first.
B15: Tab 3 · CRM · Engagement Log
B16: One row per touchpoint. Every call, email, LinkedIn message, and meeting gets its own row. Log what you did, what channel, what they said verbatim, any objections, and your next step. This is the source of truth for your engagement history. Add a row every time you make contact.
B18: Tab 4 · Account Feedback Cards
B19: One row per account — your quick-read summary view. Shows current status, touch count, last contact date, their feedback in their words, objections raised, and temperature score. Update this after every meaningful interaction. On Friday, this tab IS your weekly status report.
B22: YOUR WEEKLY RHYTHM · How To Use This Every Day
... B35: COLOR KEY · What The Colors Mean
C37: Green row background | D37: Track 1 Franchisor account or Tier 1 priority
C38: Light grey background | D38: Track 2 Franchisee or Tier 2 account
C39: Light blue background | D39: GPS Insight action required — involves Charles, Garrett, Andrea, or Angie
C40: Navy header / badge | D40: Tier 1 franchisor (BELFOR, Threshold, Empower) — move now
C41: Blue badge | D41: Tier 2 franchisor (PSB, ResiBrands, Five Star, HomeFront) — active pipeline
C42: Grey badge | D42: Tier 3 franchisor (Authority, Neighborly) — relationship build
C43: Green outcome background | D43: Positive outcome — reply, call scheduled, call complete, pilot agreed
C44: Yellow outcome background | D44: Neutral outcome — no response, opened, replied neutral
C45: Red outcome background | D45: Negative outcome — not a fit, replied negative, stalled
C46: Yellow status background | D46: Outreach status dropdowns — needs updating
B48: DROPDOWN REFERENCE · What Each Option Means
B50: OUTREACH STATUS — Use this to track where each account is in your pipeline. Update every time something changes.
C51: Not Started | D51: You haven't reached out yet
C52: Researching | D52: You're gathering contact info / doing pre-outreach research
C53: Contacted | D53: You've sent at least one message — no reply yet
C54: Replied | D54: They responded — positive, neutral, or negative
C55: Call Scheduled | D55: A call is booked on the calendar
C56: Discovery Done | D56: You've had a discovery call — mandate confirmed or denied
C57: Proposal Sent | D57: You've sent a formal proposal or ROI model
C58: Negotiating | D58: Active back-and-forth on terms or next steps
C59: Pilot Closed | D59: Pilot agreement signed
C60: Stalled | D60: Was moving, now not responding — needs a new angle
C61: Not a Fit | D61: Wrong timing, wrong account, or confirmed no path forward
B63: OUTCOME (CRM Log) — Use this in the Engagement Log every time you record an interaction.
C64: No Response | D64: Sent — no reply after 48+ hours
C65: Opened | D65: Email opened but no reply (if tracking)
C66: Replied – Positive | D66: They responded with interest or agreed to a next step
C67: Replied – Neutral | D67: They responded but non-committal
C68: Replied – Negative | D68: They said no or not interested
C69: Call Scheduled | D69: They agreed to a call — date set
C70: Call Complete | D70: Call happened — log what was said in Feedback column
C71: Meeting Complete | D71: In-person or video meeting completed
C72: Proposal Requested | D72: They asked you to send a proposal or ROI model
C73: Pilot Agreed | D73: They agreed to a pilot — get it in writing
C74: Stalled | D74: Was moving, went quiet
C75: Not a Fit | D75: Confirmed not the right fit or timing
B77: TEMPERATURE (Feedback Cards) — Score how hot each account is running. Update weekly.
C78: 🔥 Hot | D78: Active conversation, positive signals, moving toward a decision
C79: 🌡 Warm | D79: Engaged, interested, but no concrete next step yet
C80: ❄ Cold | D80: No response or very early stage — not yet warm
C81: ⛔ Dead | D81: Confirmed not a fit or permanently unresponsive — archive
B83: PILOT POTENTIAL — Score each franchisee account by how likely they are to close a pilot.
C84: HIGH | D84: Greenfield FSM, GPS warm account, or brand wedge already identified
C85: MED | D85: Greenfield but no warm path yet, or partial FSM situation
C86: LOW | D86: ServiceTitan incumbent, or low FSM fit trade type
B89: RULES OF THE ROAD · Keep This Accurate and It Pays You Back
B91: 1. Log every touch
B92: Every LinkedIn message, email, call, and meeting gets a row in Tab 3. If it isn't logged, it didn't happen. This protects you in your weekly report to Andrea and builds a record you can reference when accounts re-engage months later.
B94: 2. Log their words verbatim
B95: In the Feedback column, paste exactly what they said — not your interpretation. 'We're looking at FSM in Q3' is more useful than 'They're interested.' Exact words protect you and make your next outreach sharper.
B97: 3. Update Feedback Cards every Friday
B98: Tab 4 is what Andrea sees. If the status in Tab 4 doesn't reflect this week's activity, your report is wrong. Friday morning: open Tab 4, update every account you touched, screenshot, send.
B100: 4. GPS Insight items move first
B101: Any row highlighted in blue (GPS Insight action needed) must be flagged to Charles, Garrett, or Andrea before you move forward. These are not optional — warm intros from GPS Insight compress your sales cycle from 6 months to 6 weeks.
B103: 5. Warm before cold — every week
B104: GPS Insight telematics clients, PE warm intros, and any account that replied last week always move before cold accounts. Prioritize Tab 2 accounts with YES in the GPS Warm column first.
B106: 6. One status per account
... B113: That is your goal. Work backward from it every week: which accounts are closest to a pilot decision? Those get your time first. Everything else is pipeline building for Month 4+.
A116: Prepared by Velocity GTM Co LLC on behalf of GPS Insight / ServiceBridge · Michael Montgomery Flynt Jr · 919.434.6720 · mflyntjr@gmail.com · Confidential · April 2026
A118: FDD RESEARCH REFERENCE · Free Sources for Franchise Disclosure Documents
A119: Wisconsin DFI (BEST — easiest to use) | B119: https://apps.dfi.wi.gov/apps/FranchiseSearch/MainSearch.aspx | C119: Search by legal name. Free PDF download. All BELFOR, Empower, Authority, Neighborly brands registered here.
A120: California DFPI DocQNet | B120: https://docqnet.dfpi.ca.gov | C120: Select 'Uniform Franchise Registration' in Application Type. Full FDD + exhibits downloadable.
A121: Indiana Secretary of State | B121: https://securities.sos.in.gov/public-portfolio-search/ | C121: Select 'Franchise' under Registration Type. Clean interface.
A122: Minnesota Commerce | B122: https://cards.web.commerce.state.mn.us/franchise-registrations | C122: Select 'Franchise Registrations' under Area of Interest. Must include year.
A123: Franchise Chatter (FDD Analysis) | B123: https://www.franchisechatter.com | C123: Best free Item 19 analysis. Search '[brand name] FDD'. Paid tier for full breakdown.
A124: FDD Exchange | B124: https://fddexchange.com | C124: Summaries of Items 1-23. Some free, some paid. Good for Item 8/11 vendor requirements.
A125: SharpSheets | B125: https://sharpsheets.io | C125: Good free Item 19 summaries and unit economics estimates.
A127: 📊 INSIGHT ENGINE · How to Use the ROI Calculator in Outreach
A128: FILE | B128: Insight_Engine_Excel_v3.xlsx | C128: Always use the current version. Do not modify source formulas.
A129: TAB 1 — ROI Calculator | B129: Pre-populate Sections A, B, C with account-specific data before every meeting | C129: Section A: Business profile (techs, jobs/day, revenue/job). Section B: FSM uplift. Section C: Telematics uplift. Section D + E auto-calculate.
A130: TAB 2 — Fuel Intelligence | B130: Use for urgent opener — diesel at $5.375/gal (EIA Mar 2026) | C130: Lead with fuel cost slide when contact is ops-focused. PE contacts skip to Tab 6.
A131: TAB 3 — Sources & Methodology | B131: Leave visible — builds credibility that numbers are sourced | C131: Every benchmark cited: Aberdeen Group, BLS, GPS Insight internal, ServiceBridge data.
A132: TAB 4 — Competitive Matrix | B132: Use with Tij Bedi (Authority CTO) and any tech-savvy contact | C132: Only tool speaking to PE / CFO audience. Shows ServiceTitan and Jobber gap explicitly.
A133: TAB 5 — Trade Reference | B133: Populate with real ServiceBridge client data before Tier 1 meetings | C133: 2-3 validated references make the model credible. Validate with Andrea before BELFOR outreach.
A134: TAB 6 — 3-Way Scenario | B134: PE / CFO / COO conversations ONLY | C134: Conservative / Base / Stretch + EBITDA × exit multiple. This is the boardroom document. Print and bring to Rusty Amarante.
A135: HOW TO USE IN OUTREACH | B135: Step 1: Pre-populate with FDD data + account intel from Track 1 col V | C135: Step 2: Run 3-Way Scenario for PE-backed accounts. Step 3: Send as leave-behind after first meeting. Step 4: Validate against real client data before second meeting.
A136: BELFOR SPECIFIC | B136: Use FDD Item 19 data: $480K avg revenue, $4,500/job, 40% carrier-referred | C136: Top 25% = $1.65M. Use stretch scenario = $1.65M × 5-pt margin = $82.5K EBITDA/location × 178 locations = $14.7M system EBITDA. At 8x = $117M enterprise value uplift.

Sheet 📅 Event Intelligence
A1: 📅 EVENT INTELLIGENCE · Industry Events + Franchisor Annual Conventions · ServiceBridge GTM Engagement
A2: Velocity GTM Co LLC · Michael Montgomery Flynt Jr · V2 ranking aligned · Updated April 29, 2026
A4: TABLE 1 · INDUSTRY EVENTS
A5: EVENT NAME | B5: TYPE | C5: DATE | D5: LOCATION | E5: STATUS | F5: KEY CONTACT ATTENDING | G5: THEIR ROLE | H5: TOPIC / NOTES | I5: YOUR OPPORTUNITY | J5: PRIORITY | K5: NOTES / INTEL
A6: IFA Annual Convention 2026 | B6: IFA Convention | C6: Feb 22–25, 2026 | D6: Las Vegas, NV | E6: ✅ Occurred | F6: Codie Sanchez (ResiBrands) | G6: Main Stage Speaker | H6: Theme: 'Evolve'. 500+ brands, 300 exhibitors. Daymond John keynote. | I6: Use IFA appearance as icebreaker in Steven Montgomery outreach | J6: 🟡 Medium | K6: Codie Sanchez on main stage — warm reference point for ResiBrands outreach
A7: Multi-Unit Franchising Conference (MUFC) 2026 | B7: Multi-Unit Franchisee | C7: Mar 24–27, 2026 | D7: Caesars Forum, Las Vegas | E7: ✅ Occurred | F7: Multi-unit franchisee operators | G7: Attendees | H7: Largest multi-unit franchisee event. Track 2 audience. | I7: Attend 2027 — meet franchisee operators directly | J7: 🟡 Medium | K7: Built by/for multi-unit franchisees. Good Track 2 warm-up
A8: IFA Advocacy Summit 2026 | B8: IFA Summit | C8: Sep 14–16, 2026 | D8: Washington, DC | E8: 🟢 Upcoming | F8: Franchisor leadership (various) | G8: Attendees/Speakers | H8: Policy-focused. Lighter on operators, heavier on franchisor C-suite. | I8: Relationship building — consider attending | J8: 🟡 Medium | K8: Brad Stevenson (Neighborly CDO) on IFA board — warm reference
A9: Franchise Leadership & Development Conference (FLDC) 2026 | B9: Franchisor Leadership | C9: Oct 6–8, 2026 | D9: Atlanta, GA | E9: 🟢 UPCOMING — REGISTER | F9: Franchisor CEOs, Presidents, COOs, CDOs | G9: Attendees | H9: BEST industry event for your exact target audience — franchisor C-suite only. STAR Awards program. | I9: 🔴 ATTEND — highest-leverage industry event of 2026 | J9: 🔴 High | K9: This is the room you want to be in. All Top 9 contacts are likely attendees. Register now.
A10: IFA Franchise Show 2026 | B10: Trade Show | C10: Sep 25–26, 2026 | D10: Fort Lauderdale, FL | E10: 🟢 Upcoming | F10: (Broad franchise audience) | G10: Various | H10: Large franchise expo — more prospect-facing than C-suite. | I10: Lower priority — skip or exhibit if budget allows | J10: ⚪ Low | K10: Broad audience. Less useful for your specific targets.
A11: Emerging Franchisor Conference 2026 | B11: Emerging Brands | C11: Sep 23–25, 2026 | D11: Fort Worth, TX | E11: 🟢 Upcoming | F11: Emerging platform CEOs (ResiBrands, HomeFront, Five Star tier) | G11: Attendees/Speakers | H11: Good for Tier 2 accounts — emerging platform CEOs attend. | I11: Consider attending for ResiBrands/HomeFront/Five Star | J11: 🟡 Medium | K11: Steven Montgomery (ResiBrands) likely attends emerging brand events
A15: TABLE 2 · FRANCHISOR ANNUAL CONVENTIONS
A16: FRANCHISOR | B16: EVENT NAME | C16: TYPICAL MONTH | D16: MOST RECENT DATE | E16: LOCATION | F16: ATTENDANCE | G16: VENDORS INVITED? | H16: KEY CONTACT ATTENDING | I16: YOUR PLAY | J16: NEXT EXPECTED | K16: NOTES / STATUS
A17: BELFOR · P2 DE-FACTO ANCHOR | B17: Annual Conference (unnamed) | C17: March | D17: March 2026 (just held) | E17: TBD | F17: Multi-brand, per-brand awards | G17: Unknown | H17: Rusty Amarante, Doug Smith | I17: ⚠️ Just missed — use HOODZ Triangle + Z Plumberz award winners as warm icebreakers NOW | J17: ~March 2027 | K17: Franchise of the Year awards announced March 2026. HOODZ of the Triangle (NC) + Z Plumberz Livingston won. Local connection.
A18: THRESHOLD BRANDS · P2 AT-RISK ANCHOR | B18: Annual Convention (unnamed) | C18: Unknown | D18: Unknown | E18: Unknown | F18: Unknown | G18: Unknown | H18: Hagan Kappler (verify), Andrea Hohermuth | I18: 🔍 Research needed — confirmed exists per LinkedIn | J18: TBD | K18: LinkedIn reference confirms annual convention exists. Date/location not public. Research needed.
A19: EMPOWER BRANDS · P1 #3 GREENFIELD-LED | B19: Ignite (rebranded 2026) | C19: February | D19: Feb 10–12, 2026 (just held) | E19: Orlando, FL | F19: 1,100+ attendees · 85 vendor partners | G19: ✅ YES — 85 vendors confirmed | H19: Scott Zide (CEO), Michael Borreca (CFO) | I19: ⚠️ Just missed — build vendor relationship for Ignite 2027 | J19: ~Feb 2027 (Orlando likely) | K19: 2026 theme: 'Accelerate Growth'. Chris McChesney keynoted. Vendor path fully confirmed — 85 partners attended.
A20: PREMIUM SERVICE BRANDS · P1 #6 GREENFIELD-OPEN | B20: Annual Convention (TBD name) | C20: TBD | D20: TBD | E20: TBD | F20: TBD | G20: Unknown | H20: Paul Flick, Roxanne Conrad | I20: 🔍 Research needed | J20: TBD | K20: PSB holds annual events but name/date not publicly confirmed. Research via FDD.
A21: RESIBRANDS · P1 #4 FAST-CYCLE | B21: No confirmed annual event | C21: N/A | D21: N/A | E21: N/A | F21: N/A | G21: N/A | H21: Steven Montgomery (directly accessible) | I21: Reach Steven directly — no convention needed | J21: N/A | K21: Lean founder operation. IFA 2026 was Codie Sanchez's main appearance. Steven Montgomery is directly accessible.
A22: FIVE STAR FRANCHISING · P1 #5 WEDGE-BRAND | B22: Home Services Summit (HSS) | C22: January | D22: Jan 14–17, 2026 (just held) | E22: Caesars Palace, Las Vegas | F22: ~1,000 attendees · vendor partners | G22: ✅ YES — vendor partners attend | H22: Scott Abbott (CEO), Chad Jones (COO), Michael Moorhouse (Mosquito Shield) | I22: ⚠️ Just missed — target HSS 2027 as vendor/exhibitor | J22: ~Jan 2027 (Las Vegas likely) | K22: 76 locations got Million Dollar Club recognition. Ian Stein Jr. keynoted. Fastest growing brand: Five Star Bath Solutions.
A23: HOMEFRONT BRANDS · P1 #7 MONITOR-MODE | B23: Homecoming (Homecoming 4 next) | C23: November | D23: Nov 1–4, 2025 (Homecoming 3) | E23: Orlando, FL | F23: Hundreds of owners + vendor partners | G23: ✅ YES — vendor partners attend | H23: Jeff Dudan (hosts personally), Michael O'Driscoll | I23: 🟢 STILL TIME — Homecoming 4 ~Nov 2026. Jeff Dudan hosts personally. Contact now to get in. | J23: ~Nov 2026 (Orlando likely) | K23: ⚠️ Note: Franchisee satisfaction issues flagged behind scenes per Unhappy Franchisee Dec 2025 post. Verify health of system before committing vendor $$.
A24: AUTHORITY BRANDS · P1 #2 DISPLACEMENT-READY | B24: Annual Convention (unnamed) | C24: TBD | D24: TBD | E24: TBD | F24: TBD | G24: Unknown | H24: Jay Bhatt (CEO), Tij Bedi (CTO — primary) | I24: 🔍 Research needed — at $2B+ revenue almost certain to hold annual event | J24: TBD | K24: Tij Bedi (CTO joined Aug 2024) is building tech infrastructure for 9 non-ST brands. He is your primary contact, not the convention.
A25: NEIGHBORLY · P1 #1 PE-GATED | B25: Neighborly Reunion | C25: October | D25: Oct 2025 — Gaylord Opryland Nashville | E25: Nashville, TN (Gaylord Opryland) | F25: Large — all 16 brands + vendor partners | G25: ✅ YES — vendor partners attend | H25: Mike Davis (CEO), Brad Stevenson (CDO — now on IFA board) | I25: ⚠️ DO NOT attend without PE intro confirmed first. KKR → Charles → Felix Gernburd path only. | J25: ~Oct 2026 (Nashville likely) | K25: Brad Stevenson elected to IFA board at IFA 2026 — use as warm reference. PE intro via Charles is pre-condition for any Neighborly engagement.

Sheet 💡 Engagement Ideas
A1: 💡 ENGAGEMENT IDEAS · Franchisor + Franchisee Outreach Strategies · ServiceBridge GTM Engagement
A2: Velocity GTM Co LLC · Use these ideas when scripting outreach, prepping meetings, or planning next touches
A4: TABLE 1 · FRANCHISOR ENGAGEMENT IDEAS (Track 1)
A5: FRANCHISOR | B5: PRIORITY | C5: ENTRY ANGLE | D5: OPENING LINE / HOOK | E5: CHANNEL SEQUENCE | F5: INSIGHT ENGINE USE | G5: GPS INSIGHT ACTION | H5: OBJECTION TO PREP | I5: TIMING | J5: NOTES / STATUS
A6: BELFOR | B6: 🟡 P2 DE-FACTO ANCHOR — HOODZ + DUCTZ at 94% SB; convert to mandate | C6: Insurance carrier relationship reframe — not FSM pitch | D6: "Every 1-800 WD job that isn't documented costs you a carrier referral. We fix that at the point of service." | E6: 1. Charles → American Securities PE intro 2. LinkedIn to Rusty (parallel) 3. HOODZ Triangle local angle 4. Email with Insight Engine 3-Way Scenario | F6: 3-Way Scenario: $4,500/job × 178 locations. BELFOR-specific: carrier doc quality = more referrals. Top-25% = $1.65M stretch. | G6: 📞 On me — Charles to surface American Securities / Accel-KKR path to Sheldon Yellen | H6: "We already have BELFOR Property Restoration systems" → Counter: franchise network has no mandate, 30 new territories need onboarding | I6: Week 1–2 | J6: 🔥 Warmest Tier 1. GPS warm flag. HOODZ Triangle local NC connection for Rusty.
A7: THRESHOLD BRANDS | B7: 🔴 P2 AT-RISK ANCHOR — USA Insulation transitioning off SB; defensive | C7: Unfulfilled tech promise to franchisees | D7: "Your franchisees were promised a tech platform. We're the ones who can actually deliver it." | E7: 1. Verify Hagan Kappler CEO status 2. LinkedIn to CEO (if confirmed) or COO Andrea Hohermuth 3. Riverside PE intro via Charles | F7: Conservative scenario: 6,250 techs. Frame as fixing a credibility problem with franchisees. | G7: GPS: Riverside PE → Charles Layne intro | H7: "We're evaluating options" → Counter: franchisees have been waiting — timing is now | I7: Week 2 | J7: ⚠️ Verify Kappler status before ANY outreach. Conflicting intel.
A8: EMPOWER BRANDS | B8: 🟡 P1 #3 GREENFIELD-LED — strongest greenfield, Commercial mix | C8: 9 greenfield brands + MidOcean exit window | D8: "You have 9 brands with no FSM mandate and a PE exit window opening. That math works in both our favors." | E8: 1. LinkedIn to Scott Zide (sent Apr 8 — follow up) 2. Email with 3-Way Scenario (9 non-JAN-PRO brands) 3. Gary Bauer brand wedge on JAN-PRO separately 4. MidOcean PE intro via Charles | F8: 3-Way Scenario for 9 greenfield brands only. Exclude JAN-PRO from model. EBITDA × exit multiple for Scott Zide. | G8: GPS: MidOcean Partners → Charles Layne for PE intro | H8: "JAN-PRO already has software" → Counter: we're not pitching JAN-PRO, we're pitching the other 9 | I8: Week 2 | J8: Gary Bauer (JAN-PRO) is a separate, careful conversation. 30yr ServiceMaster background.
A9: RESIBRANDS | B9: 🟢 P1 #4 FAST-CYCLE — founder-direct, fastest decision | C9: Founder-accessible, fastest path to close | D9: "$1.67 per tech per day to go fully paperless. For 2,550 techs, that's your whole operation digitized." | E9: 1. Call scheduled Apr 15 (Steven replied positive) 2. Send Insight Engine conservative scenario before call 3. Pilot proposal on first or second call | F9: Conservative scenario ONLY. 2,550 techs × $1.67/day. Simple math. No PE exit framing needed — Steven is founder, not PE. | G9: None needed — direct founder relationship | H9: "Too much change at once" → Counter: ResiConnect handles scheduling, we only add field ops layer | I9: 🔥 This week | J9: HOTTEST LEAD IN PIPELINE. Founder-backed = fast decision. No committee. IFA 2026 main stage speaker.
A10: FIVE STAR FRANCHISING | B10: 🟡 P1 #5 WEDGE-BRAND — Mosquito Shield wedge entry | C10: Princeton Equity Year 5 + Mosquito Shield brand wedge | D10: "Princeton Equity is in Year 5. Before exit, your EBITDA story needs to include operational leverage. ServiceBridge is that leverage." | E10: 1. LinkedIn to Scott Abbott 2. Brand wedge via Michael Moorhouse (Mosquito Shield president) 3. CFO Steve White on numbers 4. Verify FieldRoutes on Mosquito Shield first | F10: 3-Way Scenario: Princeton exit math. 2,350 techs. CFO conversation focus. | G10: None — Five Star is direct path | H10: "Mosquito Shield is on another platform" → Verify FieldRoutes first. If conflict: use other 4 Five Star brands. | I10: Week 2 | J10: HSS 2026 just ended — 'we just came back energized from HSS' opener works well.
A11: HOMEFRONT BRANDS | B11: ⚪ P1 #7 MONITOR-MODE — Q3/Q4 2026 reassessment posture | C11: Content-first / Jeff Dudan podcast angle + Homecoming 4 vendor path | D11: "I've been following your Forbes work on franchise community-building. What you're describing operationally is exactly what ServiceBridge enables." | E11: 1. LinkedIn to Jeff Dudan — content angle first 2. Reference Homecoming 4 vendor opportunity 3. Window Hero brand wedge via Tyler Kirk | F11: Conservative scenario for founder conversation. Not PE math. Per-franchisee economics. | G11: None — family office, not institutional PE | H11: "We're managing costs tightly" → Counter: ServiceBridge pays for itself in first 90 days on admin savings alone | I11: Week 2 | J11: ⚠️ Franchisee satisfaction issues Dec 2025. Verify system health. Position ServiceBridge as system improvement tool, not just efficiency.
A12: AUTHORITY BRANDS | B12: 🟡 P1 #2 DISPLACEMENT-READY — leadership transition window | C12: Tij Bedi (CTO) tech champion — 9 greenfield brands | D12: "You just joined to build tech infrastructure for 9 brands with no FSM mandate. ServiceBridge is the fastest path to get there." | E12: 1. LinkedIn to Tij Bedi (CTO) — direct approach appropriate 2. Competitive Matrix tab as conversation starter 3. GPS Apax Partners intro via Charles (parallel) | F12: Competitive Matrix tab for CTO conversation. Show ServiceTitan gap on the 9 non-ST brands. | G12: GPS: Apax Partners → Charles Layne for board-level intro | H12: "We want to evaluate all options" → Counter: you have 9 brands waiting now, evaluation is the delay | I12: Week 2–3 | J12: Tij Bedi is the tech champion, not gatekeeper. He's looking for exactly this solution.
A13: NEIGHBORLY | B13: 🔴 P1 #1 PE-GATED — DO NOT APPROACH DIRECT (KKR warm path required) | C13: KKR PE intro only — no direct approach | D13: No opening line until KKR intro confirmed. PE intro is the only door. | E13: 1. Charles → Accel-KKR → KKR → Felix Gernburd 2. Only then: GPS Insight telematics conversation with Mike Davis or Gagan Sinha 3. NOT ServiceBridge FSM — ST is locked in | F13: Do not run Insight Engine until PE intro confirmed. When secured: telematics ROI only, not FSM. | G13: 🔴 GPS #1 ACTION — Charles to surface KKR intro. Follow up TODAY. | H13: N/A — must have intro first | I13: Week 1 GPS action — no direct outreach | J13: ST renewal window 2025-2027 is the only leverage. Patience required.
A14: PREMIUM SERVICE BRANDS | B14: 🟡 P1 #6 GREENFIELD-OPEN — RooterMan dominant brand wedge | C14: RooterMan 300-location plumbing brand wedge | D14: "RooterMan is 300 locations of emergency plumbing dispatch — that's exactly what ServiceBridge was built for." | E14: 1. Find RooterMan brand president name (TBD) 2. LinkedIn to brand president 3. Escalate to Paul Flick (CEO) with full PSB ROI model | F14: ROI Calculator at brand level first (RooterMan). Then scale to full PSB network for Paul Flick. | G14: None — PSB is direct path | H14: "Brand presidents run their own tech" → Counter: franchisor mandate is the faster path. Use Paul Flick ROI model. | I14: Week 2–3 | J14: Full greenfield across all 8 PSB brands. Susquehanna PE — not a prominent PE exit story.
A18: TABLE 2 · FRANCHISEE ENGAGEMENT IDEAS (Track 2)
A19: BRAND / NETWORK | B19: PARENT | C19: FSM STATUS | D19: ENGAGEMENT ANGLE | E19: OPENING MESSAGE | F19: INSIGHT ENGINE | G19: WARM PATH | H19: TIMING | I19: PILOT POTENTIAL | J19: NOTES
A20: 1-800 Water Damage (BELFOR network) | B20: BELFOR | C20: 🟢 Greenfield | D20: Insurance documentation = carrier relationship tool | E20: "Every undocumented job is an undefended claim. ServiceBridge captures the evidence before you leave the property." | F20: ROI Calc: $4,500/job, 3 techs, 3 jobs/day. FDD-sourced. Invoice cycle reduction = faster carrier payment. | G20: GPS Insight telematics list (Andrea) — warm customers are direct calls | H20: After Rusty/BELFOR franchisor close | I20: 🔴 HIGH | J20: FDD: top 25% avg $1.65M. Insurance carriers refer 40% of jobs. Documentation is the product.
A21: That 1 Painter (ResiBrands) | B21: ResiBrands | C21: 🟢 Greenfield | D21: ResiConnect handles front end — ServiceBridge handles the field | E21: "ResiConnect takes the call. We handle everything after the tech gets in the truck." | F21: Conservative: 800 territories × 5 techs × $200/job. $1.67/tech/day message. | G21: Steven Montgomery decides for all ResiBrands — closed at franchisor level | H21: After ResiBrands call Apr 15 | I21: 🔴 HIGH | J21: 800+ territories. Fastest path: win Steven, get the network.
A22: GarageUp (ResiBrands) | B22: ResiBrands | C22: 🟢 Greenfield | D22: Emergency + scheduled dispatch = dual revenue model | E22: Same as That 1 Painter — closed via Steven Montgomery | F22: Part of ResiBrands model — included in franchisor scenario | G22: Steven Montgomery | H22: With ResiBrands | I22: 🟡 MEDIUM | J22: Garage door = emergency call + maintenance schedule. Strong dispatch fit.
A23: Bumble Roofing (Empower) | B23: Empower Brands | C23: 🟢 Greenfield | D23: Estimate-to-invoice project flow | E23: "Fastest growing Empower brand in 2025. ServiceBridge keeps that growth from outpacing your ops." | F23: Project model: lower jobs/day but higher revenue/job ($2,000+). Estimate + job documentation. | G23: Empower Brands mandate via Scott Zide | H23: After Empower franchisor close | I23: 🟡 MEDIUM | J23: Fastest growing brand at Ignite 2026. Greenfield. Project-based.
A24: Top Rail Fence (HomeFront) | B24: HomeFront Brands | C24: 🟢 Greenfield | D24: Homecoming 4 vendor path + Franchisee of Year credibility | E24: "Top Rail Fence won Homecoming 3 FoY. The brand that wins uses the best ops stack." | F24: Project fencing: quote → install → invoice. Conservative scenario. | G24: Homecoming 4 vendor registration via Zack Dudan (CGO) | H24: Homecoming 4 Nov 2026 | I24: 🟡 MEDIUM | J24: FoY award = credibility for vendor conversation. Jeff Dudan hosts personally.
A25: DUCTZ (BELFOR) | B25: BELFOR | C25: 🟢 Greenfield | D25: Annual route model — recurring dispatch | E25: "DUCTZ runs annual commercial duct cleanings. ServiceBridge turns your route list into a repeating revenue engine." | F25: Route model: 4 jobs/day, annual contracts, ~$2,000/job. Recurring invoice automation. | G25: GPS Insight telematics list — warm customer path | H25: After BELFOR franchisor close | I25: 🟡 MEDIUM | J25: Annual recurring = perfect route optimization model. DUCTZ won Franchise of Year 2025.
A26: RooterMan (PSB) | B26: Premium Service Brands | C26: 🟢 Greenfield | D26: Emergency plumbing dispatch at scale | E26: "300 locations of emergency plumbing. Every call is time-sensitive. ServiceBridge puts the right tech on the right job in under a minute." | F26: 300 locations × 4 techs × 4 jobs/day × $350/job. Lead brand for PSB model. | G26: Brand president TBD → Paul Flick (CEO) | H26: Week 2–3 | I26: 🔴 HIGH | J26: 300 locations = largest PSB brand. Emergency plumbing = high dispatch urgency. Perfect FSM case study.
A27: Mosquito Shield (Five Star) | B27: Five Star Franchising | C27: ⚠️ Verify | D27: Seasonal route model — check FieldRoutes first | E27: If clear: "Mosquito Shield runs 20+ weeks of dense routing. ServiceBridge turns that density into margin." | F27: Route model: seasonal, high frequency, low revenue/visit. Volume play. | G27: Michael Moorhouse (Brand President) → Scott Abbott | H27: After FieldRoutes verification | I27: 🟡 MEDIUM — IF clear | J27: ⚠️ FieldRoutes (ST subsidiary) possible mandate. MUST verify before outreach.
A28: Window Hero (HomeFront) | B28: HomeFront Brands | C28: 🟢 Greenfield | D28: Simple exterior cleaning — collect payment same day | E28: "Window cleaning on paper means chasing invoices. ServiceBridge means collecting before the squeegee is dry." | F28: Small crew model: 2-3 techs, $150-300/job, 6 jobs/day. Mobile payment emphasis. | G28: Tyler Kirk (founder) → Jeff Dudan → Homecoming 4 vendor | H28: Homecoming 4 Nov 2026 | I28: 🟢 LOW-MED | J28: Small brand — good pilot candidate due to simplicity. Homecoming 4 vendor path is the door.
A29: JAN-PRO (Empower) | B29: Empower Brands | C29: ⚠️ Conflict | D29: Replace proprietary FSM — model $8.1M system cost savings | E29: "JAN-PRO pays $60/month/franchisee for a proprietary system. ServiceBridge does more for less." | F29: Cost elimination model: $60/mo × 11,265 units = $8.1M/yr. ServiceBridge at lower cost. | G29: Scott Zide (CEO Empower) must mandate — not brand-level decision | H29: After Empower franchisor close | I29: ⚠️ Conflict | J29: Handle carefully. Gary Bauer (30yr ServiceMaster) knows Aspire. Approach as system upgrade.
A30: Pestmaster Services (Threshold) | B30: Threshold Brands | C30: ⚠️ Verify | D30: Pest control route model — verify FieldRoutes | E30: If clear: route-based pest control is perfect ServiceBridge use case. | F30: Route model. Verify FieldRoutes conflict first. | G30: Threshold Brands franchisor mandate path | H30: After Threshold franchisor close | I30: 🟡 MEDIUM — IF clear | J30: ⚠️ FieldRoutes possible. Check Threshold FDD Item 8 before outreach.
A31: Mosquito Joe (Neighborly) | B31: Neighborly | C31: 🔴 ST/FieldRoutes | D31: DO NOT approach without PE intro | E31: No opening line until Neighborly PE intro confirmed. | F31: Do not run model — ST/FieldRoutes mandate likely. | G31: KKR → Charles Layne — PE intro only | H31: After PE intro | I31: ⚪ BLOCKED | J31: Smart Fleet USA telematics confirmed. Route model. But Neighborly = PE intro only, no direct approach.
A34: TABLE 3 · REFERENCE SELLING STRATEGY · Current Testimonials + Pilot Program
A35: REFERENCE CLIENT | B35: SOURCE | C35: CONTACT / ROLE | D35: RESULT 1 | E35: RESULT 2 | F35: RESULT 3 | G35: TRADE / RELEVANCE | H35: USE IN PITCH TO | I35: STATUS | J35: ACTION NEEDED
A36: Robertson Pools Dallas-Fort Worth TX | B36: SB Advantage Document (p.9) | C36: Kelli Griffin Service Manager | D36: 64% revenue growth | E36: 2pt net profit increase | F36: Week 1 platform ROI | G36: Pool Services — recurring route + job dispatch | H36: Five Star (Mosquito Shield), PSB, HomeFront — any route-based brand | I36: ✅ In SB Advantage — CONFIRM referenceable | J36: Andrea to confirm active + permission to use in franchise prospect meetings
A37: Critter Control National Franchise Network | B37: SB Advantage Document (p.9) | C37: Joe Felegi President | D37: Headcount-neutral growth | E37: Improved lead-to-sale ratio | F37: Eliminated daily office visits | G37: Pest Control — national franchise network ← FRANCHISE REFERENCE | H37: PSB (Pestmaster), Five Star (Mosquito Shield), Threshold (FlyFoe, Pestmaster) — EXACT MATCH | I37: ✅ In SB Advantage — CONFIRM referenceable | J37: ⭐ HIGHEST VALUE — national franchise network president. Perfect reference for any franchisor conversation.
A38: Master Mastic Regional Operator | B38: SB Advantage Document (p.10) | C38: Brian Stilwell Owner | D38: 2x sales growth | E38: Reduced admin overhead | F38: Eliminated QuickBooks double-entry | G38: Waterproofing — project-based restoration-adjacent | H38: BELFOR (restoration/water damage), Threshold, PSB — restoration/specialty trades | I38: ✅ In SB Advantage — CONFIRM referenceable | J38: Restoration-adjacent = closest to BELFOR use case. Use in Rusty Amarante outreach if confirmed.
A39: 🎯 TARGET PILOT CLIENT 1-800 Water Damage franchisee (to be identified) | B39: Andrea telematics list → GPS Insight warm customer | C39: To be identified — Owner/Operator | D39: TARGET: 64%+ revenue growth | E39: TARGET: invoice cycle -5 days | F39: TARGET: carrier referral rate increase | G39: Restoration — insurance dispatch model ← EXACT BELFOR MATCH | H39: BELFOR (Rusty Amarante, Sheldon Yellen) — this is the reference that closes the deal | I39: ⚠️ NOT YET — find via Andrea's telematics list | J39: This is the pilot. Find 1 GPS Insight telematics customer in BELFOR network. Offer 90-day free pilot. Capture results. Walk into Rusty with real numbers.
A40: 🎯 TARGET PILOT CLIENT ResiBrands franchisee (That 1 Painter / GarageUp) | B40: Steven Montgomery relationship → warm intro | C40: To be identified — Owner/Operator | D40: TARGET: admin time -1hr/tech/day | E40: TARGET: payment cycle same-day | F40: TARGET: jobs/tech/day +0.5 | G40: Painting/Home Services — high tech count, route model | H40: ResiBrands (Steven Montgomery) — if pilot data supports $1.67/tech/day claim | I40: ⚠️ NOT YET — after ResiBrands call Apr 15 | J40: If Steven agrees Apr 15 — propose a single That 1 Painter market as 90-day pilot before full network rollout.
A43: TABLE 4 · PRODUCT POSITIONING · Orchestration + Ownership + Spring Release Features
A44: A · TWO-PITCH FRAMEWORK · Based on prospect's current telematics provider
A45: SCENARIO | B45: TELEMATICS STATUS | C45: LEAD WITH | D45: ORCHESTRATION CLAIM | E45: GPS INSIGHT ROLE | F45: SERVICEBRIDGE ROLE | G45: OPENING LINE | H45: ACCOUNTS | I45: CAUTION | J45: VERIFY WITH
A46: PITCH A 'Full Ownership' (GPS Insight customers) | B46: ✅ GPS Insight or ClearPathGPS already installed | C46: Unified Orchestration — FSM + Fleet on one shared data model | D46: FULL claim: 'We own both sides. Competitors integrate. We orchestrate. One shared data model across jobs, vehicles, and technicians — in real time.' | E46: The telematics backbone. Live vehicle data, fuel card cross-ref, insurance carrier data. Already proven with this customer. | F46: The FSM layer that acts on GPS Insight data in real time. Merge Maps, Smart Scheduler, Job Confirmations — all GPS-aware. | G46: 'You're already running GPS Insight. ServiceBridge is the other half of the system. Together they don't just talk to each other — they think together.' | H46: BELFOR (GPS warm flag confirmed) All GPS Insight telematics customers in Andrea's list Any pilot candidate from telematics cross-ref | I46: Do not claim unified orchestration for non-GPS Insight customers. | J46: Andrea — telematics customer list to identify these accounts
A47: PITCH B 'Start with ServiceBridge' (Other telematics) | B47: ⚠️ Samsara / Verizon Connect / Geotab / Motive / Smart Fleet USA | C47: ServiceBridge FSM value standalone — 8 financial levers, Week 1 ROI | D47: PARTIAL claim: 'ServiceBridge delivers its core FSM value on day one, with or without GPS Insight telematics. The full orchestration story unlocks when you add GPS Insight at your next telematics renewal.' | E47: The upgrade path. Plant the flag now. Win telematics at contract renewal. | F47: Standalone FSM: dispatch, digital work orders, on-site payment, invoice automation, QuickBooks sync, Smart Scheduler, Job Confirmations. | G47: 'Start with ServiceBridge. You'll get your money back in Week 1 on admin savings alone. When your telematics contract comes up, GPS Insight is the full orchestration upgrade.' | H47: Neighborly (Smart Fleet USA — DO NOT approach direct) Authority Brands (ST mandated brands — GPS Insight only) Five Star, HomeFront, Threshold, Empower greenfield brands Any account with non-GPS Insight telematics confirmed | I47: Never claim full orchestration with third-party telematics. Verify API capability with Andrea first — may change this. | J47: Andrea/product — does ServiceBridge accept third-party telematics data via API? Answer changes this pitch materially.
A49: B · SPRING RELEASE FEATURES · GTM Angles per New Capability (Released ~Apr 11 2026)
A50: FEATURE | B50: WHAT IT DOES | C50: GTM ANGLE | D50: BEST PITCH LINE | E50: USE WITH AUDIENCE | F50: INSIGHT ENGINE IMPACT | G50: ACCOUNTS TO LEAD WITH | H50: COMPETITIVE COUNTER | I50: STATUS | J50: SOURCE
A51: 🤖 Smart Scheduler (AI Dispatch) | B51: AI-driven auto-assignment of unassigned jobs to qualified technicians. Matches skills/certs, respects time windows, optimizes routes, previews before applying. Included free for Pro/Enterprise single-branch customers. | C51: This IS the orchestration story made visible. AI acting on job + technician data in real time — exactly what the FSM Strategy doc describes as 'systems of orchestration.' No competitor offers AI dispatch at this price point. | D51: 'ServiceBridge now includes AI-powered scheduling. Your dispatcher doesn't build the schedule anymore — the system does. In minutes, not hours. Included at no extra cost.' | E51: Tij Bedi (Authority CTO) — CTO language Scott Zide (Empower CEO) — ops efficiency PE/CFO audience — labor cost reduction Rusty Amarante (BELFOR) — dispatch at scale | F51: Add to ROI Calculator: Admin time recovery column now includes scheduler time saved. Estimate 30-60 min/day dispatch reduction for franchises with 10+ techs. | G51: BELFOR (9,250 techs — manual dispatch = massive inefficiency) Empower (JAN-PRO scale — route optimization) Authority Brands (CTO conversation) ResiBrands (That 1 Painter — 800+ territories) | H51: ServiceTitan has AI scheduling but costs $245-500/tech/month. ServiceBridge delivers it at $24.95. That's 10x cheaper for the same capability. | I51: ✅ LIVE — released ~Apr 11 2026 | J51: help.servicebridge.com Spring Release Notes
A52: 💬 Job Confirmations (2-Way SMS) | B52: Send appointment confirmation texts from Estimates/Work Orders. Receive customer replies. All SMS activity in Message Center, auto-linked to job and customer records. | C52: Customer communication = no-show reduction = more revenue per day. Every franchise system struggles with no-shows. Two-way SMS is table stakes for a premium customer experience — and it's now built in, not bolted on. | D52: 'Your techs confirm appointments by text. Customers reply. Everything logs automatically. No-shows cost you 2 hours of loaded labor per tech per week — this eliminates them.' | E52: Franchisee level — direct ops benefit Franchisor — customer satisfaction / NPS story PE/Exit — customer retention metric | F52: Add to Financial Lever #7 (First-time fix rate): No-show reduction improves utilization. Estimate 1 job/tech/week recovered = $350-4,500 per tech per week depending on trade. | G52: BELFOR (insurance carrier communication — confirmation = documentation) ResiBrands pilot (That 1 Painter — customer experience) Any Tier 1 with high customer-facing volume | H52: Jobber has SMS but it's one-way. HousecallPro has 2-way but at higher price. ServiceBridge includes it in base package. | I52: ✅ LIVE — released ~Apr 11 2026 | J52: help.servicebridge.com Spring Release Notes
A53: 💳 GreenSky® Consumer Financing | B53: Third-party consumer financing built directly into estimates and invoices. Customer applies for financing, gets approved, pays via financing — all within ServiceBridge checkout. GreenSky manages underwriting. | C53: Higher-ticket jobs close faster when financing is available at point of sale. Restoration, HVAC, roofing, insulation — these are $5K-$50K jobs. Financing converts 'let me think about it' into 'yes' on the spot. For franchise systems, this is a revenue multiplier, not a payment feature. | D53: 'The average 1-800 Water Damage job is $4,500. With GreenSky® financing built into the estimate, your franchisees close more jobs same day. The system handles the underwriting. They handle the work.' | E53: BELFOR restoration brands — high ticket, insurance-adjacent Bumble Roofing (Empower) — $10K+ roofing projects USA Insulation (Threshold) — high-ticket installs Any franchise with avg job value $2,000+ | F53: Add to Financial Lever #2 (Invoice leakage + ticket size): Financing availability increases job acceptance on high-ticket estimates. Estimate 10-15% conversion lift on jobs $2,000+. | G53: BELFOR (restoration avg $4,500/job — financing closes same day) Bumble Roofing/Empower USA Insulation/Threshold | H53: No FSM competitor at this price point includes consumer financing. ServiceTitan has financing but at enterprise pricing. ServiceBridge is the only sub-$50/tech platform with native financing. | I53: ✅ LIVE — released ~Apr 11 2026 | J53: help.servicebridge.com Spring Release Notes

Sheet 📊 Scoring Model
A1: 📊 SCORING MODEL · How We Prioritize Franchisors and Franchisees · ServiceBridge GTM Engagement
A2: Velocity GTM Co LLC · V2 Greenfield-Weighted Methodology · Track 1 + Track 2 use same 7 dimensions, reweighted per stage · Updated April 28, 2026
A3: HOW THE TWO-LEVEL SYSTEM WORKS
A4: LEVEL | B4: NAME | C4: RANGE / MAX | D4: HOW IT WORKS
A5: LEVEL 1 | B5: Franchisor Score (Track 1) | C5: 7 V2 dimensions · Max 100 points | D5: Scores each of the 7 P1 franchisor targets using V2 dimensions: Greenfield (20%), Network (15%), PE (15%), DM Access (15%), Urgency (15%), Displacement (10%), C/B Mix (10%). Determines where to focus GTM effort at the network level. P2 franchisors (BELFOR, Evive, Threshold) classified separately as "existing footprint" set, not numerically ranked.
A6: LEVEL 2 | B6: Franchisee Score (Track 2) | C6: 7 dimensions · Max 100 points | D6: Scores brand-corp targets in Stage 2 using same 7 V2 dimensions, reweighted to favor brand-level velocity: Greenfield (30%), Network (15%), PE (10%), DM Access (15%), Urgency (15%), Displacement (5%), C/B Mix (10%). Higher greenfield weight reflects brand-corp dynamics where no-FSM-mandate signals fastest path to pilot.
A7: BONUS | B7: Franchisor → Franchisee Bonus | C7: +0 / +5 / +15 / +25 points | D7: The franchisor V2 score adds a bonus to every brand-corp under that parent: 70+ score = +25, 45-69 = +15, 1-44 = +5. Reflects strategic context: a brand-corp inside a P1 #1 parent gets enterprise mandate alignment, while one inside P1 #7 gets relationship-build positioning.
A8: COMBINED | B8: Combined Score (Track 2) | C8: Max 125 points | D8: Franchisee score + Franchisor bonus. This is the number you sort by. The highest combined score = your lead pilot candidate. 🔴 88+ = Lead Pilot (approach this week) · 🟡 56-87 = Queue · ⚪ Under 56 = Hold
A10: SECTION 1 · STAGE 1 (FRANCHISOR) SCORING DIMENSIONS · 7 V2 dimensions · Max 100 points
A11: # | B11: DIMENSION | C11: MAX PTS | D11: WHY THIS MATTERS | E11: SCORE 100% | F11: SCORE 50-70% | G11: SCORE LOW | H11: SCORE ZERO
A12: 1 | B12: Greenfield | C12: 20 | D12: The most important dimension. Greenfield = no incumbent FSM to displace, no contract to wait out, no migration friction. Combined with paper-based ops + QuickBooks-only signals = highest-velocity engagement opportunity. V2 reweights this from 25/100 to 20/100 to make room for new dimensions. | E12: Pure greenfield (20) No FSM, paper-based ops, QB-only | F12: Mostly greenfield (12-15) Light tools, partial coverage | G12: Mixed (5-10) Proprietary FSM partial, conflict risk | H12: ServiceTitan/incumbent mandated (0)
A13: 2 | B13: Network | C13: 15 | D13: Bigger network = bigger mandate opportunity = bigger ARR. Caps at 15 in V2 (was 20 in V1) so size doesn't dominate the score — a smaller network with stronger greenfield can outrank a larger network with displacement risk. | E13: 7,500+ techs (15) | F13: 3,000–7,499 techs (10-12) | G13: 1,000–2,999 techs (6-8) | H13: Under 1,000 techs (3-5)
A14: 3 | B14: PE | C14: 15 | D14: PE in Year 4-6 of hold needs EBITDA improvement to maximize exit multiple. That urgency is an open door — value creation initiatives align with our pitch. Reweighted from 20 to 15 in V2 to share weight with new dimensions. | E14: Year 5-6 / exit imminent (15) | F14: Year 3-4 / approaching (10-12) | G14: Founder/family / fast decision (6) | H14: Early hold / family office (3)
A15: 4 | B15: DM Access | C15: 15 | D15: NEW V2 dimension (consolidated from V1 Contact Accessibility + GPS Warm Flag). Can we reach the decision maker directly, via warm path, or only via PE intro? GPSI customer overlap, parent-level relationships, and direct LinkedIn reach all factor in. Higher score = lower friction. | E15: Direct path + GPSI warm + PE intro available (13-15) | F15: Direct LinkedIn + warm path (10-12) | G15: Requires PE intro only (5-8) | H15: No path identified (0-3)
A16: 5 | B16: Urgency | C16: 15 | D16: NEW V2 dimension. Captures *when* the engagement window opens and *what triggers it*: leadership transitions, FSM contract renewals, exit windows, reassessment periods. Higher urgency = act now, not later. | E16: Imminent trigger (renewal, leadership transition) (13-15) | F16: Mid-term window (8-12) | G16: Long-term reassessment posture (4-7) | H16: No urgency signal (0-3)
A17: 6 | B17: Displacement | C17: 10 | D17: NEW V2 dimension (replaces V1 GPS Warm Flag). Even if not pure greenfield, can we displace the incumbent? Mixed FSM landscape with no entrenched mandate = wedge entry possible. Lower weight (10) because greenfield is preferable, but real opportunities exist. | E17: Mixed FSM, no entrenched mandate (8-10) | F17: Partial competitor mandate (5-7) | G17: Entrenched competitor (2-4) | H17: ServiceTitan locked in (0)
A18: 7 | B18: C/B Mix | C18: 10 | D18: NEW V2 dimension (replaces V1 Pilot Fit). Consumer/B2B mix shapes engagement narrative and channel selection. Consumer-led brands favor recurring-billing ROI math. B2B/commercial brands need account-based outreach. Mix indicator helps calibrate the engagement framework per brand. | E18: Consumer-led, recurring service model (8-10) | F18: Mixed B2B/consumer (5-7) | G18: Heavily B2B/commercial (3-5) | H18: Project-based, low recurring (1-3)
A20: SECTION 2 · STAGE 2 (BRAND-CORP) SCORING DIMENSIONS · Same 7 V2 dimensions, reweighted for brand-corp velocity
A21: # | B21: DIMENSION | C21: MAX PTS | D21: WHY THIS MATTERS | E21: SCORE 100% | F21: SCORE 50-70% | G21: SCORE LOW | H21: SCORE ZERO
A22: 1 | B22: Greenfield | C22: 30 | D22: Same gate as Stage 1 but reweighted higher (30% vs 20%) at brand-corp level. Brand-corp velocity depends on absence of incumbent FSM. Greenfield + paper + QuickBooks-only = fastest pilot path. This is why a small brand-corp can outrank a large one if greenfield is stronger. | E22: Pure greenfield + paper/QB (30) | F22: Mostly greenfield, light tools (18-22) | G22: Mixed FSM partial (8-15) | H22: Mandated FSM (0)
A23: 2 | B23: Network | C23: 15 | D23: Brand-corp network size — operators × techs per operator. Smaller weight than franchisor level (15% same) but interpreted differently: a 100-operator brand at $300/tech can outrank a 1,000-operator brand if greenfield is strong. | E23: 500+ operators (15) | F23: 200-499 (10-12) | G23: 50-199 (6-8) | H23: <50 (3-5)
A24: 3 | B24: PE | C24: 10 | D24: LOWER WEIGHT at brand-corp (10% vs 15% at franchisor). Brand presidents don't optimize for parent-co exit math — they optimize for brand-level operations. PE inheritance is contextual, not a primary driver. Used as parent-tier modifier. | E24: P1 parent, active PE exit window (10) | F24: P1 parent, mid hold (6-8) | G24: P2/P3 parent (3-5) | H24: No parent franchisor (0)
A25: 4 | B25: DM Access | C25: 15 | D25: Same weight as franchisor level. Brand corp leadership access — brand president/COO direct, GPSI customer overlap, warm path through parent. Critical at brand-corp because relationships are more lateral than top-down. | E25: Brand president direct + GPSI warm (13-15) | F25: Brand corp accessible, no GPSI (8-12) | G25: Requires parent-franchisor warm path (4-7) | H25: No identified contact (0-3)
A26: 5 | B26: Urgency | C26: 15 | D26: Same weight. Brand-corp triggers: leadership transitions, FSM contract renewals at major franchisees, brand-level competitive pressure, parent-franchisor exit pressure cascading down. | E26: New brand president + open roadmap (13-15) | F26: Mid-term reassessment window (8-12) | G26: Stable leadership, defined roadmap (4-7) | H26: Locked in, no near-term shift (0-3)
A27: 6 | B27: Displacement | C27: 5 | D27: LOWER WEIGHT at brand-corp (5% vs 10%). Brand-corps with mandated competitive FSM are rare — most are mixed/franchisee-choice. When they ARE locked in, the conversation happens at parent level (Stage 1), not Stage 2. | E27: Mixed FSM, wedge possible (4-5) | F27: Partial mandate (2-3) | G27: Strong incumbent (1) | H27: Locked in (0)
A28: 7 | B28: C/B Mix | C28: 10 | D28: Same weight. Consumer mix favors trade press + reviews; B2B mix favors account-based outreach. Critical for calibrating engagement architecture (5-channel framework) per brand-corp profile. | E28: Consumer-led recurring (8-10) | F28: Mixed (5-7) | G28: Heavily B2B (3-5) | H28: Project-only (1-3)
A30: SECTION 3 · FRANCHISOR BONUS · How the franchisor score feeds into franchisee combined score
A31: FRANCHISOR SCORE | B31: PRIORITY TIER | C31: BONUS ADDED TO FRANCHISEE | D31: RATIONALE
A32: 70 – 100 | B32: 🔴 MOVE NOW | C32: +25 points | D32: Full GTM motion active. Pilot inside this network directly feeds the franchisor close. Maximum urgency.
A33: 45 – 69 | B33: 🟡 ACTIVE PIPELINE | C33: +15 points | D33: 30-60 day pipeline. Pilot still strategically valuable. Feeds the relationship as it develops.
A34: 1 – 44 | B34: ⚪ RELATIONSHIP BUILD | C34: +5 points | D34: Franchisor relationship early-stage. Pilot adds some value but network close is 90+ days out.
A35: 0 / None | B35: No franchisor relationship | C35: +0 points | D35: No parent relationship active. Franchisee pilot stands alone. Score on franchisee dimensions only.
A37: SECTION 4 · CURRENT FRANCHISOR SCORES · V2 Ranking Live Results from Track 1 (April 28, 2026)
A38: RANK | B38: FRANCHISOR | C38: SCORE / 100 | D38: PRIORITY | E38: FRANCHISEE BONUS | F38: KEY DRIVER
A39: 1 | B39: NEIGHBORLY | C39: 76.5 | D39: 🔴 P1 #1 | E39: +25 | F39: PE-GATED — KKR warm path required. Largest network + highest urgency.
A40: 2 | B40: AUTHORITY BRANDS | C40: 68.5 | D40: 🟡 P1 #2 | E40: +15 | F40: DISPLACEMENT-READY. New CEO + CFO. 12 non-ST brands displaceable.
A41: 3 | B41: EMPOWER BRANDS | C41: 66.2 | D41: 🟡 P1 #3 | E41: +15 | F41: GREENFIELD-LED. Strongest greenfield (90/100). Commercial mix drag.
A42: 4 | B42: RESIBRANDS | C42: 60.2 | D42: 🟢 P1 #4 | E42: +15 | F42: FAST-CYCLE. Founder direct (Kevin Luu). Smallest network but fastest decision.
A43: 5 | B43: FIVE STAR FRANCHISING | C43: 59.2 | D43: 🟡 P1 #5 | E43: +15 | F43: WEDGE-BRAND. Mosquito Shield wedge to Five Star CEO Scott Abbott.
A44: 6 | B44: PREMIUM SERVICE BRANDS | C44: 59 | D44: 🟡 P1 #6 | E44: +15 | F44: GREENFIELD-OPEN. RooterMan dominates. Susquehanna PE less active.
A45: 7 | B45: HOMEFRONT BRANDS | C45: 44 | D45: ⚪ P1 #7 | E45: +5 | F45: MONITOR-MODE. Family office, no exit pressure. Q3/Q4 2026 reassessment.
A46: P2-1 | B46: BELFOR FRANCHISE GROUP | C46: P2 SET | D46: 🟡 EXISTING | E46: +25 | F46: DE-FACTO ANCHOR — HOODZ + DUCTZ at 94% SB. Convert before exit window.
A47: P2-2 | B47: EVIVE BRANDS | C47: P2 SET | D47: 🟢 EXISTING | E47: +25 | F47: GROWING ANCHOR — Brothers Gutters 43% under contract. Riverside, Year 3.
A48: P2-3 | B48: THRESHOLD BRANDS | C48: P2 SET | D48: 🔴 AT-RISK | E48: +15 | F48: AT-RISK ANCHOR — USA Insulation transitioning OFF SB. Defensive posture.

Sheet 🔍 Competition Intel
A1: 🔍 COMPETITION INTELLIGENCE — FSM & Telematics Landscape
A2: COMPETITOR | B2: CATEGORY | C2: TARGET SEGMENT | D2: PRIMARY MESSAGING | E2: KEY CLAIMS (VERBATIM / NEAR) | F2: FRANCHISE STRATEGY | G2: KNOWN ACCOUNTS (MANDATED) | H2: PRICING SIGNAL | I2: MARKETING CHANNELS | J2: WEAKNESS / VULNERABILITY | K2: SERVICEBRIDGE COUNTER | L2: LAST UPDATED | M2: SOURCE | N2: WATCH PRIORITY
A3: ServiceTitan | B3: FSM — Enterprise | C3: Mid-market to enterprise trades. HVAC, plumbing, electrical. Franchise networks (100+ units) | D3: "The operating system for the trades." Position as infrastructure you cannot run without — not a software tool but a business platform. Empowerment, professionalism, profitability. | E3: "21% average revenue increase in first two years." "15-25% revenue lift." "24% growth in revenue reported by users ending July 2024." "95%+ gross retention rate." "110%+ net revenue retention." | F3: Active top-down mandate play. Authority Brands (Sep 2024) — Benjamin Franklin Plumbing, Mister Sparky, One Hour H&A. Neighborly group contract. Lennox preferred/exclusive FSM partner. Direct PE relationship outreach. Pantheon user conference 3,700+ attendees. ABM strategy targeting franchisors. | G3: Mr. Rooter, Mr. Electric, Mosquito Joe, Precision Door (Neighborly mandate). Benjamin Franklin Plumbing, Mister Sparky, One Hour H&A (Authority Brands mandate Sep 2024). Lennox preferred partner. | H3: Enterprise pricing. Contracts can exceed $100K/year. Three tiers: Core, Pro, FinTech. Per-technician pricing. Not publicly listed. | I3: LinkedIn (101K followers) — thought leadership + case studies. Google SEO (200+ content pieces/month). Pantheon annual conference. Toolbox Live events (8 regional in 2024). Partner co-selling (Ferguson Enterprises, Scorpion, QuickBooks). ABM outreach to franchise execs. | J3: Complex, expensive, long implementation. Overkill for 2-10 tech operators. Requires dedicated admin. Franchisee complaints about cost. No native telematics/GPS integration. Sold top-down — franchisees often resent mandate. | K3: GPS Insight + ServiceBridge = native telematics + FSM in one ecosystem — ST cannot match this. Week-1 ROI vs ST's long onboarding. Franchise-native pricing vs ST enterprise contract. Charles Layne relationship = inside track ST doesn't have. FDD-loaded Insight Engine vs ST generic demo. | L3: April 2026 | M3: servicetitan.com/press + LinkedIn company page + portersfiveforce.com analysis | N3: 🔴 #1 THREAT
A4: FieldRoutes (ServiceTitan family) | B4: FSM — Route-Based | C4: Pest control, lawn care, pool service. Route-based recurring service models. Small to mid-market. | D4: Purpose-built for route-based service businesses. Recurring revenue optimization. Customer retention tools. Part of ServiceTitan family since acquisition. | E4: Purpose-built for pest, lawn, pool. Recurring revenue platform. Route optimization. Customer portal and online booking. | F4: Bundled with ServiceTitan franchise push. Mosquito Shield (likely in use per FDD — multiple approved software). Route-based franchise networks. Less aggressive direct franchise outreach than ST. | G4: Mosquito Shield (likely — FDD notes multiple software approved). Various pest control franchise operators. Pool service networks. | H4: Mid-market pricing. Lower than full ST. Specific pricing not public. Per-technician or route-based. | I4: FieldRoutes.com content marketing. ServiceTitan ecosystem events. Trade publications (pest control, lawn). Limited LinkedIn presence vs ST parent. | J4: Limited to route-based trades — no emergency dispatch strength. No telematics integration. Less franchise infrastructure than ST. Being absorbed into ST brand may cause identity confusion. | K4: ServiceBridge covers both route AND emergency dispatch — FieldRoutes only does route. GPS Insight fleet integration is native. Better for multi-trade franchise networks (BELFOR brands need both restoration dispatch AND route pest). | L4: April 2026 | M4: fieldroutes.com + ServiceTitan press releases + FDD analysis | N4: 🟡 WATCH
A5: Jobber | B5: FSM — SMB | C5: Small businesses 1-20 techs. Solo operators to small crews. Landscaping, cleaning, HVAC, plumbing. Price-sensitive market. | D5: "Run stronger businesses, not just busier ones." Simple, affordable, mobile-first. Designed for the operator doing everything themselves. "29 million+ jobs completed." | E5: "I went from 20 customers to 60." "We've grown from $500K to nearly $3M per year — I would attribute a lot of that success to Jobber." "Saved at least 10 hours a week just doing payments." AI-powered Copilot coming. | F5: Limited franchise infrastructure. Has franchise reporting but described as lacking (90-day data limit). Not actively pursuing large franchise networks. Plus plan ($599/mo) positioned for franchises but weak vs ST. | G5: Independent operators. Some small franchise locations as individual accounts — not network-level mandates. | H5: Core $39/mo → Plus $599/mo. Per-user add-on $29/user. Annual discount up to 40%. Transparent public pricing. Most affordable FSM in the market. | I5: Google SEO. Social media (Instagram, Facebook targeting home service owners). $150K grant program (community/PR play). Jobber Blueprint educational content. Word-of-mouth/referral heavy. | J5: Not built for franchise networks. No franchisor dashboard. No PE exit math. No telematics. Per-user pricing gets expensive at scale. No insurance carrier documentation angle. AI features "coming soon" as of 2025. | K5: ServiceBridge is purpose-built for franchise networks — multi-unit owner dashboard, franchisor reporting, mandate deployment. Jobber is solo-operator software. GPS Insight integration adds fleet layer Jobber cannot match. | L5: April 2026 | M5: getjobber.com + connecteam.com review + tekpon pricing analysis | N5: 🟢 LOW — different segment
A6: Housecall Pro | B6: FSM — SMB/Mid | C6: Small-mid service businesses. HVAC, plumbing, cleaning. Growth-stage operators. Similar segment to Jobber but slightly larger. | D6: "The all-in-one platform for home service pros." Ease of use, fast setup, consumer financing (HCP Finance). Growth tools built in. | E6: Online booking, 2-way texting, automated follow-ups. Payment processing native. Consumer financing (HCP Finance). Strong mobile app. | F6: Limited. Some franchise support but not a primary market. Does not actively pursue franchisor mandates at PE level. | G6: Independent operators. Some regional franchise locations as individual accounts. | H6: Basic $49/mo → Max pricing on request. Transparent tiered pricing. Mid-range. | I6: Google + social media. Strong review presence (G2, Capterra). Content marketing for home service operators. Similar channels to Jobber. | J6: No franchise network infrastructure. No telematics. No PE exit math. No franchisor dashboard. Limited enterprise capability. | K6: Same as Jobber — ServiceBridge is franchise-native, GPS-integrated, and built for multi-unit deployment. Housecall Pro is individual operator software. | L6: April 2026 | M6: housecallpro.com + G2 reviews + competitor comparison sites | N6: 🟢 LOW — different segment
A7: Salesforce Field Service | B7: FSM — Enterprise | C7: Large enterprises. Multi-industry. Not home services specific. Requires Salesforce CRM foundation. | D7: #1 FSM on G2. AI-powered scheduling. Enterprise scale. Einstein AI built in. Full Salesforce ecosystem integration. | E7: AI-powered field service. Route optimization. Offline-first mobile. Best for enterprise requiring full CRM + FSM + ERP integration. | F7: Not actively targeting home service franchise networks. Too expensive and complex for typical franchise operator. May appear at large PE-owned service conglomerates. | G7: Large enterprise accounts. Not typically in home service franchise space. | H7: Enterprise — starts ~$150/user/month and up significantly. Full Salesforce licensing required. | I7: Salesforce ecosystem events (Dreamforce). Enterprise sales team. Digital marketing to enterprise IT buyers. | J7: Requires Salesforce CRM license — massive additional cost. Not home-service specific. Complex implementation. Overkill for franchise operators. No GPS telematics native. | K7: ServiceBridge purpose-built for franchise home service — no CRM license required, no 6-month implementation, GPS Insight native integration. | L7: April 2026 | M7: salesforce.com/service/field-service + G2 analysis | N7: 🟢 LOW — different segment
A9: 📡 HOW TO MONITOR COMPETITOR MESSAGING — Live Sources
A10: Meta Ad Library | D10: facebook.com/ads/library — Free. Search any competitor name to see every active Facebook/Instagram ad. Shows copy, creative, targeting signals. Updated in real time.
A11: LinkedIn Ad Library | D11: Go to competitor LinkedIn page → Posts → Ads tab. Shows all active sponsored content. Best for B2B franchise exec targeting.
A12: Google Ads Transparency | D12: adstransparency.google.com — See all active Google ads for any advertiser. Shows search and display copy.
A13: SpyFu | D13: spyfu.com — Shows competitor Google Ads history, keyword spend, top ad copy. Paid but affordable ($39/mo). Best for seeing what's working over time.
A14: Subscribe to their funnel | D14: Download their whitepapers. Sign up with a secondary email. Attend their webinars. Their full nurture sequence becomes visible in 2-3 weeks.
A15: G2 / Capterra reviews | D15: Read negative reviews on G2 and Capterra for each competitor. This tells you exactly what their customers complain about — those are your talking points.
A16: LinkedIn company page | D16: Follow ServiceTitan, Jobber, Housecall Pro, FieldRoutes. Watch their organic posts for messaging shifts, new product announcements, partnership news.

Sheet 📣 Marketing & Offers
A1: 📣 MARKETING, ADVERTISING, EVENTS & OFFERS — ServiceBridge GTM Program
A3: 🍽️ SECTION 1 — THE PILOT OFFER: "Lunch & Launch"
A4: Offer Name | B4: The Lunch & Launch — ServiceBridge 30-Day Pilot
A5: Tagline | B5: "We buy lunch. You get live. Let the numbers do the talking."
A6: What We Send | B6: $50 DoorDash/Uber Eats gift card + personal invite from GPS Insight account rep or Charles Layne
A7: What We Schedule | B7: 45-minute virtual 'Lunch & Install' session with a ServiceBridge tech. Franchisee gets full platform live during the call.
A8: Trial Terms | B8: 30 days full access. No credit card. No contract. No obligation. We set it up — they just show up.
A9: Target Volume | B9: 20 franchisees per cohort. Run 2-3 cohorts across different parent networks before going back to franchisor.
A10: Target Networks (Priority Order) | B10: 1. BELFOR franchisees — GPS Insight warm intro via account rep. Greenfield + insurance angle. 2. Five Star Franchising — Princeton PE exit window open. Bio-One, 1-800-Packouts, Five Star Bath Solutions. 3. PSB (Premium Service Brands) — Roxanne Conrad intro path. 360 Painting, ProLift, House Doctors.
A11: Source of 20 | B11: Andrea Rowan → GPS Insight telematics customer list → identify BELFOR franchisees already on GPS Insight → account rep makes warm intro. This is the unlock. Without the list we are cold calling.
A12: What 'Install' Means | B12: ServiceBridge tech shares screen. Enters franchisee's real business info (name, address, 3-5 services). Creates sample jobs, shows dispatch board, runs a payment. Franchisee leaves with a live account, not a demo.
A13: Ask at Day 30 | B13: 1. One testimonial quote (written or on video, 60 sec) 2. Permission to share usage data with their franchisor 3. NPS score (1-10 would you recommend to another franchisee in your network) 4. Referral to one other franchisee in their network
A14: Franchisor Close | B14: After 20 pilots: deliver 'Cohort Report' to franchisor exec showing: # active users, avg jobs dispatched, avg payment collected, NPS score, 3 verbatim quotes. Frame as: 'Your operators have already voted.'
A15: Gift Card Budget | B15: 20 franchisees × $50 = $1,000 per cohort. Three cohorts = $3,000 total pilot investment.
A16: Launch Date | B16: May 1, 2026 — aligns with outreach start date. First cohort closes June 1. Franchisor close meetings June-July.
A18: 📬 SECTION 2 — PILOT OUTREACH SEQUENCE (Per Franchisee)
A19: TOUCH | B19: TIMING | C19: CHANNEL | D19: FROM | E19: SUBJECT / HOOK | F19: MESSAGE BODY | G19: GOAL
A20: 1 | B20: May 1 Week 1 | C20: GPS Acct Rep Phone/Email | D20: GPS Insight Account Rep | E20: Quick intro — your fleet + your jobs | F20: Hey [Name], I work with GPS Insight on your fleet account. We just launched a pilot program with ServiceBridge — the FSM platform that connects directly to your GPS Insight data. We're inviting 20 operators across your network for a free 30-day trial. We send you lunch, our tech gets you live in 45 minutes. No contract, no card. Want to see it? | G20: Warm intro. Get a yes or a time.
A21: 2 | B21: May 5-7 Week 1 | C21: Email | D21: Mike Flynt Velocity GTM | E21: Lunch is on us — [Name]'s numbers in ServiceBridge | F21: Hi [Name], [Rep name] from GPS Insight mentioned you might be interested in seeing ServiceBridge live. Here's the offer: We send you a $50 DoorDash gift card. You join a 45-minute Zoom with one of our techs. We build your account live — real jobs, real dispatch, real payment. You keep it free for 30 days. No contract. No credit card. Just lunch and 45 minutes. I pre-loaded your numbers from [Parent Network] FDD data into our ROI model. Want me to share what it shows? — Mike Velocity GTM Co / GPS Insight GTM Partner | G21: Send gift card offer + Insight Engine teaser.
A22: 3 | B22: May 12-14 Week 2 | C22: Phone | D22: Mike Flynt Velocity GTM | E22: Following up on the Lunch & Launch invite | F22: Quick call to follow up on the email. Did the numbers look roughly right for your operation? I can adjust the model on the call. The 45-minute install slot is filling up — we're only running 20 operators in this first cohort. Wanted to make sure you had first access given the GPS Insight relationship. | G22: Book the install session.
A23: 4 | B23: Install Day (Booked) | C23: Zoom | D23: ServiceBridge Tech + Mike | E23: Lunch & Launch — [Name] live in ServiceBridge | F23: 45-minute session: 1. Tech shares screen, enters franchisee info live (5 min) 2. Creates 3 sample jobs matching their trade (10 min) 3. Shows dispatch board, scheduling, mobile tech view (10 min) 4. Runs a test payment, shows reporting dashboard (10 min) 5. Mike walks through Insight Engine with real numbers (10 min) Franchisee leaves with a live account and a gift card code. | G23: Get them live. Create a wow moment.
A24: 5 | B24: Day 15 Mid-trial | C24: Email | D24: ServiceBridge Tech | E24: How's [Name]'s account looking? Quick check-in | F24: Hi [Name], just checking in on your ServiceBridge account. You've had it 2 weeks — have you had a chance to dispatch any real jobs through it? Happy to jump on a quick 15-minute call if you hit any snags. We want to make sure you're getting full value out of the 30 days. | G24: Drive activation. Catch issues early.
A25: 6 | B25: Day 28-30 Close | C25: Phone + Email | D25: Mike Flynt Velocity GTM | E25: Your 30 days — what did you think? | F25: Hi [Name], Your pilot wraps up in 2 days. Here's what your account shows: [X jobs dispatched, $X collected, X active]. Two quick asks: 1. Would you be willing to share a quick quote about your experience — even one sentence? We're building a report to take back to [Parent Franchisor]. 2. NPS: On a scale of 1-10, would you recommend ServiceBridge to another [Parent Network] franchisee? Either way, we'd love to keep your account live. Happy to talk options. — Mike | G25: Get testimonial + NPS. Convert to paid or reference.
A27: 📅 SECTION 3 — FRANCHISE EVENTS CALENDAR (Vendor/Sponsor Opportunities)
A28: EVENT | B28: FRANCHISOR/NETWORK | C28: DATE | D28: LOCATION | E28: TYPE | F28: OPPORTUNITY | G28: CONTACTS | H28: STATUS | I28: PRIORITY
A29: BELFOR Franchise Group Annual Convention | B29: BELFOR / All BFG Brands | C29: Feb 2027 (est.) | D29: TBD | E29: Annual Convention | F29: Vendor expo floor. 14 brands + franchisees in one room. Rusty Amarante + Beth Toenies intro path. | G29: Beth Toenies (VP FD) Rusty Amarante (President BFG) | H29: Research 2026 date | I29: 🔴 HIGH
A30: HomeFront Homecoming 4 | B30: HomeFront Brands | C30: Nov 2026 | D30: Orlando, FL | E30: Annual Convention | F30: Vendor/sponsor opportunity. Jeff Dudan founder event. All HomeFront franchisees in one room. | G30: Jeff Dudan (CEO) Zack Dudan (CGO) | H30: ⚠️ Confirm vendor registration | I30: 🔴 HIGH
A31: IFA Annual Convention | B31: International Franchise Association | C31: Feb 2027 (est.) | D31: TBD | E31: Industry Conference | F31: Franchisor CEOs, PE operating partners, brand presidents all attend. Best place to build relationships outside of direct outreach. | G31: All franchisor contacts | H31: Research 2027 date | I31: 🟡 MEDIUM
A32: Five Star Franchising Annual Convention | B32: Five Star Franchising | C32: Q1 2027 (est.) | D32: TBD | E32: Annual Convention | F32: Princeton PE Year 5 — Scott Abbott + Steve White attending. Bio-One, Mosquito Shield franchisees. Exit window messaging. | G32: Scott Abbott (CEO) Steve White (CFO) Michael Moorhouse (Mosquito Shield) | H32: Research date | I32: 🟡 MEDIUM
A33: Threshold Brands Franchise Convention | B33: Threshold Brands / Riverside | C33: Q1-Q2 2027 (est.) | D33: TBD | E33: Annual Convention | F33: MaidPro, USA Insulation, Sir Grout franchisees. Riverside PE Year 4 exit window context. | G33: Hagan Kappler (CEO — verify) Andrea Hohermuth (COO) | H33: Research date | I33: 🟡 MEDIUM
A34: PSB Annual Conference | B34: Premium Service Brands | C34: Q2 2027 (est.) | D34: Charlottesville, VA area | E34: Annual Convention | F34: 360 Painting, ProLift, RooterMan franchisees. Paul Flick (Founder/CEO) in attendance. | G34: Paul Flick (CEO) Roxanne Conrad (COO) Gabe Colon (EVP Performance) | H34: Research date | I34: 🟡 MEDIUM
A35: Authority Brands Franchise Conference | B35: Authority Brands / Apax | C35: Q1-Q2 2027 (est.) | D35: TBD | E35: Annual Convention | F35: Jay Caiafa (new CEO Aug 2025) + Tij Bedi (CTO). New leadership = new vendor relationships possible. 12 brands in attendance. | G35: Jay Caiafa (CEO) Tij Bedi (CTO) | H35: Research date + reach via Tij Bedi | I35: 🟡 MEDIUM
A36: Franchise Times Forum | B36: Industry | C36: Oct 2026 (est.) | D36: TBD | E36: Industry Conference | F36: Franchise execs + PE operators. Good for Neighborly/KKR relationship building at safe distance. | G36: Felix Gernburd (KKR) — do not approach direct | H36: Research date | I36: ⚪ LOW
A38: 📡 SECTION 4 — ADVERTISING & CHANNEL PLAN
A39: CHANNEL | B39: TARGET AUDIENCE | C39: MESSAGE / HOOK | D39: FORMAT | E39: BUDGET SIGNAL | F39: TIMING | G39: STATUS
A40: LinkedIn — Organic | B40: Franchise CEOs, PE operating partners, CFOs, CTOs in home services | C40: Insight Engine results for specific networks. PE exit math posts. 'What franchise operators are leaving on the table' content. | D40: Text posts + images. 2-3x/week. | E40: Zero cost — Mike's LinkedIn | F40: Start May 1 | G40: 📝 Plan content calendar
A41: LinkedIn — Targeted DM | B41: CEOs, COOs, CFOs at target franchisor accounts. PE deal teams. | C41: Personalized outreach referencing FDD data, Insight Engine pre-loaded with their numbers. Not a cold pitch — a warm data share. | D41: Direct message. 200-300 words max. | E41: Zero cost | F41: Start May 1 per outreach sequence | G41: 📝 Drafts needed per account
A42: LinkedIn — Paid Ads (Phase 2) | B42: Franchise executives at target networks. Job titles: CEO, COO, CFO, CTO, VP Operations, Franchise Dev | C42: 'We already know your numbers.' Lead with Insight Engine output as creative. Drive to landing page. | D42: Single image ads + carousel. Lead gen form. | E42: $500-1,000/mo test budget (Phase 2 only) | F42: Post-first-pilot (July 2026+) | G42: ⏸️ Hold until pilot data in hand
A43: Email — Warm Intro Sequence | B43: GPS Insight account reps → their franchisee contacts | C43: Lunch & Launch offer. Gift card + 45-min install. Personalized with FDD numbers. | D43: Plain text email. 150-200 words. Personal tone. | E43: Zero cost | F43: May 1 — coordinated with Andrea | G43: ⚠️ Needs Andrea's account rep list
A44: GPS Insight Newsletter / Customer Comms | B44: GPS Insight existing customers who are franchise operators | C44: 'Did you know your GPS Insight data connects directly to ServiceBridge FSM?' Awareness play inside existing customer base. | D44: GPS Insight internal comms. Article or email blast. | E44: Zero cost (coordinate with Andrea) | F44: Q2 2026 | G44: ⚠️ Needs Andrea + Charles approval
A45: Franchise Trade Press (PR / Contributed Article) | B45: Franchise Times, Franchise Business Review, multi-unit franchising publications | C45: 'What PE-backed franchise networks look for in FSM: the exit multiple conversation no one is having.' Thought leadership positioning Mike as the expert. | D45: 1,200-word contributed article. Bylined by Mike Flynt. | E45: Zero cost (contributed editorial) | F45: Submit June 2026 — after first pilot data | G45: 📝 Draft outline needed
A46: The ServiceBridge Advantage (Direct Mail) | B46: CEOs / COOs at top 9 franchisor targets | C46: Physical copy of The ServiceBridge Advantage doc + handwritten note from Charles Layne. Delivered before first outreach touch. | D46: Printed 19-page doc + cover letter. FedEx envelope. | E46: $50-100/package × 9 = $450-900 | F46: April 28 — week before May 1 outreach | G46: ⚠️ Needs Charles to sign cover letter
A48: 🎁 SECTION 5 — OFFER LIBRARY
A49: OFFER NAME | B49: TARGET | C49: DESCRIPTION | D49: HOOK | E49: ASK IN RETURN | F49: COMMERCIAL TERMS | G49: STATUS
A50: 🍽️ Lunch & Launch 30-Day Pilot | B50: Franchisees (Greenfield operators 2-10 techs) | C50: $50 DoorDash gift card + 45-min virtual install session with ServiceBridge tech. Full platform access for 30 days. Account built live during the call. | D50: "We buy lunch. You get live. Let the numbers do the talking." | E50: 1 testimonial quote 1 NPS score (1-10) Permission to share data with franchisor 1 referral to another franchisee | F50: 30-day free trial. Standard pricing after. No contract lock-in. | G50: ✅ READY TO DEPLOY Launch May 1, 2026
A51: 📊 Insight Engine Franchisor Briefing | B51: Franchisor CEOs, CFOs, PE Operating Partners | C51: Pre-loaded ROI model with their specific network data (FDD-sourced). Delivered as a 30-minute 'data briefing' — not a pitch. 'Here's what your network looks like.' | D51: "No generic demo. Your numbers, your network, before the first call." | E51: 30-minute follow-up call with ops team Introduction to 2 franchisees for pilot | F51: No cost. Tool freely provided. Commercial conversation follows pilot data. | G51: ✅ READY TO DEPLOY Insight Engine v4 built
A52: 🤝 GPS Insight Warm Intro Offer | B52: GPS Insight existing customers who are franchise operators | C52: For franchisees already on GPS Insight: ServiceBridge as the FSM layer on top of existing fleet data. 'Your trucks are already tracked — now connect the jobs.' | D52: "You already trust GPS Insight with your fleet. ServiceBridge completes the picture." | E52: Reference call with 1 other GPS Insight customer Usage data sharing | F52: GPS Insight customer discount TBD with Andrea/Charles. Bundled pricing conversation. | G52: ⚠️ PENDING Needs Andrea approval on bundle pricing
A53: 🏆 Cohort Report Franchisor Close | B53: Franchisor CEOs after 20-pilot cohort | C53: After 20 pilot completions: deliver a branded 'Cohort Report' showing aggregate results — active users, jobs dispatched, NPS, 3 verbatim quotes, revenue impact. Walk it into the franchisor meeting. | D53: "Your operators have already voted. Here's what they said." | E53: Commitment to 90-day network pilot Introduction to PE operating partner | F53: Network pilot pricing TBD based on tech count. Volume discount vs individual operator pricing. | G53: 📝 TEMPLATE NEEDED Build after first cohort data
