Workbook

Sheet Executive Scorecard
A1: EXECUTIVE SCORECARD · ServiceBridge Franchisor GTM Engagement · April – June 2026
A2: Prepared by Velocity GTM Co LLC · Michael Montgomery Flynt Jr · Metrics auto-update as activity is logged across all tabs
B3: METRIC | D3: TARGET | E3: ACTUAL | F3: % TO GOAL | G3: STATUS
B5: PHASE 1 · 30-DAY · DEVELOP
B6: Target: End of April 2026 · Build the foundation for both tracks
B8: TRACK 1 — FRANCHISOR
B9: Franchisors Profiled (deep research complete) | D9: 9 | E9: =COUNTIF('Track 1 · Franchisors'!D4:D12,"TIER 1")+COUNTIF('Track 1 · Franchisors'!D4:D12,"TIER 2")+COUNTIF('Track 1 · Franchisors'!D4:D12,"TIER 3") | F9: =IFERROR(E9/9,0) | G9: =IF(E9>=9,"✅ On Track",IF(E9>=9*0.7,"⚠️ At Risk","🔴 Behind"))
B10: Contacts Mapped (3+ per franchisor = 27 total) | D10: 27 | E10: =0 | F10: =IFERROR(E10/27,0) | G10: =IF(E10>=27,"✅ On Track",IF(E10>=27*0.7,"⚠️ At Risk","🔴 Behind"))
B11: Outreach Sequences Live (both tracks active) | D11: 9 | E11: =COUNTIFS('Track 1 · Franchisors'!L4:L12,"Contacted")+COUNTIFS('Track 1 · Franchisors'!L4:L12,"Replied")+COUNTIFS('Track 1 · Franchisors'!L4:L12,"Call Scheduled")+COUNTIFS('Track 1 · Franchisors'!L4:L12,"Discovery Done")+COUNTIFS('Track 1 · Franchisors'!L4:L12,"Proposal Sent")+COUNTIFS('Track 1 · Franchisors'!L4:L12,"Negotiating")+COUNTIFS('Track 1 · Franchisors'!L4:L12,"Pilot Closed") | F11: =IFERROR(E11/9,0) | G11: =IF(E11>=9,"✅ On Track",IF(E11>=9*0.7,"⚠️ At Risk","🔴 Behind"))
B12: TRACK 2 — FRANCHISEE
B13: Franchisee Brands Scored (all 85 in database) | D13: 85 | E13: =COUNTA('Track 2 · Franchisees'!B4:B88)-COUNTBLANK('Track 2 · Franchisees'!B4:B88) | F13: =IFERROR(E13/85,0) | G13: =IF(E13>=85,"✅ On Track",IF(E13>=85*0.7,"⚠️ At Risk","🔴 Behind"))
B14: Contacts Validated (one per brand) | D14: 85 | E14: =COUNTA('Track 2 · Franchisees'!J4:J88)-COUNTIF('Track 2 · Franchisees'!J4:J88,"(Franchisee Owner)")-COUNTIF('Track 2 · Franchisees'!J4:J88,"(TBD — Research)")-COUNTIF('Track 2 · Franchisees'!J4:J88,"") | F14: =IFERROR(E14/85,0) | G14: =IF(E14>=85,"✅ On Track",IF(E14>=85*0.7,"⚠️ At Risk","🔴 Behind"))
B15: Outreach Sequences Live (brands contacted) | D15: 85 | E15: =COUNTIFS('Track 2 · Franchisees'!L4:L88,"Contacted")+COUNTIFS('Track 2 · Franchisees'!L4:L88,"Replied")+COUNTIFS('Track 2 · Franchisees'!L4:L88,"Call Scheduled")+COUNTIFS('Track 2 · Franchisees'!L4:L88,"Discovery Done")+COUNTIFS('Track 2 · Franchisees'!L4:L88,"Proposal Sent")+COUNTIFS('Track 2 · Franchisees'!L4:L88,"Negotiating")+COUNTIFS('Track 2 · Franchisees'!L4:L88,"Pilot Closed") | F15: =IFERROR(E15/85,0) | G15: =IF(E15>=85,"✅ On Track",IF(E15>=85*0.7,"⚠️ At Risk","🔴 Behind"))
B16: ENGAGEMENT ACTIVITY — CRM LOG
B17: Total Touchpoints Logged (all channels) | D17: 30 | E17: =COUNTA('Engagement Log'!B5:B80)-COUNTBLANK('Engagement Log'!B5:B80) | F17: =IFERROR(E17/30,0) | G17: =IF(E17>=30,"✅ On Track",IF(E17>=30*0.7,"⚠️ At Risk","🔴 Behind"))
B18: Positive Outcomes (replied, calls, meetings) | D18: 5 | E18: =COUNTIF('Engagement Log'!I5:I80,"Replied – Positive")+COUNTIF('Engagement Log'!I5:I80,"Call Scheduled")+COUNTIF('Engagement Log'!I5:I80,"Call Complete")+COUNTIF('Engagement Log'!I5:I80,"Meeting Complete")+COUNTIF('Engagement Log'!I5:I80,"Pilot Agreed") | F18: =IFERROR(E18/5,0) | G18: =IF(E18>=5,"✅ On Track",IF(E18>=5*0.7,"⚠️ At Risk","🔴 Behind"))
B20: PHASE 2 · 60-DAY · ENGAGE
B21: Target: End of May 2026 · Drive active conversations on both tracks
B23: TRACK 1 — FRANCHISOR
B24: Franchisors in Active Conversation | D24: 3 | E24: =COUNTIFS('Track 1 · Franchisors'!L4:L12,"Discovery Done")+COUNTIFS('Track 1 · Franchisors'!L4:L12,"Proposal Sent")+COUNTIFS('Track 1 · Franchisors'!L4:L12,"Negotiating")+COUNTIFS('Track 1 · Franchisors'!L4:L12,"Pilot Closed") | F24: =IFERROR(E24/3,0) | G24: =IF(E24>=3,"✅ On Track",IF(E24>=3*0.7,"⚠️ At Risk","🔴 Behind"))
B25: Mandate Validated (confirmed at franchisor level) | D25: 3 req. | E25: =0 | F25: — | G25: Manual
B26: Franchisor Discovery Calls Completed | D26: 3 | E26: =COUNTIF('Engagement Log'!H5:H80,"Discovery Call") | F26: =IFERROR(E26/3,0) | G26: =IF(E26>=3,"✅ On Track",IF(E26>=3*0.7,"⚠️ At Risk","🔴 Behind"))
B27: Proposals / ROI Models Submitted | D27: 1 | E27: =COUNTIFS('Track 1 · Franchisors'!L4:L12,"Proposal Sent")+COUNTIFS('Track 1 · Franchisors'!L4:L12,"Negotiating") | F27: =IFERROR(E27/1,0) | G27: =IF(E27>=1,"✅ On Track",IF(E27>=1*0.7,"⚠️ At Risk","🔴 Behind"))
B28: TRACK 2 — FRANCHISEE
B29: Franchisees Engaged (in active conversation) | D29: 25 | E29: =COUNTIFS('Track 2 · Franchisees'!L4:L88,"Replied")+COUNTIFS('Track 2 · Franchisees'!L4:L88,"Call Scheduled")+COUNTIFS('Track 2 · Franchisees'!L4:L88,"Discovery Done")+COUNTIFS('Track 2 · Franchisees'!L4:L88,"Proposal Sent")+COUNTIFS('Track 2 · Franchisees'!L4:L88,"Negotiating")+COUNTIFS('Track 2 · Franchisees'!L4:L88,"Pilot Closed") | F29: =IFERROR(E29/25,0) | G29: =IF(E29>=25,"✅ On Track",IF(E29>=25*0.7,"⚠️ At Risk","🔴 Behind"))
B30: Confirmed Next Steps (committed to follow-up) | D30: 10 | E30: =COUNTIFS('Track 2 · Franchisees'!L4:L88,"Call Scheduled")+COUNTIFS('Track 2 · Franchisees'!L4:L88,"Discovery Done")+COUNTIFS('Track 2 · Franchisees'!L4:L88,"Proposal Sent")+COUNTIFS('Track 2 · Franchisees'!L4:L88,"Negotiating")+COUNTIFS('Track 2 · Franchisees'!L4:L88,"Pilot Closed") | F30: =IFERROR(E30/10,0) | G30: =IF(E30>=10,"✅ On Track",IF(E30>=10*0.7,"⚠️ At Risk","🔴 Behind"))
B31: Pilots Seeded (pilot conversation started) | D31: 3–5 | E31: =COUNTIFS('Track 2 · Franchisees'!L4:L88,"Proposal Sent")+COUNTIFS('Track 2 · Franchisees'!L4:L88,"Negotiating")+COUNTIFS('Track 2 · Franchisees'!L4:L88,"Pilot Closed") | F31: — | G31: Manual
B32: HIGH Pilot Potential Accounts Contacted | D32: 15 | E32: =COUNTIFS('Track 2 · Franchisees'!I4:I88,"HIGH",'Track 2 · Franchisees'!L4:L88,"Contacted")+COUNTIFS('Track 2 · Franchisees'!I4:I88,"HIGH",'Track 2 · Franchisees'!L4:L88,"Replied")+COUNTIFS('Track 2 · Franchisees'!I4:I88,"HIGH",'Track 2 · Franchisees'!L4:L88,"Call Scheduled")+COUNTIFS('Track 2 · Franchisees'!I4:I88,"HIGH",'Track 2 · Franchisees'!L4:L88,"Discovery Done")+COUNTIFS('Track 2 · Franchisees'!I4:I88,"HIGH",'Track 2 · Franchisees'!L4:L88,"Proposal Sent")+COUNTIFS('Track 2 · Franchisees'!I4:I88,"HIGH",'Track 2 · Franchisees'!L4:L88,"Pilot Closed") | F32: =IFERROR(E32/15,0) | G32: =IF(E32>=15,"✅ On Track",IF(E32>=15*0.7,"⚠️ At Risk","🔴 Behind"))
B34: PHASE 3 · 90-DAY · CLOSE
B35: Target: End of June 2026 · Close pilots, advance franchisors, deliver playbook
B37: TRACK 1 — FRANCHISOR
B38: Franchisor in Qualified Interest Discussion | D38: 1+ req. | E38: =COUNTIFS('Track 1 · Franchisors'!L4:L12,"Negotiating")+COUNTIFS('Track 1 · Franchisors'!L4:L12,"Pilot Closed") | F38: — | G38: Manual
B39: Franchisor Deal in Progress / Closed | D39: 1 | E39: =COUNTIFS('Track 1 · Franchisors'!L4:L12,"Pilot Closed") | F39: =IFERROR(E39/1,0) | G39: =IF(E39>=1,"✅ On Track",IF(E39>=1*0.7,"⚠️ At Risk","🔴 Behind"))
B40: PE Warm Intros Activated (Charles path) | D40: Manual | E40: =0 | F40: — | G40: Manual
B41: GTM Playbook Delivered | D41: Yes/No | E41: No | F41: — | G41: Manual
B42: TRACK 2 — FRANCHISEE
B43: Pilots Closed (signed agreements) | D43: 2 | E43: =COUNTIFS('Track 2 · Franchisees'!L4:L88,"Pilot Closed") | F43: =IFERROR(E43/2,0) | G43: =IF(E43>=2,"✅ On Track",IF(E43>=2*0.7,"⚠️ At Risk","🔴 Behind"))
B44: Pilots in Active Negotiation | D44: 3 | E44: =COUNTIFS('Track 2 · Franchisees'!L4:L88,"Negotiating") | F44: =IFERROR(E44/3,0) | G44: =IF(E44>=3,"✅ On Track",IF(E44>=3*0.7,"⚠️ At Risk","🔴 Behind"))
B45: Total Pipeline Value Created (Closed + Negotiating) | D45: $50K+ | E45: =0 | F45: — | G45: Manual
B46: Extension Plan Presented to Core Team | D46: Yes/No | E46: No | F46: — | G46: Manual
B48: FRANCHISOR ACCOUNT SCORECARD · Status by Account
B49: Live from Top 9 Franchisors tab · Update status there and this auto-refreshes
B51: ACCOUNT | D51: TIER | E51: STATUS | F51: TEMP | G51: NOTES
B52: BELFOR | D52: TIER 1 | E52: ='Track 1 · Franchisors'!L4 | F52: =IFERROR(VLOOKUP("BELFOR",'Account Feedback'!A4:I28,9,0),"❄ Cold") | G52: ='Track 1 · Franchisors'!Q4
B53: THRESHOLD | D53: TIER 1 | E53: ='Track 1 · Franchisors'!L5 | F53: =IFERROR(VLOOKUP("THRESHOLD BRANDS",'Account Feedback'!A4:I28,9,0),"❄ Cold") | G53: ='Track 1 · Franchisors'!Q5
B54: EMPOWER | D54: TIER 1 | E54: ='Track 1 · Franchisors'!L6 | F54: =IFERROR(VLOOKUP("EMPOWER BRANDS",'Account Feedback'!A4:I28,9,0),"❄ Cold") | G54: ='Track 1 · Franchisors'!Q6
B55: PREMIUM SVC | D55: TIER 2 | E55: ='Track 1 · Franchisors'!L7 | F55: =IFERROR(VLOOKUP("PREMIUM SERVICE BRANDS",'Account Feedback'!A4:I28,9,0),"❄ Cold") | G55: ='Track 1 · Franchisors'!Q7
B56: RESIBRANDS | D56: TIER 2 | E56: ='Track 1 · Franchisors'!L8 | F56: =IFERROR(VLOOKUP("RESIBRANDS",'Account Feedback'!A4:I28,9,0),"❄ Cold") | G56: ='Track 1 · Franchisors'!Q8
B57: FIVE STAR | D57: TIER 2 | E57: ='Track 1 · Franchisors'!L9 | F57: =IFERROR(VLOOKUP("FIVE STAR FRANCHISING",'Account Feedback'!A4:I28,9,0),"❄ Cold") | G57: ='Track 1 · Franchisors'!Q9
B58: HOMEFRONT | D58: TIER 2 | E58: ='Track 1 · Franchisors'!L10 | F58: =IFERROR(VLOOKUP("HOMEFRONT BRANDS",'Account Feedback'!A4:I28,9,0),"❄ Cold") | G58: ='Track 1 · Franchisors'!Q10
B59: AUTHORITY | D59: TIER 3 | E59: ='Track 1 · Franchisors'!L11 | F59: =IFERROR(VLOOKUP("AUTHORITY BRANDS",'Account Feedback'!A4:I28,9,0),"❄ Cold") | G59: ='Track 1 · Franchisors'!Q11
B60: NEIGHBORLY | D60: TIER 3 | E60: ='Track 1 · Franchisors'!L12 | F60: =IFERROR(VLOOKUP("NEIGHBORLY",'Account Feedback'!A4:I28,9,0),"❄ Cold") | G60: ='Track 1 · Franchisors'!Q12
B62: FRANCHISEE PIPELINE SUMMARY · By Stage
B63: Live from 85 Franchisees tab · Status dropdowns drive these counts automatically
B65: PIPELINE STAGE | D65: TARGET | E65: ACTUAL COUNT | F65: % OF TOTAL | G65: STATUS
B66: Total Brands in Database | D66: 85 | E66: =COUNTA('Track 2 · Franchisees'!B4:B88)-COUNTBLANK('Track 2 · Franchisees'!B4:B88) | F66: =IFERROR(E66/85,0) | G66: Reference
B67: HIGH Pilot Potential Brands | D67: 30 | E67: =COUNTIF('Track 2 · Franchisees'!I4:I88,"HIGH") | F67: =IFERROR(E67/85,0) | G67: Reference
B68: MED Pilot Potential Brands | D68: 40 | E68: =COUNTIF('Track 2 · Franchisees'!I4:I88,"MED") | F68: =IFERROR(E68/85,0) | G68: Reference
B69: GPS Warm Accounts (YES) | D69: 10 | E69: =COUNTIF('Track 2 · Franchisees'!H4:H88,"YES") | F69: =IFERROR(E69/85,0) | G69: Reference
B70: Researching | D70: 10 | E70: =COUNTIF('Track 2 · Franchisees'!L4:L88,"Researching") | F70: =IFERROR(E70/85,0) | G70: =IF(E70>=10,"✅ On Track",IF(E70>=10*0.6,"⚠️ At Risk","🔴 Behind"))
B71: Contacted (outreach sent) | D71: 40 | E71: =COUNTIF('Track 2 · Franchisees'!L4:L88,"Contacted") | F71: =IFERROR(E71/85,0) | G71: =IF(E71>=40,"✅ On Track",IF(E71>=40*0.6,"⚠️ At Risk","🔴 Behind"))
B72: Replied (any response) | D72: 10 | E72: =COUNTIF('Track 2 · Franchisees'!L4:L88,"Replied") | F72: =IFERROR(E72/85,0) | G72: =IF(E72>=10,"✅ On Track",IF(E72>=10*0.6,"⚠️ At Risk","🔴 Behind"))
B73: Call Scheduled | D73: 5 | E73: =COUNTIF('Track 2 · Franchisees'!L4:L88,"Call Scheduled") | F73: =IFERROR(E73/85,0) | G73: =IF(E73>=5,"✅ On Track",IF(E73>=5*0.6,"⚠️ At Risk","🔴 Behind"))
B74: Discovery Done | D74: 3 | E74: =COUNTIF('Track 2 · Franchisees'!L4:L88,"Discovery Done") | F74: =IFERROR(E74/85,0) | G74: =IF(E74>=3,"✅ On Track",IF(E74>=3*0.6,"⚠️ At Risk","🔴 Behind"))
B75: Proposal Sent / Negotiating | D75: 3 | E75: =COUNTIF('Track 2 · Franchisees'!L4:L88,"Proposal Sent")+COUNTIF('Track 2 · Franchisees'!L4:L88,"Negotiating") | F75: =IFERROR(E75/85,0) | G75: =IF(E75>=3,"✅ On Track",IF(E75>=3*0.6,"⚠️ At Risk","🔴 Behind"))
B76: Pilot Closed 🎯 | D76: 2 | E76: =COUNTIF('Track 2 · Franchisees'!L4:L88,"Pilot Closed") | F76: =IFERROR(E76/85,0) | G76: =IF(E76>=2,"✅ On Track",IF(E76>=2*0.6,"⚠️ At Risk","🔴 Behind"))
B77: Stalled | D77: 5 | E77: =COUNTIF('Track 2 · Franchisees'!L4:L88,"Stalled") | F77: =IFERROR(E77/85,0) | G77: =IF(E77>=5,"✅ On Track",IF(E77>=5*0.6,"⚠️ At Risk","🔴 Behind"))
B80: PE RELATIONSHIP TRACKER · GPS Insight Actions Required
B81: Live from the 🔑 PE Relationship Map tab · Update status there — this section reflects the current state of all GPS Insight intro requests
B83: PE RELATIONSHIP / GPS ASK
B84: Accel-KKR Deal Team Brief (All PE intros flow from this)
B85: KKR → Felix Gernburd (Neighborly Board — ST renewal window 2025–27)
B86: Insight Engine ROI Model Sign-Off (Required before external use)
B87: American Securities → BELFOR (Board-level intro needed)
B88: Riverside Company → Threshold Brands (Approaching exit — EBITDA story) | D88: 🟡 HIGH | E88: GPS Insight (Charles Layne, CEO) | F88: =IFERROR('PE Relationship Map'!I15,"Not Started") | G88: 📞 On me — once the AKKR brief is confirmed, asking Charles to assign the Riverside intro to GPS Insight.
B90: GPS Insight Telematics List (Conflict check — required before outreach) | D90: 🔴 CRITICAL | E90: GPS Insight (Andrea Rowan, GM) | F90: Manual — update when received | G90: 📋 GPS Insight to provide the telematics client list. On me to run the conflict check once received.
B91: Micro-Franchise List from Angie (Expands Track 2 beyond 85 brands) | D91: 🟡 HIGH | E91: GPS Insight (Angie, Data Strategist) | F91: Manual — update when received | G91: 📋 GPS Insight (Angie) to pull the micro-franchise list. On me to score and integrate into Track 2 once received.
B92: Apax Partners → Authority Brands (CTO Tij Bedi — tech agenda active) | D92: 🟡 HIGH | E92: GPS Insight (Charles Layne, CEO) | F92: =IFERROR('PE Relationship Map'!I27,"Not Started") | G92: 🔍 On me — researching and asking Charles if AKKR has any Apax overlap. GPS Insight to surface the intro if the connection exists.
B93: Princeton Equity → Five Star Franchising (Year 5 — exit building) | D93: 🔵 MEDIUM | E93: GPS Insight (Charles Layne, CEO) | F93: =IFERROR('PE Relationship Map'!I23,"Not Started") | G93: 📞 On me — asking Charles to surface the Princeton Equity connection. GPS Insight to facilitate if the path exists.
B97: LAST UPDATED · Update this cell manually each Friday before sending to Andrea
B98: April 14, 2026 · Week 1 · Engagement not yet started
B100: HOW THIS SCORECARD WORKS
B101: 1. All ACTUAL numbers pull live from the other tabs via COUNTIF formulas — no manual entry needed for counts.
B102: 2. STATUS auto-calculates: ✅ On Track = at or above target · ⚠️ At Risk = 70%+ of target · 🔴 Behind = below 70%
B103: 3. Items marked 'Manual' in the ACTUAL column need to be updated by you — they cannot be counted automatically.
B104: 4. Franchisor Account Scorecard pulls status from the Top 9 Franchisors tab and temperature from Account Feedback Cards.
B105: 5. To update: change status dropdowns in Tab 2 (Top 9) or Tab 3 (85 Franchisees) — this scorecard refreshes automatically.
A107: Prepared by Velocity GTM Co LLC on behalf of GPS Insight / ServiceBridge · Michael Montgomery Flynt Jr · 919.434.6720 · mflyntjr@gmail.com · Confidential · April 2026
A109: 📊 INSIGHT ENGINE · Use Insight_Engine_Excel_v3.xlsx for all ROI conversations · FDD unit economics loaded into Track 1 col V · 3-Way Scenario = PE/CFO boardroom document

Sheet Changelog v15.6
A1: CRM v15.6 — Validation Changelog
A2: Validated April 29, 2026 by Velocity GTM Co LLC. 9 changes applied to Track 2 · Franchisees sheet.
A3: 2026-05-04 | B3: v15.35 | C3: CRM | D3: Track 2 LinkedIn URL Sync from Alumni Crossover v15 | E3: Synced 24 LinkedIn URLs from validated Alumni Crossover file. Replaced 17 stale/predecessor URLs with current brand president URLs (Aire Serv → Jay Jimenez, Rainbow → Josh Miller, Pestmaster → Bryan Shamhart, etc.) Added 7 new URL entries for previously-unverified contacts (Action Exteriors, Monty's Handyman, etc.). Major correction: TruBlue brand president confirmed as Sean Fitzgerald (linkedin.com/in/seancfitzgerald), NOT Stephen Nichols as previously mis-recorded. | F3: Mike validation | G3: 24 brand cells updated
A4: Date | B4: Row | C4: Brand | D4: Field Changed | E4: Old Value | F4: New Value | G4: Reason for Change
A5: 2026-04-29 20:24 | B5: 40 | C5: USA Insulation | D5: FSM Status | E5: Greenfield | F5: At-Risk SB | G5: Per Andrea Apr 2026: 75% SB penetration but transitioning OFF over next year. Not greenfield — retention/monitor play.
A6: 2026-04-29 20:24 | B6: 40 | C6: USA Insulation | D6: Current FSM Platform | E6: Greenfield / Paper | F6: ServiceBridge (75%, AT-RISK — transitioning off per Andrea Apr 2026) | G6: Andrea confirmed Apr 2026: USA Insulation transitioning off ServiceBridge over the next year. Not greenfield.
A7: 2026-04-29 20:24 | B7: 40 | C7: USA Insulation | D7: Notes | E7: Seasonal scheduling — strong dispatch fit | F7: ⚠️ AT-RISK / RETENTION PLAY — Andrea confirmed Apr 2026: USA Insulation transitioning off ServiceBridge over next year. Posture: dual-track — defend if reversible, reset relationship at brand-corp lev | G7: Added retention-play context per Threshold P2 readiness package.
A8: 2026-04-29 20:24 | B8: 40 | C8: USA Insulation | D8: Combined Score | E8: 84 🟡 QUEUE | F8: 84* ⚠️ RECALIBRATE — at-risk, not greenfield | G8: Score derived from greenfield assumption that does not apply. Flagged for recalibration.
A9: 2026-04-29 20:24 | B9: 37 | C9: BELFOR Property Restoration | D9: FSM Status | E9: Greenfield | F9: Not FSM Scope | G9: BELFOR Property Restoration is the parent restoration business — runs on restoration management software (Xactimate/Symbility), not FSM. Out of ServiceBridge category.
A10: 2026-04-29 20:24 | B10: 37 | C10: BELFOR Property Restoration | D10: Current FSM Platform | E10: Greenfield / Paper | F10: Restoration management software (Xactimate/Symbility ecosystem) — not FSM category | G10: Restoration management is a different software category. Not displaceable by FSM.
A11: 2026-04-29 20:24 | B11: 37 | C11: BELFOR Property Restoration | D11: Combined Score | E11: 116 🔴 LEAD PILOT | F11: EXCLUDE ⛔ NOT FSM SCOPE | G11: Excluded from FSM engagement. Score was based on incorrect greenfield framework.
A12: 2026-04-29 20:24 | B12: 37 | C12: BELFOR Property Restoration | D12: Notes | E12: Large restoration crews — documentation + compliance | F12: ⛔ EXCLUDED — different software ecosystem (restoration management). Engage at parent franchisor level (BELFOR FG) only, not as Stage 2 brand-corp target. | Large restoration crews — documentation + co | G12: Added exclusion rationale.
A13: 2026-04-29 20:24 | B13: 2 | C13: (Header) | D13: Subheader version stamp | E13: Velocity GTM Co LLC · Sorted by parent franchisor · GPS Insight warm accounts highlighted · Pilot potential scored HIGH / MED / LOW | F13: Velocity GTM Co LLC · Sorted by parent franchisor · GPS Insight warm accounts prioritized · v15.6 — validated April 29, 2026 | G13: Version bump and validation date.
A14: 2026-05-04 | B14: v15.36 | C14: CRM | D14: V19 Alumni Crossover Intel Sync — Multi-tab Update | E14: Comprehensive sync of Alumni Crossover v19 intel into CRM across 5 tabs: • Track 1: Updated Col 25 (GPS INSIGHT EXEC CONTACT) for 6 franchisor rows with consolidated warm-path summaries (Neighborly, Empower, ResiBrands, HomeFront, BELFOR, Threshold). Added v19 marker to Col 38 Signal Intel. • Engagement Log: Added 5 new entries (#79-83) — Alumni Crossover ask sent to GPS Insight team; Becky-Mike touch plan kickoff; Beth Toenies LinkedIn connection accepted; Carter Smith handoff to Garrett; Jeff Dudan App State warm-path strategy. • Account Feedback: Updated 11 accounts with [v19 Update] additions to KEY FEEDBACK + NEXT MILESTONE columns. Temperature shift: Empower → 🔥 Hot (Canopy NC State angle). • Signal Intel: Added new V19 Alumni Crossover Intel section with 20 categorized records (Active Engagement, Warm Path, Team Assignment, Status Change, Data Gap, Org Intel) with action/owner/status assignments. • Strategic frame: 'Building off existing relationships is our fastest path to success.' Cold outreach into PE-backed franchisors takes months; warm intro compresses to weeks. Becky-Mike touch plan in development this week to sequence outreach using team alumni hits as warm anchors. Status changes flagged for verification: Ben Lamb (Neighborly CFO) moved Feb 2026, Brad Roberson (Glass Doctor → Fastest Labs) may have left March 2026, Russ Jundt (Empower) retired, Doug Smith (BELFOR) may have left. | F14: Mike + alumni v19 intel | G14: 5 tabs updated · 20 intel records integrated
A16: Validation Summary
A17: ✓ Total brands in Track 2 reviewed: 78
A18: ✓ Portfolio assignments verified — CRM is correct (no misassignments found)
A19: ✓ Score-FSM consistency check passed — no logic errors
A20: ✓ No duplicate brand entries
A21: ✓ All 78 brands have parent franchisor, trade, location, FSM status fields populated
A22: ⚠️ 64 of 78 brands marked "Validate with Andrea" for GPSI customer overlap — REQUIRES GPSI team query
A23: ⚠️ ~68 of 78 brands have "TBD" for Owner/Decision Maker — REQUIRES Andrea/Marketing team intel
A24: ⚠️ 2 substantive corrections applied: USA Insulation (At-Risk, not Greenfield) + BELFOR Property Restoration (Not FSM scope)
A26: NEXT STEPS for full data closure:
A27: 1. GPSI customer database query for all 78 brands → fills GPSI Customer column + Telematics column
A28: 2. Brand-corp leadership intel from Andrea/Marketing team → fills Owner/DM column for ~68 brands
... A32: Track 1 · Franchisors V2 Realignment (April 29, 2026)
A33: 2026-04-29 | B33: 4-14 | C33: NEIGHBORLY | D33: V2 Track 1 position | E33: 9 | F33: 1 | G33: V2 ranking
A34: 2026-04-29 | B34: 4-14 | C34: NEIGHBORLY | D34: TIER label | E34: TIER 3 | F34: P1 #1 · PE-GATED | G34: V2 character label
A35: 2026-04-29 | B35: 4-14 | C35: NEIGHBORLY | D35: FRANCHISOR SCORE | E35: 39 ⚪ BUILD | F35: 76.5 🔴 PE-GATED — DO NOT APPROACH DIRECT | G35: V2 score (greenfield-weighted)
A36: 2026-04-29 | B36: 4-14 | C36: AUTHORITY BRANDS | D36: V2 Track 1 position | E36: 8 | F36: 2 | G36: V2 ranking
A37: 2026-04-29 | B37: 4-14 | C37: AUTHORITY BRANDS | D37: TIER label | E37: TIER 3 | F37: P1 #2 · DISPLACEMENT-READY | G37: V2 character label
A38: 2026-04-29 | B38: 4-14 | C38: AUTHORITY BRANDS | D38: FRANCHISOR SCORE | E38: 61 🟡 ACTIVE | F38: 68.5 🟡 ACTIVE | G38: V2 score (greenfield-weighted)
A39: 2026-04-29 | B39: 4-14 | C39: EMPOWER BRANDS | D39: V2 Track 1 position | E39: 3 | F39: 3 | G39: V2 ranking
A40: 2026-04-29 | B40: 4-14 | C40: EMPOWER BRANDS | D40: TIER label | E40: TIER 1 | F40: P1 #3 · GREENFIELD-LED | G40: V2 character label
A41: 2026-04-29 | B41: 4-14 | C41: EMPOWER BRANDS | D41: FRANCHISOR SCORE | E41: 60 🟡 ACTIVE | F41: 66.2 🟡 ACTIVE | G41: V2 score (greenfield-weighted)
A42: 2026-04-29 | B42: 4-14 | C42: RESIBRANDS | D42: V2 Track 1 position | E42: 5 | F42: 4 | G42: V2 ranking
A43: 2026-04-29 | B43: 4-14 | C43: RESIBRANDS | D43: TIER label | E43: TIER 2 | F43: P1 #4 · FAST-CYCLE | G43: V2 character label
A44: 2026-04-29 | B44: 4-14 | C44: RESIBRANDS | D44: FRANCHISOR SCORE | E44: 58 🟡 ACTIVE | F44: 60.2 🟢 ACTIVE | G44: V2 score (greenfield-weighted)
... A60: 2026-04-29 | B60: 4-14 | C60: THRESHOLD | D60: FRANCHISOR SCORE | E60: 73 🔴 MOVE NOW | F60: P2 SET | G60: P2 set qualitatively classified
A62: Other CRM Tabs V2 Realignment (April 29, 2026)
A63: 2026-04-29 | B63: 💡 Engagement Ideas | C63: BELFOR | D63: Priority cell | E63: 🔴 #1 | F63: 🟡 P2 DE-FACTO ANCHOR — HOODZ + DUCTZ at 94% SB; convert to mandate | G63: V2 ranking realignment — was old framework priority, now V2 character label.
A64: 2026-04-29 | B64: 💡 Engagement Ideas | C64: THRESHOLD BRANDS | D64: Priority cell | E64: 🟡 #2 | F64: 🔴 P2 AT-RISK ANCHOR — USA Insulation transitioning off SB; defensive | G64: V2 ranking realignment — was old framework priority, now V2 character label.
A65: 2026-04-29 | B65: 💡 Engagement Ideas | C65: EMPOWER BRANDS | D65: Priority cell | E65: 🟡 #3 | F65: 🟡 P1 #3 GREENFIELD-LED — strongest greenfield, Commercial mix | G65: V2 ranking realignment — was old framework priority, now V2 character label.
A66: 2026-04-29 | B66: 💡 Engagement Ideas | C66: RESIBRANDS | D66: Priority cell | E66: 🔴 #1 | F66: 🟢 P1 #4 FAST-CYCLE — founder-direct, fastest decision | G66: V2 ranking realignment — was old framework priority, now V2 character label.
A67: 2026-04-29 | B67: 💡 Engagement Ideas | C67: FIVE STAR FRANCHISING | D67: Priority cell | E67: 🟡 #4 | F67: 🟡 P1 #5 WEDGE-BRAND — Mosquito Shield wedge entry | G67: V2 ranking realignment — was old framework priority, now V2 character label.
A68: 2026-04-29 | B68: 💡 Engagement Ideas | C68: HOMEFRONT BRANDS | D68: Priority cell | E68: 🟡 #5 | F68: ⚪ P1 #7 MONITOR-MODE — Q3/Q4 2026 reassessment posture | G68: V2 ranking realignment — was old framework priority, now V2 character label.
A69: 2026-04-29 | B69: 💡 Engagement Ideas | C69: AUTHORITY BRANDS | D69: Priority cell | E69: 🟡 #6 | F69: 🟡 P1 #2 DISPLACEMENT-READY — leadership transition window | G69: V2 ranking realignment — was old framework priority, now V2 character label.
A70: 2026-04-29 | B70: 💡 Engagement Ideas | C70: NEIGHBORLY | D70: Priority cell | E70: ⚪ PE Only | F70: 🔴 P1 #1 PE-GATED — DO NOT APPROACH DIRECT (KKR warm path required) | G70: V2 ranking realignment — was old framework priority, now V2 character label.
A71: 2026-04-29 | B71: 💡 Engagement Ideas | C71: PREMIUM SERVICE BRANDS | D71: Priority cell | E71: 🟡 #7 | F71: 🟡 P1 #6 GREENFIELD-OPEN — RooterMan dominant brand wedge | G71: V2 ranking realignment — was old framework priority, now V2 character label.
A72: 2026-04-29 | B72: 📊 Scoring Model | C72: (Header) | D72: Subtitle | E72: Velocity GTM Co LLC · Two-level scoring: Franchisor score (Track 1) feeds a bonus into Franchisee score (Track 2). Combined score (max 125) determines pilot priority and outreach sequencing. | F72: Velocity GTM Co LLC · V2 Greenfield-Weighted Methodology · Track 1 + Track 2 use same 7 dimensions, reweighted per stage · Updated April 28, 2026 | G72: V2 methodology — same 7 dimensions across Stage 1/Stage 2 with stage-specific weights.
A73: 2026-04-29 | B73: 📊 Scoring Model | C73: Level 1 | D73: Range/Max | E73: 7 dimensions · Max 100 points | F73: 7 V2 dimensions · Max 100 points | G73: Updated to V2 framework
A74: 2026-04-29 | B74: 📊 Scoring Model | C74: Level 1 | D74: Description | E74: Scores each of the 9 PE-backed franchisor targets. Determines where we focus GTM effort at the network level. Also feeds directly into the franchisee bonus calculation. | F74: Scores each of the 7 P1 franchisor targets using V2 dimensions: Greenfield (20%), Network (15%), PE (15%), DM Access (15%), Urgency (15%), Displacement (10%), C/B Mix (10%). Determines where to focus | G74: V2 description
... A112: 2026-04-29 | B112: 📅 Event Intelligence | C112: NEIGHBORLY | D112: Franchisor label (col 1) | E112: NEIGHBORLY | F112: NEIGHBORLY · P1 #1 PE-GATED | G112: Added V2 priority/character label for visibility
A115: ═══ v15.7 ADDITIONS (May 1, 2026) — Track 1 Engagement Intelligence ═══
A117: Date | B117: Row | C117: Franchisor | D117: Field Added | E117: Notes
A118: 2026-05-01 | B118: 4 | C118: NEIGHBORLY | D118: Cols AG-AJ | E118: LinkedIn (Mike Davis verified) + public comments + Reunion event + KKR playbook
A119: 2026-05-01 | B119: 5 | C119: AUTHORITY BRANDS | D119: Cols AG-AJ | E119: LinkedIn (Tij Bedi verified) + Bedi Gartner quote + Tij playbook + Ryan Bowes flag
A120: 2026-05-01 | B120: 6 | C120: EMPOWER BRANDS | D120: Cols AG-AJ | E120: LinkedIn (Scott Zide verified) + AI quote + Ignite 2027 + 9 brand playbook
A121: 2026-05-01 | B121: 7 | C121: RESIBRANDS | D121: Cols AG-AJ | E121: LinkedIn (Steven Montgomery verified) + email/phone + Codie IFA + fast-cycle playbook
A122: 2026-05-01 | B122: 8 | C122: FIVE STAR | D122: Cols AG-AJ | E122: Contacts framework + Princeton Yr5 + Mosquito Shield wedge — Abbott LI URL pending
A123: 2026-05-01 | B123: 9 | C123: PREMIUM SERVICE BRANDS | D123: Cols AG-AJ | E123: LinkedIn (Paul Flick verified) + Forbes PE quote + David Raymond cross-brand + RooterMan playbook
A124: 2026-05-01 | B124: 10 | C124: HOMEFRONT BRANDS | D124: Cols AG-AJ | E124: LinkedIn (Jeff Dudan verified) + reputation quote + Homecoming 4 + content-first playbook
A125: 2026-05-01 | B125: 12 | C125: BELFOR | D125: Cols AG-AJ | E125: Contacts framework + American Securities + insurance reframe playbook — Doug Smith LI URL pending
A126: 2026-05-01 | B126: 13 | C126: EVIVE BRANDS | D126: Cols AG-AJ | E126: LinkedIn (Ryan Parsons verified) + replaceable quote + Brothers Gutters wedge playbook
A127: 2026-05-01 | B127: 14 | C127: THRESHOLD BRANDS | D127: Cols AG-AJ | E127: CRITICAL: CEO is Ted DeMarino (NOT Kappler). New leadership reset (DeMarino/Newby/Hughes). Defensive playbook.
A130: ═══ v15.8 ADDITIONS (May 1, 2026) — FSM/Telematics/Insurance Public Commentary ═══
A132: Date | B132: Row | C132: Franchisor | D132: Field Updated | E132: Notes
A133: 2026-05-01 | B133: 4 | C133: NEIGHBORLY | D133: Col AH FSM/Tech | E133: KKR digital transformation quote (Gernburd) + Davis martech LinkedIn post
A134: 2026-05-01 | B134: 5 | C134: AUTHORITY BRANDS | D134: Col AH FSM/Tech | E134: ★ Bedi BYLINED Franchising.com article on data lakes + siloed systems = direct ServiceBridge match
A135: 2026-05-01 | B135: 6 | C135: EMPOWER BRANDS | D135: Col AH FSM/Tech | E135: ★ Zide Apr 2026 leadership expansion includes TECHNOLOGY roles + AI/data unification quote
A136: 2026-05-01 | B136: 7 | C136: RESIBRANDS | D136: Col AH FSM/Tech | E136: ★ ResiConnect = ClickUp+Slack+Trainual = NO proper FSM. Direct evidence of gap.
A137: 2026-05-01 | B137: 8 | C137: FIVE STAR | D137: Col AH FSM/Tech | E137: Scott Abbott CO-FOUNDED ProNexis = tech seller, not buyer. Treat as peer.
A138: 2026-05-01 | B138: 9 | C138: PSB | D138: Col AH FSM/Tech | E138: ★ Flick founding thesis: industry is "TECHNOLOGY AND SOFTWARE DEFICIENT" - exact gap
A139: 2026-05-01 | B139: 10 | C139: HOMEFRONT | D139: Col AH FSM/Tech | E139: Dudan IFA 2026 keynote topic: AI & Human Co-Working - direct angle
A140: 2026-05-01 | B140: 12 | C140: BELFOR | D140: Col AH FSM/Tech | E140: AVOID tech framing - relationship-first culture. Pitch insurance carrier angle, not dashboards
A141: 2026-05-01 | B141: 13 | C141: EVIVE | D141: Col AH FSM/Tech | E141: ★ Parsons publicly committed to tech unification across portfolio - strongest P2 signal
A142: 2026-05-01 | B142: 14 | C142: THRESHOLD | D142: Col AH FSM/Tech | E142: 🚨 USA Insulation Brand President position VACANT - explains transition off SB
A145: ═══ v15.9 ADDITIONS (May 1, 2026) — Track 2 Brand-Level Engagement Intelligence ═══
A147: Date | B147: Scope | C147: Coverage | D147: New Cols | E147: Notes
A148: 2026-05-01 | B148: Track 2 · Franchisees | C148: All 78 brand rows | D148: AH-AJ | E148: Added: Brand President + LinkedIn URL, FSM/Tech/Insurance Comments, Brand-Level Engagement Notes
A149: 2026-05-01 | B149: Neighborly brands (rows 4-19) | C149: 12 brand presidents identified | D149: AH | E149: Jay Jimenez NEW Aire Serv pres. Group Pres structure: Jason Himber (Repair), Georgeanne Erickson (Maintain), Matt Crowley (Specialty)
A150: 2026-05-01 | B150: Authority brands (rows 20-31) | C150: Steve Clemente, Tom Swift, Stewart Vernon | D150: AH | E150: Authority structured around Group EVPs not brand presidents. Steve Clemente Trades cluster created Aug 2025
A151: 2026-05-01 | B151: BELFOR brands (rows 32-38) | C151: Tim Fagan, Beth Toenies, Jessica Wicks, Matt O'Rourke | D151: AH | E151: BELFOR brand-level intel from prior CRM. Yellen culture = NO dashboards/data framing
A152: 2026-05-01 | B152: Threshold brands (rows 39-48) | C152: Bryan McMurray (GGF) + USA Insulation VACANT flagged | D152: AH | E152: Critical: USA Insulation Brand President position currently VACANT per The Org
A153: 2026-05-01 | B153: Empower brands (rows 49-58) | C153: Gary Bauer, Heather Todd (NEW), Cory Lyons, Justin Mayer (NEW), David Bitan | D153: AH | E153: Multiple NEW brand presidents in honeymoon period. Cory Lyons = dual brand pres (Koala + Wallaby)
A154: 2026-05-01 | B154: PSB brands (rows 59-66) | C154: Carter Purves, Joel Gotshall, David Raymond, Ty Anderson | D154: AH | E154: David Raymond = COO + ProLift VP + personal franchisee = single most accessible
A155: 2026-05-01 | B155: Five Star brands (rows 67-71) | C155: Ben Kramer, Dean Hartley, Wanda Hoegren, Michael Moorhouse, Stefan Figley | D155: AH | E155: Full brand president list captured from official site. Shane MacKay = CTO drives unified tech
A156: 2026-05-01 | B156: HomeFront brands (rows 72-76) | C156: Tyler Kirk, Todd Bingham, David Blue, Michael Wagner | D156: AH | E156: Michael Wagner NEW Roof Scientist president (Nov 2024 acquisition)
A157: 2026-05-01 | B157: ResiBrands (rows 77-81) | C157: Steven Montgomery + Carter Smith + Tom Downer + Smola Family | D157: AH | E157: Steven controls all 5 brands. Pink's founders Carter Smith + Tom Downer stayed on after 2023 acquisition
A158: 2026-05-01 | B158: Cross-track findings | C158: ★ Aire Serv Jay Jimenez ~Apr 2026 NEW | D158: AH-AJ | E158: ★ Authority Trades cluster Steve Clemente created Aug 2025; ★ Empower hiring tech leaders Apr 2026; ★ HOMECOMING 4 Nov 2026 (HomeFront vendor slot still time)
A161: ═══ v15.10 ADDITIONS (May 1, 2026) — Track 2 Expanded to 186 Named Contacts ═══
A163: Date | B163: Scope | C163: Coverage | D163: Notes
A164: 2026-05-01 | B164: Track 2 Col AK NEW | C164: All 78 brand rows | D164: NEW column "ADDITIONAL CONTACTS + CORPORATE/PARENT TEAM" — adds 2nd/3rd contacts per brand
A165: 2026-05-01 | B165: TBD brands FILLED | C165: 8 previously TBD | D165: Junkluggers (Justin Waltz), Pestmaster (Bryan Shamhart NEW Nov 2025), FlyFoe→Patio Patrol rebrand, Canopy (Ben Wright NEW), FRSTeam (Jeff Waters NEW), House Doctors (Ann Lilly), TWS (Patrick Kiessling), Designery (Casey Ridley)
A166: 2026-05-01 | B166: Empower 2026 leadership wave | C166: April 16 2026 announcement | D166: 6 new appointments: Volker Wellman, Chris Donnelly, Melanie Watts, Joe Dominiak, Ben Wright, Jeff Waters
A167: 2026-05-01 | B167: Authority depth | C167: Corporate + brand leaders | D167: Justin Waltz (Junkluggers), Jef Flournoy (Mosquito Squad Plus), Todd Houghton (Homewatch), D'Aniello couple (DoodyCalls founders), Leanne Stapf, Farah, Jordan
A168: 2026-05-01 | B168: Threshold depth | C168: Corporate + emerging | D168: Emily Estes (MaidPro), Bryan Shamhart NEW (Pestmaster Nov 2025), Brett Shraiar prior, Kayla Cina former GGF, Melanie Perez Marketing
A169: 2026-05-01 | B169: PSB depth | C169: Brand + ops layer | D169: Ann Lilly (House Doctors), Dave Rychley, Samantha Lin, Courtney Spain, Tracey Felts, Bertie Allen
A170: 2026-05-01 | B170: HomeFront awards/franchisees | C170: IFA + Homecoming awards | D170: 11 award winners + franchisees of year captured for relationship-building reference
...

Sheet PE Relationship Map
A1: PE RELATIONSHIP MAP · GPS Insight Warm Introduction Paths · ServiceBridge GTM Engagement
A2: Velocity GTM Co LLC · These introductions require GPS Insight coordination · Every row is a GPS Insight ask tracked to completion
A3: 🔑 Each row on this tab represents an introduction path that runs through GPS Insight's PE network · Status updated as introductions progress
B5: WHY THIS TAB EXISTS
B6: A warm PE-level introduction compresses a 6-month enterprise sales cycle to 6 weeks. Accel-KKR (GPS Insight's backer) has portfolio relationships, co-investment networks, and operating partner connections that give you an immediate credibility bridge to the PE firms backing your 9 priority franchisor accounts. None of these introductions happen without Charles Layne. This tab tracks every PE relationship, who at GPS Insight owns it, what the ask is, and where the introduction stands.
B8: PE FIRM | C8: FUND TYPE & AUM | D8: PORTFOLIO COMPANY | E8: GPS INSIGHT OWNER | F8: PE TARGET CONTACT (Named Individuals) | G8: INTRO PATH | H8: PRIORITY | I8: INTRO STATUS | J8: LAST GPS ACTION | K8: NEXT GPS ACTION NEEDED | L8: NEXT DATE | M8: NOTES / INTELLIGENCE | N8: PE DEAL TEAM FOCAL POINTS ← Researched contacts
B10: SECTION 1 · ACCEL-KKR NETWORK · GPS Insight's Own PE Backer · Highest Leverage
B11: Accel-KKR backed GPS Insight. This is your warmest possible intro path. Charles Layne has direct relationships with the AKKR deal team.
B13: Accel-KKR | C13: Tech-Focused PE ~$10B+ AUM | D13: GPS Insight / ServiceBridge (Portfolio Company) | E13: GPS Insight (Charles Layne, CEO) | F13: Accel-KKR Internal (GPS Insight board-level) | G13: Charles Layne → AKKR deal team → PE portfolio introductions | H13: 🔴 Critical | I13: Not Started | K13: 📞 On me — calling Charles. Asking GPS Insight to brief AKKR and open intro paths to the four PE firms. | L13: Week 1 | M13: GPS Insight backer. Charles Layne has direct AKKR deal team relationships. This single conversation unlocks all downstream PE intros. | N13: TBD — Accel-KKR deal team partner for GPS Insight ← Charles Layne is the direct relationship Accel-KKR = GPS Insight's own PE backer — highest leverage intro chain
B14: KKR | C14: Large-Cap PE $349B+ AUM | D14: Neighborly (16 brands, 13,259 techs) | E14: GPS Insight (Charles Layne, CEO) | F14: Felix Gernburd Managing Director, KKR Led Neighborly acquisition 2021 North American PE fund | G14: Charles → Accel-KKR deal team → KKR deal team → Felix Gernburd | H14: 🔴 Critical | I14: Not Started | K14: Flag to Charles that the Accel-KKR → KKR path is the play for Neighborly. Ask him to request a warm intro to Felix Gernburd — KKR Partner, Neighborly board seat. | L14: Week 1 | M14: KKR acquired Neighborly (Jul 2021) from Harvest Partners. Felix Gernburd is on Neighborly board. ST renewal window 2025–2027. One KKR-level conversation positions us for that window. | N14: Felix Gernburd — Managing Director, KKR Named in KKR/Neighborly acquisition press release as deal lead Intro path: Charles Layne → Accel-KKR → KKR → Felix Gernburd ⚠️ DO NOT cold outreach — PE intro only
B16: SECTION 2 · TIER 1 FRANCHISOR PE BACKERS · Active Introduction Requests
B17: These PE firms back your Tier 1 accounts. A single intro at the PE level is worth months of direct franchisor outreach.
B19: American Securities | C19: Mid-Market PE ~$10B AUM | D19: BELFOR Franchise Group (14 brands, 9,250 techs) | E19: GPS Insight (Charles Layne, CEO) | F19: David Horing Co-Chair Investment Committee Director, BELFOR (since 1995) Managing Member, active funds Ryan Nolan Director, BELFOR Joined 2017, ex-JPMorgan David Musicant Director, BELFOR Joined 2011, deal sourcing Ex-BofA/Merrill Lynch MD Loren Easton Chairman, BELFOR board | G19: Charles → AKKR deal team → American Securities operating partners | H19: 🔴 Critical | I19: Not Started | K19: Week 1 — Charles Layne call. Ask him to surface any AKKR → American Securities relationship. American Securities has board representation at BELFOR — an operating partner intro skips directly to the mandate decision. | L19: Week 1 | M19: American Securities board is active on ops improvement at BELFOR. Tech standardization directly supports their portfolio thesis. BELFOR sold 30 new franchise territories Dec 2024 — mandate now = every new franchisee is a guaranteed adoption. | N19: PRIMARY: David Horing (Co-Chair IC, Director BELFOR since 1995) OPERATIONAL: Ryan Nolan (Director BELFOR, joined 2017, ex-JPMorgan) RELATIONSHIPS: David Musicant (Director BELFOR, deal sourcing/capital markets) CHAIRMAN: Loren Easton (BELFOR board chairman) INTRO PATH: Charles Layne → Accel-KKR → American Securities Source: american-securities.com team pages (confirmed)
B20: The Riverside Company | C20: Global Mid-Market PE $13B+ AUM | D20: Threshold Brands (10 brands, 6,250 techs) | E20: GPS Insight (Charles Layne, CEO) | F20: Loren Schlachet Managing Partner, Riverside Leads Threshold platform Brian Sauer Senior Partner, Riverside Named on Threshold press releases Steve Rice Principal Caroline Quoyeser Assistant Vice President Deniz Oran Associate Tom Silk Operating Partner Chrissie Yim Finance Director | G20: Charles → AKKR deal team → Riverside Company LP or operating partner relationship | H20: 🟡 High | I20: Not Started | K20: Once the AKKR brief is confirmed, ask Charles to surface any Riverside connection through the PE network. Riverside is approaching exit window — technology standardization improves the EBITDA multiple. | L20: Week 2 | M20: Threshold is Riverside's home services platform (formed 2021). Glassdoor shows high turnover and EBITDA pressure from Riverside. LP-reportable tech standardization is the pitch to the PE firm, not to Hagan Kappler. | N20: PRIMARY: Loren Schlachet (Managing Partner — leads Threshold platform) DEAL LEAD: Brian Sauer (Senior Partner — named on all Threshold add-on releases) OPERATIONAL: Steve Rice (Principal) + Caroline Quoyeser (AVP) + Deniz Oran (Associate) FINANCE: Chrissie Yim (Finance Director) SOURCING: Jeremy Holland (Partner) + Connor McLaughlin (VP Origination) Source: Riverside press release — Miracle Method add-on (Dec 2023)
B21: MidOcean Partners | C21: Mid-Market PE $6B+ AUM | D21: Empower Brands (10 brands, 5,150 techs) | E21: GPS Insight (Charles Layne, CEO) | F21: Eric Roth Principal/Partner, MidOcean Covers Empower Brands Christopher M. Grandpre Operating Partner, MidOcean Chairman, Empower Brands 30+ yrs franchise M&A Founded Outdoor Living Brands 2008 | G21: Charles → AKKR deal team → MidOcean operating partner | H21: 🟡 High | I21: Not Started | K21: Ask Charles about MidOcean connection through Charles / AKKR. MidOcean invested in Empower Dec 2020 — approaching exit window. EBITDA improvement before exit is the story. | L21: Week 2 | M21: MidOcean invested in Empower Brands Dec 2020. Typical hold 5–7 years puts exit window at 2025–2027. First-mover FSM standardization documented before exit = multiple expansion story for MidOcean LPs. | N21: PRIMARY: Eric Roth (covers Empower Brands at MidOcean — confirmed on MidOcean website) OPERATING: Christopher M. Grandpre (Operating Partner + Chairman of Empower Brands) → Founded Outdoor Living Brands 2008 (precursor to Empower) → 30+ years franchise M&A / investment banking INTRO PATH: Charles Layne → MidOcean → Eric Roth or Grandpre Source: midoceanpartners.com + The Joint Corp. press release (May 2025)
B23: SECTION 3 · TIER 2 FRANCHISOR PE BACKERS · Build Relationships in Parallel
B24: Smaller or founder-backed platforms. PE path may be lighter — but still surface any connections through Charles before going cold.
B26: Susquehanna Private Capital | C26: Growth Equity (Susquehanna Int'l Group) | D26: Premium Service Brands (8 brands, 4,950 techs) | E26: GPS Insight (Charles Layne, CEO) | F26: Kyle Squillario Co-Head, Susquehanna Private Capital Named in PSB deal announcement SPC Team: 7 people total 2 Partners, 5 Principals Bala Cynwyd PA | G26: Charles → AKKR → Susquehanna Private Capital connection (if any) | H26: 🔵 Medium | I26: Not Started | K26: Check with Charles if AKKR has any Susquehanna / SGE connection. If not, direct approach to Paul Flick (CEO) is the primary path — SGE is growth equity, not traditional PE, so the founder is the decision-maker. | L26: Week 2 | M26: Susquehanna Private Capital is the investment arm of Susquehanna International Group. PSB is founder-led with PE backing — Paul Flick still runs the business. Direct CEO outreach is the backup if PE path yields nothing. | N26: PRIMARY: Kyle Squillario (Co-Head, SPC — quoted in PSB press release 2021) FIRM: Susquehanna Private Capital — funded by founders of Susquehanna Int'l Group SPC SIZE: ~7 person team, 2 partners — small firm, direct access INTRO: Charles Layne → SPC → Kyle Squillario Source: BusinessWire PSB/SPC announcement (March 2021)
B27: Princeton Equity Group | C27: Franchise-Focused PE Franchise-only investor | D27: Five Star Franchising (5 brands, 2,350 techs) | E27: GPS Insight (Charles Layne, CEO) | F27: Derek DeBenedetto Princeton Equity Group Email: derek@princetonequity.com IFA/conference meeting contact Paul Kuppich Partner (joined 2025) Capital formation focus | G27: Charles → AKKR → Princeton Equity (franchise-focused PE — likely known in network) | H27: 🔵 Medium | I27: Not Started | K27: Week 2 — Princeton Equity exclusively invests in franchise companies — very tight network. Ask Charles if AKKR has any Princeton connection. Year 5 of investment means exit pressure building. | L27: Week 2 | M27: Princeton Equity Group exclusively invests in franchisors and multi-unit companies. Five Star is in Year 5 (invested Jun 2021). EBITDA improvement documented now = higher exit multiple for Princeton. Scott Abbott (CEO) is founder — direct outreach is solid backup. | N27: MEETING CONTACT: Derek DeBenedetto (derek@princetonequity.com) → Listed as IFA 2026 meeting contact in Princeton Year in Review PARTNER: Paul Kuppich (joined 2025 — capital formation + investor relations) FIRM CONTEXT: Princeton invested 2021, Five Star in Year 5 — exit window approaching → ~$350M deployed 2025 across 3 new platforms INTRO PATH: Charles Layne → Princeton Equity → Derek DeBenedetto Source: Princeton 2025 Year in Review + LinkedIn announcement
B28: Dudan Group | C28: Family Office (Founder Capital) | D28: HomeFront Brands (5 brands, 2,550 techs) | E28: GPS Insight (Charles Layne, CEO) | F28: Jeff Dudan Chairman & CEO, HomeFront Founder, Dudan Group Forbes contributor, podcaster Zack Dudan CGO, HomeFront Brands Family office — no external PE team | G28: Direct — Jeff Dudan is both the PE backer AND the CEO. No intermediary needed. | H28: ⚪ Low | I28: Not Started | K28: NO GPS INTRO NEEDED: Jeff Dudan controls both the capital and the operating company. Approach directly. This is the one account where PE intro is not the accelerant — the CEO relationship is. | L28: Week 2 | M28: Dudan Group is Jeff Dudan's family office. He is Chairman + CEO. Direct LinkedIn / podcast outreach to Jeff is faster than any PE path. Note for Charles: no intro needed here. | N28: FAMILY OFFICE: Dudan Group = Jeff Dudan's personal capital — no external PE team DIRECT APPROACH: Jeff Dudan is both PE backer AND operating CEO → Forbes contributor, podcaster — content/thought leadership angle OPERATIONAL: Zack Dudan (CGO) = franchise operations + Homecoming vendor path NO PE INTRO NEEDED — direct approach is the right path Source: HomeFront public filings + Forbes contributor profile
B30: SECTION 4 · TIER 3 FRANCHISOR PE BACKERS · Long Cycle · Relationship Play
B31: Authority Brands and Neighborly have large PE backers. The cycle is long — but the deal size is enormous. Build the relationship now.
B33: Apax Partners + BCI | C33: Large-Cap PE Apax $60B+ · BCI C$211B | D33: Authority Brands (12 brands, 12,098 techs) | E33: GPS Insight (Charles Layne, CEO) | F33: Ashish Karandikar Partner, Apax Partners Led Authority Brands acquisition 2018 Quoted in deal press release BCI (minority stake 2022) British Columbia Investment Mgmt Corp | G33: Charles → AKKR deal team → Apax Partners relationship (LP or co-invest level) | H33: 🟡 High | I33: Not Started | K33: WEEK 1 (research): Ask Charles if AKKR has any LP overlap with Apax fund. Apax explicitly cited 'digitalization' as the AB investment thesis — that is ServiceBridge's positioning. BCI co-invested Sep 2022. | L33: Week 1 (research) | M33: Apax acquired Authority Brands Sep 2017. BCI co-invested Sep 2022 for 'technology transformation.' Apax partner Ashish Karandikar led the deal. Tij Bedi (CTO) was hired Aug 2024 — the tech agenda is active. A PE-level intro to Apax gets us to Tij Bedi much faster. | N33: APAX LEAD: Ashish Karandikar (Partner, Apax — quoted as deal lead in 2018 acquisition) → 'We have been attracted to the home services market for some time' BCI: British Columbia Investment Management Corp (significant minority stake, Sep 2022) → Largest institutional investor in Canada INTRO PATH: Charles Layne → Apax → Ashish Karandikar NOTE: Apax-focused on digitisation/tech for Authority — CTO Tij Bedi (Aug 2024) is the signal Source: Apax.com + PRNewswire acquisition announcement (Sep 2018)
B34: KKR (Neighborly) | C34: Already covered in Section 1 $349B+ AUM | D34: Neighborly (16 brands, 13,259 techs) | E34: GPS Insight (Charles Layne, CEO) | F34: Felix Gernburd Managing Director, KKR Led Neighborly acquisition 2021 ⚠️ DO NOT approach direct | G34: See Section 1 — same KKR path. Do not duplicate effort. | H34: 🔴 Critical | I34: Not Started | K34: ↑ Same KKR path as Section 1 — no separate ask needed. Tracking there. | L34: Week 1 | M34: Neighborly is tracked in Section 1 under the KKR relationship. This row is a reminder that Neighborly PE path and Authority Brands PE path are separate KKR / Apax conversations. | N34: Same as Section 1 — Felix Gernburd is the KKR Neighborly contact ⚠️ DO NOT approach direct under any circumstances INTRO PATH ONLY: Charles Layne → Accel-KKR → KKR → Felix Gernburd Source: KKR/Neighborly acquisition press release BusinessWire (July 2021)
B36: GPS INSIGHT ACTION SUMMARY · The Specific Asks for Charles Layne by Week
B38: WEEK | C38: GPS CONTACT | E38: THE ASK | I38: FOR ACCOUNT | K38: URGENCY | L38: STATUS
B39: Week 1 | C39: GPS Insight (Charles Layne, CEO) | E39: Brief the Accel-KKR deal team on the ServiceBridge GTM initiative. Need AKKR to facilitate PE-level introductions to American Securities (BELFOR), Riverside (Threshold), MidOcean (Empower), and KKR (Neighborly). | I39: ALL 9 FRANCHISORS | K39: 🔴 Critical | L39: Not Started
B40: Week 1 | C40: GPS Insight (Charles Layne, CEO) | E40: Specific KKR ask: Ask for Accel-KKR → KKR deal team intro to Felix Gernburd (KKR Partner / Neighborly Board). One call at the KKR level positions ServiceBridge for the Neighborly ST contract renewal window 2025–2027. | I40: NEIGHBORLY | K40: 🔴 Critical | L40: Not Started
B41: Week 1 | C41: GPS Insight (Garrett Else, CFO) | E41: Schedule 30-minute session to walk through the Insight Engine ROI model assumptions. Garrett's sign-off validates the financial narrative before we take it external to any PE operating partner or franchisor CFO. | I41: ALL ACCOUNTS (ROI Model) | K41: 🔴 Critical | L41: Not Started
B42: Week 1 | C42: GPS Insight (Andrea Rowan, GM) | E42: Connect Mike Flynt with Angie (GPS Insight data strategist) to obtain the micro-franchise company list. This expands Track 2 pipeline beyond the current 85-brand database. | I42: TRACK 2 FRANCHISEE | K42: 🟡 High | L42: Not Started
B43: Week 1 | C43: GPS Insight (Andrea Rowan, GM) | E43: Get the GPS Insight existing telematics client list for cross-referencing against all 9 franchisor accounts. Required conflict check before any outreach begins. | I43: ALL 9 FRANCHISORS | K43: 🔴 Critical | L43: Not Started
B44: Week 2 | C44: GPS Insight (Charles Layne, CEO) | E44: Follow-up on AKKR intro request. Confirm which PE firms have responded and whether any calls are scheduled. If American Securities intro is confirmed, brief Mike before the call. | I44: BELFOR American Securities | K44: 🟡 High | L44: Not Started
B45: Week 2 | C45: GPS Insight (Charles Layne, CEO) | E45: 🔍 On me to check whether there's any Apax Partners (Authority Brands backer) connection through AKKR LP network or co-investment relationships. Apax cited 'digitalization' as their Authority Brands investment thesis — perfect alignment. | I45: AUTHORITY BRANDS Apax Partners | K45: 🟡 High | L45: Not Started
B46: Week 3 | C46: GPS Insight (Garrett Else, CFO) | E46: ROI model sign-off — confirm which assumptions are cleared for external use. Garrett's endorsement as GPS Insight CFO is the credibility layer when the model goes in front of a PE operating partner or franchisor CFO. | I46: ALL ACCOUNTS (ROI Model) | K46: 🔴 Critical | L46: Not Started
B47: Week 4 | C47: GPS Insight (Charles Layne, CEO) | E47: 30-Day check-in: Where do the PE intro paths stand? Which firms have responded? Is a KKR / Felix Gernburd call on the calendar? Any additional PE relationships to activate in Month 2? | I47: ALL PE PATHS | K47: 🟡 High | L47: Not Started
B48: Month 2 | C48: GPS Insight (Charles Layne, CEO) | E48: If Accel-KKR intro has not yet produced a franchisor meeting: ask Charles to make a direct personal call to the PE operating partner. His personal relationship is the accelerant — not a formal intro request. | I48: STALLED ACCOUNTS | K48: 🔵 Medium | L48: Not Started
A50: Prepared by Velocity GTM Co LLC on behalf of GPS Insight / ServiceBridge · Michael Montgomery Flynt Jr · 919.434.6720 · mflyntjr@gmail.com · Confidential · April 2026

Sheet Track 1 · Franchisors
A1: TOP FRANCHISOR ACCOUNTS · Track 1 (P1 ×7) + P2 Set (×3) · V2 Greenfield-Weighted Ranking
A2: Velocity GTM Co LLC · GPS Insight / ServiceBridge Engagement · V2 Ranking April 28, 2026 · CRM v15.6 — validated April 29, 2026
A3: # | B3: FRANCHISOR | C3: PE BACKER | D3: TIER | E3: BRANDS | F3: TECHS | G3: ARR EST. | H3: CEO | I3: CFO | J3: COO / PRESIDENT | K3: BD / FRANCHISE DEV | L3: ENGAGEMENT STATUS | M3: LAST CONTACT | N3: NEXT STEP | O3: NEXT DATE | P3: GPS INSIGHT SUPPORT | Q3: NOTES | R3: ANNUAL CONVENTION | S3: VENDORS / PARTNERS INVITED? | T3: INSURANCE PROGRAM / CARRIER | U3: INSURANCE GTM ANGLE | V3: FDD INTEL (Items 8·11·19) | W3: INSIGHT ENGINE INPUTS ← Pre-populate ROI Calc | X3: FRANCHISOR SCORE / 100 | Y3: GPS INSIGHT EXEC CONTACT ← Internal intro path | Z3: GREENFIELD SCORE (V2 · 20%) | AA3: NETWORK SCORE (V2 · 15%) | AB3: PE SCORE (V2 · 15%) | AC3: DM ACCESS SCORE (V2 · 15%) | AD3: URGENCY SCORE (V2 · 15%) | AE3: DISPLACEMENT SCORE (V2 · 10%) | AF3: C/B MIX SCORE (V2 · 10%) | AG3: KEY CONTACTS LINKEDIN URLS | AH3: FSM / TELEMATICS / INSURANCE COMMENTS | AI3: EVENTS THEY ATTEND / SPEAK AT | AJ3: HOW TO ENGAGE PLAYBOOK SUMMARY | AK3: EXPANDED CONTACTS | AL3: SIGNAL INTEL (compressed · see Signal Intel tab for full) | AM3: EDUCATION (College / University / Trade School)
A4: 1 | B4: NEIGHBORLY | C4: KKR ($349B+ AUM) | D4: P1 #1 · PE-GATED | E4: 16 | F4: 13259 | G4: $198K | H4: Mike Davis CEO (joined Jul 2024) | I4: Benjamin Lamb CFO (joined May 2025) | J4: Jason Himber Group President, Repair Brands | K4: Felix Gernburd KKR Partner / Board ← PE TARGET | N4: Flag to Charles — KKR intro is Week 1 GPS ask | O4: Week 1 (GPS only) | P4: GPS: THIS IS THE #1 GPS ACTION — Charles → Accel-KKR → KKR → Felix Gernburd. DO NOT approach Neighborly direct. | Q4: Gagan Sinha = CIO (joined Sep 2025). ST renewal window 2025–2027. PE play only. | R4: Neighborly Reunion · Oct 2025 held Nashville — next ~Oct 2026 Nashville. DO NOT attend without PE intro. | S4: ✅ Yes — vendor partners attend | T4: ProTradeNet preferred insurance broker (confirmed — ~170 vendors incl. insurance brokers). Validate specific broker via FDD. | U4: 🟡 Medium — ProTradeNet broker is warm intro path to COO/CFO. PE intro only. | V4: SOURCE: Mr. Rooter FDD (franchiseba.com 2025) / Aire Serv FDD 2025 / ProTradeNet confirmed via neighborlybrands.com ITEM 11 — Technology: ServiceTitan explicitly named as required software system across all core brands. On ST since 2012 (Mr. Handyman, Aire Serv, Mr. Rooter, Mr. Electric per ServiceTitan press release). ITEM 8 — Vendors: ProTradeNet ~170 preferred vendors including insurance brokers. Specific broker named in brand-level FDDs. Broker = warm intro path to COO/CFO. ITEM 19 — Aire Serv 2025: 158 reporting businesses, 1/1/24-12/31/24 per FDD. Full financials behind paywall. ⚠️ DO NOT APPROACH DIRECT. PE intro only via Charles → KKR → Felix Gernburd. ST RENEWAL WINDOW: 2025-2027. Only leverage is PE relationship. | W4: 📊 USE INSIGHT ENGINE → ROI Calculator tab ⚠️ DO NOT RUN INSIGHT ENGINE until PE intro confirmed. IF/WHEN PE intro secured, pre-populate: • Technicians: 13,259 • Avg Jobs/Tech/Day: 5 (mature ST-optimized system) • Avg Revenue/Job: $400 • Focus: ST renewal window — Telematics angle via GPS Insight Conversation is about GPS Insight telematics (Smart Fleet USA contract renewal), not ServiceBridge FSM displacement. 3-Way Scenario: KKR exit at 10-12x multiple. | X4: 76.5 🔴 PE-GATED — DO NOT APPROACH DIRECT | Y4: WARM-PATH STATUS (05/04/2026): Mike's active angles to existing leadership: • Mike Davis (Corporate): I have a 1st connection with a former colleague I will investigate. ⚠️ STATUS CHANGES TO VERIFY: • Benjamin Lamb (Corporate): It appears Ben moved Feb. 2026. • Brad Roberson (Glass Doctor (prior)): It appears Brad may of just left business this March 2026 Full alumni intel: see Alumni Crossover GPS Insight v19 + Signal Intel tab v19 update. Becky-Mike touch plan in development for warm-anchor outreach sequencing. | Z4: 4/20 20 (limited; ST mandate caps) | AA4: 14/15 90 (13,259 techs — largest in P1) | AB4: 13/15 85 (KKR — active investor, exit-driven) | AC4: 13/15 85 (Charles Layne → Accel-KKR → KKR warm path) | AD4: 15/15 95 (highest — ST renewals 2025-2027 + KKR window) | AE4: 5/10 50 (ST partial mandate, displaceable on non-ST brands) | AF4: 8/10 80 (consumer-led mix) | AG4: KEY LINKEDIN URLS (UPDATED v15.34): 🎯 PRIMARY TARGET — GAGAN SINHA (CIO since Sept 2025): LinkedIn: linkedin.com/in/gagansinha/ ⭐⭐⭐ Harvard MS Mgmt 2011-2013. From Bloomin' Brands. STILL FORMING FSM ROADMAP. #1 OVERALL TARGET IN ENTIRE DATASET. EXECUTIVES: • Mike Davis (CEO July 2024): linkedin.com/in/mcardavis Ex-Mathnasium/Valpak/UMG. Irving TX. • Benjamin Lamb (CFO May 2025): linkedin.com/in/benlamb-finance/ Baylor BBA Finance/Econ ⭐ • Brad Stevenson (CDO): linkedin.com/in/bradstevenson1/ Texas A&M College Station BS Kinesiology 1991-96 ⭐ MillerCoors career since 1996. • Stacy Lynn Bourgeois (CMO): linkedin.com/in/stacy-lynn-bourgeois/ Northwestern Medill MS + Florida State BA ⭐⭐ • Matt Crowley (Group Pres-Specialty): linkedin.com/in/matt-crowley-usc/ USC Marshall MBA ⭐ Ex-Valpak EVP. • Georgeanne Erickson (Group Pres-Maintain): linkedin.com/in/georgeanne-erickson/ Pending school. Ex-CMO Fogo de Chão. • Jason Himber (Group Pres-Repair): linkedin.com/in/jason-himber/ Pending school verification. WARM PATH (PE-GATED): • Felix Gernburd (KKR Partner / Board): linkedin.com/in/felix-gernburd/ ← PE TARGET via Accel-KKR network • David Brandon (Neighborly Board / KKR Operating Partner): linkedin.com/in/david-brandon/ Ex-CEO Domino's, Toys R Us, Univ Michigan AD ⭐ U Michigan KEY BRAND PRESIDENTS: • Glenn Lewis CFE (Mr. Appliance): linkedin.com/in/glenn-lewis-cfe-28347913/ Baylor ⭐ • Josh McCormick (Mr. Electric, returned Aug 2025): linkedin.com/in/joshmccormickneighborly/ Baylor BBA ⭐ • Brian Meussner (Molly Maid + Mr. Handyman dual brand NEW Jan 2026): linkedin.com/in/brian-meussner-43b22b7/ Central Michigan U ⭐ • Susan McIntosh (Lawn Pride): linkedin.com/in/susanmcintoshneighborly/ Cardinal Ritter HS — operator path 30+ yrs ⭐ • Chris Bruno CFE (Window Genie): linkedin.com/in/chris-bruno-cfe-b895122a1/ Tarleton State ⭐ • Evan Brody (Mosquito Joe): linkedin.com/in/evansbrody/ Olin/WashU ⭐ • Mike Brickner (Precision Door): linkedin.com/in/mike-brickner-precision/ Columbia College ⭐ • Justin Penard (Grout Medic VP FD): linkedin.com/in/justinpenard/ Texas Tech ⭐ | AH4: ★ FSM / TECH / DIGITAL TRANSFORMATION QUOTES ★ Felix Gernburd (KKR Partner, Neighborly press release): "Mike will guide the execution of key enterprise initiatives and the DIGITAL TRANSFORMATION IN PROGRESS aimed to elevate Neighborly as a trusted provider to customers and an attractive investment for prospective franchise owners." → KKR PUBLICLY committed to digital transformation. This is the warm-intro hook. Mike Davis (LinkedIn 2024): "Industry-leading NPS scores across most of our brands - making Fans! A growing percentage of multi-brand customers - USING MARTECH TO CONNECT THE BRANDS and consumer trust - Loyalty that compounds." → Davis is publicly investing in cross-brand data infra. ServiceBridge job-level data feeds martech. Davis (Reunion 2024): "You grow companies by growing believers." "Don't just win customers. Create fans." | AI4: Neighborly Reunion ~Oct 2026 Likely Nashville (Gaylord Opryland) 16 brands + vendor partners attend ★ DO NOT attend without KKR intro IFA Annual Convention (Feb) Brad Stevenson (CDO) on IFA board FLDC Atlanta (Oct 6-8, 2026) Davis likely speaker 👉 See Event Intelligence tab for full schedule + opportunity analysis | AJ4: ENTRY: KKR PE intro only — NO direct approach. CHANNEL: Charles → Accel-KKR → KKR → Felix Gernburd → Davis introduction. ANGLE: GPS Insight telematics conversation FIRST (Smart Fleet conflict needs Mike Davis or Gagan Sinha as decision authority). NOT ServiceBridge FSM — ServiceTitan is locked in at brand level. TIMING: Week 1 GPS Insight ask only. No outreach until warm intro confirmed. Davis tenure (since Jul 2024) + Lamb (since May 2025) = both still in honeymoon period. | AK4: NEIGHBORLY BRAND-LEVEL ROSTER: Aire Serv: Jay Jimenez (Brand Pres NEW Apr 2026, was Brad Roberson) Frederick Roberts (Operations Consultant) Glass Doctor: Gabe Lopez (Brand Pres) Lawn Pride: Susan McIntosh (Brand Pres) Molly Maid: Michael Silva-Nash (Brand Pres) Mosquito Joe: Evan Brody (Brand Pres) Mr. Appliance: Glenn Lewis (Brand Pres) Mr. Electric: Josh McCormick (Brand Pres) Mr. Handyman: Brian Meussner (Brand Pres) Mr. Rooter: Matt Kunz (Brand Pres since 2023) Doyle James (former pres) Precision Garage Door: Mike Brickner (Brand Pres) Rainbow Restoration: Josh Miller (Brand Pres) Window Genie: Chris Bruno (Brand Pres) Five Star Painting: David Sutter (Brand Pres per 2023 video) Mary Kay Liston (former pres) Matt Phillips (former pres, then Neighborly COO) Amy Davis (VP Operations) Michael & Joy Nungesser (2024 Franchise Owners of the Year) Cindy Praesal, Anthony Kulikowski, Amado Cano, Mark Lambert (featured franchisees) Junk King: Vera Peterson (Interim Brand Pres) + Lisa Merry (former) Michael Andreacchi (Co-Founder, Investor + Brand Ambassador) Dryer Vent Wizard: Kevin Busch (Brand Pres) HouseMaster: Nancy Shipley (Brand Pres) Portland Glass: Sarah Frohnhoefer (Brand Pres) ProTradeNet: Brandi Haslam (Brand Pres) Real Property Management: Jeff Pepperney (Brand Pres) ShelfGenie: Tony Ditzler (Brand Pres) Grounds Guys: Lori Johnson (Brand Pres) Group Presidents: • Vera Peterson (Group Pres Maintain cluster: Dryer Vent, Molly Maid, Window Genie, Junk King, Five Star Painting, Mosquito Joe, Grounds Guys, Mr. Appliance) • Georgeanne Erickson (Group Pres — newer arrival) • Jason Himber (Group Pres Repair cluster) • Matt Crowley (Group Pres Specialty cluster) Neighborly Corporate: • Mike Davis (CEO since July 2024) — linkedin.com/in/mcardavis • Benjamin Lamb (CFO May 2025) • Gagan Sinha (CIO Sept 2025) — ex-Bloomin' Brands • Brad Stevenson (CDO) • Stacy Lynn Bourgeois (CMO) • Grayson Brown (EVP/General Counsel) • Courtney Kolar (CPO) PE: KKR — Felix Gernburd (Partner / Board) Founder: Don Dwyer (1981, original Dwyer Group) | AL4: 🥇 #1 OVERALL TARGET: Gagan Sinha (CIO, joined Sept 2025, Harvard MS Mgmt, ex-Bloomin' Brands CIO) — explicit "shift from primarily building systems in-house to ADOPTING AND INTEGRATING BEST-IN-CLASS PLATFORMS" stance. Mike Davis (CEO, ex-Mathnasium, Atlanta): "So much of being amazing with consumers in today's world is rooted in technology." Felix Gernburd (KKR Board): public quote on "digital transformation in progress." ⚠️ HARD CONFLICT: Smart Fleet USA / Azuga = preferred telematics for ALL 16+ Neighborly brands (NOT GPS Insight). Mike Bidwell passing (Sept 2023) = sensitive context. 👉 See Signal Intel: Neighborly section [v19 Alumni Intel · 05/04/2026]: 3 warm-path/status notes captured. See Col 25 for tactical detail and Signal Intel tab for full roll-up. | AM4: 🎓 NEIGHBORLY EDUCATION CLUSTER (DEEP): TOP LEADERSHIP: • Mike Davis (CEO since July 2024): Pending school confirmation. 13 yrs UMG EVP → CEO Valpak → CEO Mathnasium → Neighborly. Irving TX office. • Jon Shell (CFO, formerly interim CEO): Pending verification • Gagan Sinha (CIO since Sept 2025): Harvard MS Mgmt 2011-2013 ⭐⭐⭐ #1 OVERALL TARGET. Ex-Bloomin' Brands, ex-Inspire Brands. • Brad Stevenson (CDO): Texas A&M College Station BS Kinesiology 1991-1996. MillerCoors career since 1996. • Stacy Lynn Bourgeois (CMO): Northwestern MS Integrated Marketing 2009-2010 + Florida State BA Communications. Ex-Yum Brands, Pizza Hut. • Ben Lamb (CFO May 2025): Baylor BBA Finance/Econ/Intl Business • Courtney Kolar (SVP People Services): Pending school. 9yrs Kohl's HR. GROUP PRESIDENTS: • Matt Crowley (Group Pres-Specialty): USC Marshall MBA. Ex-Valpak EVP. Two decades PE/digital media/Fortune 50. • Jason Himber (Group Pres-Repair: Aire Serv, Glass Doctor, Mr. Electric, Mr. Handyman, Mr. Rooter, Precision, Rainbow): Pending school. 15+ yrs. • Georgeanne Erickson (Group Pres-Maintain: Mr. Appliance, Molly Maid, Window Genie, Mosquito Joe, Five Star Painting, Junk King, Dryer Vent Wizard, Grounds Guys): Pending school. Ex-CMO Fogo de Chão. BRAND PRESIDENTS: • Glenn Lewis (Mr. Appliance): Baylor 1982-1985 + UT Austin 81-82, CFE. Wife Leslie + daughter Calli also Baylor. • Josh McCormick (Mr. Electric): Baylor BBA Mgmt 1999-2002 • Brian Meussner (Mr. Handyman): Central Michigan Univ 1999-2002 • Mike Brickner (Precision Door): Columbia College • Susan McIntosh (Lawn Pride): Cardinal Ritter HS Indianapolis (no college) • Michael Silva-Nash (Molly Maid): U Arkansas Little Rock 2010-2014, International Business + Foreign Language. CFE, bilingual. • Chris Bruno (Window Genie): Tarleton State University BAS Business Admin 2018-2020. CFE. • Evan Brody (Mosquito Joe): Olin School of Business, Washington University in St. Louis ⭐ • Jay Jimenez (Aire Serv NEW Apr 2026): CFE, school pending • Matt Kunz (former Mr. Rooter Pres, NOW LEFT for Fastest Labs CEO Jan 2026): WSU Carson MBA + Northern Illinois BBA + Morrison Tech AS 🎯 BAYLOR CLUSTER: 3 Neighborly leaders (Lewis, McCormick, Lamb) 👉 See Signal Intel tab Master Education Table for sortable view
A5: 2 | B5: AUTHORITY BRANDS | C5: Apax Partners + BCI | D5: P1 #2 · DISPLACEMENT-READY | E5: 12 | F5: 12098 | G5: $181K | H5: Jay Caiafa CEO (joined Aug 2025) Prev: COO Americas, IHG Hotels 4,600 hotels, 26 countries Data/AI focus — new leadership Rob Weddle — OUT (was CEO) | I5: Josh Greear CFO (joined Sept 22, 2025) LinkedIn: linkedin.com/in/joshgreear/ Education: U Richmond BA + Vanderbilt MA ⭐⭐ Atlanta. 4 kids. Prev: CFO Primrose Schools, VP Strategy & BD Cracker Barrel, financial leadership roles The Home Depot. 25+ yrs franchise/finance experience. | J5: Steve Clemente President & COO, Trades | K5: Tij Bedi CTO (joined Aug 2024) ← PRIMARY entry point Tech/FSM mandate angle 9 non-ST brands greenfield Note: Jay Caiafa (CEO) has data + AI background — lead with operational efficiency | N5: Map 9 non-ST brands + Tij Bedi research | O5: Week 1 (research) | P5: GPS: Apax Partners → Charles Layne for PE intro. Tij Bedi is primary tech champion. | Q5: 9 of 12 brands have no ServiceTitan. No displacement. Ryan Bowes = Chief Dev Officer. | R5: Annual Convention — research needed | S5: Unknown | T5: National program likely via Apax Partners — validate FDD Item 8/11 | U5: 🟡 Medium — $2B+ revenue, institutional program almost certain. Tij Bedi (CTO) not the right contact here. | V5: SOURCE: ServiceTitan press release Sep 2024 / public FDD summaries ITEM 11 — Technology: ServiceTitan named as required platform for 3 brands (Benjamin Franklin, Mister Sparky, One Hour) — announced Sep 2024, transition in 2025. 9 remaining brands have NO FSM mandate. PRIOR PLATFORM: Successware (acquired by Authority Brands 2019) — being replaced by ServiceTitan. ✅ GREENFIELD: ASP, Cleaning Authority, DRYmedic, Junkluggers, Lawn Squad, Monster Tree, Mosquito Squad, Screenmobile, STOP Restoration — 9 brands, no mandate. PRIMARY CONTACT: Tij Bedi (CTO, joined Aug 2024) building tech infrastructure. | W5: 📊 USE INSIGHT ENGINE → ROI Calculator tab PRE-POPULATE WITH (9 non-ST greenfield brands only): • Technicians: ~5,000 (9 non-ST brands est.) • Avg Jobs/Tech/Day: 4 • Avg Revenue/Job: $350 • Working Days: 260 PRIMARY AUDIENCE: Tij Bedi (CTO) — use Competitive Matrix tab to show ServiceBridge vs ServiceTitan side by side. Key message: ServiceBridge for the 9 brands ST doesn't serve. No displacement of existing ST mandate. | X5: 68.5 🟡 ACTIVE | Y5: Charles Layne → Apax Partners PE intro path Tij Bedi (CTO Authority Brands) — new hire Aug 2024, direct LinkedIn Andrea Rowan for brand-level account data | Z5: 12/20 60 (mixed — 3 brands ST mandated, 12 brands open) | AA5: 13/15 85 (12,098 techs) | AB5: 12/15 80 (Apax — active investor + co-investor BCI) | AC5: 11/15 70 (Tij Bedi CTO direct, plus parent path) | AD5: 13/15 85 (Jay Caiafa CEO Aug 2025, Josh Greear CFO Sept 2025 — fresh tech direction) | AE5: 7/10 70 (ServiceTitan partial — 12 non-ST brands displaceable) | AF5: 7/10 70 (mix B2B + consumer) | AG5: KEY LINKEDIN URLS (UPDATED v15.34): • Jay Caiafa (CEO Aug 2025): linkedin.com/in/jay-caiafa-65580a1/ USAFA Captain + Duke Law JD + Duke Fuqua MBA ⭐⭐⭐ TRIPLE • Josh Greear (CFO Sept 2025): linkedin.com/in/joshgreear/ U Richmond BA + Vanderbilt MA ⭐⭐ • Steve Clemente (Pres & COO Trades Dec 2025): linkedin.com/in/steve-clemente-trade-brands/ UCF + Webster Master's ⭐⭐ • Ryan Bowes (Chief Growth Officer Feb 2026): linkedin.com/in/ryan-bowes/ Clemson BS+MS Real Estate ⭐ • Tij Bedi (CTO since Aug 2024): linkedin.com/in/tijbedi/ ← PRIMARY tech entry • Stewart Vernon (EVP Emerging Brands): linkedin.com/in/stewart-vernon-asp/ College of Charleston (Macon GA hometown, Stratford Academy) ⭐ • Tom Swift (EVP Outdoor Brands): linkedin.com/in/tom-swift-597a2018/ Presbyterian + Mercer Law + UFlorida LLM Tax + CFP ⭐⭐ • Justin Waltz (Junkluggers Pres): linkedin.com/in/justinwaltz/ • Rob White (Monster Tree Pres): linkedin.com/in/robthewhitewa/ Virginia Tech BS Finance + VCU MBA ⭐ • Farah Bhayani (CLO): SMU BBA + JD ⭐ | AH5: ★ FSM / TECH / DIGITAL TRANSFORMATION QUOTES ★ Tij Bedi (CTO) — Franchising.com BYLINED ARTICLE 2025: "Historically, franchise platforms have grappled with SILOED SYSTEMS across the network and even within each brand. Today, many home service brands are BREAKING DOWN THESE BARRIERS by integrating data from various systems into centralized DATA LAKES. These data-driven decisions enable franchisees to identify trends before they become issues and OPTIMIZE OPERATIONS, improving resource allocation, marketing effectiveness, and customer satisfaction." → DIRECT MATCH for ServiceBridge value prop. He literally wrote the pitch. Reference this article in the LinkedIn DM to him. "As we look to the future, technology will play an increasingly central role in the home service industry." Bedi (Gartner Peer Community): "Better understanding of vision, growth strategy at every level in organization and collaborative decisioning allows empowered and high performing teams contributing to growth and efficiency." | AI5: Authority Brands Annual Convention 🔍 Date/location TBD - research needed Almost certain to exist at $1-2B revenue scale FLDC Atlanta (Oct 6-8, 2026) Caiafa likely C-suite attendee IFA Annual (Feb 2027) 👉 See Event Intelligence tab for full schedule + opportunity analysis | AJ5: ENTRY: Tij Bedi (CTO) tech champion — direct LinkedIn approach appropriate. He just joined to build tech for 9 brands with NO FSM mandate. HOOK: "You just joined to build tech infrastructure for 9 brands with no FSM mandate. ServiceBridge is the fastest path to get there." CHANNEL: 1. LinkedIn to Tij Bedi (direct) 2. Competitive Matrix as conversation starter 3. GPS → Apax Partners intro via Charles (parallel) DISPLACEMENT NOTE: Authority has active ServiceTitan partnership (2024). 9 non-ST brands are greenfield. Caiafa + Greear (CFO Sep 2025) + Clemente are <1yr in role = window open. TIMING: Week 2-3 | AK5: AUTHORITY BRAND-LEVEL ROSTER (UPDATED): Trades Cluster (Steve Clemente): • Benjamin Franklin Plumbing — Steve Clemente direct oversight Punctual Pros multi-unit franchisees: Matt + Aaron Buckwalter (Central PA) Jonathan Marlow (Broad Sky Partners — Punctual Pros backer) Kelley Pendergast (BFP franchisee) Scott Wood Jr. (BFP+OHHAC franchisee Omaha — veteran-supporter) Cory Clinton (BFP GM Indianapolis), Robert Armstrong (Ops Mgr N.Colorado) • One Hour Heating & Air Conditioning — Steve Clemente direct • Mister Sparky Electric — Steve Clemente direct • DRYmedic Restoration — Steve Clemente direct Lindsay Keyser (DRYmedic franchisee feature) • STOP Restoration — Steve Clemente direct Outdoor Cluster (Tom Swift): • Mosquito Squad Plus — Jef Flournoy (Brand Pres, 20yr anniversary brand enhancement) Capricia T. (franchisee feature) • Monster Tree Service — Chris Brown (VP Operations, NEW summer 2024 — former franchisee) • DoodyCalls — Jacob + Susan D'Aniello (Co-Founders) Kara Kelsey (DoodyCalls franchisee feature) • Screenmobile — Clint Rowley (Brand Pres NEW late 2024) • Lawn Squad — Tom Swift oversight, brand pres TBD Emerging Cluster (Stewart Vernon): • ASP — Stewart Vernon (Founder/EVP) • Cleaning Authority — founding brand, corporate-led Shannon Oakley (TCA franchisee Spokane+Bellevue) • Color World Painting — Chris Ring (Brand Pres NEW) Tom Hodgson (Founder 1997) Gary Sheffer (top franchisee Birmingham AL) • Junkluggers — Justin Waltz (Brand Pres Jan 2024) Josh Cohen (Founder, departed) • Homewatch CareGivers — Todd Houghton (Brand Pres) • Woofie's — Amy Addington (President & Co-Founder) Marcie Campagnola (Woofie's franchisee feature) Authority Corporate: • Jay Caiafa (CEO Aug 2025) • Josh Greear (CFO Sept 2025) • Steve Clemente (Pres COO Trades Aug 2025) • Tij Bedi (CTO) • Jordan Wilson (CDO since Jan 2025) • Ryan Bowes (CGTO Feb 2026) • Leanne Stapf (EVP) • Stewart Vernon (EVP Emerging) • Tom Swift (EVP Outdoor) • Adam Terranova (Sr Director Marketing) • Farah ___ (General Counsel May 2025) PE: Apax Partners — Ashish Karandikar (Partner / Board) Former CEOs: Rob Weddle, Craig Donaldson PR: 360PR+ (Vince Powers EVP) + Fish Consulting (Sarah Guffey, Joshua Morris, Brendan Maguire, Nikki Rode) Crisis comms: Kekst CNC (Todd Fogarty) Legal: Foley Lardner (Christina Kennedy) M&A advisor: Boxwood Partners (Brian Alas MD, Patrick Galleher Partner) | AL5: 🥇 PRIMARY: Jay Caiafa (CEO Aug 2025, USAFA Captain + Duke Law JD + Duke Fuqua MBA, 9mo in role, IHG bio "drove innovation through data and AI" across 4,600 hotels). Atlanta. Wife Meredith, 3 sons. Josh Greear (CFO Sept 2025, U Richmond + Vanderbilt, ex-Primrose CFO). 🎯 STRONG: Ryan Bowes (CGTO Feb 2026, Clemson BS+MS, oversees BuyMax GPO platform + franchise dev). Steve Clemente (Pres/COO Trade Brands Dec 2025, ex-Primrose President — oversees Benjamin Franklin, One Hour, Mister Sparky, DRYmedic). ⚠️ ServiceTitan partnership = displacement story, not greenfield. 👉 See Signal Intel: Authority Brands section | AM5: 🎓 AUTHORITY BRANDS EDUCATION CLUSTER (DEEP): EXECUTIVES: • Jay Caiafa (CEO Aug 2025): USAFA Captain + Duke Law JD + Duke Fuqua MBA ⭐⭐⭐ TRIPLE • Josh Greear (CFO Sept 2025): U Richmond BA + Vanderbilt MA. 4 kids, Atlanta. Ex-Cracker Barrel + Home Depot. • Steve Clemente (Pres/COO Trade Brands Dec 2025): UCF BS Liberal Studies + Webster University Master's. 30+ yrs Dick's, Target, Nebraska Book, Primrose Schools President. • Ryan Bowes (CGTO Feb 2026): Clemson BS+MS Real Estate Dev/Finance. Ex-IHG, Marriott, Starwood, FirstKey Homes CIO. • Farah Bhayani (CLO): SMU BBA Real Estate Finance + JD • Stewart Vernon (EVP Emerging Brands, ASP Founder): College of Charleston (corp comms). Macon GA, Stratford Academy. Wife Shannon. • Tom Swift (EVP overseeing Mosquito Squad+Monster Tree+DoodyCalls+Screenmobile, since June 2023): Presbyterian College BA + Mercer Law JD 2001-2003 + UFlorida LLM (Master Tax Law) + CFP. Macon/Bibb County GA. BRAND PRESIDENTS: • Justin Waltz (Junkluggers Pres): Towson University. Started 1-800-GOT-JUNK truck driver 2005. • Rob White (Monster Tree Service Brand Pres Nov 2023): Virginia Tech BS Business Finance + VCU MBA. Ex-Rainbow Restoration Pres. • Todd Houghton (Homewatch CareGivers Pres): Illinois State BS Econ/Business 🎯 DUKE + MACON GA CLUSTER: Caiafa = dual Duke alum. Vernon + Swift both Macon GA roots 👉 See Signal Intel tab Master Education Table for sortable view
A6: 3 | B6: EMPOWER BRANDS | C6: MidOcean Partners | D6: P1 #3 · GREENFIELD-LED | E6: 10 | F6: 5150 | G6: $77K | H6: Scott Zide CEO | I6: Michael Borreca SVP & CFO | J6: Tom Welter COO + President Residential (joined Dec 2022) LinkedIn: linkedin.com/in/thomaslwelter/ Education: University of Nebraska-Lincoln BS Business Admin ⭐⭐ 🏈 NFL alumni (Arizona Cardinals) + CoSIDA First Team Academic All-American 30 yrs ops: Avis → Yum/Taco Bell (125 corp + 325 fr) → 24 Hour Fitness → KB Home → Byrider → Lift Brands COO → Empower. | K6: R. Scott Sutton Chief Dev Officer | N6: JAN-PRO brand wedge + CEO outreach | O6: Week 1 | P6: GPS: MidOcean → Charles Layne for PE intro before approaching Scott Zide | Q6: Gary Bauer (JAN-PRO Brand President) is brand-level wedge. EBITDA before exit window. | R6: Ignite · Feb 10–12 (just held — next ~Feb 2027, Orlando) | S6: ✅ Yes — 85 vendors attended | T6: Preferred broker via MidOcean PE (likely) — validate FDD Item 8/11 | U6: 🟡 Medium — CFO Michael Borreca owns this. MidOcean institutional. | V6: SOURCE: FDD Exchange 2025 / franchiseba.com / assettfranchise.com JAN-PRO ITEM 8 — Technology: Proprietary software mandated. Technology fee: up to $60/month per franchisee. JAN-PRO ITEM 19: 11,265 unit franchises. Regional developer investment $130K-$421.5K. ⚠️ CONFLICT FLAG: JAN-PRO has proprietary FSM with fee already built in. Confirm gap vs ServiceBridge before outreach on JAN-PRO specifically. ✅ GREENFIELD: 9 non-JAN-PRO brands (Archadeck, Bumble, Canopy, Conserva, FRSTeam, Koala, OLP, Superior Fence, Wallaby) — no FSM named in FDD. These are the entry point with Scott Zide. | W6: 📊 USE INSIGHT ENGINE → ROI Calculator tab PRE-POPULATE WITH (9 non-JAN-PRO greenfield brands): • Technicians: ~3,500 (excl. JAN-PRO) • Avg Jobs/Tech/Day: 3.5 • Avg Revenue/Job: $350 • Working Days: 260 ⚠️ EXCLUDE JAN-PRO from model — proprietary FSM conflict. Run separate scenario for the 9 greenfield brands only. MidOcean exit window framing: EBITDA uplift × 8x multiple = enterprise value story for Scott Zide + Michael Borreca. | X6: 66.2 🟡 ACTIVE | Y6: WARM-PATH STATUS (05/04/2026): Mike's active angles to existing leadership: • Ben Wright (Canopy Lawn Care): I will be working an angle to get connected through existing relationships • Hunt Davis (Canopy Lawn Care): I will be working an angle to get connected through existing relationships ⚠️ STATUS CHANGES TO VERIFY: • Russ Jundt (Corporate / Conserva Founder): Retired Full alumni intel: see Alumni Crossover GPS Insight v19 + Signal Intel tab v19 update. Becky-Mike touch plan in development for warm-anchor outreach sequencing. | Z6: 18/20 90 (highest — ServiceMinder partial, most brands open) | AA6: 8/15 55 (5,150 techs — mid-tier) | AB6: 12/15 80 (MidOcean Year 3-4, building toward exit) | AC6: 12/15 80 (Scott Zide CEO + Gary Bauer JAN-PRO brand wedge) | AD6: 9/15 60 (mid-term, not immediate) | AE6: 3/10 30 (ServiceMinder 2-4x partial) | AF6: 4/10 40 (Commercial 70%+ — weaker consumer fit) | AG6: KEY LINKEDIN URLS (UPDATED v15.34): • Scott Zide (CEO): linkedin.com/in/scott-zide-974b1914/ University of Kansas BA. Ex-Mr. Goodcents franchisee at age 23. • Tom Welter (COO + Pres Residential): linkedin.com/in/thomaslwelter/ ⭐⭐ U Nebraska-Lincoln + NFL alumni Arizona Cardinals • Russ Jundt (Pres National Accounts; Conserva Founder): linkedin.com/in/russjundt/ Saint John's University (MN) BA Business Mgmt ⭐ • R. Scott Sutton (CDO Dec 2022): linkedin.com/in/rscottsuttoncfe/ U Oklahoma BA. CFE + CMAA ⭐ • Michael Borreca (SVP & CFO): linkedin.com/in/michael-borreca/ Ex-FOCUS Brands VP CorpFinance, KPMG career origin. • Justin Mayer (OLP Brand Pres): linkedin.com/in/justin-mayer-a620003a/ USNA BS Econ + UVA Darden MBA + USMC ⭐⭐⭐ TRIPLE • Heather Todd (Conserva Brand Pres): linkedin.com/in/heather-todd-cfe/ UNLV College of Business + CFE ⭐ • Jack O'Connell (Archadeck Pres): linkedin.com/in/jack-o-connell-95928b2a/ Penn State + ex-PGA Golf Professional Country Club of Virginia ⭐ • Cory Lyons (Koala/Wallaby): linkedin.com/in/cory-lyons-6a9ab919/ Rochester Community Tech College (trade-school path) • Hunt Davis (Canopy CEO): linkedin.com/in/huntdavis/ 🎯🎯🎯 NC STATE ⭐⭐⭐ Cary NC HQ • Ben Wright (Canopy Pres): linkedin.com/in/benjamin-wright-43613729/ 🎯🎯🎯 NC STATE ⭐⭐⭐ Landscaping/Horticulture | AH6: ★ FSM / TECH / DIGITAL TRANSFORMATION QUOTES ★ Scott Zide (CEO) — Franchising.com 2024 interview: "We've started a STRATEGIC INITIATIVE TO UNITE DATA AND AI ACROSS OUR BRANDS. This integration is critical for deepening our insights and enhancing our predictive capabilities, empowering us to make informed, strategic decisions. Adopting AI is not just about keeping up with the times; it's about setting a new standard in EFFICIENCY AND INNOVATION within our industry." "I've challenged our franchisees to EMBRACE TECHNOLOGY and create a more frictionless experience for customers." → Direct match. ServiceBridge IS the data-unification layer across 9 brands. Zide (Franchising.com): "First and foremost we live in a digital world. FRANCHISORS ARE GOING TO HAVE TO INVEST IN AND EMPLOY TECHNOLOGY so they can focus on the customer experience." Zide (Apr 2026 leadership announcement): "We've expanded our leadership bench across marketing, operations, TECHNOLOGY and brand leadership roles. Continued investment in franchisee support and PLATFORM INNOVATION across our portfolio." → Hiring tech leaders NOW. Time-sensitive entry window. Empower deployed EOS (Entrepreneurial Operating System) for corporate + franchisees — process-driven culture. | AI6: Empower Ignite 2027 ~Feb 2027, Orlando likely 1,100+ attendees, 85 vendor partners ✅ Build vendor relationship NOW for Ignite Zide active on FLDC + IFA stages Featured in Franchise Times 2024 cover BizCom client = press-friendly 👉 See Event Intelligence tab for full schedule + opportunity analysis | AJ6: ENTRY: 9 greenfield brands + MidOcean exit window. HOOK: "You have 9 brands with no FSM mandate and a PE exit window opening. That math works in both our favors." CHANNEL: 1. LinkedIn to Scott Zide (sent Apr 8 — follow up) 2. Email with 3-Way Scenario (9 non-JAN-PRO brands) 3. Gary Bauer brand wedge on JAN-PRO separately 4. MidOcean PE intro via Charles (parallel) WHY FIT: Zide's public AI commentary signals openness to operational tech investment. ServiceBridge is the natural fit for the operational side of his AI thesis. TIMING: Week 2 | AK6: EMPOWER BRAND-LEVEL ROSTER: JAN-PRO: Gary Bauer (Brand Pres) Volker Wellman (SVP Operations, 2026 NEW) $705.6M sys sales 2024 (Empower's largest) Archadeck Outdoor Living: Michael Reeder (Brand Pres) Bumble Roofing: David Bitan (Founder & Brand Pres) Katie Lepper (Director Franchise Dev, 2025 NEW) Canopy Lawn Care: Ben Wright (Brand Pres NEW 2026) Conserva Irrigation: Heather Todd (Brand Pres NEW Feb 2025) Russ Jundt (Founder, now Empower National Accounts) Stacy Parkelj (Director Franchise Operations) FRSTeam: Jeff Waters (Brand Pres NEW 2026) Holly Murry (prior Brand Pres) Koala Insulation: Cory Lyons (DUAL Brand Pres + Wallaby Windows) Steve Griffith (Director Franchise Dev, 2025 NEW) Outdoor Lighting Perspectives: Justin Mayer (Brand Pres NEW Apr 2025) Rich Young (prior pres) Superior Fence & Rail: Joe Dominiak (Brand Leader NEW 2026) Wallaby Windows: Cory Lyons (DUAL Brand Pres — same as Koala) Empower Corporate: • Scott Zide (CEO & Co-Founder — Mosquito Squad founder) — linkedin.com/in/scott-zide-974b1914/ • Michael Borreca (SVP & CFO) • Thomas Welter (Group Pres Residential) • R. Scott Sutton (CDO) • Joel Marr (CIO Chief Incubation Officer — oversaw Bumble+Canopy+Wallaby+Koala acquisitions) • Chris Donnelly (VP Information Technology, 2026 NEW) • Melanie Watts (VP Brand Marketing, 2026 NEW) • Brandon Yarnell (National Accounts Sales Manager Conserva + OLP) PE: MidOcean Partners Original platform: Outdoor Living Brands + Lynx Franchising rebrand 2022 Acquisition advisor: Boxwood Partners (J. Patrick Galleher MD, Dan Martinson VP) | AL6: 🥇 PRIMARY: Scott Zide (CEO since 2022, U Kansas, started as Mr. Goodcents franchisee at 23, Richmond VA). Direct Nov 2025 quote: "data warehouse stores info across all brands... technology automation improves speed of response, proposal and service times." ACG Richmond keynote Nov 2024. IFPG Summit 2024 keynote. 🎯 STRONG: Justin Mayer (OLP Brand Pres April 2025, USNA BS Econ Dean's List + UVA Darden MBA Top 10, USMC veteran, ex-DuPont Global Sales Director). Heather Todd (Conserva Irrigation Brand Pres Feb 2025, internal promotion). 👉 See Signal Intel: Empower Brands section [v19 Alumni Intel · 05/04/2026]: 3 warm-path/status notes captured. See Col 25 for tactical detail and Signal Intel tab for full roll-up. | AM6: 🎓 EMPOWER BRANDS EDUCATION CLUSTER (DEEP, V15.29 expanded): EXECUTIVES: • Scott Zide (CEO): University of Kansas BA. Ex-Mr. Goodcents franchisee at age 23. Richmond VA HQ. • Tom Welter (COO + Pres Residential, since Dec 2022): University of Nebraska-Lincoln BS Business Administration ⭐⭐ CoSIDA First Team Academic All-American + NFL alumni (Arizona Cardinals)! 30 yrs ops: Avis → Yum/Taco Bell (125 corp + 325 fr) → 24 Hour Fitness → KB Home → Byrider → Lift Brands COO. • R. Scott Sutton (CDO since Dec 2022): U Oklahoma BA. CFE + CMAA. Native Chesapeake VA. Wife Linda. Atlanta. • Russ Jundt (Pres National Accounts & Residential Home Service Brands): Saint John's University BA Business Management ⭐. Minneapolis MN. Conserva Founder. • Heather Burns (CHRO): Pending. Target/Berkeley/BJ's prior. • Michael Borrecca (CFO): Pending school. Ex-FOCUS Brands VP CorpFinance, KPMG career origin. BRAND PRESIDENTS: • Justin Mayer (OLP): USNA BS Econ (GPA 3.69, Dean's List, Honors) + UVA Darden MBA + USMC veteran ⭐⭐⭐ TRIPLE • Heather Todd (Conserva, promoted Feb 2025): UNLV College of Business. CFE. Richmond VA. • Cory Lyons (Koala Insulation Aug 2023 + Wallaby Windows mid-2025): Rochester Community and Technical College. Trade-school path. Melbourne FL. • Jack O'Connell (Archadeck Outdoor Living, Brand Pres in Training Oct 2024): Penn State University BS ⭐. Richmond VA. Ex-VP LL Flooring B2B + PGA Golf Professional! • Michael Reeder (Archadeck legacy Brand Leader): University of Houston ⭐. 15 yrs Archadeck franchisee owner ($2MM+). • Ben Wright (Canopy Lawn Care): 🎯🎯🎯 NC STATE University ⭐⭐⭐ Major: Landscaping/Horticulture. North Carolina-based. • Hunt Davis (Canopy Founder/CEO): NC State University BS ⭐⭐⭐ Cary NC. Ex-investment banker. • David Bitan (Bumble Roofing Founder/Brand Pres): Education pending. 16 yrs home services. LA. Co-founded AID Home Remodeling. • Jeff Waters + Shelly Waters (FRSTeam): Education pending. 2024 FRSTeam Franchisee of the Year, Tulsa OK. • Gary Bauer (JAN-PRO): Coe College. 30+ yrs ServiceMaster. 🎯🎯🎯 NC STATE WOLFPACK CLUSTER: Hunt Davis + Ben Wright BOTH NC State alums at Canopy Lawn Care, Cary NC HQ — Mike's backyard. STRONGEST WARM-INTRO PATH IN ENTIRE DATASET. 🎯 RICHMOND VA HQ + UVA DARDEN cluster (Mayer + Kappler-historical) 🎯 NEBRASKA cluster: Tom Welter + Brett Ponton (Servpro) 👉 See Signal Intel for Master Education Table sortable view
A7: 4 | B7: RESIBRANDS | C7: Angel / Codie Sanchez | D7: P1 #4 · FAST-CYCLE | E7: 5 | F7: 2550 | G7: $38K | H7: Steven Montgomery Founder & CEO | I7: (None confirmed) Lean team | J7: Allan Alarcon Co-Founder & Chief Growth Officer (also Brand Pres of Action Exteriors NEW 2025) LinkedIn: linkedin.com/in/allan-alarcon-20b703229/ Education: Master's Commission Bible Institute ⭐ Round Rock TX. Co-founded ResiBrands 2022 with Steven Montgomery. Trained by Montgomery as professional painter; long-time friend Jay Nielsen serves as Chief Development Officer. Per Steven's LinkedIn: "About to hit 800 units. Brand 6 coming." 🆕 Codie Sanchez joined as co-owner 2024 (popular finance/business personality, Contrarian Thinking founder). | K7: Steven Montgomery (handles directly) | N7: Direct LinkedIn to Steven Montgomery | O7: Week 2 | Q7: Founder-backed. No PE committee. One conversation closes this. $1.67/tech/day message. | R7: No confirmed annual event (emerging brand) | S7: Unknown | T7: Franchisees self-direct — lean founder operation, no group program likely | U7: 🟢 Low | V7: SOURCE: Public company info / IFA 2026 ITEM 11 — Technology: ResiConnect handles inbound scheduling only. No full FSM disclosed in any publicly available FDD summary. ITEM 19 — Unit Economics: FDD not publicly analyzed. Angel/founder-backed — lean disclosure likely. APPROACH: Steven Montgomery directly accessible. No FDD deep-dive needed before first conversation. | W7: 📊 USE INSIGHT ENGINE → ROI Calculator tab PRE-POPULATE WITH: • Technicians: 2,550 • Avg Jobs/Tech/Day: 5 (painting model — volume-based) • Avg Revenue/Job: $200 • Working Days: 260 FOUNDER PITCH: $1.67/tech/day message. Run Insight Engine conservative scenario only — Steven Montgomery responds to simplicity, not PE math. Total: 2,550 techs × $1.67/day × 260 days = ~$1.1M annual value | X7: 60.2 🟢 ACTIVE | Y7: WARM-PATH STATUS (05/04/2026): Mike's active angles to existing leadership: • Steven Montgomery (Corporate / That 1 Painter): I have a mutual connection. Investigating 👥 TEAM ASSIGNMENTS: • Carter Smith (Pink's Window Services): Garrett- this looks like your guy. Full alumni intel: see Alumni Crossover GPS Insight v19 + Signal Intel tab v19 update. Becky-Mike touch plan in development for warm-anchor outreach sequencing. | Z7: 17/20 85 (ResiConnect = scheduling only, paper for ops) | AA7: 7/15 45 (2,550 techs — smallest) | AB7: 6/15 40 (Angel/founder, no PE pressure) | AC7: 14/15 90 (Kevin Luu direct, fast decision velocity) | AD7: 11/15 75 (entrepreneurial — moves fast) | AE7: 7/10 70 (mostly greenfield) | AF7: 8/10 75 (consumer-led) | AG7: Steven Montgomery (Founder & CEO) linkedin.com/in/steven-montgomery-7a452846/ Twitter: @realsjmonty Email: steven@resibrands.com Phone: +1 (512) 270-0161 Allan Alarcon (Co-Founder) Search: 'Allan Alarcon ResiBrands' Codie Sanchez (Co-Owner since 2024) Public figure - direct LinkedIn search | AH7: ★ FSM / TECH STACK QUOTES + GAP EVIDENCE ★ ResiBrands.com (their official tech stack): "ResiConnect powers your business with smart, scalable tech. From tools like TRAINUAL, CLICKUP, AND SLACK to our flexible national scheduling system, we streamline operations and communication at every level." → DIRECT EVIDENCE OF FSM GAP. ClickUp + Slack + Trainual = no proper FSM dispatch. ResiConnect is a lead/scheduling layer, NOT field service execution. Steven Montgomery (LinkedIn): "A Franchise System, by definition, is supposed to mean that an average employee on an average day can be successful. Handing out a printed manual and telling an owner to hustle is not a franchise system." → This IS the ServiceBridge value prop. He's predisposed. "6 brands, 800 units, on the precipice of greatness." Direct: steven@resibrands.com / +1 (512) 270-0161 | AI7: No confirmed annual convention (Steven directly accessible — no event needed) Codie Sanchez = IFA 2026 Main Stage Speaker Use her IFA appearance as icebreaker Springboard franchise conferences (attended) PCA Expo (March) — That 1 Painter vertical 👉 See Event Intelligence tab for full schedule + opportunity analysis | AJ7: ENTRY: Founder-accessible, fastest path to close. HOOK: "$1.67 per tech per day to go fully paperless. For 2,550 techs, that's your whole operation digitized." CHANNEL: 1. Call scheduled Apr 15 (Steven replied positive) 2. Send Insight Engine conservative scenario before call 3. Pilot proposal on first or second call WHY FIT: Steven's public quote on franchise systems ("average employee on average day can be successful") IS the ServiceBridge value prop. He's predisposed. TIMING: 🔥 THIS WEEK | AK7: RESIBRANDS BRAND-LEVEL ROSTER (UPDATED v15.34): That 1 Painter: Steven Montgomery (Founder & CEO) LinkedIn: linkedin.com/in/steven-montgomery-7a452846/ Calvary Chapel U DROPOUT to launch That 1 Painter ⭐ Operator path. GarageUp: Steven Montgomery oversight. Co-founder Allan Alarcon. Pink's Window Services: Carter Smith + Tom Downer (Co-founders) LinkedIn (Carter): linkedin.com/in/cartersmith7/ Carter: Baylor University ⭐ — led Baylor's largest mens service org (170 members), $20K/yr Mission Waco fundraise. Tom Downer (Co-founder): pending direct verification. Action Exteriors: The Smola Family (Founders) + Allan Alarcon (Brand Pres NEW 2025) LinkedIn (Allan): linkedin.com/in/allan-alarcon-20b703229/ Joined ResiBrands 2025. Formerly Action Roofing (3-generation family-owned). NATIONAL PARTNERSHIP w/ Cornerstone Building Brands (#1 US window manufacturer) — launching window/siding program. Monty's Handyman: Steven Montgomery (Founder & Franchisor) 4th brand. "Every home deserves care." Brand 6 (TBD): Coming soon per Steven's LinkedIn. CO-OWNER: Codie Sanchez (joined 2024) Famous for Contrarian Thinking + Main Street Money biz portfolio. Adds significant amplification + capital partner network. | AL7: 🥇 PRIMARY: Steven Montgomery (Founder/CEO, Calvary Chapel BA 2017, Austin TX, son of professional painter). Built $12 → $100M company. 4.5 yrs in franchising, 6 brands, ~800 territories. Coaches son's soccer team (Eagles, age 8). Codie Sanchez (Co-Owner 2024, Contrarian Thinking founder, big public megaphone). Carter Smith (Pink's Co-Founder, Baylor — 4th Baylor connection). ⚠️ COMPETITIVE FLAG: ResiConnect (appointment center) + ResiCreative (creative agency) = internal tools, NOT full FSM (no dispatch/routing/telematics). 👉 See Signal Intel: ResiBrands section [v19 Alumni Intel · 05/04/2026]: 3 warm-path/status notes captured. See Col 25 for tactical detail and Signal Intel tab for full roll-up. | AM7: 🎓 RESIBRANDS EDUCATION CLUSTER: • Steven Montgomery (Founder/CEO): Calvary Chapel University BA (DROPPED OUT to launch That 1 Painter full-time). Junk mail delivery in Australia pre-painting. Father was professional painter. Moved to Austin 2009. Wife Emily. • Allan Alarcon (Co-Founder, Garage Up): Pending verification • Carter Smith (Pink's Co-Founder): Baylor (led Baylor's largest mens service org, 170 members; $20K annual fundraise to Mission Waco) • Brandon Downer (Pink's Co-Founder): Finance background, pending verification • Codie Sanchez (Co-Owner since 2024): Wharton/finance pedigree. Notable thought leader (Contrarian Thinking). • 6 brands: That 1 Painter, GarageUp, Pink's Window Services, Varsity Exteriors, Action Exteriors, Monty's Handyman 🎯 BAYLOR CLUSTER: Carter Smith joins Baylor cluster 👉 See Signal Intel tab Master Education Table for sortable view
A8: 5 | B8: FIVE STAR FRANCHISING | C8: Princeton Equity Group | D8: P1 #5 · WEDGE-BRAND | E8: 5 | F8: 2350 | G8: $35K | H8: Scott Abbott CEO & Co-Founder | I8: Steve White CFO | J8: Chad Jones COO & Co-Founder | K8: Michael Moorhouse Brand President, Mosquito Shield | N8: Mosquito Shield brand wedge + CEO outreach | O8: Week 2 | Q8: Princeton Equity Year 5. EBITDA story lands immediately. Greenfield — no incumbent. | R8: Home Services Summit (HSS) · Jan 14–17 (just held — next ~Jan 2027, Las Vegas) | S8: ✅ Yes — vendor partners attend | T8: Preferred broker likely via Princeton Equity — validate FDD | U8: 🟡 Medium — Year 5 PE. CFO Steve White owns. | V8: SOURCE: Public FDD summaries — full FDD not yet pulled ITEM 11 — Technology: ProNexis named as 24/7 sales support system. No FSM platform mandated in publicly available analysis. ACTION: Pull California or Wisconsin FDD for Items 8 and 11 before scripting. KNOWN: Princeton Equity Year 5. CFO Steve White owns the numbers conversation. | W8: 📊 USE INSIGHT ENGINE → ROI Calculator tab PRE-POPULATE WITH: • Technicians: 2,350 • Avg Jobs/Tech/Day: 4 • Avg Revenue/Job: $300 • Working Days: 260 Princeton Equity Year 5 → exit window framing. Run 3-Way Scenario with 8x multiple for Steve White (CFO). Mosquito Shield wedge: seasonal route model, strong FSM fit. FieldRoutes conflict risk — verify Mosquito Shield before model. | X8: 59.2 🟡 ACTIVE | Y8: No current GPS Insight relationship Princeton Equity → Charles Layne path for PE intro Scott Abbott direct on LinkedIn — Five Star CEO accessible | Z8: 14/20 70 (mixed — FieldRoutes possible at Mosquito Shield) | AA8: 7/15 45 (2,350 techs) | AB8: 9/15 60 (Princeton Equity) | AC8: 11/15 75 (Mosquito Shield wedge to Five Star CEO Scott Abbott) | AD8: 9/15 60 (mid-term) | AE8: 5/10 50 (FieldRoutes possible) | AF8: 7/10 70 (consumer-led) | AG8: KEY LINKEDIN URLS (UPDATED v15.34): • Scott Abbott (CEO & Co-Founder): linkedin.com/in/dscottabbott BYU Marriott MBA 2005-07 + U Manitoba BS (Canadian) ⭐⭐ Spanish Fork UT. Princeton Equity Group portfolio (year 5). • Chad Jones (COO & Co-Founder): linkedin.com/in/chadrobertjones/ MacEwan U Edmonton Bachelor Commerce 1997-98 ⭐ Canadian Met Abbott age 11 LDS chapel Winnipeg. • Steve White (CFO): linkedin.com/in/steve-white-fivestar/ Pending school verification. • Dean Hartley (Five Star Bath Solutions + Five Star Flooring Brand Pres): LinkedIn: linkedin.com/in/dean-hartley-5ab12711/ University of Michigan BA + Oxford studies ⭐⭐ Multi-unit operator. Rochester MI. Scaled FSBS to 400 locations. • Michael Moorhouse (Mosquito Shield Brand Pres): LinkedIn: linkedin.com/in/michael-moorhouse-mosquito-shield/ Holyoke Community College ⭐ North Attleboro MA. • Stefan Figley (1-800-Packouts Brand Pres): LinkedIn: linkedin.com/in/stefanfigley/ Texas Christian University ⭐ CFE. Dallas-Fort Worth. • Ben Kramer (Bio-One Brand Pres NEW Aug 2025): LinkedIn: linkedin.com/in/benkramer-fivestar/ Case Western Reserve ⭐ Greenwood Village CO. Previously FRSTeam Pres at Empower (competitor poach). • Wanda Hoegren CFE (Gotcha Covered Brand Pres NEW July 2025): LinkedIn: linkedin.com/in/wanda-hoegren/ CFE. Restaurant industry origin. School pending. • William Thomas (Chief of Staff): close partner to Abbott. | AH8: ★ FSM / TECH / INSURANCE QUOTES — TECH-FLUENT CEO ★ CRITICAL CONTEXT: Scott Abbott CO-FOUNDED ProNexis (2012), a lead management technology platform. He sells tech to 60+ home service brands. He's not a tech buyer — he's a tech seller. Treat as PEER, not prospect. Five Star About page: "ProNexis was introduced to help home service brands grow quickly through ON-DEMAND TECHNOLOGY, proven growth solutions, and execution excellence." Scott Abbott (Fordify Live podcast): "From the franchisee-first approach to the INTEGRATION OF TECHNOLOGY in streamlining operations and enhancing customer service..." ProNexis on Mosquito Shield + 60+ brands = tech-friendly. Verified LinkedIn: linkedin.com/in/dscottabbott | AI8: Home Services Summit (HSS) 2027 ~Jan 2027, Las Vegas likely ~1,000 attendees, vendor partners attend ✅ Just missed Jan 2026 — target as exhibitor Pest control vertical events for Mosquito Shield FLDC Atlanta (Oct 2026) — Abbott likely attends 👉 See Event Intelligence tab for full schedule + opportunity analysis | AJ8: ENTRY: Princeton Equity Year 5 + Mosquito Shield brand wedge. HOOK: "Princeton Equity is in Year 5. Before exit, your EBITDA story needs to include operational leverage. ServiceBridge is that leverage." CHANNEL: 1. LinkedIn to Scott Abbott 2. Brand wedge via Michael Moorhouse (Mosquito Shield) 3. CFO Steve White on numbers 4. Verify FieldRoutes on Mosquito Shield first TIMING: Week 2 | AK8: FIVE STAR BRAND-LEVEL ROSTER: Bio-One: Ben Kramer (Brand Pres) (Note: Danessa Itaya was prior Bio-One pres — left for Maid Brigade Nov 2025) Card My Yard: Josh Arnold (Co-Founder & Brand Pres) + Amy Arnold (Co-Founder & CBO, Josh's wife) Jessica Stanley + James Stanley (Co-Founder couple) 559 franchisees in 46 states + Canada at acquisition Founded 2014 Austin TX, joined Five Star April 2024 Five Star Bath Solutions + Five Star Flooring: Dean Hartley (DUAL Brand Pres) Gotcha Covered: Wanda Hoegren (Brand Pres) Mosquito Shield: Michael Moorhouse (Brand Pres) 1-800-Packouts: Stefan Figley (Brand Pres) Tim Williamson CPC (NEW VP Operations) Five Star Corporate: • Scott Abbott (CEO & Co-Founder, also CO-FOUNDED ProNexis tech) — linkedin.com/in/dscottabbott • Chad Jones (COO & Co-Founder) • Steve White (CFO) • J. Andrew Mengason (CRO) • Matt Morrison (CLO) • Shane MacKay (CTO — drives unified tech across brands) • Ben Fox (CGO — leads ProNexis + Customer Experience) • Colt Florence (CDO) • Lucas Hatten (VP Franchise Dev Marketing) • Missy Wright (VP Franchise Dev) • Jacob Hanika (VP Franchise Dev) PE: Princeton Equity Group (Year 5 hold, 2021 invest) | AL8: 🥇 PRIMARY: Scott Abbott (CEO/Co-Founder, Springville UT). Princeton Equity partnered 2021 (5 yrs in). Active speaker at IFA, IFPG, ACG. Just acquired Five Star Flooring April 2026 ($75B industry). Chad Jones (Co-Founder/COO, painting roots). 🎯 STRONG: Dean Hartley (Five Star Bath Solutions Brand Pres, multi-unit operator origin, HSS 2026 "Brand President of Year," approaching 400 locations). ⚠️ COMPETITIVE FLAG: ProNexis (24/7 sales support tool) built in-house — NOT FSM. Gap: dispatch, routing, telematics. HSS at Caesars Palace Vegas (Jan 14-17 2026, ~1,000 attendees) = key event. 👉 See Signal Intel: Five Star section | AM8: 🎓 FIVE STAR EDUCATION CLUSTER (DEEP): • Scott Abbott (CEO/Co-Founder): BYU Marriott School MBA 2005-2007 (Marketing/Entrepreneurship) + University of Manitoba BS Mgmt ⭐⭐ Canadian + BYU. Spanish Fork UT. • Chad Jones (COO/Co-Founder): MacEwan University Bachelor of Commerce 1997-1998 ⭐ Canadian/Edmonton Alberta. Best friend of Abbott since age 11 (LDS chapel Winnipeg). Was running basement renovation company at 2003 wedding when Five Star Painting concept born. • Steve White (CFO): Pending verification • Andrew Mengason (Chief Growth Officer): Pending verification • Matt (Legal counsel): Pending verification BRAND PRESIDENTS: • Dean Hartley (Five Star Bath): Multi-unit operator origin, no degree confirmed. HSS 2026 Brand Pres of Year. • Michael Moorhouse (Mosquito Shield): Pending verification • Wanda Hoegren (Gotcha Covered): Pending verification • Stefan Figley (1-800-Packouts): Pending verification • Ben Kramer (Bio-One): Pending verification 🎯 BYU + EDMONTON-WINNIPEG-CANADIAN cluster (2 Canadian leaders + Manitoba/MacEwan tie) 👉 See Signal Intel tab Master Education Table for sortable view
A9: 6 | B9: PREMIUM SERVICE BRANDS | C9: Susquehanna Private Capital | D9: P1 #6 · GREENFIELD-OPEN | E9: 8 | F9: 4950 | G9: $74K | H9: Paul Flick Founder & CEO | I9: (VP Finance — name TBD) Per PSB org structure, finance leadership operates under VP Finance role LinkedIn: pending direct verification (search 'PSB Premium Service Brands VP Finance') PSB lean executive team — finance reports through CEO Paul Flick + COO Roxanne Conrad. Garrett Else (GPS Insight CFO) is the analog target from our side. | J9: Roxanne Conrad COO | K9: Gabe Colon EVP Performance | N9: RooterMan brand president outreach | O9: Week 2 | Q9: RooterMan brand president (name TBD) is 300-loc plumbing wedge into PSB portfolio. | R9: Annual Convention — research needed | S9: Unknown | T9: Validate via FDD Item 8/11 — Susquehanna PE backed | U9: 🟡 Medium — validate before outreach | V9: SOURCE: State registries — FDD not yet pulled ACTION: Pull Wisconsin or California FDD for Items 8, 11, 19 before outreach. KNOWN: RooterMan = 300 plumbing locations. PSB backed by Susquehanna Private Capital. | W9: 📊 USE INSIGHT ENGINE → ROI Calculator tab PRE-POPULATE WITH: • Technicians: 4,950 • Avg Jobs/Tech/Day: 4 • Avg Revenue/Job: $300 (painting/cleaning/plumbing mix) • Working Days: 260 RooterMan wedge: 300 locations, plumbing dispatch. Run Insight Engine at brand level first (RooterMan) → then scale to full PSB network for CFO conversation. | X9: 59.0 🟡 ACTIVE | Y9: Andrea Rowan (GM, ServiceBridge) — day-to-day contact Verify GPS Insight telematics customers in PSB network via Andrea Paul Flick direct path — no PE intro needed | Z9: 17/20 85 (RooterMan dominates — paper-based) | AA9: 8/15 50 (4,950 techs) | AB9: 6/15 40 (Susquehanna — less active) | AC9: 9/15 60 (Paul Flick CEO — verify warm path) | AD9: 8/15 50 (mid-term) | AE9: 7/10 70 (mostly greenfield) | AF9: 7/10 70 (consumer-led) | AG9: KEY LINKEDIN URLS (UPDATED v15.34): • Paul Flick (Founder & CEO): linkedin.com/in/paul-e-flick-0a15186 University of Windsor BA Political Science 1988-1991 ⭐ Canadian Charlottesville VA. Daughter Anne (Trisomy 18) → Kids Lift nonprofit. Forbes contributor. • Roxanne Conrad (COO): linkedin.com/in/roxanneconrad/ Pending school verification. • Gabe Colon (EVP Performance): linkedin.com/in/gabecolon/ Pending school verification. • David Raymond (PSB COO + ProLift VP Operations + Rubbish Works/ProLift dual-brand franchisee): LinkedIn: linkedin.com/in/davidraymond3/ Saint Leo University 2009-2011 + USMC Tank Crewman veteran ⭐ • Justin Penard (Grout Medic VP Franchise Dev): LinkedIn: linkedin.com/in/justinpenard/ Texas Tech University ⭐ Dallas. • Travis Nicolette MBA (NEW ProLift Brand Pres): MBA | AH9: ★ FSM / TECH FOUNDING THESIS ★ Paul Flick (Founder & CEO) — IdeaMensch interview: "The idea came from taking a fragmented industry that is CUSTOMER SERVICE DEFICIENT, TECHNOLOGY AND SOFTWARE DEFICIENT and making it a better customer experience." → This IS PSB's founding thesis. ServiceBridge sits in the exact gap he founded the company to fill. Flick (citybiz Q&A 2025): "Customers are looking for home service providers who can offer certainty and deliver on their promises. We provide that certainty through our CALL CENTER, TECHNOLOGY, and properly trained franchise partners." Flick (Forbes): "You can use the private equity funds to fuel growth, make TECHNOLOGY INVESTMENTS, or bolster marketing efforts." David Raymond (COO, Scaling Secrets podcast): "Leverage a single client acquisition across multiple brands. Bring in a customer for your painting platform, you can target that customer for garage doors, housekeeping, or another home service project." → Cross-brand customer thesis = exactly what ServiceBridge job-level data enables. | AI9: PSB Annual Convention 🔍 Date/location TBD - research needed Atlanta training session referenced (recurring) IFA Annual (Feb) Forbes Business Council events 👉 See Event Intelligence tab for full schedule + opportunity analysis | AJ9: ENTRY: RooterMan 300-location plumbing brand wedge. HOOK: "RooterMan is 300 locations of emergency plumbing dispatch — that's exactly what ServiceBridge was built for." CHANNEL: 1. Find RooterMan brand president name (TBD) 2. LinkedIn to brand president 3. Escalate to Paul Flick (CEO) with full PSB ROI model WHY FIT: David Raymond's cross-brand customer thesis = exactly the cross-brand data ServiceBridge enables. Flick's PE/tech investment quote signals openness. TIMING: Week 2-3 | AK9: PSB BRAND-LEVEL ROSTER: RooterMan: Carter Purves (Brand Leader) 360 Painting: Joel Gotshall (VP) — original PSB brand 2006 ProLift Garage Doors: David Raymond (VP Ops + ProLift VP + COO + personal franchisee) Kyle Christie (VP Franchise Dev ProLift + Rubbish Works) Maid Right: Ty Anderson (VP) Brad Knieriem (VP Franchise Dev Maid Right + Window Gang) Window Gang: Tim McCullen (Founder & Brand Pres — built 37 yrs, sold to PSB 2023) 229 locations across 1,600 towns in 15 states at sale Rubbish Works: David Raymond (personally franchisee) Kyle Christie (VP Franchise Dev) The Grout Medic: Justin Penard (VP Franchise Dev NEW Oct 2024) JC Timmons (former CEO, transition) House Doctors: Ann Lilly (Brand Lead) Jim Hunter (former CEO, acquired House Doctors 2012) Kitchen Wise / Closet Wise: brand leadership TBD ★ STAR FRANCHISEE — Jesús Barrios (Barrios Prestige Brands Denver) Multi-brand operator: Grout Medic + 360 Painting + Window Gang + Kitchen Wise + Maid Right Grout Medic Denver = 2024 PSB Franchisee of the Year Family business: Harold + Tania Barrios (parents, Venezuela immigrants 1982) Rachelle Barrios (wife, sole female owner Kitchen Wise + 360 Painting Denver) linkedin.com/in/jesusbarrios/ PSB Corporate: • Paul Flick (Founder & CEO) • Roxanne Conrad (COO — former 360 Painting franchisee) • Gabe Colon (EVP Performance — promoted 2024) • Bertie Allen (Marketing Director, joined 2024) • Dave Rychley (VP Brand Performance) • Samantha Lin (VP Marketing) • Courtney Spain (Director Marketing/Onboarding/VP Operations) • Tracey Felts (VP Insight Business Solutions) | AL9: 🥇 PRIMARY: Roxanne Conrad (COO 2024, FORMER 360 PAINTING FRANCHISEE = practitioner background, Top 50 Women COOs 2025). Direct line to Paul Flick. Quote: "Everything we did in 2025 was about developing durable businesses for our franchisees." Paul Flick (Founder/CEO, Charlottesville VA). Gabe Colon (EVP Performance, promoted 2024, revamped franchisee training). ⚠️ COMPETITIVE FLAG: Nesto = PSB's internal multi-brand operating platform (brand stacking). May overlap with FSM. Approach: position as complement OR target individual brand-level FSM gaps. 👉 See Signal Intel: PSB section | AM9: 🎓 PSB EDUCATION CLUSTER: • Paul Flick (Founder/CEO): University of Windsor BA Political Science 1988-1991 ⭐ Canadian. Coca-Cola Bottling Sales/Logistics post-grad. Charlottesville VA. Founded Kids Lift nonprofit (daughter Anne with Trisomy 18). • Roxanne Conrad (COO): Former 360 Painting franchisee = practitioner background, no degree confirmed BRAND PRESIDENTS: • Joel Gotshall (360 Painting): Pending verification • Carter Purves (RooterMan): Pending verification • David Raymond (ProLift Garage Doors / Rubbish Works): Pending verification • Ty Anderson (Maid Right): Pending verification NOTE: PSB leadership leans operator-experience over credentialed 👉 See Signal Intel tab Master Education Table for sortable view
A10: 7 | B10: HOMEFRONT BRANDS | C10: Dudan Group (Family Office) | D10: P1 #7 · MONITOR-MODE | E10: 5 | F10: 2550 | G10: $38K | H10: Jeff Dudan Chairman & CEO | I10: Mike Dudan CFO | J10: Michael O'Driscoll COO & President of Franchising | K10: Zack Dudan Chief Growth Officer | N10: CEO direct outreach + Window Hero brand wedge | O10: Week 2 | Q10: Jeff Dudan is a podcaster + Forbes contributor — accessible. Tyler Kirk (Window Hero) is wedge. | R10: Homecoming (4th annual) · ~Nov 2026, Orlando — STILL TIME TO GET IN | S10: ✅ Yes — vendor partners attend | T10: Likely individual franchisee insurance — young company, no group program confirmed | U10: 🟢 Low — Jeff Dudan family office, not institutional PE | V10: SOURCE: Public company info / franchisewire.com ITEM 11 — Technology: No FSM platform disclosed in any public FDD analysis. Homecoming 3 (Nov 2025) featured digital marketing speaker — no FSM announced. NOTE: Franchisee satisfaction issues flagged Dec 2025 (Unhappy Franchisee post). Verify system health before vendor commitment. APPROACH: Jeff Dudan directly via podcast/Forbes channel first. | W10: 📊 USE INSIGHT ENGINE → ROI Calculator tab PRE-POPULATE WITH: • Technicians: 2,550 • Avg Jobs/Tech/Day: 3 • Avg Revenue/Job: $400 (fence/exterior) • Working Days: 260 Jeff Dudan is founder-operated — run conservative scenario only. Focus on per-franchisee story, not PE exit math. ⚠️ Note franchisee satisfaction issues — position ServiceBridge as proof point for system health, not just efficiency. | X10: 44.0 ⚪ MONITOR | Y10: WARM-PATH STATUS (05/04/2026): Mike's active angles to existing leadership: • Jeff Dudan (Corporate): I will try and work an App State angle to introduce myself. • Tim McCullen (Window Gang (HomeFront-side)): checking but I believe I have a connection with Tim. Full alumni intel: see Alumni Crossover GPS Insight v19 + Signal Intel tab v19 update. Becky-Mike touch plan in development for warm-anchor outreach sequencing. | Z10: 16/20 80 (newer brands — paper-based) | AA10: 5/15 35 (2,550 techs — smaller) | AB10: 3/15 20 (Family office, no exit pressure) | AC10: 8/15 50 (Tyler Kirk Window Hero, Jeff/Zack Dudan corp) | AD10: 5/15 30 (Q3/Q4 2026 reassessment) | AE10: 6/10 60 (mostly greenfield) | AF10: 7/10 70 (consumer) | AG10: KEY LINKEDIN URLS (UPDATED v15.34): • Jeff Dudan (Chairman & CEO): linkedin.com/in/jeffdudan/ 🎯 Appalachian State + Yosef Club athletics ⭐ NC SCHOOL Forbes contributor + Podcast host. • Mike Dudan (CFO): linkedin.com/in/mike-dudan/ 🎯 App State 1992-96 + ex-CFO Carolina Panthers 2003-19 ⭐⭐ NC + NFL • Zack Dudan (Chief Growth Officer): linkedin.com/in/zackdudan/ 🎯 Elon University Love School BS Finance ⭐ NC SCHOOL • Michael O'Driscoll (COO & Pres of Franchising): linkedin.com/in/michaelodriscollfranchising/ Pending school verification. • Tyler Kirk (Window Hero Founder/CEO): linkedin.com/in/tylerkirk-windowhero/ 🎯 UNC Charlotte ⭐⭐⭐ NC SCHOOL — Mike's home market Hearing impaired (lost all hearing early 20s). College tennis player. • Tim McCullen (Window Gang Founder/Brand Pres): linkedin.com/in/tim-mccullen/ Operator path 37+ yrs. Taylorsville NC ⭐ NC connection. • Todd Bingham (Top Rail Fence Brand Pres): linkedin.com/in/todd-bingham-7a8b2210/ School pending verification. • Michael Wagner (Roof Scientist Brand Pres): linkedin.com/in/mike-wagner-rs/ School pending verification. | AH10: ★ FSM / TECH / AI QUOTES ★ Jeff Dudan (LinkedIn 2026): "Honored to be speaking at the upcoming International Franchise Association Annual Convention! I'll be presenting 'AI & HUMAN CO-WORKING: Real-Time...'" → He's literally giving the IFA keynote on AI + human ops. ServiceBridge is the operational substrate for that thesis. Muraena profile on Dudan: "As the CEO of HomeFront Brands, he focuses on providing INNOVATIVE TECHNOLOGY AND SUPPORT for franchisee success." Zack Dudan (CGO, FranchiseWire): "Everything from support to TECHNOLOGY to learning and development is geared to franchisee success." Jeff Dudan (LinkedIn 2025): "Most leaders treat reputation as branding. But REPUTATION IS OPERATIONAL. It's built through consistency — not campaigns." → Best icebreaker quote in the entire CRM. Direct match for ServiceBridge consistency-at-scale story. | AI10: Homecoming 4 ~Nov 2026 Orlando likely Hundreds of owners + vendor partners ✅ Jeff Dudan hosts personally 🟢 STILL TIME — contact NOW for vendor slot IFA Convention (Feb 2026 — attended) FranChoice Conference (recent) On The HomeFront Podcast — Mike could guest? 👉 See Event Intelligence tab for full schedule + opportunity analysis | AJ10: ENTRY: Content-first / Jeff Dudan podcast angle + Homecoming 4 vendor path. HOOK: "I've been following your Forbes work on franchise community-building. What you're describing operationally is exactly what ServiceBridge enables." CHANNEL: 1. LinkedIn to Jeff Dudan — content angle first 2. Reference his "reputation is operational" post 3. Reference Homecoming 4 vendor opportunity 4. Window Hero brand wedge via Tyler Kirk POSTURE: MONITOR-MODE per matrix v2. Q3/Q4 2026 reassessment. Build relationship, don't push close. TIMING: Week 2 | AK10: HOMEFRONT BRAND-LEVEL ROSTER: Window Hero: Tyler Kirk (Founder & CEO) David Blue (Co-Founder & DUAL Brand Pres — also Yard Patrol Pros) Brent Chapman (IFA Franchisee of Year 2024 - Window Hero Triad) Chad Taylor + Lilly Aranda (Rookies of Year Frisco TX) Yard Patrol Pros (formerly Mozzie Dome): David Blue (Co-Founder & Brand Pres — Univ of Wisconsin entomology grad) Top Rail Fence: Todd Bingham (Brand Pres) Bob Stewart (Top Producer Year Richmond) Sean Raftery (Rookie Year Denver) Jennie Davidson (Salesperson Year Nashville) Adam Hatley (Team Member Year) Temporary Wall Systems: Patrick Kiessling (Brand Pres) Ryan Lemire + Juli Lemire (Co-Founders) Jon Williamson (Franchisee Year North Georgia) Ryan Bufalini (Franchisee Year Detroit) Brendan Mahoney (Rookie Puget Sound) Tom Welsh (Team Member Year) The Designery: Casey Ridley (Co-Founder & President) Rebecca Merola (Top Producer Quakertown PA) Steven Moore (Rookie Greensboro NC) BiltRite Home Inspections: Bill Kilgannon (Brand Pres since 2018) Michael Munn (Founder 2006) Emily Munn (Business Coach Operations Manager — Michael's daughter) Roof Scientist: Michael Wagner (Brand Pres NEW Nov 2024) HomeFront Corporate: • Jeff Dudan (Chairman & CEO) — linkedin.com/in/jeffdudan/ • Mike Dudan (CFO) • Zack Dudan (CGO) • Michael O'Driscoll (COO + Pres of Franchising Sept 2023) • Carrie Beeman (CMO) • John Haraldson (CLO) • Tom Ryan Jr. (CDO July 2025 NEW) • Julie Moretz (Team Member Year corporate) PR: Ripley PR — Heather Ripley (865-977-1973) | AL10: 🥇 PRIMARY: Jeff Dudan (CEO/Chairman, Schaumburg HS, founded AdvantaClean 1994 → 240 locations sold to Home Franchise Concepts). Author "Discernment" book. Forbes contributor. Undercover Boss S8 (2017). CSP-certified. YPO Southern Sands chapter, IFA Franchisor Forum. Family-led: Zack Dudan (CGO, Jeff's son, info@homefrontbrands.com / 704-918-8578) + Mike Dudan (CFO). Annual "Homecoming" conference. C.A.R.E.S. culture (Community/Accountability/Respect/Excellence/Service). 👉 See Signal Intel: HomeFront section [v19 Alumni Intel · 05/04/2026]: 4 warm-path/status notes captured. See Col 25 for tactical detail and Signal Intel tab for full roll-up. | AM10: 🎓 HOMEFRONT BRANDS EDUCATION CLUSTER: 🎯🎯🎯 MAJOR NC SCHOOL CLUSTER (huge for Mike — Apex NC, NC State fan): • Jeff Dudan (CEO): Appalachian State University ⭐ NC SCHOOL — active in App State's Yosef Club (athletics fundraising board) • Mike Dudan (CFO): Appalachian State 1992-1996 + Schaumburg HS 1989 ⭐ NC SCHOOL - CFO Carolina Panthers 2003-2019! Then Deloitte Audit Mgr 2002-03, Arthur Andersen 1996-2002 • Zack Dudan (CGO, Jeff's son): Elon University Martha and Spencer Love School of Business ⭐ NC SCHOOL - BS Finance + Econ minor + Varsity Football. Hobbies: fishing, football, German Shorthair Pointer named Bear 🎯 PLUS Window Hero (HomeFront brand) founder Tyler Kirk: UNC Charlotte ⭐ 5th NC school connection. Born with hearing impairment, lost all hearing in early 20s. College tennis player. Huntersville NC = SAME town as Dudan Group HQ. BRAND PRESIDENTS: • Tyler Kirk (Window Hero Founder, Largest Franchisee): UNC Charlotte ⭐ • Keven Elwood (Window Hero Brand Pres post-acquisition): Pending verification • Todd Bingham (Top Rail Fence): Pending verification • Patrick Kiessling (Temporary Wall Systems): Pending verification • Casey Ridley (The Designery): Pending verification • Michael Wagner (Roof Scientist): Pending verification ⭐⭐⭐ ENTIRE HOMEFRONT LEADERSHIP IS NC-CONNECTED — major Carolinas warm-intro angle for Mike 👉 See Signal Intel tab Master Education Table for sortable view
B11: ═══ P2 FRANCHISORS · EXISTING FOOTPRINT ═══
A12: P2-1 | B12: BELFOR | C12: American Securities | D12: P2 · DE-FACTO ANCHOR | E12: 14 | F12: 9250 | G12: $260K+ | H12: Rusty Amarante, CR President, BFG | I12: Sheldon Yellen CEO, Holdings | J12: Dan Tarantin COO, BFG | K12: Doug Smith SVP Franchise Dev Beth Toenies VP Franchise Dev | N12: Deep profile + contact map | O12: Week 1 | P12: GPS: American Securities → Charles Layne → PE warm intro before outreach to Sheldon Yellen | Q12: ═ P2 · DE-FACTO ANCHOR ═ Year 6 hold — American Securities exit window 2026-2027. HOODZ + DUCTZ at 94% SB de facto. Convert de facto into mandate before exit. | Zero FSM mandate. 30 new territories Dec 2024. Start here. | R12: BELFOR Annual Conference · March (just held — next ~Mar 2027) | S12: Unknown | T12: Insurance carriers ARE the revenue channel for restoration brands. Claims Partnership Program launched Oct 2024. Carriers: Travelers, Allstate, State Farm, USAA. | U12: 🔴 HIGH — Carriers dispatch restoration brands. ServiceBridge job documentation = defensible claims record. Reframe pitch to Rusty as carrier relationship tool, not FSM. | V12: SOURCE: Publicly available FDD analysis (2024 FDD) + franchiseba.com ITEM 11 — Technology: 'Proprietary business management and job tracking tools' named. No third-party FSM disclosed. GREENFIELD confirmed. ITEM 19 — Unit Economics (2023 data, 94 franchisees, 157 locations): • Avg gross sales per location: ~$480K • Top 25% avg: $1,654,321 • Est. EBITDA at 15% margin: ~$72K/location • Avg invoice per job: ~$4,500 • Insurance carriers refer ~40% of jobs ROYALTY: 10% on first $499K → 7% above $2M + 2% Marketing Fund SERVICEBRIDGE EBITDA CASE: 5-pt margin improvement = $24K addl EBITDA/location. Across 178 locations = $4.3M system-wide EBITDA creation. | W12: 📊 USE INSIGHT ENGINE → ROI Calculator tab PRE-POPULATE WITH: • Technicians: 9,250 (network) | Per brand: see below • Avg Jobs/Tech/Day: 3 (restoration = emergency dispatch, lower frequency) • Avg Revenue/Job: $4,500 (FDD-sourced: avg 1-800 WD invoice 2024) • Working Days: 260 • Avg Tech Wage: $28/hr FSM UPLIFT (conservative for greenfield): • Additional Jobs: 0.3/tech/day • Admin Saved: 1.0 hr/tech/day • Invoice Cycle Reduction: 5 days (critical for insurance payment lag) TELEMATICS (GPS Insight warm flag): • Fuel Savings: $1,800/vehicle/yr • Insurance Reduction: 8% 3-WAY SCENARIO OUTPUTS (base case, 1-800 WD 178 locations): • FDD Item 19: $480K avg/location • 5-pt margin improvement = $24K EBITDA/location • 178 locations × $24K = $4.3M system EBITDA creation • At 8x exit multiple = $34.4M enterprise value uplift ⚠️ USE THE TOP-25% NUMBER ($1.65M) for STRETCH scenario with Rusty | X12: P2 SET 🟡 EXISTING FOOTPRINT | Y12: WARM-PATH STATUS (05/04/2026): Mike's active angles to existing leadership: • Aaron Rich (BluSky): Lives in Cary, NC . I will try and work an angle to get to Arron. ⚠️ STATUS CHANGES TO VERIFY: • Doug Smith (Corporate): Looks like Doug may have just left belfor Full alumni intel: see Alumni Crossover GPS Insight v19 + Signal Intel tab v19 update. Becky-Mike touch plan in development for warm-anchor outreach sequencing. | Z12: 25/25 Greenfield — no FSM mandate found | AA12: 15/20 9,250 techs — large network | AB12: 15/20 American Securities — active PE, EBITDA expansion thesis | AC12: 15/15 Full FDD analysis loaded — unit economics confirmed | AD12: 10/10 Charles Layne direct — highest access level | AE12: 5/5 GPS Insight relationship confirmed | AF12: 5/5 14 brands — multiple pilot targets within network | AG12: KEY LINKEDIN URLS (UPDATED v15.34): • Sheldon Yellen (CEO BELFOR Holdings $3B): linkedin.com/in/sheldon-yellen-belfor/ ⭐⭐ Southfield-Lathrup HS DROPOUT (got HS diploma at age 53!) Honorary Doctorate Oakland U 2019. Detroit welfare childhood. Started age 11 dishwashing Leo's Coney Island. Joined BELFOR 1984 as 19th employee. • Rusty Amarante CR (Pres BELFOR FG + Director Ops Property Restoration): LinkedIn: linkedin.com/in/rusty-amarante/ 40+ yrs. Past-Pres RIA. Vice Chair IICRC S500. • Doug Smith (SVP Franchise Dev): linkedin.com/in/dougsmith-belfor/ University of Louisville Business ⭐ ← MIKE'S WARM PATH • Beth Toenies (VP Franchise Dev + COO 1-800-BOARDUP): linkedin.com/in/bethtoenies/ Asbury University '06 (Journalism, varsity tennis, honors) ⭐ Navy military spouse. Jacksonville FL. • Tim Fagan (President 1-800 WD + Blue Kangaroo): linkedin.com/in/timfagan-belfor/ UMich BS Education + EMU post-grad ⭐ RIA CR + WLS • Matt O'Rourke (Z Plumberz Founder/Brand Pres): linkedin.com/in/matthew-o-rourke-a835459/ Oakland University ⭐ Ann Arbor MI. Licensed Master Plumber. • Aaron Rich (BluSky CIO 2022): Purdue Computer Science ⭐ FSM-relevant • Mark Minasian (BluSky CEO Sept 2025): U San Diego BA Intl Relations ⭐ • Chris Jones (CFO Holdings): 24+ yrs. | AH12: ★ INSURANCE / RELATIONSHIP-FIRST QUOTES ★ BELFOR's culture is RELATIONSHIP-DRIVEN, not tech-forward. Public commentary from Yellen / Smith / Toenies / Amarante is people-first, not FSM-tech focused. Sheldon Yellen (Wikipedia / sheldonyellen.com): Famous for writing 9,200+ HANDWRITTEN BIRTHDAY CARDS annually to every employee. "They may feel old-fashioned in a world of dashboards and data, but for CEOs they remain one of the most powerful tools for building trust." → NOT a tech-quote-driven CEO. AVOID dashboards-and-data framing in any outreach. BELFOR Property Restoration is THE INSURANCE-CARRIER RELATIONSHIP for restoration. Doug Smith (SVP Franchise Dev) and 1-800-WD operate inside that carrier ecosystem. STRATEGIC ANGLE: Pitch is NOT FSM dashboards. Pitch is: "Every 1-800 WD job that isn't documented at the point of service costs you a carrier referral. Yellen wrote 9,200 birthday cards. Every job needs that same handwritten-care feel — but documented for insurance audit." American Securities (PE owner) responds to EBITDA + carrier-relationship stories, not tech features. | AI12: BELFOR Annual Conference March 2026 (just held — missed) ~March 2027 next Per-brand awards (HOODZ Triangle, Z Plumberz) Use HOODZ + Z Plumberz award winners as warm icebreakers Doug Smith / Rusty Amarante attend 👉 See Event Intelligence tab for full schedule + opportunity analysis | AJ12: ENTRY: Insurance carrier relationship reframe — NOT FSM pitch. HOOK: "Every 1-800 WD job that isn't documented costs you a carrier referral. We fix that at the point of service." CHANNEL: 1. Charles → American Securities PE intro 2. LinkedIn to Rusty (parallel) 3. HOODZ Triangle local angle 4. Email with Insight Engine 3-Way Scenario WHY FIT: HOODZ + DUCTZ already at 94% SB organically. Convert de facto to mandate. American Securities loves EBITDA improvement stories. TIMING: Week 1-2 | AK12: BELFOR BRAND-LEVEL EXPANSION: 1-800 Water Damage: Tim Fagan (Pres) 1-800-BOARDUP: Beth Toenies (COO + VP Franchise Dev BFG) Blue Kangaroo Packoutz: Tim Fagan (Pres — dual role) Chem-Dry: D'Wayne Tanner (SVP Franchise Dev), Dre Carter (Dir Franchise Dev) DUCTZ: Jessica Wicks (Brand Pres — first female brand pres at BFG) HOODZ: Mike Mendez N-Hance: Bob DeGraff (Brand Pres Feb 2024, former NY franchisee) The Patch Boys: Leo Goldberger (Founder & CEO, founded 2006) redbox+ Dumpsters: Sean Foley (Brand Pres) Patrick Kiessling (departed to TWS) Josh Skolnick (exited as CEO at acquisition) Larry Oglesby (Athens GA franchisee, podcast voice) Z PLUMBERZ: Matt O'Rourke (Founder + Brand Pres) Safer Home Services: Jim Swayne (Founder) Chuck Steinmetz (Chairman, PMP Hall of Famer 2017) BELFOR Corporate: • Sheldon Yellen (CEO BELFOR Holdings, $2B conglomerate) • Rusty Amarante CR (Pres BFG + DOO BPR — 40+ yrs restoration, past Pres RIA, IICRC S500 Vice Chair) • Doug Smith (SVP Franchise Dev — MIKE'S WARM PATH) • Beth Toenies (VP Franchise Dev) • Dan Tarantin DEPARTED PE: American Securities PR: Ripley PR — Heather Ripley (865-977-1973) | AL12: 🥇🥇 #1 P1 TARGET (American Securities PE, 9,250 techs, ZERO FSM). Doug Smith (CEO, replaced Dan Tarantin who departed). 🎯 STRONG SIGNAL: Beth Toenies (VP FD, Asbury University '06, promoted Sept 9 2025, oversees 1-800-BOARDUP, 1-800 WATER DAMAGE, Blue Kangaroo Packoutz, DUCTZ). Direct Nov 2025 quote: "BELFOR's emphasis on using SMARTER TOOLS, BUILDING SHARED SERVICES PROGRAMS." 2025 Stevie Bronze. 2025 Woman of Inspiration. Navy military spouse, Jacksonville FL. 🔗 WARM-INTRO PATH: Josh Skolnick (HorsePower Chair) sold Redbox+ to BELFOR June 2021 = direct relationship to BELFOR leadership. 👉 See Signal Intel: BELFOR section [v19 Alumni Intel · 05/04/2026]: 6 warm-path/status notes captured. See Col 25 for tactical detail and Signal Intel tab for full roll-up. | AM12: 🎓 BELFOR EDUCATION CLUSTER (CORRECTED hierarchy + DEEP): TOP LEADERSHIP: • Sheldon Yellen (CEO BELFOR Holdings $3B since 2001): Southfield-Lathrup HS DROPOUT (got diploma at age 53!). Detroit MI welfare childhood. Started age 11 as dishwasher Leo's Coney Island Diner. Joined BELFOR (then Inrecon) 1984 as 19th employee. Hurricane Hugo 1989 = $17M sales. Honorary Doctorate Oakland University 2019. CSR/ESG Pro of Year 2022. Featured Undercover Boss 2011. ⭐⭐ Compelling self-made operator story. • Chris Jones (CFO BELFOR Holdings): 24+ yrs Financial Mgmt, M&A, Tax. Pending school. • Rusty Amarante (President BELFOR FG + Director of Operations BELFOR Property Restoration): 40+ yrs restoration. Past-Pres RIA. Vice Chair IICRC S500 Standard. FRANCHISE GROUP LEADERSHIP: • Doug Smith (SVP Franchise Development): U. of Louisville Business connection (FranchiseU! Episode 82 podcast 2024). 14 yrs SVP Sales Affinion Group → SVP Harris Research → BELFOR FG. • Beth Toenies (VP FD): Asbury University '06 (Journalism, varsity tennis, honors). Navy military spouse, Jacksonville FL. ⭐ STRONG SIGNAL. • Kevin "Tim" Fagan (Pres 1-800 Water Damage + Blue Kangaroo Packoutz since 2018-19): University of Michigan BS Education + Eastern Michigan University post-grad in educational leadership ⭐. RIA Certified Restorer (CR) + Water Loss Specialist (WLS). Principal instructor for BELFOR continuing education courses for insurance agents. • Jessica Wicks (DUCTZ): Pending verification • Matt O'Rourke (Z Plumberz): Pending verification 👉 See Signal Intel tab Master Education Table for sortable view
A13: P2-2 | B13: EVIVE BRANDS | C13: The Riverside Company ($13B+ AUM) | D13: P2 · GROWING ANCHOR | E13: 7 | F13: 1100 | G13: $30K-50K (estimated) | H13: Ryan Parsons CEO, Evive Brands Known-friendly to Mike — warm path | I13: (CFO TBD — Evive Brands lean exec team) Joe Lee = Senior Partner at The Riverside Company (PE backer) LinkedIn (Joe Lee Riverside): linkedin.com/in/joe-lee-riverside/ Riverside provides finance support. Evive adding executives — recent hire VP Marketing Chelle Watson. | J13: (COO TBD — Evive Brands lean exec team) Per Ryan Parsons interview: "I'm making the effort to hire key executives to Evive to oversee these plans" — recent hires include first VP Marketing Chelle Watson + more in pipeline. Brad Stevenson (Brothers that just do Gutters operations leadership, pre-Evive transition). | K13: (BD/Sales — distributed across brand level, no central CGO) Per Evive structure: each brand has own development leader. Chelle Watson (NEW VP Marketing): newest senior addition. | L13: P2 — RESEARCH | N13: Profile + Brothers Gutters anchor leverage | P13: GPS: Riverside PE → Charles Layne. Andrea direct on Brothers Gutters. | Q13: ═ P2 · GROWING ANCHOR ═ Year 3 hold — Riverside-owned (formed 2023). Brothers Gutters at 43% SB under new contract. Maid Brigade (2024 acquisition) greenfield within Evive. Ryan Parsons = warmest P2 relationship. Same parent as Threshold (Riverside) — coordinate engagement. | X13: P2 SET 🟢 EXISTING FOOTPRINT — GROWING | AG13: KEY LINKEDIN URLS (UPDATED v15.34): • Ryan Parsons (CEO since May 2024): linkedin.com/in/brothersgutters/ ⭐ SUNY New Paltz BFA Graphics & Fine Art 1996-2000 Lagrangeville NY. Started in graphic design → VP startup → joined brother Ken in 2002 to launch The Brothers that just do Gutters. ★ KNOWN-FRIENDLY TO MIKE — warm intro path confirmed. • Ken Parsons (Co-founder Brothers + Evive board): linkedin.com/in/kenparsons-gwtb/ ⭐ "Self-Education University" — operator path. Lagrangeville NY. • Chelle Watson (VP Marketing - newest hire): linkedin.com/in/chelle-watson/ Pending school verification. • Joe Lee (Riverside Co Senior Partner / PE backer): linkedin.com/in/joe-lee-riverside/ • Juliet Diiorio (LEFT Threshold for Senior Helpers - was helpful pre-2026 transition reference): linkedin.com/in/julietdiiorio/ PORTFOLIO BRAND LEADERS: • Brothers That Just Do Gutters: Ryan + Ken Parsons (founders) • Executive Home Care: Kevin (CEO featured in Evive social posts) — pending last name • Assisted Living Locators: Angela (founder) — pending last name; "150+ franchises" • Grasons Estate Sales: Christian Campbell (founder + EHC franchisee path) | AH13: ★ TECH UNIFICATION / FSM QUOTES — STRONGEST P2 SIGNAL ★ Ryan Parsons (CEO) — Franchise Times May 2024 (his first month as CEO): "WE'RE TRYING TO UNIFY THE TECH STACK ACROSS ALL BRANDS where it makes sense. Silly things, like one is using Google and needs to go to Google Enterprise and one's using Microsoft, so HOW DO WE GET ALL THIS TECH CONSOLIDATED?" "DATA CONSOLIDATION is also in the works, especially to help marketing efforts as Evive continues to grow." → Publicly committed to tech unification across portfolio. ServiceBridge is the next layer in his stack. Parsons (IFA Article Jan 2026): "BY LEVERAGING TECHNOLOGY, structuring onboarding in phases, and providing ongoing coaching, we ensure that franchisees across our brands have the best possible foundation for long-term success." "We TRACK EVERY STEP OF ONBOARDING USING MONDAY.COM, an automation tool that ensures no detail is overlooked." → He uses monday.com for ops tracking. Already has tech muscle memory at the platform level. Parsons (Authority Magazine): "If you want to be promotable, you need to be replaceable." | AI13: Evive Brands Annual Summit 🔍 Date/location TBD - research needed Ryan Parsons hosts Riverside Company portfolio events Brothers Gutters National Conference (Hilton Head, ~annual) IFA Annual (Feb) 👉 See Event Intelligence tab for full schedule + opportunity analysis | AJ13: ENTRY: Brothers Gutters momentum + Maid Brigade as second wedge. HOOK: "Brothers Gutters is at 43% under our new contract. Same story works for Maid Brigade — fresh into Evive, hasn't standardized FSM yet." CHANNEL: 1. Ryan Parsons direct (warm relationship) 2. Maid Brigade brand pres referral via Parsons 3. Riverside operating partner via GPSI/Garrett 4. Brand-level rollout for 5 remaining brands WHY FIT: Parsons quote on "being replaceable" + niche focus = aligned with platform standardization story. TIMING: Week 1-2 | AK13: EVIVE BRAND-LEVEL EXPANSION (UPDATED v15.34): Riverside Company portfolio. ~600 locations across 4 brands. Brothers That Just Do Gutters (FLAGSHIP): • Ryan Parsons (Co-founder, now CEO Evive) • Ken Parsons (Co-founder, Evive Board) • 400+ territories nationwide. • Founded 1999 as Waterfall Seamless Gutters → rebranded 2009. • 2007 nearly lost everything in recession — "the riches are in the niches" lesson. Executive Home Care: • Kevin (CEO) — driving in-home care leadership. • Featured in Evive media re: data-driven approaches. Assisted Living Locators: • Angela (founder) — Senior placement and referral. • 150+ franchises nationwide. • "Combining healthcare insight with compassionate service." • Reached 150th franchise milestone (Southwest Metro location). Grasons Co.: • Estate sales + business liquidation. • Recent: 50th franchise milestone. • Christian Campbell example: started as EHC Franchisee → now owns Grasons. Shine (5th brand — Brand Operations & Events Director Michelle Fisher): • Founded by Chris and Michelle Fisher inspired by their time in Uganda. • 2015 launched Arrows & Hope ministry (orphan education in Uganda). • Portion of every new franchise sale funds the ministry. 🎯 CONTACT: r***@evivebrands.com via RocketReach 🎯 WARM PATH: Mike has known-friendly relationship with Ryan Parsons. | AL13: Limited deep-research signal captured this round. Riverside Company-backed ($13B+ AUM). Worth dedicated research wave for full signal map. 👉 See Signal Intel tab structure for research template | AM13: 🎓 EVIVE BRANDS EDUCATION: • Ryan Parsons (CEO): Pending verification Limited research captured. Targeted research wave needed. 👉 See Signal Intel for company structure 👉 See Signal Intel tab Master Education Table for sortable view
A14: P2-3 | B14: THRESHOLD BRANDS | C14: Riverside Company | D14: P2 · AT-RISK ANCHOR | E14: 10 | F14: 6250 | G14: $94K | H14: Ted DeMarino CEO since 2024 (replaced Hagan Kappler who LEFT for Daisy) LinkedIn: linkedin.com/in/teddemarino Pending school verification. Riverside-backed Threshold Brands. ~10 brands, 500 owners, 900+ locations per Juliet Diiorio's farewell post. Ted active on LinkedIn — recent posts about USA Insulation hiring + Christmas message to franchisees. | I14: Scott Fink / Brandon Brown CFO ⚠️ VERIFY | J14: Andrea Hohermuth COO | K14: Scott Sutton Chief Growth Officer | N14: Profile + contacts map | O14: Week 1 | P14: GPS: Riverside PE → Charles Layne. ⚠️ Verify Hagan Kappler still CEO (Daisy link 2025) | Q14: ═ P2 · AT-RISK ANCHOR ═ Year 6+ hold — Riverside-owned. USA Insulation transitioning OFF SB (75% → 0% over next year). Ted DeMarino CEO + Billy Newby CFO new. Defensive posture: defend if reversible, reset relationship at brand-corp level. Same parent as Evive. | Promised franchisees proprietary software — undelivered. ServiceBridge closes that gap. | R14: Annual Convention · Date/location TBD — research needed | S14: Unknown | T14: Preferred broker via Riverside PE (likely) — validate FDD Item 8/11 | U14: 🟡 Medium — PE-backed with structured program. CFO contact. | V14: SOURCE: Public FDD summaries / state registries ITEM 11 — Technology: Promised 'proprietary technology' to franchisees — undelivered per franchisee feedback (Glassdoor, FDD analysis). ITEM 19 — Unit Economics: Not publicly detailed in FDD analysis. Validate via Wisconsin/California FDD registry. KEY ANGLE: Unfulfilled tech promise = ServiceBridge delivers what Threshold told franchisees they'd get. | W14: 📊 USE INSIGHT ENGINE → ROI Calculator tab PRE-POPULATE WITH: • Technicians: 6,250 (network total) • Avg Jobs/Tech/Day: 4 • Avg Revenue/Job: $250 (cleaning/pest model) • Working Days: 260 KEY ANGLE FOR THRESHOLD: Unfulfilled tech promise = franchisees already expect this. Position ServiceBridge as delivering what Threshold promised. Run 3-Way Scenario showing EBITDA uplift before Riverside PE exit. | X14: P2 SET 🔴 EXISTING FOOTPRINT — AT-RISK | Y14: WARM-PATH STATUS (05/04/2026): Mike's active angles to existing leadership: 👥 TEAM ASSIGNMENTS: • Bryan McMurray (Granite Garage Floors): Charles: Typical ASU grad starting at Massage Envy Full alumni intel: see Alumni Crossover GPS Insight v19 + Signal Intel tab v19 update. Becky-Mike touch plan in development for warm-anchor outreach sequencing. | Z14: 10/25 FSM status unconfirmed — action needed | AA14: 15/20 6,250 techs — large network | AB14: 18/20 Riverside Company — Year 4, approaching exit window | AC14: 15/15 Full FDD analysis loaded — unit economics confirmed | AD14: 10/10 Charles Layne direct — highest access level | AE14: 5/5 GPS Insight relationship confirmed | AF14: 5/5 10 brands — multiple pilot targets within network | AG14: KEY LINKEDIN URLS (UPDATED v15.34): • Ted DeMarino (CEO since 2024): linkedin.com/in/teddemarino Replaced Hagan Kappler (left for Daisy). Pending school verification. • Hagan Kappler (FORMER CEO 2020-2024 — NOW Daisy CEO): LinkedIn: linkedin.com/in/hagan-kappler-7b41194/ Williams BA + UVA Darden MBA ⭐⭐ Goldman Sachs Most Exceptional Entrepreneurs 2025. • Andrea Hohermuth (COO): linkedin.com/in/andrea-hohermuth/ Pending school verification. • R. Scott Sutton (former Threshold Chief Growth Officer — LEFT 2022 for Empower CDO): LinkedIn: linkedin.com/in/rscottsuttoncfe/ U Oklahoma BA. CFE + CMAA ⭐ • Ryan Carpenter (Plumbing Paramedics + Heating + Air Paramedics Founder): LinkedIn: linkedin.com/in/ryan-carpenter-25/ Calgary-based founder, operator path. • Patrick Kiessling (Temporary Wall Systems): linkedin.com/in/pkiessling/ Operator path. Bought TWS franchise rights from founder Tom Schwager 2018. • Casey Ridley (The Designery Co-Founder): linkedin.com/in/casey-ridley-39a27914/ • Bryan Shamhart A.C.E. (Pestmaster Brand Pres NEW Nov 2025): LinkedIn: linkedin.com/in/bryan-shamhart-78938b16/ Ex-Orkin 15+ yrs. North Olmsted OH. • Rachel Southard (Men in Kilts Brand Pres): linkedin.com/in/rachel-southard/ Founder of 'She Dreams' women's empowerment platform. • Bryan McMurray (Granite Garage Floors Brand Pres): linkedin.com/in/bryan-mcmurray-72a40418/ • Ann Lilly (House Doctors Brand Lead): linkedin.com/in/ann-lilly-b15810a/ • Mark Kushinsky (MaidPro Founder): linkedin.com/in/markkushinsky/ Arizona State University ⭐ • Richard Sparacio (MaidPro Co-Founder): Suffolk University (left senior year) | AH14: ★ TECH / OPS / ABSENCE-OF-LEADERSHIP SIGNALS ★ 🚨 CRITICAL FINDING: Per The Org, the Threshold "Brand Leader / President - USA Insulation" position is currently VACANT and being hired for. This explains why USA Insulation transition off SB is happening — there's NO BRAND LEADER making decisions. → Either reach DeMarino directly OR wait for new USA Insulation president to be named, then immediately re-pitch. Ted DeMarino (CEO since 2024) — bio: "Key projects under Ted's guidance include the launch of new service offerings and the IMPLEMENTATION OF CUTTING-EDGE TRAINING PROGRAMS designed to empower franchise owners and their teams. By prioritizing CUSTOMER SATISFACTION AND OPERATIONAL EFFICIENCY..." DeMarino background: Liberty Tax (5 → 2,700 offices), Rent-A-Center EVP roles. He scaled retail/finance ops, NOT franchise FSM. Will need education on field service category. John Tubiolo (Miracle Method Brand Leader since Apr 2024) — operationally knowledgeable retained leader. Tim Swackhammer (Mold Medics Founder, retained 2023). Multiple 2025 leadership departures: Kappler, Scott, Pitrone, Diiorio. PLATFORM IN FULL RESET. | AI14: Threshold Annual Convention 🔍 Date/location TBD - research needed Confirmed exists per LinkedIn references Riverside Company portfolio events (coordinate with Evive) FLDC Atlanta (Oct 2026) — DeMarino likely C-suite 👉 See Event Intelligence tab for full schedule + opportunity analysis | AJ14: ENTRY: Unfulfilled tech promise to franchisees. HOOK: "Your franchisees were promised a tech platform. We're the ones who can actually deliver it." CHANNEL: 1. Verify USA Insulation transition driver via Andrea 2. LinkedIn to Ted DeMarino (CEO reset) 3. Riverside intro via Charles (parallel) 4. Coordinate Evive + Threshold platform conversation DUAL POSTURE: (1) Defend USA Insulation (75% SB, transitioning off) (2) Reset relationship at new top for remaining 9 brands WHY URGENT: New leadership <1yr in role + multiple departures = either intervene now or lose the platform. TIMING: Week 2 | AK14: THRESHOLD BRAND-LEVEL ROSTER (UPDATED): MaidPro: Emily Estes (Brand Pres) USA Insulation: 🚨 BRAND PRES VACANT — actively hiring Pat Pitrone (former group pres, son of founder, departed) Michael Kegley (recent franchisee per Carpenter LinkedIn) Granite Garage Floors: Bryan McMurray (Brand Pres) Alan Mishkoff + Kelly Mishkoff (Founders 2009) Kayla Cina (former GGF Brand Leader 2022) Pestmaster Services: Bryan Shamhart A.C.E. (Brand Pres NEW Nov 3, 2025) Brett Shraiar (prior pres), Kieran Scott (former 2022) Melanie Perez (Marketing Manager 2026 hire) FlyFoe → PATIO PATROL rebrand (per Kappler 2023) Sir Grout: Jeff Gill + Tom Lindberg (Founders, 2021 sale) Men In Kilts: Rachel Southard (Brand Pres since June 2021 — millennial woman, founded 'She Dreams') Nicholas Brand (Founder Vancouver Scotsman, founded 2002, also MaidPro franchisee) Chris Carrier + Robyn Carrier (former CEO + Calgary co-owner) Brad Williams (franchisee feature) Plumbing Paramedics + Heating + Air Paramedics: Ryan Carpenter (DUAL Founder & Pres) Founded 2011 Indianapolis, joined Threshold Nov 2021 Brian Sauer (Riverside Partner — invested) Chris Jensen (Noblesville IN Mayor — local government tie) Miracle Method: John Tubiolo (Brand Leader since Apr 2024) Mold Medics: Tim Swackhammer (Founder, retained 2023) Threshold Corporate: • Ted DeMarino (CEO since 2024) • Billy Newby (CFO) • Cory Hughes (COO, linkedin.com/in/corymhughes/) • R. Scott Sutton (CGO) • Brandon Brown (Threshold corp, per LinkedIn) Riverside (PE backer): Loren Schlachet, Joe Lee, Brian Sauer | AL14: 🥇 PRIMARY: Hagan Kappler (CEO since early 2022). Previously led Merry Maids + ServiceMaster Clean (sold to Roark Capital 2020). 84 new franchise agreements year 1. Featured Franchise Times "Uses Data, Founder DNA" (Nov 2022). Boston-based. 🔗 PE NOTE: Riverside Company was previous backer of Neighborly/Dwyer Group → potential cross-PE warm-intro. 🎯 CROSS-PORTFOLIO SIGNAL: Danessa Itaya joined Maid Brigade (separate co) Nov 2025 from Bio-One (Five Star). Led "system modernization, CRM implementation, national account expansion" at Bio-One. Atlanta. 25+ yrs franchising. 👉 See Signal Intel: Threshold section [v19 Alumni Intel · 05/04/2026]: 1 warm-path/status notes captured. See Col 25 for tactical detail and Signal Intel tab for full roll-up. | AM14: 🎓 THRESHOLD BRANDS EDUCATION CLUSTER: ⚠️ CRITICAL UPDATE: Hagan Kappler LEFT Threshold to found DAISY in 2024 — she is NOT current Threshold CEO. R. Scott Sutton (CGO) ALSO LEFT in Dec 2022 to Empower Brands. LEGACY/FORMER LEADERSHIP: • Hagan Kappler (former CEO 2021-2023, NOW DAISY CEO): Williams College BA History (track athlete) + UVA Darden MBA 2005-2007. Career: Goldman Sachs → McKinsey → Starbucks (Blonde Roast) → Ingersoll Rand head of M&A → ServiceMaster Clean/Merry Maids → Threshold → DAISY. Newport Beach CA, 4 kids. Goldman Sachs Most Exceptional Entrepreneurs 2025. • R. Scott Sutton (former CGO 2021-2022, NOW Empower CDO): University of Oklahoma BA. CFE + CMAA. CURRENT LEADERSHIP: • Current Threshold CEO: ❓ CONFIRMED VACANT/UNCLEAR after Kappler departure. Possibly absorbed into Riverside Co management or has interim. Need direct PE Riverside Co outreach to confirm. BRAND PRESIDENTS: • Emily Estes (MaidPro Brand President): Pending verification • Bryan Shamhart A.C.E. (Pestmaster Brand Pres Nov 2025, after Brett Shraiar): Ex-Orkin Operations Manager 15+ yrs. Then Pestmaster franchisee Cleveland OH. North Olmsted OH. A.C.E. (Associate Certified Entomologist) certification. Education pending. • Bryan McMurray (Granite Garage Floors): Pending verification • Rachel Southard (Men in Kilts): Pending verification LEGACY FOUNDERS still in network: • Mark Kushinsky (MaidPro Founder): Pending • Jeff van Diepen (Pestmaster Founder, predecessor to Shraiar): Pending • Pat Pitrone (USA Insulation, family-founded): Pending — was elevated to Group President per 2022 Franchise Times article 🎯 UVA DARDEN CLUSTER: Kappler joins Mayer (Empower) — 2 Darden alums (both 2005-2007 era) 👉 See Signal Intel tab Master Education Table for sortable view

Sheet Track 2 · Franchisees
A1: 85 PRIORITY FRANCHISEE BRANDS · Track 2 · Greenfield Volume Pipeline
A2: Velocity GTM Co LLC · Sorted by parent franchisor · GPS Insight warm accounts prioritized · v15.6 — validated April 29, 2026
A3: # | B3: BRAND / FRANCHISEE | C3: PARENT FRANCHISOR | D3: TRADE | E3: LOCATIONS | F3: TECHS (EST.) | G3: FSM STATUS | H3: GPS WARM? | I3: PILOT POTENTIAL | J3: CURRENT FSM PLATFORM | K3: CONFLICT RISK | L3: TELEMATICS PROVIDER | M3: GPS INSIGHT CUSTOMER? ← Andrea to Verify | N3: INSURANCE PROGRAM / CARRIER | O3: INSURANCE GTM ANGLE | P3: PRIMARY CONTACT | Q3: CONTACT TITLE | R3: OWNER / DECISION MAKER | S3: OPS MGR / OFFICE MANAGER | T3: GPS INSIGHT ACCOUNT REP ← Warm intro path | U3: OUTREACH STATUS | V3: LAST CONTACT | W3: NEXT STEP | X3: NEXT DATE | Y3: NOTES | Z3: FDD INTEL (Source + Key Facts) | AA3: INSIGHT ENGINE NOTES ← ROI angle for outreach | AE3: FRANCHISEE SCORE / 100 | AF3: FRANCHISOR BONUS + 0/5/15/25 | AG3: COMBINED SCORE / 125 | AH3: BRAND PRESIDENT + LINKEDIN URL | AI3: PRESIDENT EMAIL | AJ3: CFO + LINKEDIN URL + EMAIL | AK3: BIZ DEV + LINKEDIN URL + EMAIL | AL3: RECENT FSM / TECH / INSURANCE COMMENTS | AM3: BRAND-LEVEL ENGAGEMENT NOTES | AN3: ADDITIONAL CONTACTS + CORPORATE/PARENT TEAM | AO3: SIGNAL INTEL (compressed · see Signal Intel tab for full) | AP3: EVENTS (compressed · see Event Intelligence tab for full) | AQ3: EDUCATION (College / University / Trade School)
A4: 1 | B4: Aire Serv | C4: Neighborly | D4: HVAC | E4: 500 | F4: 5 | G4: Partial/ST | H4: TBD | I4: MED | J4: ServiceTitan | K4: 🔴 High | L4: Smart Fleet USA | M4: No — Smart Fleet USA | N4: ProTradeNet preferred broker — validate FDD | O4: 🟡 Medium | P4: (Franchisee Owner) | Q4: Owner/Operator | R4: TBD — franchisee owner ⚠️ DO NOT approach — Neighborly PE intro required first KKR → Charles Layne → Felix Gernburd — PE intro only | S4: TBD — office manager Smart Fleet USA telematics (NOT GPS Insight) | T4: Smart Fleet USA (NOT GPS Insight) ⚠️ No warm GPS Insight intro path Do not approach without PE intro confirmed | W4: Profile + conflict check | Y4: ServiceTitan incumbent — check mandate status before outreach | Z4: SOURCE: Aire Serv FDD 2025 / franchise.neighborly.com ITEM 11: ServiceTitan REQUIRED — 'our Software System' referenced in Item 19. ITEM 19 (2024 data): 158 reporting businesses, 1/1/24-12/31/24 full year. Avg gross sales: not disclosed in public summary — pull FDD. Telematics: Smart Fleet USA confirmed. CONFLICT: High on FSM. | AA4: ⚠️ ST mandated — no FSM pitch. Telematics only if GPS Insight customer confirmed. Do not run Insight Engine until PE intro secured. | AE4: 36 | AF4: +5 | AG4: 41 ⚪ HOLD | AH4: Jay Jimenez (Brand Pres NEW Apr 2026) LinkedIn: https://www.linkedin.com/posts/neighborly_leadership-president-aireserv-activity-7450905954415677440-12p2 🆕 Just announced - multi-state HVAC operator, Greater Orlando. Predecessor Brad Roberson LEFT Sept 2025 → Fastest Labs CEO LinkedIn (Brad Roberson): https://www.linkedin.com/in/jay-jimenez/ Lane Dixon, MBA (Aire Serv VP Operations): MTSU + Cumberland MBA ⭐ | AI4: jay.jimenez@aireserv.com | jay.jimenez@nbly.com | AJ4: Ben Lamb (corporate) https://www.linkedin.com/in/ben-lamb-31ab6258/ ben.lamb@nbly.com ✓ Pattern confirmed via NeverBounce + Susan McIntosh direct. CFO since 2024. | AK4: Brad Stevenson (CDO corporate) https://www.linkedin.com/in/brad-stevenson-537387a/ brad.stevenson@nbly.com ✓ Texas A&M, Frisco TX. Master Texas A&M. | AL4: Brad Roberson (prior pres, BobVila.com): Quoted on optimal placement of HVAC air purifiers in homes — tactical product expert. Neighborly umbrella: KKR-backed digital transformation thesis applies. Smart Fleet USA (Azuga) is mandated telematics — hard conflict for GPS Insight. ServiceTitan integration partnership is active across Neighborly Repair brands. | AM4: DO NOT direct-approach until KKR intro confirmed. Aire Serv is on ServiceTitan + Smart Fleet USA = NO-PITCH zone. Watch the Jay Jimenez transition — new president = honeymoon period for tech introductions. Telematics-only angle if franchisee is GPS Insight customer (Andrea must verify). Score: 41 ⚪ HOLD | AN4: Frederick Roberts (linkedin.com/in/fredlroberts/) — Aire Serv Operations Consultant Lane Dixon, MBA — Neighborly franchise relations Doyle James — past Mr. Rooter brand pres | AO4: ⚠️ HARD CONFLICT zone: ServiceTitan + Smart Fleet USA mandated. Brand pres TRANSITION: Brad Roberson → Brad's gone → Jay Jimenez NEW (~Apr 2026, CFE) = honeymoon period. Group Pres Repair cluster: Jason Himber. Corporate FSM-decision-maker: Gagan Sinha (CIO, Sept 2025 — "best-in-class platforms" stance). DO NOT direct-approach until KKR intro confirmed. 👉 See Signal Intel: Neighborly section | AP4: Neighborly Reunion (~Oct 2026, Nashville/Gaylord Opryland likely) 16 brands + vendor partners attend ★ DO NOT attend without KKR intro 👉 See Event Intelligence tab | AQ4: 🎓 NEIGHBORLY: • Jay Jimenez (Brand Pres NEW Apr 2026): Education pending direct LinkedIn confirmation. Multi-state HVAC operator background. Greater Orlando area. • Brad Roberson (predecessor — Sept 2025 left for Fastest Labs President/CEO): Mississippi-rooted operator path. Bought independent glass company in Brookhaven, MS in 2003 → Glass Doctor franchisee → corporate Franchise Consultant 2017 → Glass Doctor Pres 2019 → Aire Serv Pres 2023 → Fastest Labs. • Lane Dixon, MBA (Aire Serv VP Operations): Middle Tennessee State University BA Business Admin/Econ/Finance 2004 + Cumberland University MBA ⭐ • Ben Lamb (Neighborly CFO): Baylor BBA ⭐ • Brad Stevenson (Neighborly CDO): Texas A&M ⭐ 👉 See Signal Intel: Neighborly
A5: 2 | B5: Glass Doctor | C5: Neighborly | D5: Auto/Home Glass | E5: 500 | F5: 3 | G5: Partial/ST | H5: TBD | I5: LOW | J5: ServiceTitan | K5: 🔴 High | L5: Smart Fleet USA | M5: No — Smart Fleet USA | N5: ProTradeNet preferred broker — validate FDD | O5: 🟡 Medium | P5: (Franchisee Owner) | Q5: Owner/Operator | R5: TBD — franchisee owner ⚠️ DO NOT approach — Neighborly PE intro required first KKR → Charles Layne → Felix Gernburd — PE intro only | S5: TBD — office manager Smart Fleet USA telematics (NOT GPS Insight) | T5: Smart Fleet USA (NOT GPS Insight) ⚠️ No warm GPS Insight intro path Do not approach without PE intro confirmed | W5: Profile + conflict check | Y5: ST mandate — check renewal window | Z5: Pull from Wisconsin/California FDD registry. Neighborly brand — verify ST mandate status first. | AA5: ⚠️ ST mandated — no FSM pitch. Telematics only if GPS Insight customer confirmed. Do not run Insight Engine until PE intro secured. | AE5: 19 | AF5: +5 | AG5: 24 ⚪ HOLD | AH5: Gabe Lopez (Brand President) LinkedIn: pending direct verification (search 'Gabe Lopez Glass Doctor Neighborly' on LinkedIn) Predecessor Brad Roberson (Pres 2019-2023, then Aire Serv, NOW Fastest Labs CEO Sept 2025) LinkedIn (Brad): https://www.linkedin.com/in/brad-roberson-1871a72b/ Mississippi-rooted operator path. Bought Glass Doctor Brookhaven MS franchise 2003. | AI5: gabe.lopez@glassdoctor.com | gabe.lopez@nbly.com | AJ5: Ben Lamb (corporate) https://www.linkedin.com/in/ben-lamb-31ab6258/ ben.lamb@nbly.com ✓ Pattern confirmed via NeverBounce + Susan McIntosh direct. CFO since 2024. | AK5: Brad Stevenson (CDO corporate) https://www.linkedin.com/in/brad-stevenson-537387a/ brad.stevenson@nbly.com ✓ Texas A&M, Frisco TX. Master Texas A&M. | AL5: Auto/home glass = lower telematics need. ServiceTitan mandate may be looser here. Smart Fleet USA mandate still applies to all Neighborly fleet vehicles per platform standards. | AM5: ST partial deployment — check actual mandate strength. Lower priority within Neighborly repair cluster. Score: 24 ⚪ HOLD | AN5: Glass Doctor team rolls up to Jason Himber (Repair cluster Group Pres) | AO5: ⚠️ Same Neighborly stack: ServiceTitan + Smart Fleet USA. Brand pres: Gabe Lopez. Auto/home glass = lower telematics need. Lower priority within Neighborly repair cluster (Score 24 ⚪ HOLD). 👉 See Signal Intel: Neighborly section | AP5: Neighborly Reunion (~Oct 2026, Nashville/Gaylord Opryland likely) 16 brands + vendor partners attend ★ DO NOT attend without KKR intro 👉 See Event Intelligence tab | AQ5: 🎓 NEIGHBORLY (LEADERSHIP TRANSITION): • Gabe Lopez (Brand Pres): Education pending direct LinkedIn confirmation • Predecessor Brad Roberson: Now Fastest Labs CEO. Mississippi-rooted operator (bought independent glass co Brookhaven MS 2003). • Corporate: Baylor cluster (Lamb CFO, Lewis Mr. Appliance, McCormick Mr. Electric) + Texas A&M (Stevenson CDO) 👉 See Signal Intel: Neighborly
A6: 3 | B6: Lawn Pride | C6: Neighborly | D6: Lawn Care | E6: 150 | F6: 3 | G6: Partial/ST | H6: TBD | I6: MED | J6: FieldRoutes (ST) | K6: 🔴 High | L6: Smart Fleet USA | M6: No — Smart Fleet USA | N6: Validate via FDD | O6: ❓ Unknown | P6: (Franchisee Owner) | Q6: Owner/Operator | R6: TBD — franchisee owner ⚠️ DO NOT approach — Neighborly PE intro required first KKR → Charles Layne → Felix Gernburd — PE intro only | S6: TBD — office manager Smart Fleet USA telematics (NOT GPS Insight) | T6: Smart Fleet USA (NOT GPS Insight) ⚠️ No warm GPS Insight intro path Do not approach without PE intro confirmed | W6: Profile + conflict check | Y6: Route model — check ST mandate status | Z6: Pull from Wisconsin/California FDD registry. Neighborly brand — verify ST mandate status first. | AA6: ⚠️ ST mandated — no FSM pitch. Telematics only if GPS Insight customer confirmed. Do not run Insight Engine until PE intro secured. | AE6: 24 | AF6: +5 | AG6: 29 ⚪ HOLD | AH6: Susan McIntosh (Brand President since March 2023) LinkedIn: https://www.linkedin.com/in/susanmcintoshneighborly/ Cardinal Ritter HS Indianapolis ⭐ NO COLLEGE - Operator path 30+ yrs Lawn Pride Started 1994 as telemarketer → Office Mgr → GM → VP → Brand Pres Husband Bryan also Lawn Pride 30+ yrs. Email: susan.mcintosh@nbly.com | AI6: susan.mcintosh@lawnpride.com | susan.mcintosh@nbly.com | AJ6: Ben Lamb (corporate) https://www.linkedin.com/in/ben-lamb-31ab6258/ ben.lamb@nbly.com ✓ Pattern confirmed via NeverBounce + Susan McIntosh direct. CFO since 2024. | AK6: Brad Stevenson (CDO corporate) https://www.linkedin.com/in/brad-stevenson-537387a/ brad.stevenson@nbly.com ✓ Texas A&M, Frisco TX. Master Texas A&M. | AL6: Neighborly LinkedIn post about Lawn Pride team and Ruby Caggiano-Cooper. Lawn Pride is acquired brand (relatively newer to Neighborly) — possibly less tech-mandated than legacy brands. | AM6: Lawn care = seasonal scheduling fits ServiceBridge well. Acquired brand status MAY mean less ST mandate strength — verify with Andrea. Score: 29 ⚪ HOLD | AN6: Ruby Caggiano-Cooper — Lawn Pride team (LinkedIn referenced) Matt Crowley (Group Pres Specialty) | AO6: Brand Pres: Susan McIntosh (Cardinal Ritter HS Indianapolis, came up from landscape crew, Pres March 2023). Lawn = high fleet utilization despite ST mandate. 👉 See Signal Intel: Neighborly section | AP6: Neighborly Reunion (~Oct 2026, Nashville/Gaylord Opryland likely) 16 brands + vendor partners attend ★ DO NOT attend without KKR intro 👉 See Event Intelligence tab | AQ6: 🎓 NEIGHBORLY: • Susan McIntosh (Brand Pres since March 2023): Cardinal Ritter High School Indianapolis. NO COLLEGE — Operator path. Started 1994 at Lawn Pride as telemarketer → office mgr → general mgr → VP → Brand Pres (30+ year career). Husband Bryan also at Lawn Pride 30+ years. • Indianapolis IN headquartered. Joined Neighborly via acquisition. • Matt Crowley (Group Pres-Specialty oversight): USC Marshall MBA ⭐ 👉 See Signal Intel: Neighborly
A7: 4 | B7: Molly Maid | C7: Neighborly | D7: Cleaning | E7: 448 | F7: 3 | G7: Partial/ST | H7: TBD | I7: MED | J7: ServiceTitan | K7: 🔴 High | L7: Smart Fleet USA | M7: No — Smart Fleet USA | N7: Validate via FDD | O7: ❓ Unknown | P7: (Franchisee Owner) | Q7: Owner/Operator | R7: TBD — franchisee owner ⚠️ DO NOT approach — Neighborly PE intro required first KKR → Charles Layne → Felix Gernburd — PE intro only | S7: TBD — office manager Smart Fleet USA telematics (NOT GPS Insight) | T7: Smart Fleet USA (NOT GPS Insight) ⚠️ No warm GPS Insight intro path Do not approach without PE intro confirmed | W7: Profile + conflict check | Y7: Recurring cleaning crews | Z7: Pull from Wisconsin/California FDD registry. Neighborly brand — verify ST mandate status first. | AA7: ⚠️ ST mandated — no FSM pitch. Telematics only if GPS Insight customer confirmed. Do not run Insight Engine until PE intro secured. | AE7: 21 | AF7: +5 | AG7: 26 ⚪ HOLD | AH7: Brian Meussner (Brand President NEW Jan 2026) LinkedIn: https://www.linkedin.com/in/brian-meussner-43b22b7/ Central Michigan University 1999-2002. Detroit MI. Hospitality background. Note: PRIOR Pres Marla Mock transitioned out; Meussner now leads Molly Maid USA + Mr. Handyman dual role. Michael Silva-Nash, CFE (VP Operations Molly Maid USA): U Arkansas at Little Rock 2010-2014 ⭐ CFE Bilingual LinkedIn (Silva-Nash): https://www.linkedin.com/in/michael-silva-nash-cfe-a759a448/ | AI7: michael.silva-nash@mollymaid.com | michael.silva-nash@nbly.com | AJ7: Ben Lamb (corporate) https://www.linkedin.com/in/ben-lamb-31ab6258/ ben.lamb@nbly.com ✓ Pattern confirmed via NeverBounce + Susan McIntosh direct. CFO since 2024. | AK7: Brad Stevenson (CDO corporate) https://www.linkedin.com/in/brad-stevenson-537387a/ brad.stevenson@nbly.com ✓ Texas A&M, Frisco TX. Master Texas A&M. | AL7: Molly Maid Franchise Business Coach team celebrating Franchise Business Review survey results — operationally strong. Cleaning vertical: lower telematics priority (no truck-heavy ops). | AM7: Cleaning brands historically lower-priority for FSM dispatch — Molly Maid likely on Booking software not full FSM. Score: 26 ⚪ HOLD | AN7: Georgeanne Erickson (Maintain cluster Group Pres) Jessica Eaddy — Molly Maid Franchise Business Coach team | AO7: 🎯 STRONG: Brand Pres Michael Silva-Nash (CFE, started in family franchise N. Little Rock at age 21, bilingual). Bio: "spearheaded launch of AI SMS Lead Management and other cognitive intelligence tools." 2017 Franchisee of Year. AI-tool-friendly mindset. 👉 See Signal Intel: Neighborly section | AP7: Neighborly Reunion (~Oct 2026) Cleaning industry events (ISSA, etc.) Silva-Nash bilingual = Hispanic franchise events 👉 See Event Intelligence tab | AQ7: 🎓 NEIGHBORLY: • Michael Silva-Nash (Brand Pres): University of Arkansas at Little Rock 2010-2014, International Business + Foreign Language Business Admin ⭐ - CFE, bilingual, LULAC Director of Public Relations - Wife Rebecca Nash. Father-in-law Pedro Silva. Maumelle AR. Family franchisee origin (started age 21). • Georgeanne Erickson (Group Pres-Maintain): Pending school. Ex-CMO Fogo de Chão. 👉 See Signal Intel: Neighborly
A8: 5 | B8: Mosquito Joe | C8: Neighborly | D8: Pest Control | E8: 400 | F8: 3 | G8: Partial/ST | H8: TBD | I8: HIGH — ServiceTitan mandated via Neighborly group contract — do not pitch FSM | J8: FieldRoutes (ST) | K8: 🔴 High | L8: Smart Fleet USA | M8: No — Smart Fleet USA | N8: Validate via FDD | O8: ❓ Unknown | P8: (Franchisee Owner) | Q8: Owner/Operator | R8: TBD — franchisee owner ⚠️ DO NOT approach — Neighborly PE intro required first KKR → Charles Layne → Felix Gernburd — PE intro only | S8: TBD — office manager Smart Fleet USA telematics (NOT GPS Insight) | T8: Smart Fleet USA (NOT GPS Insight) ⚠️ No warm GPS Insight intro path Do not approach without PE intro confirmed | W8: Profile + conflict check | Y8: Route recurring — strong FSM fit if not ST | Z8: Pull from Wisconsin/California FDD registry. Neighborly brand — verify ST mandate status first. | AA8: ⚠️ ST mandated — no FSM pitch. Telematics only if GPS Insight customer confirmed. Do not run Insight Engine until PE intro secured. | AE8: 24 | AF8: +5 | AG8: 29 ⚪ HOLD | AH8: Evan Brody (Brand President) LinkedIn: https://www.linkedin.com/in/evansbrody/ Olin School of Business / Washington University in St. Louis ⭐ Dallas. Group Pres oversight: Georgeanne Erickson (Maintain cluster). | AI8: evan.brody@mosquitojoe.com | evan.brody@nbly.com | AJ8: Ben Lamb (corporate) https://www.linkedin.com/in/ben-lamb-31ab6258/ ben.lamb@nbly.com ✓ Pattern confirmed via NeverBounce + Susan McIntosh direct. CFO since 2024. | AK8: Brad Stevenson (CDO corporate) https://www.linkedin.com/in/brad-stevenson-537387a/ brad.stevenson@nbly.com ✓ Texas A&M, Frisco TX. Master Texas A&M. | AL8: Pest control vertical — overlaps directly with Mosquito Squad (Authority) and Mosquito Shield (Five Star). Original Mosquito Squad founder = Scott Zide (now Empower CEO). History matters. | AM8: Pest control fleet management = strong telematics fit. But Smart Fleet USA mandate blocks GPS Insight angle. Score: 29 ⚪ HOLD (49 non-ST 🟡 QUEUE) | AN8: Mosquito Joe rolls up to Georgeanne Erickson | AO8: Pest control = high-frequency route-based service = strong telematics ROI. ⚠️ Smart Fleet USA mandate applies. 👉 See Signal Intel: Neighborly section | AP8: Neighborly Reunion (~Oct 2026, Nashville/Gaylord Opryland likely) 16 brands + vendor partners attend ★ DO NOT attend without KKR intro 👉 See Event Intelligence tab | AQ8: 🎓 NEIGHBORLY: • Evan Brody (Brand Pres): Olin School of Business, Washington University in St. Louis ⭐ • Georgeanne Erickson (Group Pres-Maintain): Ex-CMO Fogo de Chão. School pending. • Brad Stevenson (Neighborly CDO): Texas A&M ⭐ 👉 See Signal Intel: Neighborly
A9: 6 | B9: Mr. Appliance | C9: Neighborly | D9: Appliance Repair | E9: 150 | F9: 3 | G9: Partial/ST | H9: TBD | I9: MED | J9: ServiceTitan | K9: 🔴 High | L9: Smart Fleet USA | M9: No — Smart Fleet USA | N9: Validate via FDD | O9: ❓ Unknown | P9: (Franchisee Owner) | Q9: Owner/Operator | R9: TBD — franchisee owner ⚠️ DO NOT approach — Neighborly PE intro required first KKR → Charles Layne → Felix Gernburd — PE intro only | S9: TBD — office manager Smart Fleet USA telematics (NOT GPS Insight) | T9: Smart Fleet USA (NOT GPS Insight) ⚠️ No warm GPS Insight intro path Do not approach without PE intro confirmed | W9: Profile + conflict check | Y9: Solo tech model | Z9: Pull from Wisconsin/California FDD registry. Neighborly brand — verify ST mandate status first. | AA9: ⚠️ ST mandated — no FSM pitch. Telematics only if GPS Insight customer confirmed. Do not run Insight Engine until PE intro secured. | AE9: 26 | AF9: +5 | AG9: 31 ⚪ HOLD | AH9: Glenn Lewis, CFE (Brand President) LinkedIn: https://www.linkedin.com/in/glenn-lewis-cfe-28347913/ Baylor University 1982-85 + UT Austin 81-82 ⭐ CFE China Spring TX. Wife Leslie + daughter Calli also Baylor (multi-gen). | AI9: glenn.lewis@mrappliance.com | glenn.lewis@nbly.com | AJ9: Ben Lamb (corporate) https://www.linkedin.com/in/ben-lamb-31ab6258/ ben.lamb@nbly.com ✓ Pattern confirmed via NeverBounce + Susan McIntosh direct. CFO since 2024. | AK9: Brad Stevenson (CDO corporate) https://www.linkedin.com/in/brad-stevenson-537387a/ brad.stevenson@nbly.com ✓ Texas A&M, Frisco TX. Master Texas A&M. | AL9: Appliance repair = scheduling-heavy vertical. Neighborly Mosquito Joe team referenced in Lane Dixon's LinkedIn posts. | AM9: Score: 31 ⚪ HOLD Lower-priority appliance vertical within Neighborly Maintain cluster. | AN9: Mr. Appliance rolls up to Georgeanne Erickson | AO9: Brand Pres: Glenn Lewis (Baylor 1982-85, CFE, Pres May 2024). Baylor cluster (4 connections in dataset). 👉 See Signal Intel: Neighborly section | AP9: Neighborly Reunion (~Oct 2026, Nashville/Gaylord Opryland likely) 16 brands + vendor partners attend ★ DO NOT attend without KKR intro 👉 See Event Intelligence tab | AQ9: 🎓 BAYLOR ALUM ⭐ MULTI-GEN: • Glenn Lewis (Brand Pres): Baylor 1982-1985 + UT Austin 1981-82, CFE - Wife Leslie also Baylor + daughter Calli also Baylor. China Spring TX - Career: Jim's Formal Wear 18 yrs → Decor Group → Dwyer/Neighborly • Baylor cluster: 4 connections in dataset (Lewis, McCormick, Lamb CFO, Carter Smith Pink's) • Georgeanne Erickson (Group Pres-Maintain oversight): Pending 👉 See Signal Intel: Neighborly
A10: 7 | B10: Mr. Electric | C10: Neighborly | D10: Electrical | E10: 219 | F10: 5 | G10: Partial/ST | H10: TBD | I10: HIGH — ServiceTitan MANDATED — on ST since 2012, confirmed in FDD Item 11 | J10: ServiceTitan | K10: 🔴 High | L10: Smart Fleet USA | M10: No — Smart Fleet USA | N10: ProTradeNet preferred broker — validate FDD | O10: 🟡 Medium | P10: (Franchisee Owner) | Q10: Owner/Operator | R10: TBD — franchisee owner ⚠️ DO NOT approach — Neighborly PE intro required first KKR → Charles Layne → Felix Gernburd — PE intro only | S10: TBD — office manager Smart Fleet USA telematics (NOT GPS Insight) | T10: Smart Fleet USA (NOT GPS Insight) ⚠️ No warm GPS Insight intro path Do not approach without PE intro confirmed | W10: Profile + conflict check | Y10: Licensed electricians — dispatch + compliance fit | Z10: SOURCE: ServiceTitan acquisition of Servant Systems 2020 ITEM 11: ServiceTitan REQUIRED — on ST since 2012 per ST press release. Telematics: Smart Fleet USA confirmed. CONFLICT: High on FSM. | AA10: ⚠️ ST mandated — no FSM pitch. Telematics only if GPS Insight customer confirmed. Do not run Insight Engine until PE intro secured. | AE10: 36 | AF10: +5 | AG10: 41 ⚪ HOLD | AH10: Josh McCormick (Brand President — RETURNED to Mr. Electric ~Aug 2025) LinkedIn: https://www.linkedin.com/in/joshmccormickneighborly/ Baylor University BBA Mgmt 1999-2002 ⭐ Was Mr. Electric VP Sales, then HouseMaster Brand Pres, now back to Mr. Electric. | AI10: josh.mccormick@mrelectric.com | josh.mccormick@nbly.com | AJ10: Ben Lamb (corporate) https://www.linkedin.com/in/ben-lamb-31ab6258/ ben.lamb@nbly.com ✓ Pattern confirmed via NeverBounce + Susan McIntosh direct. CFO since 2024. | AK10: Brad Stevenson (CDO corporate) https://www.linkedin.com/in/brad-stevenson-537387a/ brad.stevenson@nbly.com ✓ Texas A&M, Frisco TX. Master Texas A&M. | AL10: Mr. Electric is referenced in Neighborly LinkedIn for franchisee training series — operational maturity. Electric trade = full FSM target profile (dispatch, work orders, stock). | AM10: Higher FSM priority within Neighborly. ST mandate is the blocker. Score: 41 ⚪ HOLD (61 non-ST 🟡 QUEUE) — non-ST locations are real opportunity. | AN10: Mr. Electric rolls up to Jason Himber | AO10: Brand Pres: Josh McCormick (Baylor BBA Mgmt 1999-2002, 18+ yrs at Neighborly, Mr. Electric Galveston peer group 10+ yrs, Pres Aug 2025). 👉 See Signal Intel: Neighborly section | AP10: Neighborly Reunion (~Oct 2026, Nashville/Gaylord Opryland likely) 16 brands + vendor partners attend ★ DO NOT attend without KKR intro 👉 See Event Intelligence tab | AQ10: 🎓 BAYLOR ALUM: • Josh McCormick (Brand Pres): Baylor BBA Mgmt 1999-2002 ⭐ • 18+ years Neighborly. Mr. Electric Galveston peer group 10+ years • Baylor cluster: 4 connections total 👉 See Signal Intel: Neighborly
A11: 8 | B11: Mr. Handyman | C11: Neighborly | D11: Handyman | E11: 150 | F11: 3 | G11: Partial/ST | H11: TBD | I11: MED | J11: ServiceTitan | K11: 🔴 High | L11: Smart Fleet USA | M11: No — Smart Fleet USA | N11: Validate via FDD | O11: ❓ Unknown | P11: (Franchisee Owner) | Q11: Owner/Operator | R11: TBD — franchisee owner ⚠️ DO NOT approach — Neighborly PE intro required first KKR → Charles Layne → Felix Gernburd — PE intro only | S11: TBD — office manager Smart Fleet USA telematics (NOT GPS Insight) | T11: Smart Fleet USA (NOT GPS Insight) ⚠️ No warm GPS Insight intro path Do not approach without PE intro confirmed | W11: Profile + conflict check | Y11: Multi-trade skilled service | Z11: SOURCE: ServiceTitan acquisition of Servant Systems 2020 ITEM 11: ServiceTitan REQUIRED — on ST since 2012. Telematics: Smart Fleet USA confirmed. CONFLICT: High on FSM. | AA11: ⚠️ ST mandated — no FSM pitch. Telematics only if GPS Insight customer confirmed. Do not run Insight Engine until PE intro secured. | AE11: 19 | AF11: +5 | AG11: 24 ⚪ HOLD | AH11: Brian Meussner (Brand President NEW Jan 2026 — ALSO Molly Maid) LinkedIn: https://www.linkedin.com/in/brian-meussner-43b22b7/ Central Michigan University 1999-2002. Detroit MI. Hospitality background, dual brand role with Molly Maid USA. Jon Gallagher (executive partner per Meussner LinkedIn posts). | AI11: brian.meussner@mrhandyman.com | brian.meussner@nbly.com | AJ11: Ben Lamb (corporate) https://www.linkedin.com/in/ben-lamb-31ab6258/ ben.lamb@nbly.com ✓ Pattern confirmed via NeverBounce + Susan McIntosh direct. CFO since 2024. | AK11: Brad Stevenson (CDO corporate) https://www.linkedin.com/in/brad-stevenson-537387a/ brad.stevenson@nbly.com ✓ Texas A&M, Frisco TX. Master Texas A&M. | AL11: Handyman = generalist trade. Booking-driven scheduling more than dispatch-heavy. | AM11: Score: 24 ⚪ HOLD Lower priority within Neighborly Repair. | AN11: Mr. Handyman rolls up to Jason Himber Mr. Rooter brand: Matt Kunz (Brand Pres since 2023) Vera Peterson (Group Pres Maintain — re Five Star Painting which moves to Maintain cluster) Mary Kay Liston (Former Five Star Painting president) Matt Phillips (Former Neighborly COO + Five Star Painting Pres) Amy Davis (Five Star Painting VP Operations) | AO11: Brand Pres: Brian Meussner (Central Michigan Univ 1999-2002, hospitality background, Pres Jan 2026, Detroit MI). NEW = honeymoon. 👉 See Signal Intel: Neighborly section | AP11: Neighborly Reunion (~Oct 2026, Nashville/Gaylord Opryland likely) 16 brands + vendor partners attend ★ DO NOT attend without KKR intro 👉 See Event Intelligence tab | AQ11: 🎓 NEIGHBORLY: • Brian Meussner (Brand Pres NEW Jan 2026): Central Michigan University 1999-2002, hospitality background, Detroit MI ⭐ • Jason Himber (Group Pres-Repair oversight): Pending 👉 See Signal Intel: Neighborly
A12: 9 | B12: Mr. Rooter | C12: Neighborly | D12: Plumbing | E12: 237 | F12: 6 | G12: Partial/ST | H12: TBD | I12: HIGH — ServiceTitan MANDATED — on ST since 2012, confirmed in FDD Item 11 | J12: ServiceTitan | K12: 🔴 High | L12: Smart Fleet USA | M12: No — Smart Fleet USA | N12: ProTradeNet preferred broker — validate FDD | O12: 🟡 Medium | P12: (Franchisee Owner) | Q12: Owner/Operator | R12: TBD — franchisee owner ⚠️ DO NOT approach — Neighborly PE intro required first KKR → Charles Layne → Felix Gernburd — PE intro only | S12: TBD — office manager Smart Fleet USA telematics (NOT GPS Insight) | T12: Smart Fleet USA (NOT GPS Insight) ⚠️ No warm GPS Insight intro path Do not approach without PE intro confirmed | W12: Profile + conflict check | Y12: 237 locations FDD 2025. Emergency + scheduled dispatch | Z12: SOURCE: Mr. Rooter FDD 2025 / franchiseba.com 2026 ITEM 11: ServiceTitan REQUIRED — named explicitly. On ST since 2012. Also required: Qvinci, QuickBooks Online. ITEM 19: 188 franchised businesses reporting. Avg not disclosed in public summaries. Telematics: Smart Fleet USA (Neighborly preferred provider, confirmed). CONFLICT: High on FSM. No GPS Insight path. | AA12: ⚠️ ST mandated — no FSM pitch. Telematics only if GPS Insight customer confirmed. Do not run Insight Engine until PE intro secured. | AE12: 36 | AF12: +5 | AG12: 41 ⚪ HOLD | AH12: Matt Kunz (PRIOR President — LEFT Jan 2026 for Fastest Labs CEO) LinkedIn: https://www.linkedin.com/in/mattkunz/ WSU Carson MBA + Northern Illinois BBA + Morrison Tech AS ⭐⭐ NEW Mr. Rooter Brand Pres: pending public announcement. | AI12: chris.porcelli@mrrooter.com | chris.porcelli@nbly.com | AJ12: Ben Lamb (corporate) https://www.linkedin.com/in/ben-lamb-31ab6258/ ben.lamb@nbly.com ✓ Pattern confirmed via NeverBounce + Susan McIntosh direct. CFO since 2024. | AK12: Brad Stevenson (CDO corporate) https://www.linkedin.com/in/brad-stevenson-537387a/ brad.stevenson@nbly.com ✓ Texas A&M, Frisco TX. Master Texas A&M. | AL12: Plumbing trade = ServiceTitan stronghold, where ST competes most aggressively. Doyle James = past brand president, started as Mr. Rooter franchisee. | AM12: ST mandate locked in. Lower priority. Score: 41 ⚪ HOLD | AN12: Mr. Rooter independent franchisees roll up to Jason Himber Matt Crowley oversees corporately-owned Mr. Rooter / Plumb Enterprises | AO12: Plumbing = highest FSM intensity (truck rolls, dispatch, parts). ⚠️ ServiceTitan + Smart Fleet USA mandated. 👉 See Signal Intel: Neighborly section | AP12: Neighborly Reunion (~Oct 2026, Nashville/Gaylord Opryland likely) 16 brands + vendor partners attend ★ DO NOT attend without KKR intro 👉 See Event Intelligence tab | AQ12: 🎓 ⚠️ LEADERSHIP TRANSITION: Matt Kunz LEFT Mr. Rooter for Fastest Labs CEO (Jan 2026). New Mr. Rooter Brand Pres pending. • Matt Kunz (former, now Fastest Labs): WSU Carson MBA 2014-2015 + Northern Illinois BBA + Morrison Tech AS • Jason Himber (Group Pres-Repair, oversees Mr. Rooter): Pending school. 15+ yrs. • Ben Lamb (Neighborly CFO): Baylor BBA ⭐ 👉 See Signal Intel: Neighborly
A13: 10 | B13: Precision Door Service | C13: Neighborly | D13: Garage Doors | E13: 150 | F13: 3 | G13: Partial/ST | H13: TBD | I13: HIGH — ServiceTitan mandated via Neighborly group contract — do not pitch FSM | J13: ServiceTitan | K13: 🔴 High | L13: Smart Fleet USA | M13: No — Smart Fleet USA | N13: Validate via FDD | O13: ❓ Unknown | P13: (Franchisee Owner) | Q13: Owner/Operator | R13: TBD — franchisee owner ⚠️ DO NOT approach — Neighborly PE intro required first KKR → Charles Layne → Felix Gernburd — PE intro only | S13: TBD — office manager Smart Fleet USA telematics (NOT GPS Insight) | T13: Smart Fleet USA (NOT GPS Insight) ⚠️ No warm GPS Insight intro path Do not approach without PE intro confirmed | W13: Profile + conflict check | Y13: High dispatch fit | Z13: Pull from Wisconsin/California FDD registry. Neighborly brand — verify ST mandate status first. | AA13: ⚠️ ST mandated — no FSM pitch. Telematics only if GPS Insight customer confirmed. Do not run Insight Engine until PE intro secured. | AE13: 19 | AF13: +5 | AG13: 24 ⚪ HOLD | AH13: Mike Brickner (Brand President since 2011) LinkedIn: https://www.linkedin.com/in/mike-brickner-precision/ Columbia College ⭐. Ex-Brevard County Sheriff's 911 Center Director. Reliable Residential = largest franchisee operator (per FEP April 2025 PE deal). | AI13: mike.brickner@precisiondoor.com | mike.brickner@nbly.com | AJ13: Ben Lamb (corporate) https://www.linkedin.com/in/ben-lamb-31ab6258/ ben.lamb@nbly.com ✓ Pattern confirmed via NeverBounce + Susan McIntosh direct. CFO since 2024. | AK13: Brad Stevenson (CDO corporate) https://www.linkedin.com/in/brad-stevenson-537387a/ brad.stevenson@nbly.com ✓ Texas A&M, Frisco TX. Master Texas A&M. | AL13: Precision Garage Door Service hosted event at Google Atlanta (per Lee Downing LinkedIn). Garage door = call-out + on-site service model. Strong FSM fit. | AM13: Score: 24 ⚪ HOLD Tied to Repair cluster ST mandate. | AN13: Precision Garage Door rolls up to Jason Himber | AO13: Brand Pres: Mike Brickner (Columbia College, Titusville FL, ex-Brevard County Sheriff's Office Director of 911 Center, at Precision since 2011). 👉 See Signal Intel: Neighborly section | AP13: Neighborly Reunion (~Oct 2026, Nashville/Gaylord Opryland likely) 16 brands + vendor partners attend ★ DO NOT attend without KKR intro 👉 See Event Intelligence tab | AQ13: 🎓 Mike Brickner (Brand Pres): Columbia College, Titusville FL. Ex-Brevard County Sheriff's Office Director of 911 Center. At Precision since 2011. 👉 See Signal Intel: Neighborly
A14: 11 | B14: Rainbow Restoration | C14: Neighborly | D14: Restoration | E14: 330 | F14: 5 | G14: Partial/ST | H14: TBD | I14: MED | J14: ServiceTitan | K14: 🔴 High | L14: Smart Fleet USA | M14: No — Smart Fleet USA | N14: Insurance dispatch + ProTradeNet broker | O14: 🔴 High | P14: (Franchisee Owner) | Q14: Owner/Operator | R14: TBD — franchisee owner ⚠️ DO NOT approach — Neighborly PE intro required first KKR → Charles Layne → Felix Gernburd — PE intro only | S14: TBD — office manager Smart Fleet USA telematics (NOT GPS Insight) | T14: Smart Fleet USA (NOT GPS Insight) ⚠️ No warm GPS Insight intro path Do not approach without PE intro confirmed | W14: Profile + conflict check | Y14: Event-driven restoration crews | Z14: Pull from Wisconsin/California FDD registry. Neighborly brand — verify ST mandate status first. | AA14: ⚠️ ST mandated — no FSM pitch. Telematics only if GPS Insight customer confirmed. Do not run Insight Engine until PE intro secured. | AE14: 39 | AF14: +5 | AG14: 44 ⚪ HOLD | AH14: Josh Miller (Brand President) LinkedIn: pending direct verification (search 'Josh Miller Rainbow Restoration Neighborly') Predecessor Rob White (NOW Monster Tree Service Brand Pres at Authority Brands since Nov 2023) LinkedIn (Rob White): https://www.linkedin.com/in/josh-miller-cr-cfe-277111256/ Rob: Virginia Tech BS Finance + VCU MBA ⭐ | AI14: josh.miller@rainbowintl.com | josh.miller@nbly.com | AJ14: Ben Lamb (corporate) https://www.linkedin.com/in/ben-lamb-31ab6258/ ben.lamb@nbly.com ✓ Pattern confirmed via NeverBounce + Susan McIntosh direct. CFO since 2024. | AK14: Brad Stevenson (CDO corporate) https://www.linkedin.com/in/brad-stevenson-537387a/ brad.stevenson@nbly.com ✓ Texas A&M, Frisco TX. Master Texas A&M. | AL14: Restoration vertical = INSURANCE-CARRIER DRIVEN. Direct overlap with BELFOR. Mr. Rooter Plumbing has rebrand-pivot history with Plumb Enterprises corporate. | AM14: Score: 44 ⚪ HOLD Restoration vertical matches BELFOR playbook — insurance carrier angle, not FSM features. | AN14: Rainbow Restoration rolls up to Jason Himber | AO14: ⚠️ Smart Fleet USA + ServiceTitan zone (most brands). Corporate FSM decision-maker: Gagan Sinha (CIO, Sept 2025). Approach via parent franchisor (KKR intro required). 👉 See Signal Intel: Neighborly section | AP14: Neighborly Reunion (~Oct 2026, Nashville/Gaylord Opryland likely) 16 brands + vendor partners attend ★ DO NOT attend without KKR intro 👉 See Event Intelligence tab | AQ14: 🎓 NEIGHBORLY: • Josh Miller (Brand Pres): Pending verification • Predecessor Rob White (now Monster Tree Service Brand Pres at Authority): Virginia Tech BS Finance + VCU MBA ⭐ • Jason Himber (Group Pres-Repair): Pending 👉 See Signal Intel: Neighborly
A15: 12 | B15: Window Genie | C15: Neighborly | D15: Window/Exterior | E15: 200 | F15: 3 | G15: Partial/ST | H15: TBD | I15: MED | J15: ServiceTitan | K15: 🔴 High | L15: Smart Fleet USA | M15: No — Smart Fleet USA | N15: Validate via FDD | O15: ❓ Unknown | P15: (Franchisee Owner) | Q15: Owner/Operator | R15: TBD — franchisee owner ⚠️ DO NOT approach — Neighborly PE intro required first KKR → Charles Layne → Felix Gernburd — PE intro only | S15: TBD — office manager Smart Fleet USA telematics (NOT GPS Insight) | T15: Smart Fleet USA (NOT GPS Insight) ⚠️ No warm GPS Insight intro path Do not approach without PE intro confirmed | W15: Profile + conflict check | Y15: Seasonal recurring route | Z15: Pull from Wisconsin/California FDD registry. Neighborly brand — verify ST mandate status first. | AA15: ⚠️ ST mandated — no FSM pitch. Telematics only if GPS Insight customer confirmed. Do not run Insight Engine until PE intro secured. | AE15: 21 | AF15: +5 | AG15: 26 ⚪ HOLD | AH15: Chris Bruno, CFE (Brand President — appointed under Erickson Group) LinkedIn: https://www.linkedin.com/in/chris-bruno-cfe-b895122a1/ Tarleton State University BAS Business Admin 2018-2020 ⭐ CFE Came up via Five Star Painting Franchise Business Consultant role. | AI15: chris.bruno@windowgenie.com | chris.bruno@nbly.com | AJ15: Ben Lamb (corporate) https://www.linkedin.com/in/ben-lamb-31ab6258/ ben.lamb@nbly.com ✓ Pattern confirmed via NeverBounce + Susan McIntosh direct. CFO since 2024. | AK15: Brad Stevenson (CDO corporate) https://www.linkedin.com/in/brad-stevenson-537387a/ brad.stevenson@nbly.com ✓ Texas A&M, Frisco TX. Master Texas A&M. | AL15: Window cleaning = direct overlap with Pink's (ResiBrands) and Shine (Evive). | AM15: Score: 26 ⚪ HOLD Lower priority cleaning vertical. | AN15: Window Genie rolls up to Georgeanne Erickson | AO15: ⚠️ Smart Fleet USA + ServiceTitan zone (most brands). Corporate FSM decision-maker: Gagan Sinha (CIO, Sept 2025). Approach via parent franchisor (KKR intro required). 👉 See Signal Intel: Neighborly section | AP15: Neighborly Reunion (~Oct 2026, Nashville/Gaylord Opryland likely) 16 brands + vendor partners attend ★ DO NOT attend without KKR intro 👉 See Event Intelligence tab | AQ15: 🎓 NEIGHBORLY: • Chris Bruno (Brand Pres): Tarleton State University BAS Business Admin 2018-2020. CFE. • Georgeanne Erickson (Group Pres-Maintain): School pending. 👉 See Signal Intel: Neighborly
... A18: 15 | B18: Aire Serv (non-ST) | C18: Neighborly | D18: HVAC | E18: 100 | F18: 5 | G18: Greenfield | H18: TBD | I18: MED | J18: Greenfield / Paper | K18: 🟢 None | L18: Smart Fleet USA | M18: No — Smart Fleet USA | N18: Validate via FDD | O18: ❓ Unknown | P18: (Franchisee Owner) | Q18: Owner/Operator | R18: TBD — franchisee owner ⚠️ DO NOT approach — Neighborly PE intro required first KKR → Charles Layne → Felix Gernburd — PE intro only | S18: TBD — office manager Smart Fleet USA telematics (NOT GPS Insight) | T18: Smart Fleet USA (NOT GPS Insight) ⚠️ No warm GPS Insight intro path Do not approach without PE intro confirmed | W18: Profile + outreach | Y18: Non-ST HVAC locations within Neighborly | Z18: Pull from Wisconsin/California FDD registry. Neighborly brand — verify ST mandate status first. | AA18: ⚠️ ST mandated — no FSM pitch. Telematics only if GPS Insight customer confirmed. Do not run Insight Engine until PE intro secured. | AE18: 56 | AF18: +5 | AG18: 61 🟡 QUEUE | AH18: Jay Jimenez (Aire Serv Pres NEW Apr 2026) LinkedIn: https://www.linkedin.com/posts/neighborly_leadership-president-aireserv-activity-7450905954415677440-12p2 FOR NON-ST LOCATIONS specifically — same person as Aire Serv brand president 🆕 Multi-state HVAC operator path. Greater Orlando. Education: Operator path background. Lane Dixon (VP Ops): MTSU + Cumberland MBA ⭐ | AI18: jay.jimenez@aireserv.com | jay.jimenez@nbly.com | AJ18: Ben Lamb (corporate) https://www.linkedin.com/in/ben-lamb-31ab6258/ ben.lamb@nbly.com ✓ Pattern confirmed via NeverBounce + Susan McIntosh direct. CFO since 2024. | AK18: Brad Stevenson (CDO corporate) https://www.linkedin.com/in/brad-stevenson-537387a/ brad.stevenson@nbly.com ✓ Texas A&M, Frisco TX. Master Texas A&M. | AL18: HVAC vintage franchisees who avoided ST migration = pilot candidates. | AM18: Score: 61 🟡 QUEUE ★ Higher priority HVAC vertical. | AN18: Same as Aire Serv (Jay Jimenez NEW) | AO18: ⚠️ Smart Fleet USA + ServiceTitan zone (most brands). Corporate FSM decision-maker: Gagan Sinha (CIO, Sept 2025). Approach via parent franchisor (KKR intro required). 👉 See Signal Intel: Neighborly section | AP18: Neighborly Reunion (~Oct 2026, Nashville/Gaylord Opryland likely) 16 brands + vendor partners attend ★ DO NOT attend without KKR intro 👉 See Event Intelligence tab | AQ18: 🎓 NEIGHBORLY: • Jay Jimenez (Brand Pres NEW Apr 2026): CFE designation, undergrad pending • Brad Roberson (predecessor): Mississippi State 👉 See Signal Intel: Neighborly
A19: 16 | B19: Neighborly (other brands) | C19: Neighborly | D19: Mixed | E19: 200 | F19: 3 | G19: Partial/ST | H19: TBD | I19: LOW | J19: ServiceTitan | K19: 🔴 High | L19: Smart Fleet USA | M19: No — Smart Fleet USA | N19: Validate via FDD | O19: ❓ Unknown | P19: (Franchisee Owner) | Q19: Owner/Operator | R19: TBD — franchisee owner ⚠️ DO NOT approach — Neighborly PE intro required first KKR → Charles Layne → Felix Gernburd — PE intro only | S19: TBD — office manager Smart Fleet USA telematics (NOT GPS Insight) | T19: Smart Fleet USA (NOT GPS Insight) ⚠️ No warm GPS Insight intro path Do not approach without PE intro confirmed | W19: Conflict check first | Y19: Remaining Neighborly brands — verify ST mandate before contact | Z19: Pull from Wisconsin/California FDD registry. Neighborly brand — verify ST mandate status first. | AA19: ⚠️ ST mandated — no FSM pitch. Telematics only if GPS Insight customer confirmed. Do not run Insight Engine until PE intro secured. | AE19: 19 | AF19: +5 | AG19: 24 ⚪ HOLD | AH19: Aggregate — varies by brand LinkedIn (Neighborly CEO Mike Davis): https://www.linkedin.com/in/mcardavis Mike Davis (Neighborly CEO): Education from Mathnasium/Valpak/UMG path Gagan Sinha (CIO #1 OVERALL TARGET): Harvard MS Mgmt 2011-2013 ⭐⭐⭐ Brad Stevenson (CDO): Texas A&M College Station ⭐ Stacy Lynn Bourgeois (CMO): Northwestern Medill + Florida State ⭐ Ben Lamb (CFO): Baylor BBA ⭐ Matt Crowley (Group Pres-Specialty): USC Marshall MBA ⭐ Georgeanne Erickson (Group Pres-Maintain): Pending; Ex-CMO Fogo de Chão Jason Himber (Group Pres-Repair): Pending verification | AL19: Aggregate Neighborly metrics: ST mandate, Smart Fleet USA telematics, ProTradeNet insurance. | AM19: Score: 24 ⚪ HOLD | AN19: Other Neighborly brands: Five Star Painting (David Sutter), Dryer Vent Wizard (Kevin Busch), HouseMaster (Nancy Shipley), Junk King (Paul Tis), Portland Glass (Sarah Frohnhoefer), ProTradeNet (Brandi Haslam), Real Property Mgmt (Jeff Pepperney), ShelfGenie (Tony Ditzler), Grounds Guys (Lori Johnson) | AO19: ⚠️ Smart Fleet USA + ServiceTitan zone (most brands). Corporate FSM decision-maker: Gagan Sinha (CIO, Sept 2025). Approach via parent franchisor (KKR intro required). 👉 See Signal Intel: Neighborly section | AP19: Neighborly Reunion (~Oct 2026, Nashville/Gaylord Opryland likely) 16 brands + vendor partners attend ★ DO NOT attend without KKR intro 👉 See Event Intelligence tab | AQ19: Most brand presidents tied to Neighborly leadership. Notable Baylor cluster (Glenn Lewis Mr. Appliance, Josh McCormick Mr. Electric, Ben Lamb CFO). Corporate: Gagan Sinha Harvard MS, Brad Stevenson Texas A&M, Stacy Lynn Bourgeois Northwestern + FSU. 👉 See Signal Intel: Neighborly section for full bios
A20: 17 | B20: ASP Swimming Pool | C20: Authority Brands | D20: Pool Service | E20: 150 | F20: 3 | G20: Greenfield | H20: TBD | I20: VERIFY — PoolOps proprietary CRM — do not pitch FSM replacement; GPS telematics only | J20: Greenfield / Paper | K20: 🟢 None | L20: Validate with Andrea | M20: Validate with Andrea | N20: Validate via FDD | O20: ❓ Unknown | P20: (Franchisee Owner) | Q20: Owner/Operator | R20: TBD — ASP brand president ← Approach via Tij Bedi (CTO Authority Brands) Greenfield FSM — pool service route model | S20: TBD | T20: TBD | W20: Profile + outreach | Y20: Route pool service — weekly recurring | Z20: SOURCE: 2025 FDD (2023 data) — franchisechatter.com + leadtruffle.co ITEM 19 — Unit Economics: • 113 franchisees / 133 territories as of Dec 31, 2023 • Avg gross revenue per territory: ~$590,000 (sharpsheets) • Top 25%: avg $1.78M/year (leadtruffle) • 257-375 locations depending on source/year • Investment range: $84,395-$210,121 • Royalty: 7-5% sliding scale + 1% brand fund • Technology fee: $250/mo for PoolOps CRM + tools • Local marketing: 3% or $30K/yr • Route-based recurring pool service + renovation ITEM 11 — Technology: PROPRIETARY PoolOps CRM CONFIRMED — $250/month tech fee Pool service management, scheduling, client reporting built in CONFLICT RISK: High — proprietary CRM + mandatory fee NOTE: Authority Brands portfolio (Apax). Jay Caiafa new CEO. Entry point: Tij Bedi (CTO) or via Jay Caiafa data/AI angle | AA20: CONFLICT: PoolOps proprietary CRM — do not pitch FSM replacement IF ENGAGED: • GPS Insight telematics standalone — route-based fleet • Frame as complement to PoolOps, not replacement • 8-12 pools/truck/day = route optimization ROI story • Jay Caiafa AI/data background = frame as operational intelligence layer • Authority Brands mandate conversation — top-down PE play | AE20: 46 | AF20: +15 | AG20: 61 🟡 QUEUE | AH20: Stewart Vernon (Founder ASP, EVP Emerging Brands at Authority Brands) LinkedIn: https://www.linkedin.com/in/stewart-vernon-asp/ College of Charleston ⭐. Macon GA hometown. Stratford Academy. Founded ASP 2002. Wife Shannon. Two children Stewart Jr + Sloan. | AI20: JMeece@authoritybrandsllc.com | AJ20: Josh Greear (corporate CFO) https://www.linkedin.com/in/joshgreear/ JGreear@authoritybrandsllc.com ✓ NEW Sep 2025. Ex-CFO Primrose Schools, ex-Cracker Barrel, ex-Home Depot. | AK20: Jordan Wilson (CDO corporate) https://www.linkedin.com/in/jwilsoncfe/ JWilson@authoritybrandsllc.com ✓ Joined Jan 2023, ex-Scorpion SVP Franchise Sales. CFE. Reports to CEO. | AL20: Stewart Vernon (Authority site): "Starting from the bottom as a young entrepreneur has inspired me to help other entrepreneurs. Seeing the growth of our franchise owners is truly satisfying." Founded ASP with $500 award, built to $91M system sales = entrepreneur-CEO fluent. Authority Brands has active ST partnership (2024) but ASP could be greenfield. | AM20: Pool/water-focused vertical. Seasonal scheduling fits ServiceBridge well. Score: 61 🟡 QUEUE Approach via Tij Bedi (CTO) entry path. ASP under Stewart's Emerging Brands is outside ST locked Trades cluster. | AN20: Stewart Vernon (EVP Emerging Brands / ASP Founder) Tom Swift (EVP Outdoor Brands) Tij Bedi (CTO) Jordan Wilson (CDO since Jan 2025, ex-Scorpion) Vince Powers (360PR+ EVP — Authority's PR firm) Adam Terranova (Sr Director Marketing) Christina Kennedy (Foley Lardner — Authority's franchise lawyer) | AO20: Pool service = seasonal route. Authority's BuyMax GPO available. 👉 See Signal Intel: Authority Brands section | AP20: Authority Brands Annual Convention / IGNITE 2026 (Reno held early 2026 with Caiafa keynote) Service Trades Brands Conference w/ BuyMax breakouts 👉 See Event Intelligence tab | AQ20: 🎓 STEWART VERNON (ASP Founder, now EVP Emerging Brands at Authority): • College of Charleston (corporate communications) ⭐ • Hometown Macon GA. Stratford Academy. • Founded ASP 2002 in Macon GA. Married to Shannon. Two children: Stewart Jr, Sloan • Active speaker at Wesleyan College, College of Charleston, Georgia Tech, Mercer University. Founding partner KUDU Outdoor Grills, Classic Overland. • Authority Brands oversight: Tom Swift (EVP), Jay Caiafa (CEO Duke + USAFA) 👉 See Signal Intel: Authority Brands
A21: 18 | B21: Benjamin Franklin Plumbing | C21: Authority Brands | D21: Plumbing | E21: 363 | F21: 5 | G21: Greenfield | H21: TBD | I21: HIGH — ServiceTitan MANDATED — transition announced Sep 2024, completing 2025 | J21: ServiceTitan | K21: 🔴 High | L21: Validate with Andrea | M21: Validate with Andrea | N21: Validate via FDD | O21: ❓ Unknown | P21: (Franchisee Owner) | Q21: Owner/Operator | R21: TBD — BFP brand president ⚠️ ST MANDATED Sep 2024 — NO FSM pitch GPS Insight telematics only if confirmed customer | S21: TBD | T21: TBD — GPS Insight telematics angle only | W21: Profile + outreach | Y21: 363 units FDD 2025. Emergency dispatch fit | Z21: SOURCE: ServiceTitan press release Sep 2024 ServiceTitan MANDATED — transition announced Sep 2024, completing 2025. CONFLICT: High. Do not approach with ServiceBridge as FSM replacement. GPS Insight angle only if confirmed telematics customer via Andrea. | AA21: Check FSM mandate first. If ST-mandated: no FSM pitch, GPS Insight only. If greenfield: run Insight Engine ROI Calculator. | AE21: 63 | AF21: +15 | AG21: 78 🟡 QUEUE | AH21: Steve Clemente (President & COO Trade Brands at Authority since Dec 2025) LinkedIn: https://www.linkedin.com/in/steve-clemente-b4244539/ UCF BS Liberal Studies + Webster University Master's ⭐⭐ 30+ yrs Dick's Sporting Goods, Target, Nebraska Book, Primrose Schools President. | AI21: SClemente@authoritybrandsllc.com | AJ21: Josh Greear (corporate CFO) https://www.linkedin.com/in/joshgreear/ JGreear@authoritybrandsllc.com ✓ NEW Sep 2025. Ex-CFO Primrose Schools, ex-Cracker Barrel, ex-Home Depot. | AK21: Jordan Wilson (CDO corporate) https://www.linkedin.com/in/jwilsoncfe/ JWilson@authoritybrandsllc.com ✓ Joined Jan 2023, ex-Scorpion SVP Franchise Sales. CFE. Reports to CEO. | AL21: Steve Clemente (Authority press): "Spearhead initiatives to enhance operational excellence, drive organic growth, and unlock cross-selling opportunities across Authority Brands' four trade brands." Clemente's mandate IS cross-brand operational excellence + cross-selling = DIRECT match for ServiceBridge unified platform value prop. | AM21: ★ HIGHEST priority within Authority — Steve Clemente's Trades cluster was specifically created to unlock cross-brand operations. Score: 78 🟡 QUEUE BFP is THE flagship plumbing brand — ST lock-in here is strongest. Displacement play, not greenfield. | AN21: Steve Clemente (Pres & COO Trades Brands) Jay Caiafa (CEO) Josh Greear (CFO) Jordan Wilson (CDO) Matt Buckwalter (Punctual Pros multi-unit franchisee — BFP+OHHAC+MS in Central PA, backed by Broad Sky Partners) Aaron Buckwalter (Punctual Pros multi-unit franchisee) Jonathan Marlow (Broad Sky Partners — invested in Punctual Pros) Kelley Pendergast (BFP franchisee, featured Franchising Mag) Scott Wood Jr. (BFP+OHHAC franchisee Omaha) Cory Clinton (BFP General Manager Indianapolis) Robert Armstrong (BFP Operations Manager Northern Colorado) | AO21: Falls under Steve Clemente (Pres/COO Trade Brands Dec 2025, ex-Primrose Schools President). Plumbing = high FSM intensity. 👉 See Signal Intel: Authority Brands section | AP21: Authority Brands Annual Convention / IGNITE 2026 (Reno held early 2026 with Caiafa keynote) Service Trades Brands Conference w/ BuyMax breakouts 👉 See Event Intelligence tab | AQ21: 🎓 AUTHORITY BRANDS: • Steve Clemente (Pres/COO Trade Brands oversight Dec 2025): University of Central Florida BS Liberal Studies + Webster University Master's • Jay Caiafa (Authority CEO): USAFA + Duke Law + Duke Fuqua ⭐ 👉 See Signal Intel: Authority Brands
A22: 19 | B22: DRYmedic Restoration | C22: Authority Brands | D22: Restoration | E22: 200 | F22: 5 | G22: Greenfield | H22: TBD | I22: MED | J22: Greenfield / Paper | K22: 🟢 None | L22: Validate with Andrea | M22: Validate with Andrea | N22: Validate via FDD | O22: ❓ Unknown | P22: (Franchisee Owner) | Q22: Owner/Operator | R22: TBD — DRYmedic brand president ← Approach via Tij Bedi (CTO Authority Brands) Greenfield FSM — restoration trade = strong pilot fit | S22: TBD — local franchisee ops contact | T22: TBD — verify GPS Insight customer via Andrea | W22: Profile + outreach | Y22: Water/fire restoration crews | Z22: SOURCE: Authority Brands website + franchise directories 2025 ITEM 19 — Unit Economics: • Water/fire/mold restoration franchise • Part of Authority Brands portfolio • Insurance-paid restoration model • Investment range: est. $150K-$350K ITEM 11 — Technology: Authority Brands centrally managed technology Verify FSM mandate — restoration brands often use ServiceTitan or Xactimate INSURANCE ANGLE: High — restoration = carrier documentation critical NOTE: Authority Brands portfolio. Jay Caiafa new CEO (Aug 2025). | AA22: VERIFY: Authority Brands FSM mandate status with Tij Bedi (CTO) KEY ANGLES: • Job photo documentation = insurance carrier compliance • Xactimate integration potential • Jay Caiafa data/AI angle • Authority mandate = top-down play | AE22: 66 | AF22: +15 | AG22: 81 🟡 QUEUE | AH22: Steve Clemente (Pres & COO Trades) — covers DRYmedic as part of Trade Brands portfolio LinkedIn: https://www.linkedin.com/in/steve-clemente-trade-brands/ UCF + Webster Master's ⭐⭐ | AI22: SClemente@authoritybrandsllc.com | AJ22: Josh Greear (corporate CFO) https://www.linkedin.com/in/joshgreear/ JGreear@authoritybrandsllc.com ✓ NEW Sep 2025. Ex-CFO Primrose Schools, ex-Cracker Barrel, ex-Home Depot. | AK22: Jordan Wilson (CDO corporate) https://www.linkedin.com/in/jwilsoncfe/ JWilson@authoritybrandsllc.com ✓ Joined Jan 2023, ex-Scorpion SVP Franchise Sales. CFE. Reports to CEO. | AL22: Restoration vertical = INSURANCE-CARRIER DRIVEN. Direct overlap with BELFOR. Authority added DRYmedic via 2023 acquisition — under 3 yrs in portfolio. | AM22: Score: 81 🟡 QUEUE — TOP-3 IN AUTHORITY ★ Restoration brand under Trades cluster = rare combo. Insurance carrier angle works (BELFOR playbook applies). Recent acquisition + Steve Clemente looking for cross-brand wins = ENTRY WINDOW. | AN22: Steve Clemente (Pres & COO Trades) Lindsay Keyser (DRYmedic franchisee, featured Franchising Mag) Insurance carrier relationships from 2023 acquisition | AO22: Restoration vertical = aligns with BELFOR + BluSky + Servpro thesis (Wave 6 strategic insight). Falls under Steve Clemente. 👉 See Signal Intel: Authority Brands section | AP22: Authority Brands Annual Convention / IGNITE 2026 (Reno held early 2026 with Caiafa keynote) Service Trades Brands Conference w/ BuyMax breakouts 👉 See Event Intelligence tab | AQ22: 🎓 AUTHORITY BRANDS (Trade Brands oversight): • Steve Clemente (Pres/COO Trade Brands Dec 2025): UCF BS Liberal Studies + Webster University Master's ⭐ - 30+ yrs Dick's Sporting Goods, Target, Nebraska Book Co, Primrose Schools President • Jay Caiafa (Authority CEO): USAFA + Duke Law + Duke Fuqua ⭐⭐⭐ 👉 See Signal Intel: Authority Brands
